Workbook

Sheet Plan
B1: Schulden-Plan Schweiz
B2: Gelbe Felder ausfüllen. Der Plan rechnet Monat für Monat, wann du schuldenfrei bist.
B5: Schuld | C5: Offen (CHF) | D5: Zins % p. a. | E5: Rate pro Monat | F5: Schuldenfrei (Monat) | G5: Warnung
B6: Kreditkarte | C6: 3200 | D6: 12 | E6: 120 | F6: =Monatsplan!D3 | G6: =IF(AND(C6>0,E6<=C6*D6/100/12),"Rate deckt Zins nicht!","")
B7: Kleinkredit | C7: 15000 | D7: 7.9 | E7: 350 | F7: =Monatsplan!J3 | G7: =IF(AND(C7>0,E7<=C7*D7/100/12),"Rate deckt Zins nicht!","")
B8: Auto-Leasing | C8: 9000 | D8: 4.9 | E8: 280 | F8: =Monatsplan!P3 | G8: =IF(AND(C8>0,E8<=C8*D8/100/12),"Rate deckt Zins nicht!","")
B9: Darlehen Familie | C9: 2000 | D9: 0 | E9: 50 | F9: =Monatsplan!V3 | G9: =IF(AND(C9>0,E9<=C9*D9/100/12),"Rate deckt Zins nicht!","")
C10: 0 | D10: 0 | E10: 0 | F10: =Monatsplan!AB3 | G10: =IF(AND(C10>0,E10<=C10*D10/100/12),"Rate deckt Zins nicht!","")
C11: 0 | D11: 0 | E11: 0 | F11: =Monatsplan!AH3 | G11: =IF(AND(C11>0,E11<=C11*D11/100/12),"Rate deckt Zins nicht!","")
C12: 0 | D12: 0 | E12: 0 | F12: =Monatsplan!AN3 | G12: =IF(AND(C12>0,E12<=C12*D12/100/12),"Rate deckt Zins nicht!","")
C13: 0 | D13: 0 | E13: 0 | F13: =Monatsplan!AT3 | G13: =IF(AND(C13>0,E13<=C13*D13/100/12),"Rate deckt Zins nicht!","")
B16: Extra pro Monat (CHF) | C16: 300
B17: Methode | C17: Lawine | D17: Lawine = höchster Zins zuerst (günstigste) · Schneeball = kleinste Schuld zuerst
B18: Startmonat | C18: =DATE(YEAR(TODAY()),MONTH(TODAY())+1,1)
B20: Ergebnis
B21: Schuldenfrei nach (Monaten) | C21: =Monatsplan!BA2
B22: Schuldenfrei im | C22: =IF(ISNUMBER(C21),EDATE(C18,C21-1),"—")
B23: Zinsen total (gewählte Methode) | C23: =Monatsplan!BA1
B24: Zinsen mit der anderen Methode | C24: ='Rechnung andere Methode'!BA1
B25: Zinsen nur mit Mindestraten | C25: ='Rechnung ohne Extra'!BA1
B26: Ersparnis durch das Extra | C26: =C25-C23
B27: Schuldenfrei nur mit Mindestraten (Monate) | C27: ='Rechnung ohne Extra'!BA2
B29: Tipp: Die Lawine kostet am wenigsten Zins. Der Schneeball bringt schneller ein erstes Erfolgserlebnis. Nimm die Methode, bei der du durchhältst.

Sheet Anleitung
A1: Schulden-Plan Schweiz — so geht's
A3: 1. Blatt „Plan“: bis zu 8 Schulden eintragen: offener Betrag, Jahreszins aus dem Vertrag, heutige Rate.
A4: 2. Extra pro Monat eintragen: was du zusätzlich zahlen kannst. Auch CHF 50 zählen.
A5: 3. Methode wählen: Lawine (höchster Zins zuerst, günstigste) oder Schneeball (kleinste Schuld zuerst).
A6: 4. Ergebnis lesen: schuldenfrei-Datum, Zinsen total, Vergleich mit der anderen Methode und ohne Extra.
A7: 5. Blatt „Monatsplan“: Monat für Monat, was bei jeder Schuld passiert. Frei werdende Raten gehen automatisch
A8: an die nächste Schuld in der Reihenfolge.
A10: Rot in der Spalte „Warnung“: Die Rate deckt nicht einmal die Zinsen, die Schuld wächst. Das hat Vorrang.
A11: Leasing: vorzeitige Auflösung ist oft teuer. Die normale Rate laufen lassen und Extra-Geld auf andere Schulden lenken.
A12: Schweiz: Private Schuldzinsen sind in der Regel von den Steuern abziehbar (Bund: bis Vermögenserträge + CHF 50'000).
A13: Zuerst eine Notreserve von etwa drei Monatsausgaben, dann tilgen.
A14: Hilfe, wenn es nicht aufgeht: kantonale Budget- und Schuldenberatungen, kostenlos (Übersicht: schulden.ch).
... A19: © aban news · abannews.com

Sheet Monatsplan
A1: Methode | B1: =Plan!$C$17 | AZ1: Zinsen total | BA1: =SUM(D7:D366)+SUM(J7:J366)+SUM(P7:P366)+SUM(V7:V366)+SUM(AB7:AB366)+SUM(AH7:AH366)+SUM(AN7:AN366)+SUM(AT7:AT366)
A2: Extra pro Monat | B2: =Plan!$C$16 | AZ2: Schuldenfrei nach Monaten | BA2: =IFERROR(MATCH(0,BC7:BC366,0),"über 30 Jahre")
A3: Budget pro Monat | B3: =SUMPRODUCT((Plan!$C$6:$C$13>0)*Plan!$E$6:$E$13)+B2 | C3: frei ab Monat | D3: =IF(Plan!C6<=0,"",IFERROR(MATCH(0,H7:H366,0),"über 30 J.")) | I3: frei ab Monat | J3: =IF(Plan!C7<=0,"",IFERROR(MATCH(0,N7:N366,0),"über 30 J.")) | O3: frei ab Monat | P3: =IF(Plan!C8<=0,"",IFERROR(MATCH(0,T7:T366,0),"über 30 J.")) | U3: frei ab Monat | V3: =IF(Plan!C9<=0,"",IFERROR(MATCH(0,Z7:Z366,0),"über 30 J.")) | AA3: frei ab Monat | AB3: =IF(Plan!C10<=0,"",IFERROR(MATCH(0,AF7:AF366,0),"über 30 J.")) | AG3: frei ab Monat | AH3: =IF(Plan!C11<=0,"",IFERROR(MATCH(0,AL7:AL366,0),"über 30 J.")) | AM3: frei ab Monat | AN3: =IF(Plan!C12<=0,"",IFERROR(MATCH(0,AR7:AR366,0),"über 30 J.")) | AS3: frei ab Monat | AT3: =IF(Plan!C13<=0,"",IFERROR(MATCH(0,AX7:AX366,0),"über 30 J."))
C4: =Plan!B6 | I4: =Plan!B7 | O4: =Plan!B8 | U4: =Plan!B9 | AA4: =Plan!B10 | AG4: =Plan!B11 | AM4: =Plan!B12 | AS4: =Plan!B13
C5: =IF(Plan!C6<=0,-1E+15,IF($B$1="Lawine",Plan!D6*1E+9-Plan!C6,-Plan!C6*1000+Plan!D6)) | D5: Rang | E5: =1+(C$5>C$5)+(I$5>C$5)+(O$5>C$5)+(U$5>C$5)+(AA$5>C$5)+(AG$5>C$5)+(AM$5>C$5)+(AS$5>C$5)+0 | I5: =IF(Plan!C7<=0,-1E+15,IF($B$1="Lawine",Plan!D7*1E+9-Plan!C7,-Plan!C7*1000+Plan!D7)) | J5: Rang | K5: =1+(C$5>I$5)+(I$5>I$5)+(O$5>I$5)+(U$5>I$5)+(AA$5>I$5)+(AG$5>I$5)+(AM$5>I$5)+(AS$5>I$5)+(C$5=I$5) | O5: =IF(Plan!C8<=0,-1E+15,IF($B$1="Lawine",Plan!D8*1E+9-Plan!C8,-Plan!C8*1000+Plan!D8)) | P5: Rang | Q5: =1+(C$5>O$5)+(I$5>O$5)+(O$5>O$5)+(U$5>O$5)+(AA$5>O$5)+(AG$5>O$5)+(AM$5>O$5)+(AS$5>O$5)+(C$5=O$5)+(I$5=O$5) | U5: =IF(Plan!C9<=0,-1E+15,IF($B$1="Lawine",Plan!D9*1E+9-Plan!C9,-Plan!C9*1000+Plan!D9)) | V5: Rang | W5: =1+(C$5>U$5)+(I$5>U$5)+(O$5>U$5)+(U$5>U$5)+(AA$5>U$5)+(AG$5>U$5)+(AM$5>U$5)+(AS$5>U$5)+(C$5=U$5)+(I$5=U$5)+(O$5=U$5) | AA5: =IF(Plan!C10<=0,-1E+15,IF($B$1="Lawine",Plan!D10*1E+9-Plan!C10,-Plan!C10*1000+Plan!D10)) | AB5: Rang | AC5: =1+(C$5>AA$5)+(I$5>AA$5)+(O$5>AA$5)+(U$5>AA$5)+(AA$5>AA$5)+(AG$5>AA$5)+(AM$5>AA$5)+(AS$5>AA$5)+(C$5=AA$5)+(I$5=AA$5)+(O$5=AA$5)+(U$5=AA$5) | AG5: =IF(Plan!C11<=0,-1E+15,IF($B$1="Lawine",Plan!D11*1E+9-Plan!C11,-Plan!C11*1000+Plan!D11)) | AH5: Rang | AI5: =1+(C$5>AG$5)+(I$5>AG$5)+(O$5>AG$5)+(U$5>AG$5)+(AA$5>AG$5)+(AG$5>AG$5)+(AM$5>AG$5)+(AS$5>AG$5)+(C$5=AG$5)+(I$5=AG$5)+(O$5=AG$5)+(U$5=AG$5)+(AA$5=AG$5) | AM5: =IF(Plan!C12<=0,-1E+15,IF($B$1="Lawine",Plan!D12*1E+9-Plan!C12,-Plan!C12*1000+Plan!D12)) | AN5: Rang | AO5: =1+(C$5>AM$5)+(I$5>AM$5)+(O$5>AM$5)+(U$5>AM$5)+(AA$5>AM$5)+(AG$5>AM$5)+(AM$5>AM$5)+(AS$5>AM$5)+(C$5=AM$5)+(I$5=AM$5)+(O$5=AM$5)+(U$5=AM$5)+(AA$5=AM$5)+(AG$5=AM$5) | AS5: =IF(Plan!C13<=0,-1E+15,IF($B$1="Lawine",Plan!D13*1E+9-Plan!C13,-Plan!C13*1000+Plan!D13)) | AT5: Rang | AU5: =1+(C$5>AS$5)+(I$5>AS$5)+(O$5>AS$5)+(U$5>AS$5)+(AA$5>AS$5)+(AG$5>AS$5)+(AM$5>AS$5)+(AS$5>AS$5)+(C$5=AS$5)+(I$5=AS$5)+(O$5=AS$5)+(U$5=AS$5)+(AA$5=AS$5)+(AG$5=AS$5)+(AM$5=AS$5)
A6: Monat | B6: frei für Extra | C6: Start | D6: Zins | E6: Mindestrate | F6: Rest | G6: Extra | H6: Ende | I6: Start | J6: Zins | K6: Mindestrate | L6: Rest | M6: Extra | N6: Ende | O6: Start | P6: Zins | Q6: Mindestrate | R6: Rest | S6: Extra | T6: Ende | U6: Start | V6: Zins | W6: Mindestrate | X6: Rest | Y6: Extra | Z6: Ende | AA6: Start | AB6: Zins | AC6: Mindestrate | AD6: Rest | AE6: Extra | AF6: Ende | AG6: Start | AH6: Zins | AI6: Mindestrate | AJ6: Rest | AK6: Extra | AL6: Ende | AM6: Start | AN6: Zins | AO6: Mindestrate | AP6: Rest | AQ6: Extra | AR6: Ende | AS6: Start | AT6: Zins | AU6: Mindestrate | AV6: Rest | AW6: Extra | AX6: Ende | BC6: offen total
A7: 1 | B7: =MAX(0,$B$3-(E7+K7+Q7+W7+AC7+AI7+AO7+AU7)) | C7: =MAX(0,Plan!C6) | D7: =C7*Plan!D6/100/12 | E7: =MIN(Plan!E6,C7+D7) | F7: =C7+D7-E7 | G7: =MIN(F7,MAX(0,$B7-((K$5<E$5)*L7+(Q$5<E$5)*R7+(W$5<E$5)*X7+(AC$5<E$5)*AD7+(AI$5<E$5)*AJ7+(AO$5<E$5)*AP7+(AU$5<E$5)*AV7))) | H7: =IF(F7-G7<0.005,0,F7-G7) | I7: =MAX(0,Plan!C7) | J7: =I7*Plan!D7/100/12 | K7: =MIN(Plan!E7,I7+J7) | L7: =I7+J7-K7 | M7: =MIN(L7,MAX(0,$B7-((E$5<K$5)*F7+(Q$5<K$5)*R7+(W$5<K$5)*X7+(AC$5<K$5)*AD7+(AI$5<K$5)*AJ7+(AO$5<K$5)*AP7+(AU$5<K$5)*AV7))) | N7: =IF(L7-M7<0.005,0,L7-M7) | O7: =MAX(0,Plan!C8) | P7: =O7*Plan!D8/100/12 | Q7: =MIN(Plan!E8,O7+P7) | R7: =O7+P7-Q7 | S7: =MIN(R7,MAX(0,$B7-((E$5<Q$5)*F7+(K$5<Q$5)*L7+(W$5<Q$5)*X7+(AC$5<Q$5)*AD7+(AI$5<Q$5)*AJ7+(AO$5<Q$5)*AP7+(AU$5<Q$5)*AV7))) | T7: =IF(R7-S7<0.005,0,R7-S7) | U7: =MAX(0,Plan!C9) | V7: =U7*Plan!D9/100/12 | W7: =MIN(Plan!E9,U7+V7) | X7: =U7+V7-W7 | Y7: =MIN(X7,MAX(0,$B7-((E$5<W$5)*F7+(K$5<W$5)*L7+(Q$5<W$5)*R7+(AC$5<W$5)*AD7+(AI$5<W$5)*AJ7+(AO$5<W$5)*AP7+(AU$5<W$5)*AV7))) | Z7: =IF(X7-Y7<0.005,0,X7-Y7) | AA7: =MAX(0,Plan!C10) | AB7: =AA7*Plan!D10/100/12 | AC7: =MIN(Plan!E10,AA7+AB7) | AD7: =AA7+AB7-AC7 | AE7: =MIN(AD7,MAX(0,$B7-((E$5<AC$5)*F7+(K$5<AC$5)*L7+(Q$5<AC$5)*R7+(W$5<AC$5)*X7+(AI$5<AC$5)*AJ7+(AO$5<AC$5)*AP7+(AU$5<AC$5)*AV7))) | AF7: =IF(AD7-AE7<0.005,0,AD7-AE7) | AG7: =MAX(0,Plan!C11) | AH7: =AG7*Plan!D11/100/12 | AI7: =MIN(Plan!E11,AG7+AH7) | AJ7: =AG7+AH7-AI7 | AK7: =MIN(AJ7,MAX(0,$B7-((E$5<AI$5)*F7+(K$5<AI$5)*L7+(Q$5<AI$5)*R7+(W$5<AI$5)*X7+(AC$5<AI$5)*AD7+(AO$5<AI$5)*AP7+(AU$5<AI$5)*AV7))) | AL7: =IF(AJ7-AK7<0.005,0,AJ7-AK7) | AM7: =MAX(0,Plan!C12) | AN7: =AM7*Plan!D12/100/12 | AO7: =MIN(Plan!E12,AM7+AN7) | AP7: =AM7+AN7-AO7 | AQ7: =MIN(AP7,MAX(0,$B7-((E$5<AO$5)*F7+(K$5<AO$5)*L7+(Q$5<AO$5)*R7+(W$5<AO$5)*X7+(AC$5<AO$5)*AD7+(AI$5<AO$5)*AJ7+(AU$5<AO$5)*AV7))) | AR7: =IF(AP7-AQ7<0.005,0,AP7-AQ7) | AS7: =MAX(0,Plan!C13) | AT7: =AS7*Plan!D13/100/12 | AU7: =MIN(Plan!E13,AS7+AT7) | AV7: =AS7+AT7-AU7 | AW7: =MIN(AV7,MAX(0,$B7-((E$5<AU$5)*F7+(K$5<AU$5)*L7+(Q$5<AU$5)*R7+(W$5<AU$5)*X7+(AC$5<AU$5)*AD7+(AI$5<AU$5)*AJ7+(AO$5<AU$5)*AP7))) | AX7: =IF(AV7-AW7<0.005,0,AV7-AW7) | BC7: =H7+N7+T7+Z7+AF7+AL7+AR7+AX7
A8: 2 | B8: =MAX(0,$B$3-(E8+K8+Q8+W8+AC8+AI8+AO8+AU8)) | C8: =H7 | D8: =C8*Plan!D6/100/12 | E8: =MIN(Plan!E6,C8+D8) | F8: =C8+D8-E8 | G8: =MIN(F8,MAX(0,$B8-((K$5<E$5)*L8+(Q$5<E$5)*R8+(W$5<E$5)*X8+(AC$5<E$5)*AD8+(AI$5<E$5)*AJ8+(AO$5<E$5)*AP8+(AU$5<E$5)*AV8))) | H8: =IF(F8-G8<0.005,0,F8-G8) | I8: =N7 | J8: =I8*Plan!D7/100/12 | K8: =MIN(Plan!E7,I8+J8) | L8: =I8+J8-K8 | M8: =MIN(L8,MAX(0,$B8-((E$5<K$5)*F8+(Q$5<K$5)*R8+(W$5<K$5)*X8+(AC$5<K$5)*AD8+(AI$5<K$5)*AJ8+(AO$5<K$5)*AP8+(AU$5<K$5)*AV8))) | N8: =IF(L8-M8<0.005,0,L8-M8) | O8: =T7 | P8: =O8*Plan!D8/100/12 | Q8: =MIN(Plan!E8,O8+P8) | R8: =O8+P8-Q8 | S8: =MIN(R8,MAX(0,$B8-((E$5<Q$5)*F8+(K$5<Q$5)*L8+(W$5<Q$5)*X8+(AC$5<Q$5)*AD8+(AI$5<Q$5)*AJ8+(AO$5<Q$5)*AP8+(AU$5<Q$5)*AV8))) | T8: =IF(R8-S8<0.005,0,R8-S8) | U8: =Z7 | V8: =U8*Plan!D9/100/12 | W8: =MIN(Plan!E9,U8+V8) | X8: =U8+V8-W8 | Y8: =MIN(X8,MAX(0,$B8-((E$5<W$5)*F8+(K$5<W$5)*L8+(Q$5<W$5)*R8+(AC$5<W$5)*AD8+(AI$5<W$5)*AJ8+(AO$5<W$5)*AP8+(AU$5<W$5)*AV8))) | Z8: =IF(X8-Y8<0.005,0,X8-Y8) | AA8: =AF7 | AB8: =AA8*Plan!D10/100/12 | AC8: =MIN(Plan!E10,AA8+AB8) | AD8: =AA8+AB8-AC8 | AE8: =MIN(AD8,MAX(0,$B8-((E$5<AC$5)*F8+(K$5<AC$5)*L8+(Q$5<AC$5)*R8+(W$5<AC$5)*X8+(AI$5<AC$5)*AJ8+(AO$5<AC$5)*AP8+(AU$5<AC$5)*AV8))) | AF8: =IF(AD8-AE8<0.005,0,AD8-AE8) | AG8: =AL7 | AH8: =AG8*Plan!D11/100/12 | AI8: =MIN(Plan!E11,AG8+AH8) | AJ8: =AG8+AH8-AI8 | AK8: =MIN(AJ8,MAX(0,$B8-((E$5<AI$5)*F8+(K$5<AI$5)*L8+(Q$5<AI$5)*R8+(W$5<AI$5)*X8+(AC$5<AI$5)*AD8+(AO$5<AI$5)*AP8+(AU$5<AI$5)*AV8))) | AL8: =IF(AJ8-AK8<0.005,0,AJ8-AK8) | AM8: =AR7 | AN8: =AM8*Plan!D12/100/12 | AO8: =MIN(Plan!E12,AM8+AN8) | AP8: =AM8+AN8-AO8 | AQ8: =MIN(AP8,MAX(0,$B8-((E$5<AO$5)*F8+(K$5<AO$5)*L8+(Q$5<AO$5)*R8+(W$5<AO$5)*X8+(AC$5<AO$5)*AD8+(AI$5<AO$5)*AJ8+(AU$5<AO$5)*AV8))) | AR8: =IF(AP8-AQ8<0.005,0,AP8-AQ8) | AS8: =AX7 | AT8: =AS8*Plan!D13/100/12 | AU8: =MIN(Plan!E13,AS8+AT8) | AV8: =AS8+AT8-AU8 | AW8: =MIN(AV8,MAX(0,$B8-((E$5<AU$5)*F8+(K$5<AU$5)*L8+(Q$5<AU$5)*R8+(W$5<AU$5)*X8+(AC$5<AU$5)*AD8+(AI$5<AU$5)*AJ8+(AO$5<AU$5)*AP8))) | AX8: =IF(AV8-AW8<0.005,0,AV8-AW8) | BC8: =H8+N8+T8+Z8+AF8+AL8+AR8+AX8
A9: 3 | B9: =MAX(0,$B$3-(E9+K9+Q9+W9+AC9+AI9+AO9+AU9)) | C9: =H8 | D9: =C9*Plan!D6/100/12 | E9: =MIN(Plan!E6,C9+D9) | F9: =C9+D9-E9 | G9: =MIN(F9,MAX(0,$B9-((K$5<E$5)*L9+(Q$5<E$5)*R9+(W$5<E$5)*X9+(AC$5<E$5)*AD9+(AI$5<E$5)*AJ9+(AO$5<E$5)*AP9+(AU$5<E$5)*AV9))) | H9: =IF(F9-G9<0.005,0,F9-G9) | I9: =N8 | J9: =I9*Plan!D7/100/12 | K9: =MIN(Plan!E7,I9+J9) | L9: =I9+J9-K9 | M9: =MIN(L9,MAX(0,$B9-((E$5<K$5)*F9+(Q$5<K$5)*R9+(W$5<K$5)*X9+(AC$5<K$5)*AD9+(AI$5<K$5)*AJ9+(AO$5<K$5)*AP9+(AU$5<K$5)*AV9))) | N9: =IF(L9-M9<0.005,0,L9-M9) | O9: =T8 | P9: =O9*Plan!D8/100/12 | Q9: =MIN(Plan!E8,O9+P9) | R9: =O9+P9-Q9 | S9: =MIN(R9,MAX(0,$B9-((E$5<Q$5)*F9+(K$5<Q$5)*L9+(W$5<Q$5)*X9+(AC$5<Q$5)*AD9+(AI$5<Q$5)*AJ9+(AO$5<Q$5)*AP9+(AU$5<Q$5)*AV9))) | T9: =IF(R9-S9<0.005,0,R9-S9) | U9: =Z8 | V9: =U9*Plan!D9/100/12 | W9: =MIN(Plan!E9,U9+V9) | X9: =U9+V9-W9 | Y9: =MIN(X9,MAX(0,$B9-((E$5<W$5)*F9+(K$5<W$5)*L9+(Q$5<W$5)*R9+(AC$5<W$5)*AD9+(AI$5<W$5)*AJ9+(AO$5<W$5)*AP9+(AU$5<W$5)*AV9))) | Z9: =IF(X9-Y9<0.005,0,X9-Y9) | AA9: =AF8 | AB9: =AA9*Plan!D10/100/12 | AC9: =MIN(Plan!E10,AA9+AB9) | AD9: =AA9+AB9-AC9 | AE9: =MIN(AD9,MAX(0,$B9-((E$5<AC$5)*F9+(K$5<AC$5)*L9+(Q$5<AC$5)*R9+(W$5<AC$5)*X9+(AI$5<AC$5)*AJ9+(AO$5<AC$5)*AP9+(AU$5<AC$5)*AV9))) | AF9: =IF(AD9-AE9<0.005,0,AD9-AE9) | AG9: =AL8 | AH9: =AG9*Plan!D11/100/12 | AI9: =MIN(Plan!E11,AG9+AH9) | AJ9: =AG9+AH9-AI9 | AK9: =MIN(AJ9,MAX(0,$B9-((E$5<AI$5)*F9+(K$5<AI$5)*L9+(Q$5<AI$5)*R9+(W$5<AI$5)*X9+(AC$5<AI$5)*AD9+(AO$5<AI$5)*AP9+(AU$5<AI$5)*AV9))) | AL9: =IF(AJ9-AK9<0.005,0,AJ9-AK9) | AM9: =AR8 | AN9: =AM9*Plan!D12/100/12 | AO9: =MIN(Plan!E12,AM9+AN9) | AP9: =AM9+AN9-AO9 | AQ9: =MIN(AP9,MAX(0,$B9-((E$5<AO$5)*F9+(K$5<AO$5)*L9+(Q$5<AO$5)*R9+(W$5<AO$5)*X9+(AC$5<AO$5)*AD9+(AI$5<AO$5)*AJ9+(AU$5<AO$5)*AV9))) | AR9: =IF(AP9-AQ9<0.005,0,AP9-AQ9) | AS9: =AX8 | AT9: =AS9*Plan!D13/100/12 | AU9: =MIN(Plan!E13,AS9+AT9) | AV9: =AS9+AT9-AU9 | AW9: =MIN(AV9,MAX(0,$B9-((E$5<AU$5)*F9+(K$5<AU$5)*L9+(Q$5<AU$5)*R9+(W$5<AU$5)*X9+(AC$5<AU$5)*AD9+(AI$5<AU$5)*AJ9+(AO$5<AU$5)*AP9))) | AX9: =IF(AV9-AW9<0.005,0,AV9-AW9) | BC9: =H9+N9+T9+Z9+AF9+AL9+AR9+AX9
A10: 4 | B10: =MAX(0,$B$3-(E10+K10+Q10+W10+AC10+AI10+AO10+AU10)) | C10: =H9 | D10: =C10*Plan!D6/100/12 | E10: =MIN(Plan!E6,C10+D10) | F10: =C10+D10-E10 | G10: =MIN(F10,MAX(0,$B10-((K$5<E$5)*L10+(Q$5<E$5)*R10+(W$5<E$5)*X10+(AC$5<E$5)*AD10+(AI$5<E$5)*AJ10+(AO$5<E$5)*AP10+(AU$5<E$5)*AV10))) | H10: =IF(F10-G10<0.005,0,F10-G10) | I10: =N9 | J10: =I10*Plan!D7/100/12 | K10: =MIN(Plan!E7,I10+J10) | L10: =I10+J10-K10 | M10: =MIN(L10,MAX(0,$B10-((E$5<K$5)*F10+(Q$5<K$5)*R10+(W$5<K$5)*X10+(AC$5<K$5)*AD10+(AI$5<K$5)*AJ10+(AO$5<K$5)*AP10+(AU$5<K$5)*AV10))) | N10: =IF(L10-M10<0.005,0,L10-M10) | O10: =T9 | P10: =O10*Plan!D8/100/12 | Q10: =MIN(Plan!E8,O10+P10) | R10: =O10+P10-Q10 | S10: =MIN(R10,MAX(0,$B10-((E$5<Q$5)*F10+(K$5<Q$5)*L10+(W$5<Q$5)*X10+(AC$5<Q$5)*AD10+(AI$5<Q$5)*AJ10+(AO$5<Q$5)*AP10+(AU$5<Q$5)*AV10))) | T10: =IF(R10-S10<0.005,0,R10-S10) | U10: =Z9 | V10: =U10*Plan!D9/100/12 | W10: =MIN(Plan!E9,U10+V10) | X10: =U10+V10-W10 | Y10: =MIN(X10,MAX(0,$B10-((E$5<W$5)*F10+(K$5<W$5)*L10+(Q$5<W$5)*R10+(AC$5<W$5)*AD10+(AI$5<W$5)*AJ10+(AO$5<W$5)*AP10+(AU$5<W$5)*AV10))) | Z10: =IF(X10-Y10<0.005,0,X10-Y10) | AA10: =AF9 | AB10: =AA10*Plan!D10/100/12 | AC10: =MIN(Plan!E10,AA10+AB10) | AD10: =AA10+AB10-AC10 | AE10: =MIN(AD10,MAX(0,$B10-((E$5<AC$5)*F10+(K$5<AC$5)*L10+(Q$5<AC$5)*R10+(W$5<AC$5)*X10+(AI$5<AC$5)*AJ10+(AO$5<AC$5)*AP10+(AU$5<AC$5)*AV10))) | AF10: =IF(AD10-AE10<0.005,0,AD10-AE10) | AG10: =AL9 | AH10: =AG10*Plan!D11/100/12 | AI10: =MIN(Plan!E11,AG10+AH10) | AJ10: =AG10+AH10-AI10 | AK10: =MIN(AJ10,MAX(0,$B10-((E$5<AI$5)*F10+(K$5<AI$5)*L10+(Q$5<AI$5)*R10+(W$5<AI$5)*X10+(AC$5<AI$5)*AD10+(AO$5<AI$5)*AP10+(AU$5<AI$5)*AV10))) | AL10: =IF(AJ10-AK10<0.005,0,AJ10-AK10) | AM10: =AR9 | AN10: =AM10*Plan!D12/100/12 | AO10: =MIN(Plan!E12,AM10+AN10) | AP10: =AM10+AN10-AO10 | AQ10: =MIN(AP10,MAX(0,$B10-((E$5<AO$5)*F10+(K$5<AO$5)*L10+(Q$5<AO$5)*R10+(W$5<AO$5)*X10+(AC$5<AO$5)*AD10+(AI$5<AO$5)*AJ10+(AU$5<AO$5)*AV10))) | AR10: =IF(AP10-AQ10<0.005,0,AP10-AQ10) | AS10: =AX9 | AT10: =AS10*Plan!D13/100/12 | AU10: =MIN(Plan!E13,AS10+AT10) | AV10: =AS10+AT10-AU10 | AW10: =MIN(AV10,MAX(0,$B10-((E$5<AU$5)*F10+(K$5<AU$5)*L10+(Q$5<AU$5)*R10+(W$5<AU$5)*X10+(AC$5<AU$5)*AD10+(AI$5<AU$5)*AJ10+(AO$5<AU$5)*AP10))) | AX10: =IF(AV10-AW10<0.005,0,AV10-AW10) | BC10: =H10+N10+T10+Z10+AF10+AL10+AR10+AX10
A11: 5 | B11: =MAX(0,$B$3-(E11+K11+Q11+W11+AC11+AI11+AO11+AU11)) | C11: =H10 | D11: =C11*Plan!D6/100/12 | E11: =MIN(Plan!E6,C11+D11) | F11: =C11+D11-E11 | G11: =MIN(F11,MAX(0,$B11-((K$5<E$5)*L11+(Q$5<E$5)*R11+(W$5<E$5)*X11+(AC$5<E$5)*AD11+(AI$5<E$5)*AJ11+(AO$5<E$5)*AP11+(AU$5<E$5)*AV11))) | H11: =IF(F11-G11<0.005,0,F11-G11) | I11: =N10 | J11: =I11*Plan!D7/100/12 | K11: =MIN(Plan!E7,I11+J11) | L11: =I11+J11-K11 | M11: =MIN(L11,MAX(0,$B11-((E$5<K$5)*F11+(Q$5<K$5)*R11+(W$5<K$5)*X11+(AC$5<K$5)*AD11+(AI$5<K$5)*AJ11+(AO$5<K$5)*AP11+(AU$5<K$5)*AV11))) | N11: =IF(L11-M11<0.005,0,L11-M11) | O11: =T10 | P11: =O11*Plan!D8/100/12 | Q11: =MIN(Plan!E8,O11+P11) | R11: =O11+P11-Q11 | S11: =MIN(R11,MAX(0,$B11-((E$5<Q$5)*F11+(K$5<Q$5)*L11+(W$5<Q$5)*X11+(AC$5<Q$5)*AD11+(AI$5<Q$5)*AJ11+(AO$5<Q$5)*AP11+(AU$5<Q$5)*AV11))) | T11: =IF(R11-S11<0.005,0,R11-S11) | U11: =Z10 | V11: =U11*Plan!D9/100/12 | W11: =MIN(Plan!E9,U11+V11) | X11: =U11+V11-W11 | Y11: =MIN(X11,MAX(0,$B11-((E$5<W$5)*F11+(K$5<W$5)*L11+(Q$5<W$5)*R11+(AC$5<W$5)*AD11+(AI$5<W$5)*AJ11+(AO$5<W$5)*AP11+(AU$5<W$5)*AV11))) | Z11: =IF(X11-Y11<0.005,0,X11-Y11) | AA11: =AF10 | AB11: =AA11*Plan!D10/100/12 | AC11: =MIN(Plan!E10,AA11+AB11) | AD11: =AA11+AB11-AC11 | AE11: =MIN(AD11,MAX(0,$B11-((E$5<AC$5)*F11+(K$5<AC$5)*L11+(Q$5<AC$5)*R11+(W$5<AC$5)*X11+(AI$5<AC$5)*AJ11+(AO$5<AC$5)*AP11+(AU$5<AC$5)*AV11))) | AF11: =IF(AD11-AE11<0.005,0,AD11-AE11) | AG11: =AL10 | AH11: =AG11*Plan!D11/100/12 | AI11: =MIN(Plan!E11,AG11+AH11) | AJ11: =AG11+AH11-AI11 | AK11: =MIN(AJ11,MAX(0,$B11-((E$5<AI$5)*F11+(K$5<AI$5)*L11+(Q$5<AI$5)*R11+(W$5<AI$5)*X11+(AC$5<AI$5)*AD11+(AO$5<AI$5)*AP11+(AU$5<AI$5)*AV11))) | AL11: =IF(AJ11-AK11<0.005,0,AJ11-AK11) | AM11: =AR10 | AN11: =AM11*Plan!D12/100/12 | AO11: =MIN(Plan!E12,AM11+AN11) | AP11: =AM11+AN11-AO11 | AQ11: =MIN(AP11,MAX(0,$B11-((E$5<AO$5)*F11+(K$5<AO$5)*L11+(Q$5<AO$5)*R11+(W$5<AO$5)*X11+(AC$5<AO$5)*AD11+(AI$5<AO$5)*AJ11+(AU$5<AO$5)*AV11))) | AR11: =IF(AP11-AQ11<0.005,0,AP11-AQ11) | AS11: =AX10 | AT11: =AS11*Plan!D13/100/12 | AU11: =MIN(Plan!E13,AS11+AT11) | AV11: =AS11+AT11-AU11 | AW11: =MIN(AV11,MAX(0,$B11-((E$5<AU$5)*F11+(K$5<AU$5)*L11+(Q$5<AU$5)*R11+(W$5<AU$5)*X11+(AC$5<AU$5)*AD11+(AI$5<AU$5)*AJ11+(AO$5<AU$5)*AP11))) | AX11: =IF(AV11-AW11<0.005,0,AV11-AW11) | BC11: =H11+N11+T11+Z11+AF11+AL11+AR11+AX11
A12: 6 | B12: =MAX(0,$B$3-(E12+K12+Q12+W12+AC12+AI12+AO12+AU12)) | C12: =H11 | D12: =C12*Plan!D6/100/12 | E12: =MIN(Plan!E6,C12+D12) | F12: =C12+D12-E12 | G12: =MIN(F12,MAX(0,$B12-((K$5<E$5)*L12+(Q$5<E$5)*R12+(W$5<E$5)*X12+(AC$5<E$5)*AD12+(AI$5<E$5)*AJ12+(AO$5<E$5)*AP12+(AU$5<E$5)*AV12))) | H12: =IF(F12-G12<0.005,0,F12-G12) | I12: =N11 | J12: =I12*Plan!D7/100/12 | K12: =MIN(Plan!E7,I12+J12) | L12: =I12+J12-K12 | M12: =MIN(L12,MAX(0,$B12-((E$5<K$5)*F12+(Q$5<K$5)*R12+(W$5<K$5)*X12+(AC$5<K$5)*AD12+(AI$5<K$5)*AJ12+(AO$5<K$5)*AP12+(AU$5<K$5)*AV12))) | N12: =IF(L12-M12<0.005,0,L12-M12) | O12: =T11 | P12: =O12*Plan!D8/100/12 | Q12: =MIN(Plan!E8,O12+P12) | R12: =O12+P12-Q12 | S12: =MIN(R12,MAX(0,$B12-((E$5<Q$5)*F12+(K$5<Q$5)*L12+(W$5<Q$5)*X12+(AC$5<Q$5)*AD12+(AI$5<Q$5)*AJ12+(AO$5<Q$5)*AP12+(AU$5<Q$5)*AV12))) | T12: =IF(R12-S12<0.005,0,R12-S12) | U12: =Z11 | V12: =U12*Plan!D9/100/12 | W12: =MIN(Plan!E9,U12+V12) | X12: =U12+V12-W12 | Y12: =MIN(X12,MAX(0,$B12-((E$5<W$5)*F12+(K$5<W$5)*L12+(Q$5<W$5)*R12+(AC$5<W$5)*AD12+(AI$5<W$5)*AJ12+(AO$5<W$5)*AP12+(AU$5<W$5)*AV12))) | Z12: =IF(X12-Y12<0.005,0,X12-Y12) | AA12: =AF11 | AB12: =AA12*Plan!D10/100/12 | AC12: =MIN(Plan!E10,AA12+AB12) | AD12: =AA12+AB12-AC12 | AE12: =MIN(AD12,MAX(0,$B12-((E$5<AC$5)*F12+(K$5<AC$5)*L12+(Q$5<AC$5)*R12+(W$5<AC$5)*X12+(AI$5<AC$5)*AJ12+(AO$5<AC$5)*AP12+(AU$5<AC$5)*AV12))) | AF12: =IF(AD12-AE12<0.005,0,AD12-AE12) | AG12: =AL11 | AH12: =AG12*Plan!D11/100/12 | AI12: =MIN(Plan!E11,AG12+AH12) | AJ12: =AG12+AH12-AI12 | AK12: =MIN(AJ12,MAX(0,$B12-((E$5<AI$5)*F12+(K$5<AI$5)*L12+(Q$5<AI$5)*R12+(W$5<AI$5)*X12+(AC$5<AI$5)*AD12+(AO$5<AI$5)*AP12+(AU$5<AI$5)*AV12))) | AL12: =IF(AJ12-AK12<0.005,0,AJ12-AK12) | AM12: =AR11 | AN12: =AM12*Plan!D12/100/12 | AO12: =MIN(Plan!E12,AM12+AN12) | AP12: =AM12+AN12-AO12 | AQ12: =MIN(AP12,MAX(0,$B12-((E$5<AO$5)*F12+(K$5<AO$5)*L12+(Q$5<AO$5)*R12+(W$5<AO$5)*X12+(AC$5<AO$5)*AD12+(AI$5<AO$5)*AJ12+(AU$5<AO$5)*AV12))) | AR12: =IF(AP12-AQ12<0.005,0,AP12-AQ12) | AS12: =AX11 | AT12: =AS12*Plan!D13/100/12 | AU12: =MIN(Plan!E13,AS12+AT12) | AV12: =AS12+AT12-AU12 | AW12: =MIN(AV12,MAX(0,$B12-((E$5<AU$5)*F12+(K$5<AU$5)*L12+(Q$5<AU$5)*R12+(W$5<AU$5)*X12+(AC$5<AU$5)*AD12+(AI$5<AU$5)*AJ12+(AO$5<AU$5)*AP12))) | AX12: =IF(AV12-AW12<0.005,0,AV12-AW12) | BC12: =H12+N12+T12+Z12+AF12+AL12+AR12+AX12
A13: 7 | B13: =MAX(0,$B$3-(E13+K13+Q13+W13+AC13+AI13+AO13+AU13)) | C13: =H12 | D13: =C13*Plan!D6/100/12 | E13: =MIN(Plan!E6,C13+D13) | F13: =C13+D13-E13 | G13: =MIN(F13,MAX(0,$B13-((K$5<E$5)*L13+(Q$5<E$5)*R13+(W$5<E$5)*X13+(AC$5<E$5)*AD13+(AI$5<E$5)*AJ13+(AO$5<E$5)*AP13+(AU$5<E$5)*AV13))) | H13: =IF(F13-G13<0.005,0,F13-G13) | I13: =N12 | J13: =I13*Plan!D7/100/12 | K13: =MIN(Plan!E7,I13+J13) | L13: =I13+J13-K13 | M13: =MIN(L13,MAX(0,$B13-((E$5<K$5)*F13+(Q$5<K$5)*R13+(W$5<K$5)*X13+(AC$5<K$5)*AD13+(AI$5<K$5)*AJ13+(AO$5<K$5)*AP13+(AU$5<K$5)*AV13))) | N13: =IF(L13-M13<0.005,0,L13-M13) | O13: =T12 | P13: =O13*Plan!D8/100/12 | Q13: =MIN(Plan!E8,O13+P13) | R13: =O13+P13-Q13 | S13: =MIN(R13,MAX(0,$B13-((E$5<Q$5)*F13+(K$5<Q$5)*L13+(W$5<Q$5)*X13+(AC$5<Q$5)*AD13+(AI$5<Q$5)*AJ13+(AO$5<Q$5)*AP13+(AU$5<Q$5)*AV13))) | T13: =IF(R13-S13<0.005,0,R13-S13) | U13: =Z12 | V13: =U13*Plan!D9/100/12 | W13: =MIN(Plan!E9,U13+V13) | X13: =U13+V13-W13 | Y13: =MIN(X13,MAX(0,$B13-((E$5<W$5)*F13+(K$5<W$5)*L13+(Q$5<W$5)*R13+(AC$5<W$5)*AD13+(AI$5<W$5)*AJ13+(AO$5<W$5)*AP13+(AU$5<W$5)*AV13))) | Z13: =IF(X13-Y13<0.005,0,X13-Y13) | AA13: =AF12 | AB13: =AA13*Plan!D10/100/12 | AC13: =MIN(Plan!E10,AA13+AB13) | AD13: =AA13+AB13-AC13 | AE13: =MIN(AD13,MAX(0,$B13-((E$5<AC$5)*F13+(K$5<AC$5)*L13+(Q$5<AC$5)*R13+(W$5<AC$5)*X13+(AI$5<AC$5)*AJ13+(AO$5<AC$5)*AP13+(AU$5<AC$5)*AV13))) | AF13: =IF(AD13-AE13<0.005,0,AD13-AE13) | AG13: =AL12 | AH13: =AG13*Plan!D11/100/12 | AI13: =MIN(Plan!E11,AG13+AH13) | AJ13: =AG13+AH13-AI13 | AK13: =MIN(AJ13,MAX(0,$B13-((E$5<AI$5)*F13+(K$5<AI$5)*L13+(Q$5<AI$5)*R13+(W$5<AI$5)*X13+(AC$5<AI$5)*AD13+(AO$5<AI$5)*AP13+(AU$5<AI$5)*AV13))) | AL13: =IF(AJ13-AK13<0.005,0,AJ13-AK13) | AM13: =AR12 | AN13: =AM13*Plan!D12/100/12 | AO13: =MIN(Plan!E12,AM13+AN13) | AP13: =AM13+AN13-AO13 | AQ13: =MIN(AP13,MAX(0,$B13-((E$5<AO$5)*F13+(K$5<AO$5)*L13+(Q$5<AO$5)*R13+(W$5<AO$5)*X13+(AC$5<AO$5)*AD13+(AI$5<AO$5)*AJ13+(AU$5<AO$5)*AV13))) | AR13: =IF(AP13-AQ13<0.005,0,AP13-AQ13) | AS13: =AX12 | AT13: =AS13*Plan!D13/100/12 | AU13: =MIN(Plan!E13,AS13+AT13) | AV13: =AS13+AT13-AU13 | AW13: =MIN(AV13,MAX(0,$B13-((E$5<AU$5)*F13+(K$5<AU$5)*L13+(Q$5<AU$5)*R13+(W$5<AU$5)*X13+(AC$5<AU$5)*AD13+(AI$5<AU$5)*AJ13+(AO$5<AU$5)*AP13))) | AX13: =IF(AV13-AW13<0.005,0,AV13-AW13) | BC13: =H13+N13+T13+Z13+AF13+AL13+AR13+AX13
A14: 8 | B14: =MAX(0,$B$3-(E14+K14+Q14+W14+AC14+AI14+AO14+AU14)) | C14: =H13 | D14: =C14*Plan!D6/100/12 | E14: =MIN(Plan!E6,C14+D14) | F14: =C14+D14-E14 | G14: =MIN(F14,MAX(0,$B14-((K$5<E$5)*L14+(Q$5<E$5)*R14+(W$5<E$5)*X14+(AC$5<E$5)*AD14+(AI$5<E$5)*AJ14+(AO$5<E$5)*AP14+(AU$5<E$5)*AV14))) | H14: =IF(F14-G14<0.005,0,F14-G14) | I14: =N13 | J14: =I14*Plan!D7/100/12 | K14: =MIN(Plan!E7,I14+J14) | L14: =I14+J14-K14 | M14: =MIN(L14,MAX(0,$B14-((E$5<K$5)*F14+(Q$5<K$5)*R14+(W$5<K$5)*X14+(AC$5<K$5)*AD14+(AI$5<K$5)*AJ14+(AO$5<K$5)*AP14+(AU$5<K$5)*AV14))) | N14: =IF(L14-M14<0.005,0,L14-M14) | O14: =T13 | P14: =O14*Plan!D8/100/12 | Q14: =MIN(Plan!E8,O14+P14) | R14: =O14+P14-Q14 | S14: =MIN(R14,MAX(0,$B14-((E$5<Q$5)*F14+(K$5<Q$5)*L14+(W$5<Q$5)*X14+(AC$5<Q$5)*AD14+(AI$5<Q$5)*AJ14+(AO$5<Q$5)*AP14+(AU$5<Q$5)*AV14))) | T14: =IF(R14-S14<0.005,0,R14-S14) | U14: =Z13 | V14: =U14*Plan!D9/100/12 | W14: =MIN(Plan!E9,U14+V14) | X14: =U14+V14-W14 | Y14: =MIN(X14,MAX(0,$B14-((E$5<W$5)*F14+(K$5<W$5)*L14+(Q$5<W$5)*R14+(AC$5<W$5)*AD14+(AI$5<W$5)*AJ14+(AO$5<W$5)*AP14+(AU$5<W$5)*AV14))) | Z14: =IF(X14-Y14<0.005,0,X14-Y14) | AA14: =AF13 | AB14: =AA14*Plan!D10/100/12 | AC14: =MIN(Plan!E10,AA14+AB14) | AD14: =AA14+AB14-AC14 | AE14: =MIN(AD14,MAX(0,$B14-((E$5<AC$5)*F14+(K$5<AC$5)*L14+(Q$5<AC$5)*R14+(W$5<AC$5)*X14+(AI$5<AC$5)*AJ14+(AO$5<AC$5)*AP14+(AU$5<AC$5)*AV14))) | AF14: =IF(AD14-AE14<0.005,0,AD14-AE14) | AG14: =AL13 | AH14: =AG14*Plan!D11/100/12 | AI14: =MIN(Plan!E11,AG14+AH14) | AJ14: =AG14+AH14-AI14 | AK14: =MIN(AJ14,MAX(0,$B14-((E$5<AI$5)*F14+(K$5<AI$5)*L14+(Q$5<AI$5)*R14+(W$5<AI$5)*X14+(AC$5<AI$5)*AD14+(AO$5<AI$5)*AP14+(AU$5<AI$5)*AV14))) | AL14: =IF(AJ14-AK14<0.005,0,AJ14-AK14) | AM14: =AR13 | AN14: =AM14*Plan!D12/100/12 | AO14: =MIN(Plan!E12,AM14+AN14) | AP14: =AM14+AN14-AO14 | AQ14: =MIN(AP14,MAX(0,$B14-((E$5<AO$5)*F14+(K$5<AO$5)*L14+(Q$5<AO$5)*R14+(W$5<AO$5)*X14+(AC$5<AO$5)*AD14+(AI$5<AO$5)*AJ14+(AU$5<AO$5)*AV14))) | AR14: =IF(AP14-AQ14<0.005,0,AP14-AQ14) | AS14: =AX13 | AT14: =AS14*Plan!D13/100/12 | AU14: =MIN(Plan!E13,AS14+AT14) | AV14: =AS14+AT14-AU14 | AW14: =MIN(AV14,MAX(0,$B14-((E$5<AU$5)*F14+(K$5<AU$5)*L14+(Q$5<AU$5)*R14+(W$5<AU$5)*X14+(AC$5<AU$5)*AD14+(AI$5<AU$5)*AJ14+(AO$5<AU$5)*AP14))) | AX14: =IF(AV14-AW14<0.005,0,AV14-AW14) | BC14: =H14+N14+T14+Z14+AF14+AL14+AR14+AX14
A15: 9 | B15: =MAX(0,$B$3-(E15+K15+Q15+W15+AC15+AI15+AO15+AU15)) | C15: =H14 | D15: =C15*Plan!D6/100/12 | E15: =MIN(Plan!E6,C15+D15) | F15: =C15+D15-E15 | G15: =MIN(F15,MAX(0,$B15-((K$5<E$5)*L15+(Q$5<E$5)*R15+(W$5<E$5)*X15+(AC$5<E$5)*AD15+(AI$5<E$5)*AJ15+(AO$5<E$5)*AP15+(AU$5<E$5)*AV15))) | H15: =IF(F15-G15<0.005,0,F15-G15) | I15: =N14 | J15: =I15*Plan!D7/100/12 | K15: =MIN(Plan!E7,I15+J15) | L15: =I15+J15-K15 | M15: =MIN(L15,MAX(0,$B15-((E$5<K$5)*F15+(Q$5<K$5)*R15+(W$5<K$5)*X15+(AC$5<K$5)*AD15+(AI$5<K$5)*AJ15+(AO$5<K$5)*AP15+(AU$5<K$5)*AV15))) | N15: =IF(L15-M15<0.005,0,L15-M15) | O15: =T14 | P15: =O15*Plan!D8/100/12 | Q15: =MIN(Plan!E8,O15+P15) | R15: =O15+P15-Q15 | S15: =MIN(R15,MAX(0,$B15-((E$5<Q$5)*F15+(K$5<Q$5)*L15+(W$5<Q$5)*X15+(AC$5<Q$5)*AD15+(AI$5<Q$5)*AJ15+(AO$5<Q$5)*AP15+(AU$5<Q$5)*AV15))) | T15: =IF(R15-S15<0.005,0,R15-S15) | U15: =Z14 | V15: =U15*Plan!D9/100/12 | W15: =MIN(Plan!E9,U15+V15) | X15: =U15+V15-W15 | Y15: =MIN(X15,MAX(0,$B15-((E$5<W$5)*F15+(K$5<W$5)*L15+(Q$5<W$5)*R15+(AC$5<W$5)*AD15+(AI$5<W$5)*AJ15+(AO$5<W$5)*AP15+(AU$5<W$5)*AV15))) | Z15: =IF(X15-Y15<0.005,0,X15-Y15) | AA15: =AF14 | AB15: =AA15*Plan!D10/100/12 | AC15: =MIN(Plan!E10,AA15+AB15) | AD15: =AA15+AB15-AC15 | AE15: =MIN(AD15,MAX(0,$B15-((E$5<AC$5)*F15+(K$5<AC$5)*L15+(Q$5<AC$5)*R15+(W$5<AC$5)*X15+(AI$5<AC$5)*AJ15+(AO$5<AC$5)*AP15+(AU$5<AC$5)*AV15))) | AF15: =IF(AD15-AE15<0.005,0,AD15-AE15) | AG15: =AL14 | AH15: =AG15*Plan!D11/100/12 | AI15: =MIN(Plan!E11,AG15+AH15) | AJ15: =AG15+AH15-AI15 | AK15: =MIN(AJ15,MAX(0,$B15-((E$5<AI$5)*F15+(K$5<AI$5)*L15+(Q$5<AI$5)*R15+(W$5<AI$5)*X15+(AC$5<AI$5)*AD15+(AO$5<AI$5)*AP15+(AU$5<AI$5)*AV15))) | AL15: =IF(AJ15-AK15<0.005,0,AJ15-AK15) | AM15: =AR14 | AN15: =AM15*Plan!D12/100/12 | AO15: =MIN(Plan!E12,AM15+AN15) | AP15: =AM15+AN15-AO15 | AQ15: =MIN(AP15,MAX(0,$B15-((E$5<AO$5)*F15+(K$5<AO$5)*L15+(Q$5<AO$5)*R15+(W$5<AO$5)*X15+(AC$5<AO$5)*AD15+(AI$5<AO$5)*AJ15+(AU$5<AO$5)*AV15))) | AR15: =IF(AP15-AQ15<0.005,0,AP15-AQ15) | AS15: =AX14 | AT15: =AS15*Plan!D13/100/12 | AU15: =MIN(Plan!E13,AS15+AT15) | AV15: =AS15+AT15-AU15 | AW15: =MIN(AV15,MAX(0,$B15-((E$5<AU$5)*F15+(K$5<AU$5)*L15+(Q$5<AU$5)*R15+(W$5<AU$5)*X15+(AC$5<AU$5)*AD15+(AI$5<AU$5)*AJ15+(AO$5<AU$5)*AP15))) | AX15: =IF(AV15-AW15<0.005,0,AV15-AW15) | BC15: =H15+N15+T15+Z15+AF15+AL15+AR15+AX15
A16: 10 | B16: =MAX(0,$B$3-(E16+K16+Q16+W16+AC16+AI16+AO16+AU16)) | C16: =H15 | D16: =C16*Plan!D6/100/12 | E16: =MIN(Plan!E6,C16+D16) | F16: =C16+D16-E16 | G16: =MIN(F16,MAX(0,$B16-((K$5<E$5)*L16+(Q$5<E$5)*R16+(W$5<E$5)*X16+(AC$5<E$5)*AD16+(AI$5<E$5)*AJ16+(AO$5<E$5)*AP16+(AU$5<E$5)*AV16))) | H16: =IF(F16-G16<0.005,0,F16-G16) | I16: =N15 | J16: =I16*Plan!D7/100/12 | K16: =MIN(Plan!E7,I16+J16) | L16: =I16+J16-K16 | M16: =MIN(L16,MAX(0,$B16-((E$5<K$5)*F16+(Q$5<K$5)*R16+(W$5<K$5)*X16+(AC$5<K$5)*AD16+(AI$5<K$5)*AJ16+(AO$5<K$5)*AP16+(AU$5<K$5)*AV16))) | N16: =IF(L16-M16<0.005,0,L16-M16) | O16: =T15 | P16: =O16*Plan!D8/100/12 | Q16: =MIN(Plan!E8,O16+P16) | R16: =O16+P16-Q16 | S16: =MIN(R16,MAX(0,$B16-((E$5<Q$5)*F16+(K$5<Q$5)*L16+(W$5<Q$5)*X16+(AC$5<Q$5)*AD16+(AI$5<Q$5)*AJ16+(AO$5<Q$5)*AP16+(AU$5<Q$5)*AV16))) | T16: =IF(R16-S16<0.005,0,R16-S16) | U16: =Z15 | V16: =U16*Plan!D9/100/12 | W16: =MIN(Plan!E9,U16+V16) | X16: =U16+V16-W16 | Y16: =MIN(X16,MAX(0,$B16-((E$5<W$5)*F16+(K$5<W$5)*L16+(Q$5<W$5)*R16+(AC$5<W$5)*AD16+(AI$5<W$5)*AJ16+(AO$5<W$5)*AP16+(AU$5<W$5)*AV16))) | Z16: =IF(X16-Y16<0.005,0,X16-Y16) | AA16: =AF15 | AB16: =AA16*Plan!D10/100/12 | AC16: =MIN(Plan!E10,AA16+AB16) | AD16: =AA16+AB16-AC16 | AE16: =MIN(AD16,MAX(0,$B16-((E$5<AC$5)*F16+(K$5<AC$5)*L16+(Q$5<AC$5)*R16+(W$5<AC$5)*X16+(AI$5<AC$5)*AJ16+(AO$5<AC$5)*AP16+(AU$5<AC$5)*AV16))) | AF16: =IF(AD16-AE16<0.005,0,AD16-AE16) | AG16: =AL15 | AH16: =AG16*Plan!D11/100/12 | AI16: =MIN(Plan!E11,AG16+AH16) | AJ16: =AG16+AH16-AI16 | AK16: =MIN(AJ16,MAX(0,$B16-((E$5<AI$5)*F16+(K$5<AI$5)*L16+(Q$5<AI$5)*R16+(W$5<AI$5)*X16+(AC$5<AI$5)*AD16+(AO$5<AI$5)*AP16+(AU$5<AI$5)*AV16))) | AL16: =IF(AJ16-AK16<0.005,0,AJ16-AK16) | AM16: =AR15 | AN16: =AM16*Plan!D12/100/12 | AO16: =MIN(Plan!E12,AM16+AN16) | AP16: =AM16+AN16-AO16 | AQ16: =MIN(AP16,MAX(0,$B16-((E$5<AO$5)*F16+(K$5<AO$5)*L16+(Q$5<AO$5)*R16+(W$5<AO$5)*X16+(AC$5<AO$5)*AD16+(AI$5<AO$5)*AJ16+(AU$5<AO$5)*AV16))) | AR16: =IF(AP16-AQ16<0.005,0,AP16-AQ16) | AS16: =AX15 | AT16: =AS16*Plan!D13/100/12 | AU16: =MIN(Plan!E13,AS16+AT16) | AV16: =AS16+AT16-AU16 | AW16: =MIN(AV16,MAX(0,$B16-((E$5<AU$5)*F16+(K$5<AU$5)*L16+(Q$5<AU$5)*R16+(W$5<AU$5)*X16+(AC$5<AU$5)*AD16+(AI$5<AU$5)*AJ16+(AO$5<AU$5)*AP16))) | AX16: =IF(AV16-AW16<0.005,0,AV16-AW16) | BC16: =H16+N16+T16+Z16+AF16+AL16+AR16+AX16
A17: 11 | B17: =MAX(0,$B$3-(E17+K17+Q17+W17+AC17+AI17+AO17+AU17)) | C17: =H16 | D17: =C17*Plan!D6/100/12 | E17: =MIN(Plan!E6,C17+D17) | F17: =C17+D17-E17 | G17: =MIN(F17,MAX(0,$B17-((K$5<E$5)*L17+(Q$5<E$5)*R17+(W$5<E$5)*X17+(AC$5<E$5)*AD17+(AI$5<E$5)*AJ17+(AO$5<E$5)*AP17+(AU$5<E$5)*AV17))) | H17: =IF(F17-G17<0.005,0,F17-G17) | I17: =N16 | J17: =I17*Plan!D7/100/12 | K17: =MIN(Plan!E7,I17+J17) | L17: =I17+J17-K17 | M17: =MIN(L17,MAX(0,$B17-((E$5<K$5)*F17+(Q$5<K$5)*R17+(W$5<K$5)*X17+(AC$5<K$5)*AD17+(AI$5<K$5)*AJ17+(AO$5<K$5)*AP17+(AU$5<K$5)*AV17))) | N17: =IF(L17-M17<0.005,0,L17-M17) | O17: =T16 | P17: =O17*Plan!D8/100/12 | Q17: =MIN(Plan!E8,O17+P17) | R17: =O17+P17-Q17 | S17: =MIN(R17,MAX(0,$B17-((E$5<Q$5)*F17+(K$5<Q$5)*L17+(W$5<Q$5)*X17+(AC$5<Q$5)*AD17+(AI$5<Q$5)*AJ17+(AO$5<Q$5)*AP17+(AU$5<Q$5)*AV17))) | T17: =IF(R17-S17<0.005,0,R17-S17) | U17: =Z16 | V17: =U17*Plan!D9/100/12 | W17: =MIN(Plan!E9,U17+V17) | X17: =U17+V17-W17 | Y17: =MIN(X17,MAX(0,$B17-((E$5<W$5)*F17+(K$5<W$5)*L17+(Q$5<W$5)*R17+(AC$5<W$5)*AD17+(AI$5<W$5)*AJ17+(AO$5<W$5)*AP17+(AU$5<W$5)*AV17))) | Z17: =IF(X17-Y17<0.005,0,X17-Y17) | AA17: =AF16 | AB17: =AA17*Plan!D10/100/12 | AC17: =MIN(Plan!E10,AA17+AB17) | AD17: =AA17+AB17-AC17 | AE17: =MIN(AD17,MAX(0,$B17-((E$5<AC$5)*F17+(K$5<AC$5)*L17+(Q$5<AC$5)*R17+(W$5<AC$5)*X17+(AI$5<AC$5)*AJ17+(AO$5<AC$5)*AP17+(AU$5<AC$5)*AV17))) | AF17: =IF(AD17-AE17<0.005,0,AD17-AE17) | AG17: =AL16 | AH17: =AG17*Plan!D11/100/12 | AI17: =MIN(Plan!E11,AG17+AH17) | AJ17: =AG17+AH17-AI17 | AK17: =MIN(AJ17,MAX(0,$B17-((E$5<AI$5)*F17+(K$5<AI$5)*L17+(Q$5<AI$5)*R17+(W$5<AI$5)*X17+(AC$5<AI$5)*AD17+(AO$5<AI$5)*AP17+(AU$5<AI$5)*AV17))) | AL17: =IF(AJ17-AK17<0.005,0,AJ17-AK17) | AM17: =AR16 | AN17: =AM17*Plan!D12/100/12 | AO17: =MIN(Plan!E12,AM17+AN17) | AP17: =AM17+AN17-AO17 | AQ17: =MIN(AP17,MAX(0,$B17-((E$5<AO$5)*F17+(K$5<AO$5)*L17+(Q$5<AO$5)*R17+(W$5<AO$5)*X17+(AC$5<AO$5)*AD17+(AI$5<AO$5)*AJ17+(AU$5<AO$5)*AV17))) | AR17: =IF(AP17-AQ17<0.005,0,AP17-AQ17) | AS17: =AX16 | AT17: =AS17*Plan!D13/100/12 | AU17: =MIN(Plan!E13,AS17+AT17) | AV17: =AS17+AT17-AU17 | AW17: =MIN(AV17,MAX(0,$B17-((E$5<AU$5)*F17+(K$5<AU$5)*L17+(Q$5<AU$5)*R17+(W$5<AU$5)*X17+(AC$5<AU$5)*AD17+(AI$5<AU$5)*AJ17+(AO$5<AU$5)*AP17))) | AX17: =IF(AV17-AW17<0.005,0,AV17-AW17) | BC17: =H17+N17+T17+Z17+AF17+AL17+AR17+AX17
A18: 12 | B18: =MAX(0,$B$3-(E18+K18+Q18+W18+AC18+AI18+AO18+AU18)) | C18: =H17 | D18: =C18*Plan!D6/100/12 | E18: =MIN(Plan!E6,C18+D18) | F18: =C18+D18-E18 | G18: =MIN(F18,MAX(0,$B18-((K$5<E$5)*L18+(Q$5<E$5)*R18+(W$5<E$5)*X18+(AC$5<E$5)*AD18+(AI$5<E$5)*AJ18+(AO$5<E$5)*AP18+(AU$5<E$5)*AV18))) | H18: =IF(F18-G18<0.005,0,F18-G18) | I18: =N17 | J18: =I18*Plan!D7/100/12 | K18: =MIN(Plan!E7,I18+J18) | L18: =I18+J18-K18 | M18: =MIN(L18,MAX(0,$B18-((E$5<K$5)*F18+(Q$5<K$5)*R18+(W$5<K$5)*X18+(AC$5<K$5)*AD18+(AI$5<K$5)*AJ18+(AO$5<K$5)*AP18+(AU$5<K$5)*AV18))) | N18: =IF(L18-M18<0.005,0,L18-M18) | O18: =T17 | P18: =O18*Plan!D8/100/12 | Q18: =MIN(Plan!E8,O18+P18) | R18: =O18+P18-Q18 | S18: =MIN(R18,MAX(0,$B18-((E$5<Q$5)*F18+(K$5<Q$5)*L18+(W$5<Q$5)*X18+(AC$5<Q$5)*AD18+(AI$5<Q$5)*AJ18+(AO$5<Q$5)*AP18+(AU$5<Q$5)*AV18))) | T18: =IF(R18-S18<0.005,0,R18-S18) | U18: =Z17 | V18: =U18*Plan!D9/100/12 | W18: =MIN(Plan!E9,U18+V18) | X18: =U18+V18-W18 | Y18: =MIN(X18,MAX(0,$B18-((E$5<W$5)*F18+(K$5<W$5)*L18+(Q$5<W$5)*R18+(AC$5<W$5)*AD18+(AI$5<W$5)*AJ18+(AO$5<W$5)*AP18+(AU$5<W$5)*AV18))) | Z18: =IF(X18-Y18<0.005,0,X18-Y18) | AA18: =AF17 | AB18: =AA18*Plan!D10/100/12 | AC18: =MIN(Plan!E10,AA18+AB18) | AD18: =AA18+AB18-AC18 | AE18: =MIN(AD18,MAX(0,$B18-((E$5<AC$5)*F18+(K$5<AC$5)*L18+(Q$5<AC$5)*R18+(W$5<AC$5)*X18+(AI$5<AC$5)*AJ18+(AO$5<AC$5)*AP18+(AU$5<AC$5)*AV18))) | AF18: =IF(AD18-AE18<0.005,0,AD18-AE18) | AG18: =AL17 | AH18: =AG18*Plan!D11/100/12 | AI18: =MIN(Plan!E11,AG18+AH18) | AJ18: =AG18+AH18-AI18 | AK18: =MIN(AJ18,MAX(0,$B18-((E$5<AI$5)*F18+(K$5<AI$5)*L18+(Q$5<AI$5)*R18+(W$5<AI$5)*X18+(AC$5<AI$5)*AD18+(AO$5<AI$5)*AP18+(AU$5<AI$5)*AV18))) | AL18: =IF(AJ18-AK18<0.005,0,AJ18-AK18) | AM18: =AR17 | AN18: =AM18*Plan!D12/100/12 | AO18: =MIN(Plan!E12,AM18+AN18) | AP18: =AM18+AN18-AO18 | AQ18: =MIN(AP18,MAX(0,$B18-((E$5<AO$5)*F18+(K$5<AO$5)*L18+(Q$5<AO$5)*R18+(W$5<AO$5)*X18+(AC$5<AO$5)*AD18+(AI$5<AO$5)*AJ18+(AU$5<AO$5)*AV18))) | AR18: =IF(AP18-AQ18<0.005,0,AP18-AQ18) | AS18: =AX17 | AT18: =AS18*Plan!D13/100/12 | AU18: =MIN(Plan!E13,AS18+AT18) | AV18: =AS18+AT18-AU18 | AW18: =MIN(AV18,MAX(0,$B18-((E$5<AU$5)*F18+(K$5<AU$5)*L18+(Q$5<AU$5)*R18+(W$5<AU$5)*X18+(AC$5<AU$5)*AD18+(AI$5<AU$5)*AJ18+(AO$5<AU$5)*AP18))) | AX18: =IF(AV18-AW18<0.005,0,AV18-AW18) | BC18: =H18+N18+T18+Z18+AF18+AL18+AR18+AX18
A19: 13 | B19: =MAX(0,$B$3-(E19+K19+Q19+W19+AC19+AI19+AO19+AU19)) | C19: =H18 | D19: =C19*Plan!D6/100/12 | E19: =MIN(Plan!E6,C19+D19) | F19: =C19+D19-E19 | G19: =MIN(F19,MAX(0,$B19-((K$5<E$5)*L19+(Q$5<E$5)*R19+(W$5<E$5)*X19+(AC$5<E$5)*AD19+(AI$5<E$5)*AJ19+(AO$5<E$5)*AP19+(AU$5<E$5)*AV19))) | H19: =IF(F19-G19<0.005,0,F19-G19) | I19: =N18 | J19: =I19*Plan!D7/100/12 | K19: =MIN(Plan!E7,I19+J19) | L19: =I19+J19-K19 | M19: =MIN(L19,MAX(0,$B19-((E$5<K$5)*F19+(Q$5<K$5)*R19+(W$5<K$5)*X19+(AC$5<K$5)*AD19+(AI$5<K$5)*AJ19+(AO$5<K$5)*AP19+(AU$5<K$5)*AV19))) | N19: =IF(L19-M19<0.005,0,L19-M19) | O19: =T18 | P19: =O19*Plan!D8/100/12 | Q19: =MIN(Plan!E8,O19+P19) | R19: =O19+P19-Q19 | S19: =MIN(R19,MAX(0,$B19-((E$5<Q$5)*F19+(K$5<Q$5)*L19+(W$5<Q$5)*X19+(AC$5<Q$5)*AD19+(AI$5<Q$5)*AJ19+(AO$5<Q$5)*AP19+(AU$5<Q$5)*AV19))) | T19: =IF(R19-S19<0.005,0,R19-S19) | U19: =Z18 | V19: =U19*Plan!D9/100/12 | W19: =MIN(Plan!E9,U19+V19) | X19: =U19+V19-W19 | Y19: =MIN(X19,MAX(0,$B19-((E$5<W$5)*F19+(K$5<W$5)*L19+(Q$5<W$5)*R19+(AC$5<W$5)*AD19+(AI$5<W$5)*AJ19+(AO$5<W$5)*AP19+(AU$5<W$5)*AV19))) | Z19: =IF(X19-Y19<0.005,0,X19-Y19) | AA19: =AF18 | AB19: =AA19*Plan!D10/100/12 | AC19: =MIN(Plan!E10,AA19+AB19) | AD19: =AA19+AB19-AC19 | AE19: =MIN(AD19,MAX(0,$B19-((E$5<AC$5)*F19+(K$5<AC$5)*L19+(Q$5<AC$5)*R19+(W$5<AC$5)*X19+(AI$5<AC$5)*AJ19+(AO$5<AC$5)*AP19+(AU$5<AC$5)*AV19))) | AF19: =IF(AD19-AE19<0.005,0,AD19-AE19) | AG19: =AL18 | AH19: =AG19*Plan!D11/100/12 | AI19: =MIN(Plan!E11,AG19+AH19) | AJ19: =AG19+AH19-AI19 | AK19: =MIN(AJ19,MAX(0,$B19-((E$5<AI$5)*F19+(K$5<AI$5)*L19+(Q$5<AI$5)*R19+(W$5<AI$5)*X19+(AC$5<AI$5)*AD19+(AO$5<AI$5)*AP19+(AU$5<AI$5)*AV19))) | AL19: =IF(AJ19-AK19<0.005,0,AJ19-AK19) | AM19: =AR18 | AN19: =AM19*Plan!D12/100/12 | AO19: =MIN(Plan!E12,AM19+AN19) | AP19: =AM19+AN19-AO19 | AQ19: =MIN(AP19,MAX(0,$B19-((E$5<AO$5)*F19+(K$5<AO$5)*L19+(Q$5<AO$5)*R19+(W$5<AO$5)*X19+(AC$5<AO$5)*AD19+(AI$5<AO$5)*AJ19+(AU$5<AO$5)*AV19))) | AR19: =IF(AP19-AQ19<0.005,0,AP19-AQ19) | AS19: =AX18 | AT19: =AS19*Plan!D13/100/12 | AU19: =MIN(Plan!E13,AS19+AT19) | AV19: =AS19+AT19-AU19 | AW19: =MIN(AV19,MAX(0,$B19-((E$5<AU$5)*F19+(K$5<AU$5)*L19+(Q$5<AU$5)*R19+(W$5<AU$5)*X19+(AC$5<AU$5)*AD19+(AI$5<AU$5)*AJ19+(AO$5<AU$5)*AP19))) | AX19: =IF(AV19-AW19<0.005,0,AV19-AW19) | BC19: =H19+N19+T19+Z19+AF19+AL19+AR19+AX19
A20: 14 | B20: =MAX(0,$B$3-(E20+K20+Q20+W20+AC20+AI20+AO20+AU20)) | C20: =H19 | D20: =C20*Plan!D6/100/12 | E20: =MIN(Plan!E6,C20+D20) | F20: =C20+D20-E20 | G20: =MIN(F20,MAX(0,$B20-((K$5<E$5)*L20+(Q$5<E$5)*R20+(W$5<E$5)*X20+(AC$5<E$5)*AD20+(AI$5<E$5)*AJ20+(AO$5<E$5)*AP20+(AU$5<E$5)*AV20))) | H20: =IF(F20-G20<0.005,0,F20-G20) | I20: =N19 | J20: =I20*Plan!D7/100/12 | K20: =MIN(Plan!E7,I20+J20) | L20: =I20+J20-K20 | M20: =MIN(L20,MAX(0,$B20-((E$5<K$5)*F20+(Q$5<K$5)*R20+(W$5<K$5)*X20+(AC$5<K$5)*AD20+(AI$5<K$5)*AJ20+(AO$5<K$5)*AP20+(AU$5<K$5)*AV20))) | N20: =IF(L20-M20<0.005,0,L20-M20) | O20: =T19 | P20: =O20*Plan!D8/100/12 | Q20: =MIN(Plan!E8,O20+P20) | R20: =O20+P20-Q20 | S20: =MIN(R20,MAX(0,$B20-((E$5<Q$5)*F20+(K$5<Q$5)*L20+(W$5<Q$5)*X20+(AC$5<Q$5)*AD20+(AI$5<Q$5)*AJ20+(AO$5<Q$5)*AP20+(AU$5<Q$5)*AV20))) | T20: =IF(R20-S20<0.005,0,R20-S20) | U20: =Z19 | V20: =U20*Plan!D9/100/12 | W20: =MIN(Plan!E9,U20+V20) | X20: =U20+V20-W20 | Y20: =MIN(X20,MAX(0,$B20-((E$5<W$5)*F20+(K$5<W$5)*L20+(Q$5<W$5)*R20+(AC$5<W$5)*AD20+(AI$5<W$5)*AJ20+(AO$5<W$5)*AP20+(AU$5<W$5)*AV20))) | Z20: =IF(X20-Y20<0.005,0,X20-Y20) | AA20: =AF19 | AB20: =AA20*Plan!D10/100/12 | AC20: =MIN(Plan!E10,AA20+AB20) | AD20: =AA20+AB20-AC20 | AE20: =MIN(AD20,MAX(0,$B20-((E$5<AC$5)*F20+(K$5<AC$5)*L20+(Q$5<AC$5)*R20+(W$5<AC$5)*X20+(AI$5<AC$5)*AJ20+(AO$5<AC$5)*AP20+(AU$5<AC$5)*AV20))) | AF20: =IF(AD20-AE20<0.005,0,AD20-AE20) | AG20: =AL19 | AH20: =AG20*Plan!D11/100/12 | AI20: =MIN(Plan!E11,AG20+AH20) | AJ20: =AG20+AH20-AI20 | AK20: =MIN(AJ20,MAX(0,$B20-((E$5<AI$5)*F20+(K$5<AI$5)*L20+(Q$5<AI$5)*R20+(W$5<AI$5)*X20+(AC$5<AI$5)*AD20+(AO$5<AI$5)*AP20+(AU$5<AI$5)*AV20))) | AL20: =IF(AJ20-AK20<0.005,0,AJ20-AK20) | AM20: =AR19 | AN20: =AM20*Plan!D12/100/12 | AO20: =MIN(Plan!E12,AM20+AN20) | AP20: =AM20+AN20-AO20 | AQ20: =MIN(AP20,MAX(0,$B20-((E$5<AO$5)*F20+(K$5<AO$5)*L20+(Q$5<AO$5)*R20+(W$5<AO$5)*X20+(AC$5<AO$5)*AD20+(AI$5<AO$5)*AJ20+(AU$5<AO$5)*AV20))) | AR20: =IF(AP20-AQ20<0.005,0,AP20-AQ20) | AS20: =AX19 | AT20: =AS20*Plan!D13/100/12 | AU20: =MIN(Plan!E13,AS20+AT20) | AV20: =AS20+AT20-AU20 | AW20: =MIN(AV20,MAX(0,$B20-((E$5<AU$5)*F20+(K$5<AU$5)*L20+(Q$5<AU$5)*R20+(W$5<AU$5)*X20+(AC$5<AU$5)*AD20+(AI$5<AU$5)*AJ20+(AO$5<AU$5)*AP20))) | AX20: =IF(AV20-AW20<0.005,0,AV20-AW20) | BC20: =H20+N20+T20+Z20+AF20+AL20+AR20+AX20
A21: 15 | B21: =MAX(0,$B$3-(E21+K21+Q21+W21+AC21+AI21+AO21+AU21)) | C21: =H20 | D21: =C21*Plan!D6/100/12 | E21: =MIN(Plan!E6,C21+D21) | F21: =C21+D21-E21 | G21: =MIN(F21,MAX(0,$B21-((K$5<E$5)*L21+(Q$5<E$5)*R21+(W$5<E$5)*X21+(AC$5<E$5)*AD21+(AI$5<E$5)*AJ21+(AO$5<E$5)*AP21+(AU$5<E$5)*AV21))) | H21: =IF(F21-G21<0.005,0,F21-G21) | I21: =N20 | J21: =I21*Plan!D7/100/12 | K21: =MIN(Plan!E7,I21+J21) | L21: =I21+J21-K21 | M21: =MIN(L21,MAX(0,$B21-((E$5<K$5)*F21+(Q$5<K$5)*R21+(W$5<K$5)*X21+(AC$5<K$5)*AD21+(AI$5<K$5)*AJ21+(AO$5<K$5)*AP21+(AU$5<K$5)*AV21))) | N21: =IF(L21-M21<0.005,0,L21-M21) | O21: =T20 | P21: =O21*Plan!D8/100/12 | Q21: =MIN(Plan!E8,O21+P21) | R21: =O21+P21-Q21 | S21: =MIN(R21,MAX(0,$B21-((E$5<Q$5)*F21+(K$5<Q$5)*L21+(W$5<Q$5)*X21+(AC$5<Q$5)*AD21+(AI$5<Q$5)*AJ21+(AO$5<Q$5)*AP21+(AU$5<Q$5)*AV21))) | T21: =IF(R21-S21<0.005,0,R21-S21) | U21: =Z20 | V21: =U21*Plan!D9/100/12 | W21: =MIN(Plan!E9,U21+V21) | X21: =U21+V21-W21 | Y21: =MIN(X21,MAX(0,$B21-((E$5<W$5)*F21+(K$5<W$5)*L21+(Q$5<W$5)*R21+(AC$5<W$5)*AD21+(AI$5<W$5)*AJ21+(AO$5<W$5)*AP21+(AU$5<W$5)*AV21))) | Z21: =IF(X21-Y21<0.005,0,X21-Y21) | AA21: =AF20 | AB21: =AA21*Plan!D10/100/12 | AC21: =MIN(Plan!E10,AA21+AB21) | AD21: =AA21+AB21-AC21 | AE21: =MIN(AD21,MAX(0,$B21-((E$5<AC$5)*F21+(K$5<AC$5)*L21+(Q$5<AC$5)*R21+(W$5<AC$5)*X21+(AI$5<AC$5)*AJ21+(AO$5<AC$5)*AP21+(AU$5<AC$5)*AV21))) | AF21: =IF(AD21-AE21<0.005,0,AD21-AE21) | AG21: =AL20 | AH21: =AG21*Plan!D11/100/12 | AI21: =MIN(Plan!E11,AG21+AH21) | AJ21: =AG21+AH21-AI21 | AK21: =MIN(AJ21,MAX(0,$B21-((E$5<AI$5)*F21+(K$5<AI$5)*L21+(Q$5<AI$5)*R21+(W$5<AI$5)*X21+(AC$5<AI$5)*AD21+(AO$5<AI$5)*AP21+(AU$5<AI$5)*AV21))) | AL21: =IF(AJ21-AK21<0.005,0,AJ21-AK21) | AM21: =AR20 | AN21: =AM21*Plan!D12/100/12 | AO21: =MIN(Plan!E12,AM21+AN21) | AP21: =AM21+AN21-AO21 | AQ21: =MIN(AP21,MAX(0,$B21-((E$5<AO$5)*F21+(K$5<AO$5)*L21+(Q$5<AO$5)*R21+(W$5<AO$5)*X21+(AC$5<AO$5)*AD21+(AI$5<AO$5)*AJ21+(AU$5<AO$5)*AV21))) | AR21: =IF(AP21-AQ21<0.005,0,AP21-AQ21) | AS21: =AX20 | AT21: =AS21*Plan!D13/100/12 | AU21: =MIN(Plan!E13,AS21+AT21) | AV21: =AS21+AT21-AU21 | AW21: =MIN(AV21,MAX(0,$B21-((E$5<AU$5)*F21+(K$5<AU$5)*L21+(Q$5<AU$5)*R21+(W$5<AU$5)*X21+(AC$5<AU$5)*AD21+(AI$5<AU$5)*AJ21+(AO$5<AU$5)*AP21))) | AX21: =IF(AV21-AW21<0.005,0,AV21-AW21) | BC21: =H21+N21+T21+Z21+AF21+AL21+AR21+AX21
A22: 16 | B22: =MAX(0,$B$3-(E22+K22+Q22+W22+AC22+AI22+AO22+AU22)) | C22: =H21 | D22: =C22*Plan!D6/100/12 | E22: =MIN(Plan!E6,C22+D22) | F22: =C22+D22-E22 | G22: =MIN(F22,MAX(0,$B22-((K$5<E$5)*L22+(Q$5<E$5)*R22+(W$5<E$5)*X22+(AC$5<E$5)*AD22+(AI$5<E$5)*AJ22+(AO$5<E$5)*AP22+(AU$5<E$5)*AV22))) | H22: =IF(F22-G22<0.005,0,F22-G22) | I22: =N21 | J22: =I22*Plan!D7/100/12 | K22: =MIN(Plan!E7,I22+J22) | L22: =I22+J22-K22 | M22: =MIN(L22,MAX(0,$B22-((E$5<K$5)*F22+(Q$5<K$5)*R22+(W$5<K$5)*X22+(AC$5<K$5)*AD22+(AI$5<K$5)*AJ22+(AO$5<K$5)*AP22+(AU$5<K$5)*AV22))) | N22: =IF(L22-M22<0.005,0,L22-M22) | O22: =T21 | P22: =O22*Plan!D8/100/12 | Q22: =MIN(Plan!E8,O22+P22) | R22: =O22+P22-Q22 | S22: =MIN(R22,MAX(0,$B22-((E$5<Q$5)*F22+(K$5<Q$5)*L22+(W$5<Q$5)*X22+(AC$5<Q$5)*AD22+(AI$5<Q$5)*AJ22+(AO$5<Q$5)*AP22+(AU$5<Q$5)*AV22))) | T22: =IF(R22-S22<0.005,0,R22-S22) | U22: =Z21 | V22: =U22*Plan!D9/100/12 | W22: =MIN(Plan!E9,U22+V22) | X22: =U22+V22-W22 | Y22: =MIN(X22,MAX(0,$B22-((E$5<W$5)*F22+(K$5<W$5)*L22+(Q$5<W$5)*R22+(AC$5<W$5)*AD22+(AI$5<W$5)*AJ22+(AO$5<W$5)*AP22+(AU$5<W$5)*AV22))) | Z22: =IF(X22-Y22<0.005,0,X22-Y22) | AA22: =AF21 | AB22: =AA22*Plan!D10/100/12 | AC22: =MIN(Plan!E10,AA22+AB22) | AD22: =AA22+AB22-AC22 | AE22: =MIN(AD22,MAX(0,$B22-((E$5<AC$5)*F22+(K$5<AC$5)*L22+(Q$5<AC$5)*R22+(W$5<AC$5)*X22+(AI$5<AC$5)*AJ22+(AO$5<AC$5)*AP22+(AU$5<AC$5)*AV22))) | AF22: =IF(AD22-AE22<0.005,0,AD22-AE22) | AG22: =AL21 | AH22: =AG22*Plan!D11/100/12 | AI22: =MIN(Plan!E11,AG22+AH22) | AJ22: =AG22+AH22-AI22 | AK22: =MIN(AJ22,MAX(0,$B22-((E$5<AI$5)*F22+(K$5<AI$5)*L22+(Q$5<AI$5)*R22+(W$5<AI$5)*X22+(AC$5<AI$5)*AD22+(AO$5<AI$5)*AP22+(AU$5<AI$5)*AV22))) | AL22: =IF(AJ22-AK22<0.005,0,AJ22-AK22) | AM22: =AR21 | AN22: =AM22*Plan!D12/100/12 | AO22: =MIN(Plan!E12,AM22+AN22) | AP22: =AM22+AN22-AO22 | AQ22: =MIN(AP22,MAX(0,$B22-((E$5<AO$5)*F22+(K$5<AO$5)*L22+(Q$5<AO$5)*R22+(W$5<AO$5)*X22+(AC$5<AO$5)*AD22+(AI$5<AO$5)*AJ22+(AU$5<AO$5)*AV22))) | AR22: =IF(AP22-AQ22<0.005,0,AP22-AQ22) | AS22: =AX21 | AT22: =AS22*Plan!D13/100/12 | AU22: =MIN(Plan!E13,AS22+AT22) | AV22: =AS22+AT22-AU22 | AW22: =MIN(AV22,MAX(0,$B22-((E$5<AU$5)*F22+(K$5<AU$5)*L22+(Q$5<AU$5)*R22+(W$5<AU$5)*X22+(AC$5<AU$5)*AD22+(AI$5<AU$5)*AJ22+(AO$5<AU$5)*AP22))) | AX22: =IF(AV22-AW22<0.005,0,AV22-AW22) | BC22: =H22+N22+T22+Z22+AF22+AL22+AR22+AX22
A23: 17 | B23: =MAX(0,$B$3-(E23+K23+Q23+W23+AC23+AI23+AO23+AU23)) | C23: =H22 | D23: =C23*Plan!D6/100/12 | E23: =MIN(Plan!E6,C23+D23) | F23: =C23+D23-E23 | G23: =MIN(F23,MAX(0,$B23-((K$5<E$5)*L23+(Q$5<E$5)*R23+(W$5<E$5)*X23+(AC$5<E$5)*AD23+(AI$5<E$5)*AJ23+(AO$5<E$5)*AP23+(AU$5<E$5)*AV23))) | H23: =IF(F23-G23<0.005,0,F23-G23) | I23: =N22 | J23: =I23*Plan!D7/100/12 | K23: =MIN(Plan!E7,I23+J23) | L23: =I23+J23-K23 | M23: =MIN(L23,MAX(0,$B23-((E$5<K$5)*F23+(Q$5<K$5)*R23+(W$5<K$5)*X23+(AC$5<K$5)*AD23+(AI$5<K$5)*AJ23+(AO$5<K$5)*AP23+(AU$5<K$5)*AV23))) | N23: =IF(L23-M23<0.005,0,L23-M23) | O23: =T22 | P23: =O23*Plan!D8/100/12 | Q23: =MIN(Plan!E8,O23+P23) | R23: =O23+P23-Q23 | S23: =MIN(R23,MAX(0,$B23-((E$5<Q$5)*F23+(K$5<Q$5)*L23+(W$5<Q$5)*X23+(AC$5<Q$5)*AD23+(AI$5<Q$5)*AJ23+(AO$5<Q$5)*AP23+(AU$5<Q$5)*AV23))) | T23: =IF(R23-S23<0.005,0,R23-S23) | U23: =Z22 | V23: =U23*Plan!D9/100/12 | W23: =MIN(Plan!E9,U23+V23) | X23: =U23+V23-W23 | Y23: =MIN(X23,MAX(0,$B23-((E$5<W$5)*F23+(K$5<W$5)*L23+(Q$5<W$5)*R23+(AC$5<W$5)*AD23+(AI$5<W$5)*AJ23+(AO$5<W$5)*AP23+(AU$5<W$5)*AV23))) | Z23: =IF(X23-Y23<0.005,0,X23-Y23) | AA23: =AF22 | AB23: =AA23*Plan!D10/100/12 | AC23: =MIN(Plan!E10,AA23+AB23) | AD23: =AA23+AB23-AC23 | AE23: =MIN(AD23,MAX(0,$B23-((E$5<AC$5)*F23+(K$5<AC$5)*L23+(Q$5<AC$5)*R23+(W$5<AC$5)*X23+(AI$5<AC$5)*AJ23+(AO$5<AC$5)*AP23+(AU$5<AC$5)*AV23))) | AF23: =IF(AD23-AE23<0.005,0,AD23-AE23) | AG23: =AL22 | AH23: =AG23*Plan!D11/100/12 | AI23: =MIN(Plan!E11,AG23+AH23) | AJ23: =AG23+AH23-AI23 | AK23: =MIN(AJ23,MAX(0,$B23-((E$5<AI$5)*F23+(K$5<AI$5)*L23+(Q$5<AI$5)*R23+(W$5<AI$5)*X23+(AC$5<AI$5)*AD23+(AO$5<AI$5)*AP23+(AU$5<AI$5)*AV23))) | AL23: =IF(AJ23-AK23<0.005,0,AJ23-AK23) | AM23: =AR22 | AN23: =AM23*Plan!D12/100/12 | AO23: =MIN(Plan!E12,AM23+AN23) | AP23: =AM23+AN23-AO23 | AQ23: =MIN(AP23,MAX(0,$B23-((E$5<AO$5)*F23+(K$5<AO$5)*L23+(Q$5<AO$5)*R23+(W$5<AO$5)*X23+(AC$5<AO$5)*AD23+(AI$5<AO$5)*AJ23+(AU$5<AO$5)*AV23))) | AR23: =IF(AP23-AQ23<0.005,0,AP23-AQ23) | AS23: =AX22 | AT23: =AS23*Plan!D13/100/12 | AU23: =MIN(Plan!E13,AS23+AT23) | AV23: =AS23+AT23-AU23 | AW23: =MIN(AV23,MAX(0,$B23-((E$5<AU$5)*F23+(K$5<AU$5)*L23+(Q$5<AU$5)*R23+(W$5<AU$5)*X23+(AC$5<AU$5)*AD23+(AI$5<AU$5)*AJ23+(AO$5<AU$5)*AP23))) | AX23: =IF(AV23-AW23<0.005,0,AV23-AW23) | BC23: =H23+N23+T23+Z23+AF23+AL23+AR23+AX23
A24: 18 | B24: =MAX(0,$B$3-(E24+K24+Q24+W24+AC24+AI24+AO24+AU24)) | C24: =H23 | D24: =C24*Plan!D6/100/12 | E24: =MIN(Plan!E6,C24+D24) | F24: =C24+D24-E24 | G24: =MIN(F24,MAX(0,$B24-((K$5<E$5)*L24+(Q$5<E$5)*R24+(W$5<E$5)*X24+(AC$5<E$5)*AD24+(AI$5<E$5)*AJ24+(AO$5<E$5)*AP24+(AU$5<E$5)*AV24))) | H24: =IF(F24-G24<0.005,0,F24-G24) | I24: =N23 | J24: =I24*Plan!D7/100/12 | K24: =MIN(Plan!E7,I24+J24) | L24: =I24+J24-K24 | M24: =MIN(L24,MAX(0,$B24-((E$5<K$5)*F24+(Q$5<K$5)*R24+(W$5<K$5)*X24+(AC$5<K$5)*AD24+(AI$5<K$5)*AJ24+(AO$5<K$5)*AP24+(AU$5<K$5)*AV24))) | N24: =IF(L24-M24<0.005,0,L24-M24) | O24: =T23 | P24: =O24*Plan!D8/100/12 | Q24: =MIN(Plan!E8,O24+P24) | R24: =O24+P24-Q24 | S24: =MIN(R24,MAX(0,$B24-((E$5<Q$5)*F24+(K$5<Q$5)*L24+(W$5<Q$5)*X24+(AC$5<Q$5)*AD24+(AI$5<Q$5)*AJ24+(AO$5<Q$5)*AP24+(AU$5<Q$5)*AV24))) | T24: =IF(R24-S24<0.005,0,R24-S24) | U24: =Z23 | V24: =U24*Plan!D9/100/12 | W24: =MIN(Plan!E9,U24+V24) | X24: =U24+V24-W24 | Y24: =MIN(X24,MAX(0,$B24-((E$5<W$5)*F24+(K$5<W$5)*L24+(Q$5<W$5)*R24+(AC$5<W$5)*AD24+(AI$5<W$5)*AJ24+(AO$5<W$5)*AP24+(AU$5<W$5)*AV24))) | Z24: =IF(X24-Y24<0.005,0,X24-Y24) | AA24: =AF23 | AB24: =AA24*Plan!D10/100/12 | AC24: =MIN(Plan!E10,AA24+AB24) | AD24: =AA24+AB24-AC24 | AE24: =MIN(AD24,MAX(0,$B24-((E$5<AC$5)*F24+(K$5<AC$5)*L24+(Q$5<AC$5)*R24+(W$5<AC$5)*X24+(AI$5<AC$5)*AJ24+(AO$5<AC$5)*AP24+(AU$5<AC$5)*AV24))) | AF24: =IF(AD24-AE24<0.005,0,AD24-AE24) | AG24: =AL23 | AH24: =AG24*Plan!D11/100/12 | AI24: =MIN(Plan!E11,AG24+AH24) | AJ24: =AG24+AH24-AI24 | AK24: =MIN(AJ24,MAX(0,$B24-((E$5<AI$5)*F24+(K$5<AI$5)*L24+(Q$5<AI$5)*R24+(W$5<AI$5)*X24+(AC$5<AI$5)*AD24+(AO$5<AI$5)*AP24+(AU$5<AI$5)*AV24))) | AL24: =IF(AJ24-AK24<0.005,0,AJ24-AK24) | AM24: =AR23 | AN24: =AM24*Plan!D12/100/12 | AO24: =MIN(Plan!E12,AM24+AN24) | AP24: =AM24+AN24-AO24 | AQ24: =MIN(AP24,MAX(0,$B24-((E$5<AO$5)*F24+(K$5<AO$5)*L24+(Q$5<AO$5)*R24+(W$5<AO$5)*X24+(AC$5<AO$5)*AD24+(AI$5<AO$5)*AJ24+(AU$5<AO$5)*AV24))) | AR24: =IF(AP24-AQ24<0.005,0,AP24-AQ24) | AS24: =AX23 | AT24: =AS24*Plan!D13/100/12 | AU24: =MIN(Plan!E13,AS24+AT24) | AV24: =AS24+AT24-AU24 | AW24: =MIN(AV24,MAX(0,$B24-((E$5<AU$5)*F24+(K$5<AU$5)*L24+(Q$5<AU$5)*R24+(W$5<AU$5)*X24+(AC$5<AU$5)*AD24+(AI$5<AU$5)*AJ24+(AO$5<AU$5)*AP24))) | AX24: =IF(AV24-AW24<0.005,0,AV24-AW24) | BC24: =H24+N24+T24+Z24+AF24+AL24+AR24+AX24
A25: 19 | B25: =MAX(0,$B$3-(E25+K25+Q25+W25+AC25+AI25+AO25+AU25)) | C25: =H24 | D25: =C25*Plan!D6/100/12 | E25: =MIN(Plan!E6,C25+D25) | F25: =C25+D25-E25 | G25: =MIN(F25,MAX(0,$B25-((K$5<E$5)*L25+(Q$5<E$5)*R25+(W$5<E$5)*X25+(AC$5<E$5)*AD25+(AI$5<E$5)*AJ25+(AO$5<E$5)*AP25+(AU$5<E$5)*AV25))) | H25: =IF(F25-G25<0.005,0,F25-G25) | I25: =N24 | J25: =I25*Plan!D7/100/12 | K25: =MIN(Plan!E7,I25+J25) | L25: =I25+J25-K25 | M25: =MIN(L25,MAX(0,$B25-((E$5<K$5)*F25+(Q$5<K$5)*R25+(W$5<K$5)*X25+(AC$5<K$5)*AD25+(AI$5<K$5)*AJ25+(AO$5<K$5)*AP25+(AU$5<K$5)*AV25))) | N25: =IF(L25-M25<0.005,0,L25-M25) | O25: =T24 | P25: =O25*Plan!D8/100/12 | Q25: =MIN(Plan!E8,O25+P25) | R25: =O25+P25-Q25 | S25: =MIN(R25,MAX(0,$B25-((E$5<Q$5)*F25+(K$5<Q$5)*L25+(W$5<Q$5)*X25+(AC$5<Q$5)*AD25+(AI$5<Q$5)*AJ25+(AO$5<Q$5)*AP25+(AU$5<Q$5)*AV25))) | T25: =IF(R25-S25<0.005,0,R25-S25) | U25: =Z24 | V25: =U25*Plan!D9/100/12 | W25: =MIN(Plan!E9,U25+V25) | X25: =U25+V25-W25 | Y25: =MIN(X25,MAX(0,$B25-((E$5<W$5)*F25+(K$5<W$5)*L25+(Q$5<W$5)*R25+(AC$5<W$5)*AD25+(AI$5<W$5)*AJ25+(AO$5<W$5)*AP25+(AU$5<W$5)*AV25))) | Z25: =IF(X25-Y25<0.005,0,X25-Y25) | AA25: =AF24 | AB25: =AA25*Plan!D10/100/12 | AC25: =MIN(Plan!E10,AA25+AB25) | AD25: =AA25+AB25-AC25 | AE25: =MIN(AD25,MAX(0,$B25-((E$5<AC$5)*F25+(K$5<AC$5)*L25+(Q$5<AC$5)*R25+(W$5<AC$5)*X25+(AI$5<AC$5)*AJ25+(AO$5<AC$5)*AP25+(AU$5<AC$5)*AV25))) | AF25: =IF(AD25-AE25<0.005,0,AD25-AE25) | AG25: =AL24 | AH25: =AG25*Plan!D11/100/12 | AI25: =MIN(Plan!E11,AG25+AH25) | AJ25: =AG25+AH25-AI25 | AK25: =MIN(AJ25,MAX(0,$B25-((E$5<AI$5)*F25+(K$5<AI$5)*L25+(Q$5<AI$5)*R25+(W$5<AI$5)*X25+(AC$5<AI$5)*AD25+(AO$5<AI$5)*AP25+(AU$5<AI$5)*AV25))) | AL25: =IF(AJ25-AK25<0.005,0,AJ25-AK25) | AM25: =AR24 | AN25: =AM25*Plan!D12/100/12 | AO25: =MIN(Plan!E12,AM25+AN25) | AP25: =AM25+AN25-AO25 | AQ25: =MIN(AP25,MAX(0,$B25-((E$5<AO$5)*F25+(K$5<AO$5)*L25+(Q$5<AO$5)*R25+(W$5<AO$5)*X25+(AC$5<AO$5)*AD25+(AI$5<AO$5)*AJ25+(AU$5<AO$5)*AV25))) | AR25: =IF(AP25-AQ25<0.005,0,AP25-AQ25) | AS25: =AX24 | AT25: =AS25*Plan!D13/100/12 | AU25: =MIN(Plan!E13,AS25+AT25) | AV25: =AS25+AT25-AU25 | AW25: =MIN(AV25,MAX(0,$B25-((E$5<AU$5)*F25+(K$5<AU$5)*L25+(Q$5<AU$5)*R25+(W$5<AU$5)*X25+(AC$5<AU$5)*AD25+(AI$5<AU$5)*AJ25+(AO$5<AU$5)*AP25))) | AX25: =IF(AV25-AW25<0.005,0,AV25-AW25) | BC25: =H25+N25+T25+Z25+AF25+AL25+AR25+AX25
A26: 20 | B26: =MAX(0,$B$3-(E26+K26+Q26+W26+AC26+AI26+AO26+AU26)) | C26: =H25 | D26: =C26*Plan!D6/100/12 | E26: =MIN(Plan!E6,C26+D26) | F26: =C26+D26-E26 | G26: =MIN(F26,MAX(0,$B26-((K$5<E$5)*L26+(Q$5<E$5)*R26+(W$5<E$5)*X26+(AC$5<E$5)*AD26+(AI$5<E$5)*AJ26+(AO$5<E$5)*AP26+(AU$5<E$5)*AV26))) | H26: =IF(F26-G26<0.005,0,F26-G26) | I26: =N25 | J26: =I26*Plan!D7/100/12 | K26: =MIN(Plan!E7,I26+J26) | L26: =I26+J26-K26 | M26: =MIN(L26,MAX(0,$B26-((E$5<K$5)*F26+(Q$5<K$5)*R26+(W$5<K$5)*X26+(AC$5<K$5)*AD26+(AI$5<K$5)*AJ26+(AO$5<K$5)*AP26+(AU$5<K$5)*AV26))) | N26: =IF(L26-M26<0.005,0,L26-M26) | O26: =T25 | P26: =O26*Plan!D8/100/12 | Q26: =MIN(Plan!E8,O26+P26) | R26: =O26+P26-Q26 | S26: =MIN(R26,MAX(0,$B26-((E$5<Q$5)*F26+(K$5<Q$5)*L26+(W$5<Q$5)*X26+(AC$5<Q$5)*AD26+(AI$5<Q$5)*AJ26+(AO$5<Q$5)*AP26+(AU$5<Q$5)*AV26))) | T26: =IF(R26-S26<0.005,0,R26-S26) | U26: =Z25 | V26: =U26*Plan!D9/100/12 | W26: =MIN(Plan!E9,U26+V26) | X26: =U26+V26-W26 | Y26: =MIN(X26,MAX(0,$B26-((E$5<W$5)*F26+(K$5<W$5)*L26+(Q$5<W$5)*R26+(AC$5<W$5)*AD26+(AI$5<W$5)*AJ26+(AO$5<W$5)*AP26+(AU$5<W$5)*AV26))) | Z26: =IF(X26-Y26<0.005,0,X26-Y26) | AA26: =AF25 | AB26: =AA26*Plan!D10/100/12 | AC26: =MIN(Plan!E10,AA26+AB26) | AD26: =AA26+AB26-AC26 | AE26: =MIN(AD26,MAX(0,$B26-((E$5<AC$5)*F26+(K$5<AC$5)*L26+(Q$5<AC$5)*R26+(W$5<AC$5)*X26+(AI$5<AC$5)*AJ26+(AO$5<AC$5)*AP26+(AU$5<AC$5)*AV26))) | AF26: =IF(AD26-AE26<0.005,0,AD26-AE26) | AG26: =AL25 | AH26: =AG26*Plan!D11/100/12 | AI26: =MIN(Plan!E11,AG26+AH26) | AJ26: =AG26+AH26-AI26 | AK26: =MIN(AJ26,MAX(0,$B26-((E$5<AI$5)*F26+(K$5<AI$5)*L26+(Q$5<AI$5)*R26+(W$5<AI$5)*X26+(AC$5<AI$5)*AD26+(AO$5<AI$5)*AP26+(AU$5<AI$5)*AV26))) | AL26: =IF(AJ26-AK26<0.005,0,AJ26-AK26) | AM26: =AR25 | AN26: =AM26*Plan!D12/100/12 | AO26: =MIN(Plan!E12,AM26+AN26) | AP26: =AM26+AN26-AO26 | AQ26: =MIN(AP26,MAX(0,$B26-((E$5<AO$5)*F26+(K$5<AO$5)*L26+(Q$5<AO$5)*R26+(W$5<AO$5)*X26+(AC$5<AO$5)*AD26+(AI$5<AO$5)*AJ26+(AU$5<AO$5)*AV26))) | AR26: =IF(AP26-AQ26<0.005,0,AP26-AQ26) | AS26: =AX25 | AT26: =AS26*Plan!D13/100/12 | AU26: =MIN(Plan!E13,AS26+AT26) | AV26: =AS26+AT26-AU26 | AW26: =MIN(AV26,MAX(0,$B26-((E$5<AU$5)*F26+(K$5<AU$5)*L26+(Q$5<AU$5)*R26+(W$5<AU$5)*X26+(AC$5<AU$5)*AD26+(AI$5<AU$5)*AJ26+(AO$5<AU$5)*AP26))) | AX26: =IF(AV26-AW26<0.005,0,AV26-AW26) | BC26: =H26+N26+T26+Z26+AF26+AL26+AR26+AX26
A27: 21 | B27: =MAX(0,$B$3-(E27+K27+Q27+W27+AC27+AI27+AO27+AU27)) | C27: =H26 | D27: =C27*Plan!D6/100/12 | E27: =MIN(Plan!E6,C27+D27) | F27: =C27+D27-E27 | G27: =MIN(F27,MAX(0,$B27-((K$5<E$5)*L27+(Q$5<E$5)*R27+(W$5<E$5)*X27+(AC$5<E$5)*AD27+(AI$5<E$5)*AJ27+(AO$5<E$5)*AP27+(AU$5<E$5)*AV27))) | H27: =IF(F27-G27<0.005,0,F27-G27) | I27: =N26 | J27: =I27*Plan!D7/100/12 | K27: =MIN(Plan!E7,I27+J27) | L27: =I27+J27-K27 | M27: =MIN(L27,MAX(0,$B27-((E$5<K$5)*F27+(Q$5<K$5)*R27+(W$5<K$5)*X27+(AC$5<K$5)*AD27+(AI$5<K$5)*AJ27+(AO$5<K$5)*AP27+(AU$5<K$5)*AV27))) | N27: =IF(L27-M27<0.005,0,L27-M27) | O27: =T26 | P27: =O27*Plan!D8/100/12 | Q27: =MIN(Plan!E8,O27+P27) | R27: =O27+P27-Q27 | S27: =MIN(R27,MAX(0,$B27-((E$5<Q$5)*F27+(K$5<Q$5)*L27+(W$5<Q$5)*X27+(AC$5<Q$5)*AD27+(AI$5<Q$5)*AJ27+(AO$5<Q$5)*AP27+(AU$5<Q$5)*AV27))) | T27: =IF(R27-S27<0.005,0,R27-S27) | U27: =Z26 | V27: =U27*Plan!D9/100/12 | W27: =MIN(Plan!E9,U27+V27) | X27: =U27+V27-W27 | Y27: =MIN(X27,MAX(0,$B27-((E$5<W$5)*F27+(K$5<W$5)*L27+(Q$5<W$5)*R27+(AC$5<W$5)*AD27+(AI$5<W$5)*AJ27+(AO$5<W$5)*AP27+(AU$5<W$5)*AV27))) | Z27: =IF(X27-Y27<0.005,0,X27-Y27) | AA27: =AF26 | AB27: =AA27*Plan!D10/100/12 | AC27: =MIN(Plan!E10,AA27+AB27) | AD27: =AA27+AB27-AC27 | AE27: =MIN(AD27,MAX(0,$B27-((E$5<AC$5)*F27+(K$5<AC$5)*L27+(Q$5<AC$5)*R27+(W$5<AC$5)*X27+(AI$5<AC$5)*AJ27+(AO$5<AC$5)*AP27+(AU$5<AC$5)*AV27))) | AF27: =IF(AD27-AE27<0.005,0,AD27-AE27) | AG27: =AL26 | AH27: =AG27*Plan!D11/100/12 | AI27: =MIN(Plan!E11,AG27+AH27) | AJ27: =AG27+AH27-AI27 | AK27: =MIN(AJ27,MAX(0,$B27-((E$5<AI$5)*F27+(K$5<AI$5)*L27+(Q$5<AI$5)*R27+(W$5<AI$5)*X27+(AC$5<AI$5)*AD27+(AO$5<AI$5)*AP27+(AU$5<AI$5)*AV27))) | AL27: =IF(AJ27-AK27<0.005,0,AJ27-AK27) | AM27: =AR26 | AN27: =AM27*Plan!D12/100/12 | AO27: =MIN(Plan!E12,AM27+AN27) | AP27: =AM27+AN27-AO27 | AQ27: =MIN(AP27,MAX(0,$B27-((E$5<AO$5)*F27+(K$5<AO$5)*L27+(Q$5<AO$5)*R27+(W$5<AO$5)*X27+(AC$5<AO$5)*AD27+(AI$5<AO$5)*AJ27+(AU$5<AO$5)*AV27))) | AR27: =IF(AP27-AQ27<0.005,0,AP27-AQ27) | AS27: =AX26 | AT27: =AS27*Plan!D13/100/12 | AU27: =MIN(Plan!E13,AS27+AT27) | AV27: =AS27+AT27-AU27 | AW27: =MIN(AV27,MAX(0,$B27-((E$5<AU$5)*F27+(K$5<AU$5)*L27+(Q$5<AU$5)*R27+(W$5<AU$5)*X27+(AC$5<AU$5)*AD27+(AI$5<AU$5)*AJ27+(AO$5<AU$5)*AP27))) | AX27: =IF(AV27-AW27<0.005,0,AV27-AW27) | BC27: =H27+N27+T27+Z27+AF27+AL27+AR27+AX27
A28: 22 | B28: =MAX(0,$B$3-(E28+K28+Q28+W28+AC28+AI28+AO28+AU28)) | C28: =H27 | D28: =C28*Plan!D6/100/12 | E28: =MIN(Plan!E6,C28+D28) | F28: =C28+D28-E28 | G28: =MIN(F28,MAX(0,$B28-((K$5<E$5)*L28+(Q$5<E$5)*R28+(W$5<E$5)*X28+(AC$5<E$5)*AD28+(AI$5<E$5)*AJ28+(AO$5<E$5)*AP28+(AU$5<E$5)*AV28))) | H28: =IF(F28-G28<0.005,0,F28-G28) | I28: =N27 | J28: =I28*Plan!D7/100/12 | K28: =MIN(Plan!E7,I28+J28) | L28: =I28+J28-K28 | M28: =MIN(L28,MAX(0,$B28-((E$5<K$5)*F28+(Q$5<K$5)*R28+(W$5<K$5)*X28+(AC$5<K$5)*AD28+(AI$5<K$5)*AJ28+(AO$5<K$5)*AP28+(AU$5<K$5)*AV28))) | N28: =IF(L28-M28<0.005,0,L28-M28) | O28: =T27 | P28: =O28*Plan!D8/100/12 | Q28: =MIN(Plan!E8,O28+P28) | R28: =O28+P28-Q28 | S28: =MIN(R28,MAX(0,$B28-((E$5<Q$5)*F28+(K$5<Q$5)*L28+(W$5<Q$5)*X28+(AC$5<Q$5)*AD28+(AI$5<Q$5)*AJ28+(AO$5<Q$5)*AP28+(AU$5<Q$5)*AV28))) | T28: =IF(R28-S28<0.005,0,R28-S28) | U28: =Z27 | V28: =U28*Plan!D9/100/12 | W28: =MIN(Plan!E9,U28+V28) | X28: =U28+V28-W28 | Y28: =MIN(X28,MAX(0,$B28-((E$5<W$5)*F28+(K$5<W$5)*L28+(Q$5<W$5)*R28+(AC$5<W$5)*AD28+(AI$5<W$5)*AJ28+(AO$5<W$5)*AP28+(AU$5<W$5)*AV28))) | Z28: =IF(X28-Y28<0.005,0,X28-Y28) | AA28: =AF27 | AB28: =AA28*Plan!D10/100/12 | AC28: =MIN(Plan!E10,AA28+AB28) | AD28: =AA28+AB28-AC28 | AE28: =MIN(AD28,MAX(0,$B28-((E$5<AC$5)*F28+(K$5<AC$5)*L28+(Q$5<AC$5)*R28+(W$5<AC$5)*X28+(AI$5<AC$5)*AJ28+(AO$5<AC$5)*AP28+(AU$5<AC$5)*AV28))) | AF28: =IF(AD28-AE28<0.005,0,AD28-AE28) | AG28: =AL27 | AH28: =AG28*Plan!D11/100/12 | AI28: =MIN(Plan!E11,AG28+AH28) | AJ28: =AG28+AH28-AI28 | AK28: =MIN(AJ28,MAX(0,$B28-((E$5<AI$5)*F28+(K$5<AI$5)*L28+(Q$5<AI$5)*R28+(W$5<AI$5)*X28+(AC$5<AI$5)*AD28+(AO$5<AI$5)*AP28+(AU$5<AI$5)*AV28))) | AL28: =IF(AJ28-AK28<0.005,0,AJ28-AK28) | AM28: =AR27 | AN28: =AM28*Plan!D12/100/12 | AO28: =MIN(Plan!E12,AM28+AN28) | AP28: =AM28+AN28-AO28 | AQ28: =MIN(AP28,MAX(0,$B28-((E$5<AO$5)*F28+(K$5<AO$5)*L28+(Q$5<AO$5)*R28+(W$5<AO$5)*X28+(AC$5<AO$5)*AD28+(AI$5<AO$5)*AJ28+(AU$5<AO$5)*AV28))) | AR28: =IF(AP28-AQ28<0.005,0,AP28-AQ28) | AS28: =AX27 | AT28: =AS28*Plan!D13/100/12 | AU28: =MIN(Plan!E13,AS28+AT28) | AV28: =AS28+AT28-AU28 | AW28: =MIN(AV28,MAX(0,$B28-((E$5<AU$5)*F28+(K$5<AU$5)*L28+(Q$5<AU$5)*R28+(W$5<AU$5)*X28+(AC$5<AU$5)*AD28+(AI$5<AU$5)*AJ28+(AO$5<AU$5)*AP28))) | AX28: =IF(AV28-AW28<0.005,0,AV28-AW28) | BC28: =H28+N28+T28+Z28+AF28+AL28+AR28+AX28
A29: 23 | B29: =MAX(0,$B$3-(E29+K29+Q29+W29+AC29+AI29+AO29+AU29)) | C29: =H28 | D29: =C29*Plan!D6/100/12 | E29: =MIN(Plan!E6,C29+D29) | F29: =C29+D29-E29 | G29: =MIN(F29,MAX(0,$B29-((K$5<E$5)*L29+(Q$5<E$5)*R29+(W$5<E$5)*X29+(AC$5<E$5)*AD29+(AI$5<E$5)*AJ29+(AO$5<E$5)*AP29+(AU$5<E$5)*AV29))) | H29: =IF(F29-G29<0.005,0,F29-G29) | I29: =N28 | J29: =I29*Plan!D7/100/12 | K29: =MIN(Plan!E7,I29+J29) | L29: =I29+J29-K29 | M29: =MIN(L29,MAX(0,$B29-((E$5<K$5)*F29+(Q$5<K$5)*R29+(W$5<K$5)*X29+(AC$5<K$5)*AD29+(AI$5<K$5)*AJ29+(AO$5<K$5)*AP29+(AU$5<K$5)*AV29))) | N29: =IF(L29-M29<0.005,0,L29-M29) | O29: =T28 | P29: =O29*Plan!D8/100/12 | Q29: =MIN(Plan!E8,O29+P29) | R29: =O29+P29-Q29 | S29: =MIN(R29,MAX(0,$B29-((E$5<Q$5)*F29+(K$5<Q$5)*L29+(W$5<Q$5)*X29+(AC$5<Q$5)*AD29+(AI$5<Q$5)*AJ29+(AO$5<Q$5)*AP29+(AU$5<Q$5)*AV29))) | T29: =IF(R29-S29<0.005,0,R29-S29) | U29: =Z28 | V29: =U29*Plan!D9/100/12 | W29: =MIN(Plan!E9,U29+V29) | X29: =U29+V29-W29 | Y29: =MIN(X29,MAX(0,$B29-((E$5<W$5)*F29+(K$5<W$5)*L29+(Q$5<W$5)*R29+(AC$5<W$5)*AD29+(AI$5<W$5)*AJ29+(AO$5<W$5)*AP29+(AU$5<W$5)*AV29))) | Z29: =IF(X29-Y29<0.005,0,X29-Y29) | AA29: =AF28 | AB29: =AA29*Plan!D10/100/12 | AC29: =MIN(Plan!E10,AA29+AB29) | AD29: =AA29+AB29-AC29 | AE29: =MIN(AD29,MAX(0,$B29-((E$5<AC$5)*F29+(K$5<AC$5)*L29+(Q$5<AC$5)*R29+(W$5<AC$5)*X29+(AI$5<AC$5)*AJ29+(AO$5<AC$5)*AP29+(AU$5<AC$5)*AV29))) | AF29: =IF(AD29-AE29<0.005,0,AD29-AE29) | AG29: =AL28 | AH29: =AG29*Plan!D11/100/12 | AI29: =MIN(Plan!E11,AG29+AH29) | AJ29: =AG29+AH29-AI29 | AK29: =MIN(AJ29,MAX(0,$B29-((E$5<AI$5)*F29+(K$5<AI$5)*L29+(Q$5<AI$5)*R29+(W$5<AI$5)*X29+(AC$5<AI$5)*AD29+(AO$5<AI$5)*AP29+(AU$5<AI$5)*AV29))) | AL29: =IF(AJ29-AK29<0.005,0,AJ29-AK29) | AM29: =AR28 | AN29: =AM29*Plan!D12/100/12 | AO29: =MIN(Plan!E12,AM29+AN29) | AP29: =AM29+AN29-AO29 | AQ29: =MIN(AP29,MAX(0,$B29-((E$5<AO$5)*F29+(K$5<AO$5)*L29+(Q$5<AO$5)*R29+(W$5<AO$5)*X29+(AC$5<AO$5)*AD29+(AI$5<AO$5)*AJ29+(AU$5<AO$5)*AV29))) | AR29: =IF(AP29-AQ29<0.005,0,AP29-AQ29) | AS29: =AX28 | AT29: =AS29*Plan!D13/100/12 | AU29: =MIN(Plan!E13,AS29+AT29) | AV29: =AS29+AT29-AU29 | AW29: =MIN(AV29,MAX(0,$B29-((E$5<AU$5)*F29+(K$5<AU$5)*L29+(Q$5<AU$5)*R29+(W$5<AU$5)*X29+(AC$5<AU$5)*AD29+(AI$5<AU$5)*AJ29+(AO$5<AU$5)*AP29))) | AX29: =IF(AV29-AW29<0.005,0,AV29-AW29) | BC29: =H29+N29+T29+Z29+AF29+AL29+AR29+AX29
A30: 24 | B30: =MAX(0,$B$3-(E30+K30+Q30+W30+AC30+AI30+AO30+AU30)) | C30: =H29 | D30: =C30*Plan!D6/100/12 | E30: =MIN(Plan!E6,C30+D30) | F30: =C30+D30-E30 | G30: =MIN(F30,MAX(0,$B30-((K$5<E$5)*L30+(Q$5<E$5)*R30+(W$5<E$5)*X30+(AC$5<E$5)*AD30+(AI$5<E$5)*AJ30+(AO$5<E$5)*AP30+(AU$5<E$5)*AV30))) | H30: =IF(F30-G30<0.005,0,F30-G30) | I30: =N29 | J30: =I30*Plan!D7/100/12 | K30: =MIN(Plan!E7,I30+J30) | L30: =I30+J30-K30 | M30: =MIN(L30,MAX(0,$B30-((E$5<K$5)*F30+(Q$5<K$5)*R30+(W$5<K$5)*X30+(AC$5<K$5)*AD30+(AI$5<K$5)*AJ30+(AO$5<K$5)*AP30+(AU$5<K$5)*AV30))) | N30: =IF(L30-M30<0.005,0,L30-M30) | O30: =T29 | P30: =O30*Plan!D8/100/12 | Q30: =MIN(Plan!E8,O30+P30) | R30: =O30+P30-Q30 | S30: =MIN(R30,MAX(0,$B30-((E$5<Q$5)*F30+(K$5<Q$5)*L30+(W$5<Q$5)*X30+(AC$5<Q$5)*AD30+(AI$5<Q$5)*AJ30+(AO$5<Q$5)*AP30+(AU$5<Q$5)*AV30))) | T30: =IF(R30-S30<0.005,0,R30-S30) | U30: =Z29 | V30: =U30*Plan!D9/100/12 | W30: =MIN(Plan!E9,U30+V30) | X30: =U30+V30-W30 | Y30: =MIN(X30,MAX(0,$B30-((E$5<W$5)*F30+(K$5<W$5)*L30+(Q$5<W$5)*R30+(AC$5<W$5)*AD30+(AI$5<W$5)*AJ30+(AO$5<W$5)*AP30+(AU$5<W$5)*AV30))) | Z30: =IF(X30-Y30<0.005,0,X30-Y30) | AA30: =AF29 | AB30: =AA30*Plan!D10/100/12 | AC30: =MIN(Plan!E10,AA30+AB30) | AD30: =AA30+AB30-AC30 | AE30: =MIN(AD30,MAX(0,$B30-((E$5<AC$5)*F30+(K$5<AC$5)*L30+(Q$5<AC$5)*R30+(W$5<AC$5)*X30+(AI$5<AC$5)*AJ30+(AO$5<AC$5)*AP30+(AU$5<AC$5)*AV30))) | AF30: =IF(AD30-AE30<0.005,0,AD30-AE30) | AG30: =AL29 | AH30: =AG30*Plan!D11/100/12 | AI30: =MIN(Plan!E11,AG30+AH30) | AJ30: =AG30+AH30-AI30 | AK30: =MIN(AJ30,MAX(0,$B30-((E$5<AI$5)*F30+(K$5<AI$5)*L30+(Q$5<AI$5)*R30+(W$5<AI$5)*X30+(AC$5<AI$5)*AD30+(AO$5<AI$5)*AP30+(AU$5<AI$5)*AV30))) | AL30: =IF(AJ30-AK30<0.005,0,AJ30-AK30) | AM30: =AR29 | AN30: =AM30*Plan!D12/100/12 | AO30: =MIN(Plan!E12,AM30+AN30) | AP30: =AM30+AN30-AO30 | AQ30: =MIN(AP30,MAX(0,$B30-((E$5<AO$5)*F30+(K$5<AO$5)*L30+(Q$5<AO$5)*R30+(W$5<AO$5)*X30+(AC$5<AO$5)*AD30+(AI$5<AO$5)*AJ30+(AU$5<AO$5)*AV30))) | AR30: =IF(AP30-AQ30<0.005,0,AP30-AQ30) | AS30: =AX29 | AT30: =AS30*Plan!D13/100/12 | AU30: =MIN(Plan!E13,AS30+AT30) | AV30: =AS30+AT30-AU30 | AW30: =MIN(AV30,MAX(0,$B30-((E$5<AU$5)*F30+(K$5<AU$5)*L30+(Q$5<AU$5)*R30+(W$5<AU$5)*X30+(AC$5<AU$5)*AD30+(AI$5<AU$5)*AJ30+(AO$5<AU$5)*AP30))) | AX30: =IF(AV30-AW30<0.005,0,AV30-AW30) | BC30: =H30+N30+T30+Z30+AF30+AL30+AR30+AX30
A31: 25 | B31: =MAX(0,$B$3-(E31+K31+Q31+W31+AC31+AI31+AO31+AU31)) | C31: =H30 | D31: =C31*Plan!D6/100/12 | E31: =MIN(Plan!E6,C31+D31) | F31: =C31+D31-E31 | G31: =MIN(F31,MAX(0,$B31-((K$5<E$5)*L31+(Q$5<E$5)*R31+(W$5<E$5)*X31+(AC$5<E$5)*AD31+(AI$5<E$5)*AJ31+(AO$5<E$5)*AP31+(AU$5<E$5)*AV31))) | H31: =IF(F31-G31<0.005,0,F31-G31) | I31: =N30 | J31: =I31*Plan!D7/100/12 | K31: =MIN(Plan!E7,I31+J31) | L31: =I31+J31-K31 | M31: =MIN(L31,MAX(0,$B31-((E$5<K$5)*F31+(Q$5<K$5)*R31+(W$5<K$5)*X31+(AC$5<K$5)*AD31+(AI$5<K$5)*AJ31+(AO$5<K$5)*AP31+(AU$5<K$5)*AV31))) | N31: =IF(L31-M31<0.005,0,L31-M31) | O31: =T30 | P31: =O31*Plan!D8/100/12 | Q31: =MIN(Plan!E8,O31+P31) | R31: =O31+P31-Q31 | S31: =MIN(R31,MAX(0,$B31-((E$5<Q$5)*F31+(K$5<Q$5)*L31+(W$5<Q$5)*X31+(AC$5<Q$5)*AD31+(AI$5<Q$5)*AJ31+(AO$5<Q$5)*AP31+(AU$5<Q$5)*AV31))) | T31: =IF(R31-S31<0.005,0,R31-S31) | U31: =Z30 | V31: =U31*Plan!D9/100/12 | W31: =MIN(Plan!E9,U31+V31) | X31: =U31+V31-W31 | Y31: =MIN(X31,MAX(0,$B31-((E$5<W$5)*F31+(K$5<W$5)*L31+(Q$5<W$5)*R31+(AC$5<W$5)*AD31+(AI$5<W$5)*AJ31+(AO$5<W$5)*AP31+(AU$5<W$5)*AV31))) | Z31: =IF(X31-Y31<0.005,0,X31-Y31) | AA31: =AF30 | AB31: =AA31*Plan!D10/100/12 | AC31: =MIN(Plan!E10,AA31+AB31) | AD31: =AA31+AB31-AC31 | AE31: =MIN(AD31,MAX(0,$B31-((E$5<AC$5)*F31+(K$5<AC$5)*L31+(Q$5<AC$5)*R31+(W$5<AC$5)*X31+(AI$5<AC$5)*AJ31+(AO$5<AC$5)*AP31+(AU$5<AC$5)*AV31))) | AF31: =IF(AD31-AE31<0.005,0,AD31-AE31) | AG31: =AL30 | AH31: =AG31*Plan!D11/100/12 | AI31: =MIN(Plan!E11,AG31+AH31) | AJ31: =AG31+AH31-AI31 | AK31: =MIN(AJ31,MAX(0,$B31-((E$5<AI$5)*F31+(K$5<AI$5)*L31+(Q$5<AI$5)*R31+(W$5<AI$5)*X31+(AC$5<AI$5)*AD31+(AO$5<AI$5)*AP31+(AU$5<AI$5)*AV31))) | AL31: =IF(AJ31-AK31<0.005,0,AJ31-AK31) | AM31: =AR30 | AN31: =AM31*Plan!D12/100/12 | AO31: =MIN(Plan!E12,AM31+AN31) | AP31: =AM31+AN31-AO31 | AQ31: =MIN(AP31,MAX(0,$B31-((E$5<AO$5)*F31+(K$5<AO$5)*L31+(Q$5<AO$5)*R31+(W$5<AO$5)*X31+(AC$5<AO$5)*AD31+(AI$5<AO$5)*AJ31+(AU$5<AO$5)*AV31))) | AR31: =IF(AP31-AQ31<0.005,0,AP31-AQ31) | AS31: =AX30 | AT31: =AS31*Plan!D13/100/12 | AU31: =MIN(Plan!E13,AS31+AT31) | AV31: =AS31+AT31-AU31 | AW31: =MIN(AV31,MAX(0,$B31-((E$5<AU$5)*F31+(K$5<AU$5)*L31+(Q$5<AU$5)*R31+(W$5<AU$5)*X31+(AC$5<AU$5)*AD31+(AI$5<AU$5)*AJ31+(AO$5<AU$5)*AP31))) | AX31: =IF(AV31-AW31<0.005,0,AV31-AW31) | BC31: =H31+N31+T31+Z31+AF31+AL31+AR31+AX31
A32: 26 | B32: =MAX(0,$B$3-(E32+K32+Q32+W32+AC32+AI32+AO32+AU32)) | C32: =H31 | D32: =C32*Plan!D6/100/12 | E32: =MIN(Plan!E6,C32+D32) | F32: =C32+D32-E32 | G32: =MIN(F32,MAX(0,$B32-((K$5<E$5)*L32+(Q$5<E$5)*R32+(W$5<E$5)*X32+(AC$5<E$5)*AD32+(AI$5<E$5)*AJ32+(AO$5<E$5)*AP32+(AU$5<E$5)*AV32))) | H32: =IF(F32-G32<0.005,0,F32-G32) | I32: =N31 | J32: =I32*Plan!D7/100/12 | K32: =MIN(Plan!E7,I32+J32) | L32: =I32+J32-K32 | M32: =MIN(L32,MAX(0,$B32-((E$5<K$5)*F32+(Q$5<K$5)*R32+(W$5<K$5)*X32+(AC$5<K$5)*AD32+(AI$5<K$5)*AJ32+(AO$5<K$5)*AP32+(AU$5<K$5)*AV32))) | N32: =IF(L32-M32<0.005,0,L32-M32) | O32: =T31 | P32: =O32*Plan!D8/100/12 | Q32: =MIN(Plan!E8,O32+P32) | R32: =O32+P32-Q32 | S32: =MIN(R32,MAX(0,$B32-((E$5<Q$5)*F32+(K$5<Q$5)*L32+(W$5<Q$5)*X32+(AC$5<Q$5)*AD32+(AI$5<Q$5)*AJ32+(AO$5<Q$5)*AP32+(AU$5<Q$5)*AV32))) | T32: =IF(R32-S32<0.005,0,R32-S32) | U32: =Z31 | V32: =U32*Plan!D9/100/12 | W32: =MIN(Plan!E9,U32+V32) | X32: =U32+V32-W32 | Y32: =MIN(X32,MAX(0,$B32-((E$5<W$5)*F32+(K$5<W$5)*L32+(Q$5<W$5)*R32+(AC$5<W$5)*AD32+(AI$5<W$5)*AJ32+(AO$5<W$5)*AP32+(AU$5<W$5)*AV32))) | Z32: =IF(X32-Y32<0.005,0,X32-Y32) | AA32: =AF31 | AB32: =AA32*Plan!D10/100/12 | AC32: =MIN(Plan!E10,AA32+AB32) | AD32: =AA32+AB32-AC32 | AE32: =MIN(AD32,MAX(0,$B32-((E$5<AC$5)*F32+(K$5<AC$5)*L32+(Q$5<AC$5)*R32+(W$5<AC$5)*X32+(AI$5<AC$5)*AJ32+(AO$5<AC$5)*AP32+(AU$5<AC$5)*AV32))) | AF32: =IF(AD32-AE32<0.005,0,AD32-AE32) | AG32: =AL31 | AH32: =AG32*Plan!D11/100/12 | AI32: =MIN(Plan!E11,AG32+AH32) | AJ32: =AG32+AH32-AI32 | AK32: =MIN(AJ32,MAX(0,$B32-((E$5<AI$5)*F32+(K$5<AI$5)*L32+(Q$5<AI$5)*R32+(W$5<AI$5)*X32+(AC$5<AI$5)*AD32+(AO$5<AI$5)*AP32+(AU$5<AI$5)*AV32))) | AL32: =IF(AJ32-AK32<0.005,0,AJ32-AK32) | AM32: =AR31 | AN32: =AM32*Plan!D12/100/12 | AO32: =MIN(Plan!E12,AM32+AN32) | AP32: =AM32+AN32-AO32 | AQ32: =MIN(AP32,MAX(0,$B32-((E$5<AO$5)*F32+(K$5<AO$5)*L32+(Q$5<AO$5)*R32+(W$5<AO$5)*X32+(AC$5<AO$5)*AD32+(AI$5<AO$5)*AJ32+(AU$5<AO$5)*AV32))) | AR32: =IF(AP32-AQ32<0.005,0,AP32-AQ32) | AS32: =AX31 | AT32: =AS32*Plan!D13/100/12 | AU32: =MIN(Plan!E13,AS32+AT32) | AV32: =AS32+AT32-AU32 | AW32: =MIN(AV32,MAX(0,$B32-((E$5<AU$5)*F32+(K$5<AU$5)*L32+(Q$5<AU$5)*R32+(W$5<AU$5)*X32+(AC$5<AU$5)*AD32+(AI$5<AU$5)*AJ32+(AO$5<AU$5)*AP32))) | AX32: =IF(AV32-AW32<0.005,0,AV32-AW32) | BC32: =H32+N32+T32+Z32+AF32+AL32+AR32+AX32
A33: 27 | B33: =MAX(0,$B$3-(E33+K33+Q33+W33+AC33+AI33+AO33+AU33)) | C33: =H32 | D33: =C33*Plan!D6/100/12 | E33: =MIN(Plan!E6,C33+D33) | F33: =C33+D33-E33 | G33: =MIN(F33,MAX(0,$B33-((K$5<E$5)*L33+(Q$5<E$5)*R33+(W$5<E$5)*X33+(AC$5<E$5)*AD33+(AI$5<E$5)*AJ33+(AO$5<E$5)*AP33+(AU$5<E$5)*AV33))) | H33: =IF(F33-G33<0.005,0,F33-G33) | I33: =N32 | J33: =I33*Plan!D7/100/12 | K33: =MIN(Plan!E7,I33+J33) | L33: =I33+J33-K33 | M33: =MIN(L33,MAX(0,$B33-((E$5<K$5)*F33+(Q$5<K$5)*R33+(W$5<K$5)*X33+(AC$5<K$5)*AD33+(AI$5<K$5)*AJ33+(AO$5<K$5)*AP33+(AU$5<K$5)*AV33))) | N33: =IF(L33-M33<0.005,0,L33-M33) | O33: =T32 | P33: =O33*Plan!D8/100/12 | Q33: =MIN(Plan!E8,O33+P33) | R33: =O33+P33-Q33 | S33: =MIN(R33,MAX(0,$B33-((E$5<Q$5)*F33+(K$5<Q$5)*L33+(W$5<Q$5)*X33+(AC$5<Q$5)*AD33+(AI$5<Q$5)*AJ33+(AO$5<Q$5)*AP33+(AU$5<Q$5)*AV33))) | T33: =IF(R33-S33<0.005,0,R33-S33) | U33: =Z32 | V33: =U33*Plan!D9/100/12 | W33: =MIN(Plan!E9,U33+V33) | X33: =U33+V33-W33 | Y33: =MIN(X33,MAX(0,$B33-((E$5<W$5)*F33+(K$5<W$5)*L33+(Q$5<W$5)*R33+(AC$5<W$5)*AD33+(AI$5<W$5)*AJ33+(AO$5<W$5)*AP33+(AU$5<W$5)*AV33))) | Z33: =IF(X33-Y33<0.005,0,X33-Y33) | AA33: =AF32 | AB33: =AA33*Plan!D10/100/12 | AC33: =MIN(Plan!E10,AA33+AB33) | AD33: =AA33+AB33-AC33 | AE33: =MIN(AD33,MAX(0,$B33-((E$5<AC$5)*F33+(K$5<AC$5)*L33+(Q$5<AC$5)*R33+(W$5<AC$5)*X33+(AI$5<AC$5)*AJ33+(AO$5<AC$5)*AP33+(AU$5<AC$5)*AV33))) | AF33: =IF(AD33-AE33<0.005,0,AD33-AE33) | AG33: =AL32 | AH33: =AG33*Plan!D11/100/12 | AI33: =MIN(Plan!E11,AG33+AH33) | AJ33: =AG33+AH33-AI33 | AK33: =MIN(AJ33,MAX(0,$B33-((E$5<AI$5)*F33+(K$5<AI$5)*L33+(Q$5<AI$5)*R33+(W$5<AI$5)*X33+(AC$5<AI$5)*AD33+(AO$5<AI$5)*AP33+(AU$5<AI$5)*AV33))) | AL33: =IF(AJ33-AK33<0.005,0,AJ33-AK33) | AM33: =AR32 | AN33: =AM33*Plan!D12/100/12 | AO33: =MIN(Plan!E12,AM33+AN33) | AP33: =AM33+AN33-AO33 | AQ33: =MIN(AP33,MAX(0,$B33-((E$5<AO$5)*F33+(K$5<AO$5)*L33+(Q$5<AO$5)*R33+(W$5<AO$5)*X33+(AC$5<AO$5)*AD33+(AI$5<AO$5)*AJ33+(AU$5<AO$5)*AV33))) | AR33: =IF(AP33-AQ33<0.005,0,AP33-AQ33) | AS33: =AX32 | AT33: =AS33*Plan!D13/100/12 | AU33: =MIN(Plan!E13,AS33+AT33) | AV33: =AS33+AT33-AU33 | AW33: =MIN(AV33,MAX(0,$B33-((E$5<AU$5)*F33+(K$5<AU$5)*L33+(Q$5<AU$5)*R33+(W$5<AU$5)*X33+(AC$5<AU$5)*AD33+(AI$5<AU$5)*AJ33+(AO$5<AU$5)*AP33))) | AX33: =IF(AV33-AW33<0.005,0,AV33-AW33) | BC33: =H33+N33+T33+Z33+AF33+AL33+AR33+AX33
A34: 28 | B34: =MAX(0,$B$3-(E34+K34+Q34+W34+AC34+AI34+AO34+AU34)) | C34: =H33 | D34: =C34*Plan!D6/100/12 | E34: =MIN(Plan!E6,C34+D34) | F34: =C34+D34-E34 | G34: =MIN(F34,MAX(0,$B34-((K$5<E$5)*L34+(Q$5<E$5)*R34+(W$5<E$5)*X34+(AC$5<E$5)*AD34+(AI$5<E$5)*AJ34+(AO$5<E$5)*AP34+(AU$5<E$5)*AV34))) | H34: =IF(F34-G34<0.005,0,F34-G34) | I34: =N33 | J34: =I34*Plan!D7/100/12 | K34: =MIN(Plan!E7,I34+J34) | L34: =I34+J34-K34 | M34: =MIN(L34,MAX(0,$B34-((E$5<K$5)*F34+(Q$5<K$5)*R34+(W$5<K$5)*X34+(AC$5<K$5)*AD34+(AI$5<K$5)*AJ34+(AO$5<K$5)*AP34+(AU$5<K$5)*AV34))) | N34: =IF(L34-M34<0.005,0,L34-M34) | O34: =T33 | P34: =O34*Plan!D8/100/12 | Q34: =MIN(Plan!E8,O34+P34) | R34: =O34+P34-Q34 | S34: =MIN(R34,MAX(0,$B34-((E$5<Q$5)*F34+(K$5<Q$5)*L34+(W$5<Q$5)*X34+(AC$5<Q$5)*AD34+(AI$5<Q$5)*AJ34+(AO$5<Q$5)*AP34+(AU$5<Q$5)*AV34))) | T34: =IF(R34-S34<0.005,0,R34-S34) | U34: =Z33 | V34: =U34*Plan!D9/100/12 | W34: =MIN(Plan!E9,U34+V34) | X34: =U34+V34-W34 | Y34: =MIN(X34,MAX(0,$B34-((E$5<W$5)*F34+(K$5<W$5)*L34+(Q$5<W$5)*R34+(AC$5<W$5)*AD34+(AI$5<W$5)*AJ34+(AO$5<W$5)*AP34+(AU$5<W$5)*AV34))) | Z34: =IF(X34-Y34<0.005,0,X34-Y34) | AA34: =AF33 | AB34: =AA34*Plan!D10/100/12 | AC34: =MIN(Plan!E10,AA34+AB34) | AD34: =AA34+AB34-AC34 | AE34: =MIN(AD34,MAX(0,$B34-((E$5<AC$5)*F34+(K$5<AC$5)*L34+(Q$5<AC$5)*R34+(W$5<AC$5)*X34+(AI$5<AC$5)*AJ34+(AO$5<AC$5)*AP34+(AU$5<AC$5)*AV34))) | AF34: =IF(AD34-AE34<0.005,0,AD34-AE34) | AG34: =AL33 | AH34: =AG34*Plan!D11/100/12 | AI34: =MIN(Plan!E11,AG34+AH34) | AJ34: =AG34+AH34-AI34 | AK34: =MIN(AJ34,MAX(0,$B34-((E$5<AI$5)*F34+(K$5<AI$5)*L34+(Q$5<AI$5)*R34+(W$5<AI$5)*X34+(AC$5<AI$5)*AD34+(AO$5<AI$5)*AP34+(AU$5<AI$5)*AV34))) | AL34: =IF(AJ34-AK34<0.005,0,AJ34-AK34) | AM34: =AR33 | AN34: =AM34*Plan!D12/100/12 | AO34: =MIN(Plan!E12,AM34+AN34) | AP34: =AM34+AN34-AO34 | AQ34: =MIN(AP34,MAX(0,$B34-((E$5<AO$5)*F34+(K$5<AO$5)*L34+(Q$5<AO$5)*R34+(W$5<AO$5)*X34+(AC$5<AO$5)*AD34+(AI$5<AO$5)*AJ34+(AU$5<AO$5)*AV34))) | AR34: =IF(AP34-AQ34<0.005,0,AP34-AQ34) | AS34: =AX33 | AT34: =AS34*Plan!D13/100/12 | AU34: =MIN(Plan!E13,AS34+AT34) | AV34: =AS34+AT34-AU34 | AW34: =MIN(AV34,MAX(0,$B34-((E$5<AU$5)*F34+(K$5<AU$5)*L34+(Q$5<AU$5)*R34+(W$5<AU$5)*X34+(AC$5<AU$5)*AD34+(AI$5<AU$5)*AJ34+(AO$5<AU$5)*AP34))) | AX34: =IF(AV34-AW34<0.005,0,AV34-AW34) | BC34: =H34+N34+T34+Z34+AF34+AL34+AR34+AX34
A35: 29 | B35: =MAX(0,$B$3-(E35+K35+Q35+W35+AC35+AI35+AO35+AU35)) | C35: =H34 | D35: =C35*Plan!D6/100/12 | E35: =MIN(Plan!E6,C35+D35) | F35: =C35+D35-E35 | G35: =MIN(F35,MAX(0,$B35-((K$5<E$5)*L35+(Q$5<E$5)*R35+(W$5<E$5)*X35+(AC$5<E$5)*AD35+(AI$5<E$5)*AJ35+(AO$5<E$5)*AP35+(AU$5<E$5)*AV35))) | H35: =IF(F35-G35<0.005,0,F35-G35) | I35: =N34 | J35: =I35*Plan!D7/100/12 | K35: =MIN(Plan!E7,I35+J35) | L35: =I35+J35-K35 | M35: =MIN(L35,MAX(0,$B35-((E$5<K$5)*F35+(Q$5<K$5)*R35+(W$5<K$5)*X35+(AC$5<K$5)*AD35+(AI$5<K$5)*AJ35+(AO$5<K$5)*AP35+(AU$5<K$5)*AV35))) | N35: =IF(L35-M35<0.005,0,L35-M35) | O35: =T34 | P35: =O35*Plan!D8/100/12 | Q35: =MIN(Plan!E8,O35+P35) | R35: =O35+P35-Q35 | S35: =MIN(R35,MAX(0,$B35-((E$5<Q$5)*F35+(K$5<Q$5)*L35+(W$5<Q$5)*X35+(AC$5<Q$5)*AD35+(AI$5<Q$5)*AJ35+(AO$5<Q$5)*AP35+(AU$5<Q$5)*AV35))) | T35: =IF(R35-S35<0.005,0,R35-S35) | U35: =Z34 | V35: =U35*Plan!D9/100/12 | W35: =MIN(Plan!E9,U35+V35) | X35: =U35+V35-W35 | Y35: =MIN(X35,MAX(0,$B35-((E$5<W$5)*F35+(K$5<W$5)*L35+(Q$5<W$5)*R35+(AC$5<W$5)*AD35+(AI$5<W$5)*AJ35+(AO$5<W$5)*AP35+(AU$5<W$5)*AV35))) | Z35: =IF(X35-Y35<0.005,0,X35-Y35) | AA35: =AF34 | AB35: =AA35*Plan!D10/100/12 | AC35: =MIN(Plan!E10,AA35+AB35) | AD35: =AA35+AB35-AC35 | AE35: =MIN(AD35,MAX(0,$B35-((E$5<AC$5)*F35+(K$5<AC$5)*L35+(Q$5<AC$5)*R35+(W$5<AC$5)*X35+(AI$5<AC$5)*AJ35+(AO$5<AC$5)*AP35+(AU$5<AC$5)*AV35))) | AF35: =IF(AD35-AE35<0.005,0,AD35-AE35) | AG35: =AL34 | AH35: =AG35*Plan!D11/100/12 | AI35: =MIN(Plan!E11,AG35+AH35) | AJ35: =AG35+AH35-AI35 | AK35: =MIN(AJ35,MAX(0,$B35-((E$5<AI$5)*F35+(K$5<AI$5)*L35+(Q$5<AI$5)*R35+(W$5<AI$5)*X35+(AC$5<AI$5)*AD35+(AO$5<AI$5)*AP35+(AU$5<AI$5)*AV35))) | AL35: =IF(AJ35-AK35<0.005,0,AJ35-AK35) | AM35: =AR34 | AN35: =AM35*Plan!D12/100/12 | AO35: =MIN(Plan!E12,AM35+AN35) | AP35: =AM35+AN35-AO35 | AQ35: =MIN(AP35,MAX(0,$B35-((E$5<AO$5)*F35+(K$5<AO$5)*L35+(Q$5<AO$5)*R35+(W$5<AO$5)*X35+(AC$5<AO$5)*AD35+(AI$5<AO$5)*AJ35+(AU$5<AO$5)*AV35))) | AR35: =IF(AP35-AQ35<0.005,0,AP35-AQ35) | AS35: =AX34 | AT35: =AS35*Plan!D13/100/12 | AU35: =MIN(Plan!E13,AS35+AT35) | AV35: =AS35+AT35-AU35 | AW35: =MIN(AV35,MAX(0,$B35-((E$5<AU$5)*F35+(K$5<AU$5)*L35+(Q$5<AU$5)*R35+(W$5<AU$5)*X35+(AC$5<AU$5)*AD35+(AI$5<AU$5)*AJ35+(AO$5<AU$5)*AP35))) | AX35: =IF(AV35-AW35<0.005,0,AV35-AW35) | BC35: =H35+N35+T35+Z35+AF35+AL35+AR35+AX35
A36: 30 | B36: =MAX(0,$B$3-(E36+K36+Q36+W36+AC36+AI36+AO36+AU36)) | C36: =H35 | D36: =C36*Plan!D6/100/12 | E36: =MIN(Plan!E6,C36+D36) | F36: =C36+D36-E36 | G36: =MIN(F36,MAX(0,$B36-((K$5<E$5)*L36+(Q$5<E$5)*R36+(W$5<E$5)*X36+(AC$5<E$5)*AD36+(AI$5<E$5)*AJ36+(AO$5<E$5)*AP36+(AU$5<E$5)*AV36))) | H36: =IF(F36-G36<0.005,0,F36-G36) | I36: =N35 | J36: =I36*Plan!D7/100/12 | K36: =MIN(Plan!E7,I36+J36) | L36: =I36+J36-K36 | M36: =MIN(L36,MAX(0,$B36-((E$5<K$5)*F36+(Q$5<K$5)*R36+(W$5<K$5)*X36+(AC$5<K$5)*AD36+(AI$5<K$5)*AJ36+(AO$5<K$5)*AP36+(AU$5<K$5)*AV36))) | N36: =IF(L36-M36<0.005,0,L36-M36) | O36: =T35 | P36: =O36*Plan!D8/100/12 | Q36: =MIN(Plan!E8,O36+P36) | R36: =O36+P36-Q36 | S36: =MIN(R36,MAX(0,$B36-((E$5<Q$5)*F36+(K$5<Q$5)*L36+(W$5<Q$5)*X36+(AC$5<Q$5)*AD36+(AI$5<Q$5)*AJ36+(AO$5<Q$5)*AP36+(AU$5<Q$5)*AV36))) | T36: =IF(R36-S36<0.005,0,R36-S36) | U36: =Z35 | V36: =U36*Plan!D9/100/12 | W36: =MIN(Plan!E9,U36+V36) | X36: =U36+V36-W36 | Y36: =MIN(X36,MAX(0,$B36-((E$5<W$5)*F36+(K$5<W$5)*L36+(Q$5<W$5)*R36+(AC$5<W$5)*AD36+(AI$5<W$5)*AJ36+(AO$5<W$5)*AP36+(AU$5<W$5)*AV36))) | Z36: =IF(X36-Y36<0.005,0,X36-Y36) | AA36: =AF35 | AB36: =AA36*Plan!D10/100/12 | AC36: =MIN(Plan!E10,AA36+AB36) | AD36: =AA36+AB36-AC36 | AE36: =MIN(AD36,MAX(0,$B36-((E$5<AC$5)*F36+(K$5<AC$5)*L36+(Q$5<AC$5)*R36+(W$5<AC$5)*X36+(AI$5<AC$5)*AJ36+(AO$5<AC$5)*AP36+(AU$5<AC$5)*AV36))) | AF36: =IF(AD36-AE36<0.005,0,AD36-AE36) | AG36: =AL35 | AH36: =AG36*Plan!D11/100/12 | AI36: =MIN(Plan!E11,AG36+AH36) | AJ36: =AG36+AH36-AI36 | AK36: =MIN(AJ36,MAX(0,$B36-((E$5<AI$5)*F36+(K$5<AI$5)*L36+(Q$5<AI$5)*R36+(W$5<AI$5)*X36+(AC$5<AI$5)*AD36+(AO$5<AI$5)*AP36+(AU$5<AI$5)*AV36))) | AL36: =IF(AJ36-AK36<0.005,0,AJ36-AK36) | AM36: =AR35 | AN36: =AM36*Plan!D12/100/12 | AO36: =MIN(Plan!E12,AM36+AN36) | AP36: =AM36+AN36-AO36 | AQ36: =MIN(AP36,MAX(0,$B36-((E$5<AO$5)*F36+(K$5<AO$5)*L36+(Q$5<AO$5)*R36+(W$5<AO$5)*X36+(AC$5<AO$5)*AD36+(AI$5<AO$5)*AJ36+(AU$5<AO$5)*AV36))) | AR36: =IF(AP36-AQ36<0.005,0,AP36-AQ36) | AS36: =AX35 | AT36: =AS36*Plan!D13/100/12 | AU36: =MIN(Plan!E13,AS36+AT36) | AV36: =AS36+AT36-AU36 | AW36: =MIN(AV36,MAX(0,$B36-((E$5<AU$5)*F36+(K$5<AU$5)*L36+(Q$5<AU$5)*R36+(W$5<AU$5)*X36+(AC$5<AU$5)*AD36+(AI$5<AU$5)*AJ36+(AO$5<AU$5)*AP36))) | AX36: =IF(AV36-AW36<0.005,0,AV36-AW36) | BC36: =H36+N36+T36+Z36+AF36+AL36+AR36+AX36
A37: 31 | B37: =MAX(0,$B$3-(E37+K37+Q37+W37+AC37+AI37+AO37+AU37)) | C37: =H36 | D37: =C37*Plan!D6/100/12 | E37: =MIN(Plan!E6,C37+D37) | F37: =C37+D37-E37 | G37: =MIN(F37,MAX(0,$B37-((K$5<E$5)*L37+(Q$5<E$5)*R37+(W$5<E$5)*X37+(AC$5<E$5)*AD37+(AI$5<E$5)*AJ37+(AO$5<E$5)*AP37+(AU$5<E$5)*AV37))) | H37: =IF(F37-G37<0.005,0,F37-G37) | I37: =N36 | J37: =I37*Plan!D7/100/12 | K37: =MIN(Plan!E7,I37+J37) | L37: =I37+J37-K37 | M37: =MIN(L37,MAX(0,$B37-((E$5<K$5)*F37+(Q$5<K$5)*R37+(W$5<K$5)*X37+(AC$5<K$5)*AD37+(AI$5<K$5)*AJ37+(AO$5<K$5)*AP37+(AU$5<K$5)*AV37))) | N37: =IF(L37-M37<0.005,0,L37-M37) | O37: =T36 | P37: =O37*Plan!D8/100/12 | Q37: =MIN(Plan!E8,O37+P37) | R37: =O37+P37-Q37 | S37: =MIN(R37,MAX(0,$B37-((E$5<Q$5)*F37+(K$5<Q$5)*L37+(W$5<Q$5)*X37+(AC$5<Q$5)*AD37+(AI$5<Q$5)*AJ37+(AO$5<Q$5)*AP37+(AU$5<Q$5)*AV37))) | T37: =IF(R37-S37<0.005,0,R37-S37) | U37: =Z36 | V37: =U37*Plan!D9/100/12 | W37: =MIN(Plan!E9,U37+V37) | X37: =U37+V37-W37 | Y37: =MIN(X37,MAX(0,$B37-((E$5<W$5)*F37+(K$5<W$5)*L37+(Q$5<W$5)*R37+(AC$5<W$5)*AD37+(AI$5<W$5)*AJ37+(AO$5<W$5)*AP37+(AU$5<W$5)*AV37))) | Z37: =IF(X37-Y37<0.005,0,X37-Y37) | AA37: =AF36 | AB37: =AA37*Plan!D10/100/12 | AC37: =MIN(Plan!E10,AA37+AB37) | AD37: =AA37+AB37-AC37 | AE37: =MIN(AD37,MAX(0,$B37-((E$5<AC$5)*F37+(K$5<AC$5)*L37+(Q$5<AC$5)*R37+(W$5<AC$5)*X37+(AI$5<AC$5)*AJ37+(AO$5<AC$5)*AP37+(AU$5<AC$5)*AV37))) | AF37: =IF(AD37-AE37<0.005,0,AD37-AE37) | AG37: =AL36 | AH37: =AG37*Plan!D11/100/12 | AI37: =MIN(Plan!E11,AG37+AH37) | AJ37: =AG37+AH37-AI37 | AK37: =MIN(AJ37,MAX(0,$B37-((E$5<AI$5)*F37+(K$5<AI$5)*L37+(Q$5<AI$5)*R37+(W$5<AI$5)*X37+(AC$5<AI$5)*AD37+(AO$5<AI$5)*AP37+(AU$5<AI$5)*AV37))) | AL37: =IF(AJ37-AK37<0.005,0,AJ37-AK37) | AM37: =AR36 | AN37: =AM37*Plan!D12/100/12 | AO37: =MIN(Plan!E12,AM37+AN37) | AP37: =AM37+AN37-AO37 | AQ37: =MIN(AP37,MAX(0,$B37-((E$5<AO$5)*F37+(K$5<AO$5)*L37+(Q$5<AO$5)*R37+(W$5<AO$5)*X37+(AC$5<AO$5)*AD37+(AI$5<AO$5)*AJ37+(AU$5<AO$5)*AV37))) | AR37: =IF(AP37-AQ37<0.005,0,AP37-AQ37) | AS37: =AX36 | AT37: =AS37*Plan!D13/100/12 | AU37: =MIN(Plan!E13,AS37+AT37) | AV37: =AS37+AT37-AU37 | AW37: =MIN(AV37,MAX(0,$B37-((E$5<AU$5)*F37+(K$5<AU$5)*L37+(Q$5<AU$5)*R37+(W$5<AU$5)*X37+(AC$5<AU$5)*AD37+(AI$5<AU$5)*AJ37+(AO$5<AU$5)*AP37))) | AX37: =IF(AV37-AW37<0.005,0,AV37-AW37) | BC37: =H37+N37+T37+Z37+AF37+AL37+AR37+AX37
A38: 32 | B38: =MAX(0,$B$3-(E38+K38+Q38+W38+AC38+AI38+AO38+AU38)) | C38: =H37 | D38: =C38*Plan!D6/100/12 | E38: =MIN(Plan!E6,C38+D38) | F38: =C38+D38-E38 | G38: =MIN(F38,MAX(0,$B38-((K$5<E$5)*L38+(Q$5<E$5)*R38+(W$5<E$5)*X38+(AC$5<E$5)*AD38+(AI$5<E$5)*AJ38+(AO$5<E$5)*AP38+(AU$5<E$5)*AV38))) | H38: =IF(F38-G38<0.005,0,F38-G38) | I38: =N37 | J38: =I38*Plan!D7/100/12 | K38: =MIN(Plan!E7,I38+J38) | L38: =I38+J38-K38 | M38: =MIN(L38,MAX(0,$B38-((E$5<K$5)*F38+(Q$5<K$5)*R38+(W$5<K$5)*X38+(AC$5<K$5)*AD38+(AI$5<K$5)*AJ38+(AO$5<K$5)*AP38+(AU$5<K$5)*AV38))) | N38: =IF(L38-M38<0.005,0,L38-M38) | O38: =T37 | P38: =O38*Plan!D8/100/12 | Q38: =MIN(Plan!E8,O38+P38) | R38: =O38+P38-Q38 | S38: =MIN(R38,MAX(0,$B38-((E$5<Q$5)*F38+(K$5<Q$5)*L38+(W$5<Q$5)*X38+(AC$5<Q$5)*AD38+(AI$5<Q$5)*AJ38+(AO$5<Q$5)*AP38+(AU$5<Q$5)*AV38))) | T38: =IF(R38-S38<0.005,0,R38-S38) | U38: =Z37 | V38: =U38*Plan!D9/100/12 | W38: =MIN(Plan!E9,U38+V38) | X38: =U38+V38-W38 | Y38: =MIN(X38,MAX(0,$B38-((E$5<W$5)*F38+(K$5<W$5)*L38+(Q$5<W$5)*R38+(AC$5<W$5)*AD38+(AI$5<W$5)*AJ38+(AO$5<W$5)*AP38+(AU$5<W$5)*AV38))) | Z38: =IF(X38-Y38<0.005,0,X38-Y38) | AA38: =AF37 | AB38: =AA38*Plan!D10/100/12 | AC38: =MIN(Plan!E10,AA38+AB38) | AD38: =AA38+AB38-AC38 | AE38: =MIN(AD38,MAX(0,$B38-((E$5<AC$5)*F38+(K$5<AC$5)*L38+(Q$5<AC$5)*R38+(W$5<AC$5)*X38+(AI$5<AC$5)*AJ38+(AO$5<AC$5)*AP38+(AU$5<AC$5)*AV38))) | AF38: =IF(AD38-AE38<0.005,0,AD38-AE38) | AG38: =AL37 | AH38: =AG38*Plan!D11/100/12 | AI38: =MIN(Plan!E11,AG38+AH38) | AJ38: =AG38+AH38-AI38 | AK38: =MIN(AJ38,MAX(0,$B38-((E$5<AI$5)*F38+(K$5<AI$5)*L38+(Q$5<AI$5)*R38+(W$5<AI$5)*X38+(AC$5<AI$5)*AD38+(AO$5<AI$5)*AP38+(AU$5<AI$5)*AV38))) | AL38: =IF(AJ38-AK38<0.005,0,AJ38-AK38) | AM38: =AR37 | AN38: =AM38*Plan!D12/100/12 | AO38: =MIN(Plan!E12,AM38+AN38) | AP38: =AM38+AN38-AO38 | AQ38: =MIN(AP38,MAX(0,$B38-((E$5<AO$5)*F38+(K$5<AO$5)*L38+(Q$5<AO$5)*R38+(W$5<AO$5)*X38+(AC$5<AO$5)*AD38+(AI$5<AO$5)*AJ38+(AU$5<AO$5)*AV38))) | AR38: =IF(AP38-AQ38<0.005,0,AP38-AQ38) | AS38: =AX37 | AT38: =AS38*Plan!D13/100/12 | AU38: =MIN(Plan!E13,AS38+AT38) | AV38: =AS38+AT38-AU38 | AW38: =MIN(AV38,MAX(0,$B38-((E$5<AU$5)*F38+(K$5<AU$5)*L38+(Q$5<AU$5)*R38+(W$5<AU$5)*X38+(AC$5<AU$5)*AD38+(AI$5<AU$5)*AJ38+(AO$5<AU$5)*AP38))) | AX38: =IF(AV38-AW38<0.005,0,AV38-AW38) | BC38: =H38+N38+T38+Z38+AF38+AL38+AR38+AX38
A39: 33 | B39: =MAX(0,$B$3-(E39+K39+Q39+W39+AC39+AI39+AO39+AU39)) | C39: =H38 | D39: =C39*Plan!D6/100/12 | E39: =MIN(Plan!E6,C39+D39) | F39: =C39+D39-E39 | G39: =MIN(F39,MAX(0,$B39-((K$5<E$5)*L39+(Q$5<E$5)*R39+(W$5<E$5)*X39+(AC$5<E$5)*AD39+(AI$5<E$5)*AJ39+(AO$5<E$5)*AP39+(AU$5<E$5)*AV39))) | H39: =IF(F39-G39<0.005,0,F39-G39) | I39: =N38 | J39: =I39*Plan!D7/100/12 | K39: =MIN(Plan!E7,I39+J39) | L39: =I39+J39-K39 | M39: =MIN(L39,MAX(0,$B39-((E$5<K$5)*F39+(Q$5<K$5)*R39+(W$5<K$5)*X39+(AC$5<K$5)*AD39+(AI$5<K$5)*AJ39+(AO$5<K$5)*AP39+(AU$5<K$5)*AV39))) | N39: =IF(L39-M39<0.005,0,L39-M39) | O39: =T38 | P39: =O39*Plan!D8/100/12 | Q39: =MIN(Plan!E8,O39+P39) | R39: =O39+P39-Q39 | S39: =MIN(R39,MAX(0,$B39-((E$5<Q$5)*F39+(K$5<Q$5)*L39+(W$5<Q$5)*X39+(AC$5<Q$5)*AD39+(AI$5<Q$5)*AJ39+(AO$5<Q$5)*AP39+(AU$5<Q$5)*AV39))) | T39: =IF(R39-S39<0.005,0,R39-S39) | U39: =Z38 | V39: =U39*Plan!D9/100/12 | W39: =MIN(Plan!E9,U39+V39) | X39: =U39+V39-W39 | Y39: =MIN(X39,MAX(0,$B39-((E$5<W$5)*F39+(K$5<W$5)*L39+(Q$5<W$5)*R39+(AC$5<W$5)*AD39+(AI$5<W$5)*AJ39+(AO$5<W$5)*AP39+(AU$5<W$5)*AV39))) | Z39: =IF(X39-Y39<0.005,0,X39-Y39) | AA39: =AF38 | AB39: =AA39*Plan!D10/100/12 | AC39: =MIN(Plan!E10,AA39+AB39) | AD39: =AA39+AB39-AC39 | AE39: =MIN(AD39,MAX(0,$B39-((E$5<AC$5)*F39+(K$5<AC$5)*L39+(Q$5<AC$5)*R39+(W$5<AC$5)*X39+(AI$5<AC$5)*AJ39+(AO$5<AC$5)*AP39+(AU$5<AC$5)*AV39))) | AF39: =IF(AD39-AE39<0.005,0,AD39-AE39) | AG39: =AL38 | AH39: =AG39*Plan!D11/100/12 | AI39: =MIN(Plan!E11,AG39+AH39) | AJ39: =AG39+AH39-AI39 | AK39: =MIN(AJ39,MAX(0,$B39-((E$5<AI$5)*F39+(K$5<AI$5)*L39+(Q$5<AI$5)*R39+(W$5<AI$5)*X39+(AC$5<AI$5)*AD39+(AO$5<AI$5)*AP39+(AU$5<AI$5)*AV39))) | AL39: =IF(AJ39-AK39<0.005,0,AJ39-AK39) | AM39: =AR38 | AN39: =AM39*Plan!D12/100/12 | AO39: =MIN(Plan!E12,AM39+AN39) | AP39: =AM39+AN39-AO39 | AQ39: =MIN(AP39,MAX(0,$B39-((E$5<AO$5)*F39+(K$5<AO$5)*L39+(Q$5<AO$5)*R39+(W$5<AO$5)*X39+(AC$5<AO$5)*AD39+(AI$5<AO$5)*AJ39+(AU$5<AO$5)*AV39))) | AR39: =IF(AP39-AQ39<0.005,0,AP39-AQ39) | AS39: =AX38 | AT39: =AS39*Plan!D13/100/12 | AU39: =MIN(Plan!E13,AS39+AT39) | AV39: =AS39+AT39-AU39 | AW39: =MIN(AV39,MAX(0,$B39-((E$5<AU$5)*F39+(K$5<AU$5)*L39+(Q$5<AU$5)*R39+(W$5<AU$5)*X39+(AC$5<AU$5)*AD39+(AI$5<AU$5)*AJ39+(AO$5<AU$5)*AP39))) | AX39: =IF(AV39-AW39<0.005,0,AV39-AW39) | BC39: =H39+N39+T39+Z39+AF39+AL39+AR39+AX39
A40: 34 | B40: =MAX(0,$B$3-(E40+K40+Q40+W40+AC40+AI40+AO40+AU40)) | C40: =H39 | D40: =C40*Plan!D6/100/12 | E40: =MIN(Plan!E6,C40+D40) | F40: =C40+D40-E40 | G40: =MIN(F40,MAX(0,$B40-((K$5<E$5)*L40+(Q$5<E$5)*R40+(W$5<E$5)*X40+(AC$5<E$5)*AD40+(AI$5<E$5)*AJ40+(AO$5<E$5)*AP40+(AU$5<E$5)*AV40))) | H40: =IF(F40-G40<0.005,0,F40-G40) | I40: =N39 | J40: =I40*Plan!D7/100/12 | K40: =MIN(Plan!E7,I40+J40) | L40: =I40+J40-K40 | M40: =MIN(L40,MAX(0,$B40-((E$5<K$5)*F40+(Q$5<K$5)*R40+(W$5<K$5)*X40+(AC$5<K$5)*AD40+(AI$5<K$5)*AJ40+(AO$5<K$5)*AP40+(AU$5<K$5)*AV40))) | N40: =IF(L40-M40<0.005,0,L40-M40) | O40: =T39 | P40: =O40*Plan!D8/100/12 | Q40: =MIN(Plan!E8,O40+P40) | R40: =O40+P40-Q40 | S40: =MIN(R40,MAX(0,$B40-((E$5<Q$5)*F40+(K$5<Q$5)*L40+(W$5<Q$5)*X40+(AC$5<Q$5)*AD40+(AI$5<Q$5)*AJ40+(AO$5<Q$5)*AP40+(AU$5<Q$5)*AV40))) | T40: =IF(R40-S40<0.005,0,R40-S40) | U40: =Z39 | V40: =U40*Plan!D9/100/12 | W40: =MIN(Plan!E9,U40+V40) | X40: =U40+V40-W40 | Y40: =MIN(X40,MAX(0,$B40-((E$5<W$5)*F40+(K$5<W$5)*L40+(Q$5<W$5)*R40+(AC$5<W$5)*AD40+(AI$5<W$5)*AJ40+(AO$5<W$5)*AP40+(AU$5<W$5)*AV40))) | Z40: =IF(X40-Y40<0.005,0,X40-Y40) | AA40: =AF39 | AB40: =AA40*Plan!D10/100/12 | AC40: =MIN(Plan!E10,AA40+AB40) | AD40: =AA40+AB40-AC40 | AE40: =MIN(AD40,MAX(0,$B40-((E$5<AC$5)*F40+(K$5<AC$5)*L40+(Q$5<AC$5)*R40+(W$5<AC$5)*X40+(AI$5<AC$5)*AJ40+(AO$5<AC$5)*AP40+(AU$5<AC$5)*AV40))) | AF40: =IF(AD40-AE40<0.005,0,AD40-AE40) | AG40: =AL39 | AH40: =AG40*Plan!D11/100/12 | AI40: =MIN(Plan!E11,AG40+AH40) | AJ40: =AG40+AH40-AI40 | AK40: =MIN(AJ40,MAX(0,$B40-((E$5<AI$5)*F40+(K$5<AI$5)*L40+(Q$5<AI$5)*R40+(W$5<AI$5)*X40+(AC$5<AI$5)*AD40+(AO$5<AI$5)*AP40+(AU$5<AI$5)*AV40))) | AL40: =IF(AJ40-AK40<0.005,0,AJ40-AK40) | AM40: =AR39 | AN40: =AM40*Plan!D12/100/12 | AO40: =MIN(Plan!E12,AM40+AN40) | AP40: =AM40+AN40-AO40 | AQ40: =MIN(AP40,MAX(0,$B40-((E$5<AO$5)*F40+(K$5<AO$5)*L40+(Q$5<AO$5)*R40+(W$5<AO$5)*X40+(AC$5<AO$5)*AD40+(AI$5<AO$5)*AJ40+(AU$5<AO$5)*AV40))) | AR40: =IF(AP40-AQ40<0.005,0,AP40-AQ40) | AS40: =AX39 | AT40: =AS40*Plan!D13/100/12 | AU40: =MIN(Plan!E13,AS40+AT40) | AV40: =AS40+AT40-AU40 | AW40: =MIN(AV40,MAX(0,$B40-((E$5<AU$5)*F40+(K$5<AU$5)*L40+(Q$5<AU$5)*R40+(W$5<AU$5)*X40+(AC$5<AU$5)*AD40+(AI$5<AU$5)*AJ40+(AO$5<AU$5)*AP40))) | AX40: =IF(AV40-AW40<0.005,0,AV40-AW40) | BC40: =H40+N40+T40+Z40+AF40+AL40+AR40+AX40
A41: 35 | B41: =MAX(0,$B$3-(E41+K41+Q41+W41+AC41+AI41+AO41+AU41)) | C41: =H40 | D41: =C41*Plan!D6/100/12 | E41: =MIN(Plan!E6,C41+D41) | F41: =C41+D41-E41 | G41: =MIN(F41,MAX(0,$B41-((K$5<E$5)*L41+(Q$5<E$5)*R41+(W$5<E$5)*X41+(AC$5<E$5)*AD41+(AI$5<E$5)*AJ41+(AO$5<E$5)*AP41+(AU$5<E$5)*AV41))) | H41: =IF(F41-G41<0.005,0,F41-G41) | I41: =N40 | J41: =I41*Plan!D7/100/12 | K41: =MIN(Plan!E7,I41+J41) | L41: =I41+J41-K41 | M41: =MIN(L41,MAX(0,$B41-((E$5<K$5)*F41+(Q$5<K$5)*R41+(W$5<K$5)*X41+(AC$5<K$5)*AD41+(AI$5<K$5)*AJ41+(AO$5<K$5)*AP41+(AU$5<K$5)*AV41))) | N41: =IF(L41-M41<0.005,0,L41-M41) | O41: =T40 | P41: =O41*Plan!D8/100/12 | Q41: =MIN(Plan!E8,O41+P41) | R41: =O41+P41-Q41 | S41: =MIN(R41,MAX(0,$B41-((E$5<Q$5)*F41+(K$5<Q$5)*L41+(W$5<Q$5)*X41+(AC$5<Q$5)*AD41+(AI$5<Q$5)*AJ41+(AO$5<Q$5)*AP41+(AU$5<Q$5)*AV41))) | T41: =IF(R41-S41<0.005,0,R41-S41) | U41: =Z40 | V41: =U41*Plan!D9/100/12 | W41: =MIN(Plan!E9,U41+V41) | X41: =U41+V41-W41 | Y41: =MIN(X41,MAX(0,$B41-((E$5<W$5)*F41+(K$5<W$5)*L41+(Q$5<W$5)*R41+(AC$5<W$5)*AD41+(AI$5<W$5)*AJ41+(AO$5<W$5)*AP41+(AU$5<W$5)*AV41))) | Z41: =IF(X41-Y41<0.005,0,X41-Y41) | AA41: =AF40 | AB41: =AA41*Plan!D10/100/12 | AC41: =MIN(Plan!E10,AA41+AB41) | AD41: =AA41+AB41-AC41 | AE41: =MIN(AD41,MAX(0,$B41-((E$5<AC$5)*F41+(K$5<AC$5)*L41+(Q$5<AC$5)*R41+(W$5<AC$5)*X41+(AI$5<AC$5)*AJ41+(AO$5<AC$5)*AP41+(AU$5<AC$5)*AV41))) | AF41: =IF(AD41-AE41<0.005,0,AD41-AE41) | AG41: =AL40 | AH41: =AG41*Plan!D11/100/12 | AI41: =MIN(Plan!E11,AG41+AH41) | AJ41: =AG41+AH41-AI41 | AK41: =MIN(AJ41,MAX(0,$B41-((E$5<AI$5)*F41+(K$5<AI$5)*L41+(Q$5<AI$5)*R41+(W$5<AI$5)*X41+(AC$5<AI$5)*AD41+(AO$5<AI$5)*AP41+(AU$5<AI$5)*AV41))) | AL41: =IF(AJ41-AK41<0.005,0,AJ41-AK41) | AM41: =AR40 | AN41: =AM41*Plan!D12/100/12 | AO41: =MIN(Plan!E12,AM41+AN41) | AP41: =AM41+AN41-AO41 | AQ41: =MIN(AP41,MAX(0,$B41-((E$5<AO$5)*F41+(K$5<AO$5)*L41+(Q$5<AO$5)*R41+(W$5<AO$5)*X41+(AC$5<AO$5)*AD41+(AI$5<AO$5)*AJ41+(AU$5<AO$5)*AV41))) | AR41: =IF(AP41-AQ41<0.005,0,AP41-AQ41) | AS41: =AX40 | AT41: =AS41*Plan!D13/100/12 | AU41: =MIN(Plan!E13,AS41+AT41) | AV41: =AS41+AT41-AU41 | AW41: =MIN(AV41,MAX(0,$B41-((E$5<AU$5)*F41+(K$5<AU$5)*L41+(Q$5<AU$5)*R41+(W$5<AU$5)*X41+(AC$5<AU$5)*AD41+(AI$5<AU$5)*AJ41+(AO$5<AU$5)*AP41))) | AX41: =IF(AV41-AW41<0.005,0,AV41-AW41) | BC41: =H41+N41+T41+Z41+AF41+AL41+AR41+AX41
A42: 36 | B42: =MAX(0,$B$3-(E42+K42+Q42+W42+AC42+AI42+AO42+AU42)) | C42: =H41 | D42: =C42*Plan!D6/100/12 | E42: =MIN(Plan!E6,C42+D42) | F42: =C42+D42-E42 | G42: =MIN(F42,MAX(0,$B42-((K$5<E$5)*L42+(Q$5<E$5)*R42+(W$5<E$5)*X42+(AC$5<E$5)*AD42+(AI$5<E$5)*AJ42+(AO$5<E$5)*AP42+(AU$5<E$5)*AV42))) | H42: =IF(F42-G42<0.005,0,F42-G42) | I42: =N41 | J42: =I42*Plan!D7/100/12 | K42: =MIN(Plan!E7,I42+J42) | L42: =I42+J42-K42 | M42: =MIN(L42,MAX(0,$B42-((E$5<K$5)*F42+(Q$5<K$5)*R42+(W$5<K$5)*X42+(AC$5<K$5)*AD42+(AI$5<K$5)*AJ42+(AO$5<K$5)*AP42+(AU$5<K$5)*AV42))) | N42: =IF(L42-M42<0.005,0,L42-M42) | O42: =T41 | P42: =O42*Plan!D8/100/12 | Q42: =MIN(Plan!E8,O42+P42) | R42: =O42+P42-Q42 | S42: =MIN(R42,MAX(0,$B42-((E$5<Q$5)*F42+(K$5<Q$5)*L42+(W$5<Q$5)*X42+(AC$5<Q$5)*AD42+(AI$5<Q$5)*AJ42+(AO$5<Q$5)*AP42+(AU$5<Q$5)*AV42))) | T42: =IF(R42-S42<0.005,0,R42-S42) | U42: =Z41 | V42: =U42*Plan!D9/100/12 | W42: =MIN(Plan!E9,U42+V42) | X42: =U42+V42-W42 | Y42: =MIN(X42,MAX(0,$B42-((E$5<W$5)*F42+(K$5<W$5)*L42+(Q$5<W$5)*R42+(AC$5<W$5)*AD42+(AI$5<W$5)*AJ42+(AO$5<W$5)*AP42+(AU$5<W$5)*AV42))) | Z42: =IF(X42-Y42<0.005,0,X42-Y42) | AA42: =AF41 | AB42: =AA42*Plan!D10/100/12 | AC42: =MIN(Plan!E10,AA42+AB42) | AD42: =AA42+AB42-AC42 | AE42: =MIN(AD42,MAX(0,$B42-((E$5<AC$5)*F42+(K$5<AC$5)*L42+(Q$5<AC$5)*R42+(W$5<AC$5)*X42+(AI$5<AC$5)*AJ42+(AO$5<AC$5)*AP42+(AU$5<AC$5)*AV42))) | AF42: =IF(AD42-AE42<0.005,0,AD42-AE42) | AG42: =AL41 | AH42: =AG42*Plan!D11/100/12 | AI42: =MIN(Plan!E11,AG42+AH42) | AJ42: =AG42+AH42-AI42 | AK42: =MIN(AJ42,MAX(0,$B42-((E$5<AI$5)*F42+(K$5<AI$5)*L42+(Q$5<AI$5)*R42+(W$5<AI$5)*X42+(AC$5<AI$5)*AD42+(AO$5<AI$5)*AP42+(AU$5<AI$5)*AV42))) | AL42: =IF(AJ42-AK42<0.005,0,AJ42-AK42) | AM42: =AR41 | AN42: =AM42*Plan!D12/100/12 | AO42: =MIN(Plan!E12,AM42+AN42) | AP42: =AM42+AN42-AO42 | AQ42: =MIN(AP42,MAX(0,$B42-((E$5<AO$5)*F42+(K$5<AO$5)*L42+(Q$5<AO$5)*R42+(W$5<AO$5)*X42+(AC$5<AO$5)*AD42+(AI$5<AO$5)*AJ42+(AU$5<AO$5)*AV42))) | AR42: =IF(AP42-AQ42<0.005,0,AP42-AQ42) | AS42: =AX41 | AT42: =AS42*Plan!D13/100/12 | AU42: =MIN(Plan!E13,AS42+AT42) | AV42: =AS42+AT42-AU42 | AW42: =MIN(AV42,MAX(0,$B42-((E$5<AU$5)*F42+(K$5<AU$5)*L42+(Q$5<AU$5)*R42+(W$5<AU$5)*X42+(AC$5<AU$5)*AD42+(AI$5<AU$5)*AJ42+(AO$5<AU$5)*AP42))) | AX42: =IF(AV42-AW42<0.005,0,AV42-AW42) | BC42: =H42+N42+T42+Z42+AF42+AL42+AR42+AX42
A43: 37 | B43: =MAX(0,$B$3-(E43+K43+Q43+W43+AC43+AI43+AO43+AU43)) | C43: =H42 | D43: =C43*Plan!D6/100/12 | E43: =MIN(Plan!E6,C43+D43) | F43: =C43+D43-E43 | G43: =MIN(F43,MAX(0,$B43-((K$5<E$5)*L43+(Q$5<E$5)*R43+(W$5<E$5)*X43+(AC$5<E$5)*AD43+(AI$5<E$5)*AJ43+(AO$5<E$5)*AP43+(AU$5<E$5)*AV43))) | H43: =IF(F43-G43<0.005,0,F43-G43) | I43: =N42 | J43: =I43*Plan!D7/100/12 | K43: =MIN(Plan!E7,I43+J43) | L43: =I43+J43-K43 | M43: =MIN(L43,MAX(0,$B43-((E$5<K$5)*F43+(Q$5<K$5)*R43+(W$5<K$5)*X43+(AC$5<K$5)*AD43+(AI$5<K$5)*AJ43+(AO$5<K$5)*AP43+(AU$5<K$5)*AV43))) | N43: =IF(L43-M43<0.005,0,L43-M43) | O43: =T42 | P43: =O43*Plan!D8/100/12 | Q43: =MIN(Plan!E8,O43+P43) | R43: =O43+P43-Q43 | S43: =MIN(R43,MAX(0,$B43-((E$5<Q$5)*F43+(K$5<Q$5)*L43+(W$5<Q$5)*X43+(AC$5<Q$5)*AD43+(AI$5<Q$5)*AJ43+(AO$5<Q$5)*AP43+(AU$5<Q$5)*AV43))) | T43: =IF(R43-S43<0.005,0,R43-S43) | U43: =Z42 | V43: =U43*Plan!D9/100/12 | W43: =MIN(Plan!E9,U43+V43) | X43: =U43+V43-W43 | Y43: =MIN(X43,MAX(0,$B43-((E$5<W$5)*F43+(K$5<W$5)*L43+(Q$5<W$5)*R43+(AC$5<W$5)*AD43+(AI$5<W$5)*AJ43+(AO$5<W$5)*AP43+(AU$5<W$5)*AV43))) | Z43: =IF(X43-Y43<0.005,0,X43-Y43) | AA43: =AF42 | AB43: =AA43*Plan!D10/100/12 | AC43: =MIN(Plan!E10,AA43+AB43) | AD43: =AA43+AB43-AC43 | AE43: =MIN(AD43,MAX(0,$B43-((E$5<AC$5)*F43+(K$5<AC$5)*L43+(Q$5<AC$5)*R43+(W$5<AC$5)*X43+(AI$5<AC$5)*AJ43+(AO$5<AC$5)*AP43+(AU$5<AC$5)*AV43))) | AF43: =IF(AD43-AE43<0.005,0,AD43-AE43) | AG43: =AL42 | AH43: =AG43*Plan!D11/100/12 | AI43: =MIN(Plan!E11,AG43+AH43) | AJ43: =AG43+AH43-AI43 | AK43: =MIN(AJ43,MAX(0,$B43-((E$5<AI$5)*F43+(K$5<AI$5)*L43+(Q$5<AI$5)*R43+(W$5<AI$5)*X43+(AC$5<AI$5)*AD43+(AO$5<AI$5)*AP43+(AU$5<AI$5)*AV43))) | AL43: =IF(AJ43-AK43<0.005,0,AJ43-AK43) | AM43: =AR42 | AN43: =AM43*Plan!D12/100/12 | AO43: =MIN(Plan!E12,AM43+AN43) | AP43: =AM43+AN43-AO43 | AQ43: =MIN(AP43,MAX(0,$B43-((E$5<AO$5)*F43+(K$5<AO$5)*L43+(Q$5<AO$5)*R43+(W$5<AO$5)*X43+(AC$5<AO$5)*AD43+(AI$5<AO$5)*AJ43+(AU$5<AO$5)*AV43))) | AR43: =IF(AP43-AQ43<0.005,0,AP43-AQ43) | AS43: =AX42 | AT43: =AS43*Plan!D13/100/12 | AU43: =MIN(Plan!E13,AS43+AT43) | AV43: =AS43+AT43-AU43 | AW43: =MIN(AV43,MAX(0,$B43-((E$5<AU$5)*F43+(K$5<AU$5)*L43+(Q$5<AU$5)*R43+(W$5<AU$5)*X43+(AC$5<AU$5)*AD43+(AI$5<AU$5)*AJ43+(AO$5<AU$5)*AP43))) | AX43: =IF(AV43-AW43<0.005,0,AV43-AW43) | BC43: =H43+N43+T43+Z43+AF43+AL43+AR43+AX43
A44: 38 | B44: =MAX(0,$B$3-(E44+K44+Q44+W44+AC44+AI44+AO44+AU44)) | C44: =H43 | D44: =C44*Plan!D6/100/12 | E44: =MIN(Plan!E6,C44+D44) | F44: =C44+D44-E44 | G44: =MIN(F44,MAX(0,$B44-((K$5<E$5)*L44+(Q$5<E$5)*R44+(W$5<E$5)*X44+(AC$5<E$5)*AD44+(AI$5<E$5)*AJ44+(AO$5<E$5)*AP44+(AU$5<E$5)*AV44))) | H44: =IF(F44-G44<0.005,0,F44-G44) | I44: =N43 | J44: =I44*Plan!D7/100/12 | K44: =MIN(Plan!E7,I44+J44) | L44: =I44+J44-K44 | M44: =MIN(L44,MAX(0,$B44-((E$5<K$5)*F44+(Q$5<K$5)*R44+(W$5<K$5)*X44+(AC$5<K$5)*AD44+(AI$5<K$5)*AJ44+(AO$5<K$5)*AP44+(AU$5<K$5)*AV44))) | N44: =IF(L44-M44<0.005,0,L44-M44) | O44: =T43 | P44: =O44*Plan!D8/100/12 | Q44: =MIN(Plan!E8,O44+P44) | R44: =O44+P44-Q44 | S44: =MIN(R44,MAX(0,$B44-((E$5<Q$5)*F44+(K$5<Q$5)*L44+(W$5<Q$5)*X44+(AC$5<Q$5)*AD44+(AI$5<Q$5)*AJ44+(AO$5<Q$5)*AP44+(AU$5<Q$5)*AV44))) | T44: =IF(R44-S44<0.005,0,R44-S44) | U44: =Z43 | V44: =U44*Plan!D9/100/12 | W44: =MIN(Plan!E9,U44+V44) | X44: =U44+V44-W44 | Y44: =MIN(X44,MAX(0,$B44-((E$5<W$5)*F44+(K$5<W$5)*L44+(Q$5<W$5)*R44+(AC$5<W$5)*AD44+(AI$5<W$5)*AJ44+(AO$5<W$5)*AP44+(AU$5<W$5)*AV44))) | Z44: =IF(X44-Y44<0.005,0,X44-Y44) | AA44: =AF43 | AB44: =AA44*Plan!D10/100/12 | AC44: =MIN(Plan!E10,AA44+AB44) | AD44: =AA44+AB44-AC44 | AE44: =MIN(AD44,MAX(0,$B44-((E$5<AC$5)*F44+(K$5<AC$5)*L44+(Q$5<AC$5)*R44+(W$5<AC$5)*X44+(AI$5<AC$5)*AJ44+(AO$5<AC$5)*AP44+(AU$5<AC$5)*AV44))) | AF44: =IF(AD44-AE44<0.005,0,AD44-AE44) | AG44: =AL43 | AH44: =AG44*Plan!D11/100/12 | AI44: =MIN(Plan!E11,AG44+AH44) | AJ44: =AG44+AH44-AI44 | AK44: =MIN(AJ44,MAX(0,$B44-((E$5<AI$5)*F44+(K$5<AI$5)*L44+(Q$5<AI$5)*R44+(W$5<AI$5)*X44+(AC$5<AI$5)*AD44+(AO$5<AI$5)*AP44+(AU$5<AI$5)*AV44))) | AL44: =IF(AJ44-AK44<0.005,0,AJ44-AK44) | AM44: =AR43 | AN44: =AM44*Plan!D12/100/12 | AO44: =MIN(Plan!E12,AM44+AN44) | AP44: =AM44+AN44-AO44 | AQ44: =MIN(AP44,MAX(0,$B44-((E$5<AO$5)*F44+(K$5<AO$5)*L44+(Q$5<AO$5)*R44+(W$5<AO$5)*X44+(AC$5<AO$5)*AD44+(AI$5<AO$5)*AJ44+(AU$5<AO$5)*AV44))) | AR44: =IF(AP44-AQ44<0.005,0,AP44-AQ44) | AS44: =AX43 | AT44: =AS44*Plan!D13/100/12 | AU44: =MIN(Plan!E13,AS44+AT44) | AV44: =AS44+AT44-AU44 | AW44: =MIN(AV44,MAX(0,$B44-((E$5<AU$5)*F44+(K$5<AU$5)*L44+(Q$5<AU$5)*R44+(W$5<AU$5)*X44+(AC$5<AU$5)*AD44+(AI$5<AU$5)*AJ44+(AO$5<AU$5)*AP44))) | AX44: =IF(AV44-AW44<0.005,0,AV44-AW44) | BC44: =H44+N44+T44+Z44+AF44+AL44+AR44+AX44
A45: 39 | B45: =MAX(0,$B$3-(E45+K45+Q45+W45+AC45+AI45+AO45+AU45)) | C45: =H44 | D45: =C45*Plan!D6/100/12 | E45: =MIN(Plan!E6,C45+D45) | F45: =C45+D45-E45 | G45: =MIN(F45,MAX(0,$B45-((K$5<E$5)*L45+(Q$5<E$5)*R45+(W$5<E$5)*X45+(AC$5<E$5)*AD45+(AI$5<E$5)*AJ45+(AO$5<E$5)*AP45+(AU$5<E$5)*AV45))) | H45: =IF(F45-G45<0.005,0,F45-G45) | I45: =N44 | J45: =I45*Plan!D7/100/12 | K45: =MIN(Plan!E7,I45+J45) | L45: =I45+J45-K45 | M45: =MIN(L45,MAX(0,$B45-((E$5<K$5)*F45+(Q$5<K$5)*R45+(W$5<K$5)*X45+(AC$5<K$5)*AD45+(AI$5<K$5)*AJ45+(AO$5<K$5)*AP45+(AU$5<K$5)*AV45))) | N45: =IF(L45-M45<0.005,0,L45-M45) | O45: =T44 | P45: =O45*Plan!D8/100/12 | Q45: =MIN(Plan!E8,O45+P45) | R45: =O45+P45-Q45 | S45: =MIN(R45,MAX(0,$B45-((E$5<Q$5)*F45+(K$5<Q$5)*L45+(W$5<Q$5)*X45+(AC$5<Q$5)*AD45+(AI$5<Q$5)*AJ45+(AO$5<Q$5)*AP45+(AU$5<Q$5)*AV45))) | T45: =IF(R45-S45<0.005,0,R45-S45) | U45: =Z44 | V45: =U45*Plan!D9/100/12 | W45: =MIN(Plan!E9,U45+V45) | X45: =U45+V45-W45 | Y45: =MIN(X45,MAX(0,$B45-((E$5<W$5)*F45+(K$5<W$5)*L45+(Q$5<W$5)*R45+(AC$5<W$5)*AD45+(AI$5<W$5)*AJ45+(AO$5<W$5)*AP45+(AU$5<W$5)*AV45))) | Z45: =IF(X45-Y45<0.005,0,X45-Y45) | AA45: =AF44 | AB45: =AA45*Plan!D10/100/12 | AC45: =MIN(Plan!E10,AA45+AB45) | AD45: =AA45+AB45-AC45 | AE45: =MIN(AD45,MAX(0,$B45-((E$5<AC$5)*F45+(K$5<AC$5)*L45+(Q$5<AC$5)*R45+(W$5<AC$5)*X45+(AI$5<AC$5)*AJ45+(AO$5<AC$5)*AP45+(AU$5<AC$5)*AV45))) | AF45: =IF(AD45-AE45<0.005,0,AD45-AE45) | AG45: =AL44 | AH45: =AG45*Plan!D11/100/12 | AI45: =MIN(Plan!E11,AG45+AH45) | AJ45: =AG45+AH45-AI45 | AK45: =MIN(AJ45,MAX(0,$B45-((E$5<AI$5)*F45+(K$5<AI$5)*L45+(Q$5<AI$5)*R45+(W$5<AI$5)*X45+(AC$5<AI$5)*AD45+(AO$5<AI$5)*AP45+(AU$5<AI$5)*AV45))) | AL45: =IF(AJ45-AK45<0.005,0,AJ45-AK45) | AM45: =AR44 | AN45: =AM45*Plan!D12/100/12 | AO45: =MIN(Plan!E12,AM45+AN45) | AP45: =AM45+AN45-AO45 | AQ45: =MIN(AP45,MAX(0,$B45-((E$5<AO$5)*F45+(K$5<AO$5)*L45+(Q$5<AO$5)*R45+(W$5<AO$5)*X45+(AC$5<AO$5)*AD45+(AI$5<AO$5)*AJ45+(AU$5<AO$5)*AV45))) | AR45: =IF(AP45-AQ45<0.005,0,AP45-AQ45) | AS45: =AX44 | AT45: =AS45*Plan!D13/100/12 | AU45: =MIN(Plan!E13,AS45+AT45) | AV45: =AS45+AT45-AU45 | AW45: =MIN(AV45,MAX(0,$B45-((E$5<AU$5)*F45+(K$5<AU$5)*L45+(Q$5<AU$5)*R45+(W$5<AU$5)*X45+(AC$5<AU$5)*AD45+(AI$5<AU$5)*AJ45+(AO$5<AU$5)*AP45))) | AX45: =IF(AV45-AW45<0.005,0,AV45-AW45) | BC45: =H45+N45+T45+Z45+AF45+AL45+AR45+AX45
A46: 40 | B46: =MAX(0,$B$3-(E46+K46+Q46+W46+AC46+AI46+AO46+AU46)) | C46: =H45 | D46: =C46*Plan!D6/100/12 | E46: =MIN(Plan!E6,C46+D46) | F46: =C46+D46-E46 | G46: =MIN(F46,MAX(0,$B46-((K$5<E$5)*L46+(Q$5<E$5)*R46+(W$5<E$5)*X46+(AC$5<E$5)*AD46+(AI$5<E$5)*AJ46+(AO$5<E$5)*AP46+(AU$5<E$5)*AV46))) | H46: =IF(F46-G46<0.005,0,F46-G46) | I46: =N45 | J46: =I46*Plan!D7/100/12 | K46: =MIN(Plan!E7,I46+J46) | L46: =I46+J46-K46 | M46: =MIN(L46,MAX(0,$B46-((E$5<K$5)*F46+(Q$5<K$5)*R46+(W$5<K$5)*X46+(AC$5<K$5)*AD46+(AI$5<K$5)*AJ46+(AO$5<K$5)*AP46+(AU$5<K$5)*AV46))) | N46: =IF(L46-M46<0.005,0,L46-M46) | O46: =T45 | P46: =O46*Plan!D8/100/12 | Q46: =MIN(Plan!E8,O46+P46) | R46: =O46+P46-Q46 | S46: =MIN(R46,MAX(0,$B46-((E$5<Q$5)*F46+(K$5<Q$5)*L46+(W$5<Q$5)*X46+(AC$5<Q$5)*AD46+(AI$5<Q$5)*AJ46+(AO$5<Q$5)*AP46+(AU$5<Q$5)*AV46))) | T46: =IF(R46-S46<0.005,0,R46-S46) | U46: =Z45 | V46: =U46*Plan!D9/100/12 | W46: =MIN(Plan!E9,U46+V46) | X46: =U46+V46-W46 | Y46: =MIN(X46,MAX(0,$B46-((E$5<W$5)*F46+(K$5<W$5)*L46+(Q$5<W$5)*R46+(AC$5<W$5)*AD46+(AI$5<W$5)*AJ46+(AO$5<W$5)*AP46+(AU$5<W$5)*AV46))) | Z46: =IF(X46-Y46<0.005,0,X46-Y46) | AA46: =AF45 | AB46: =AA46*Plan!D10/100/12 | AC46: =MIN(Plan!E10,AA46+AB46) | AD46: =AA46+AB46-AC46 | AE46: =MIN(AD46,MAX(0,$B46-((E$5<AC$5)*F46+(K$5<AC$5)*L46+(Q$5<AC$5)*R46+(W$5<AC$5)*X46+(AI$5<AC$5)*AJ46+(AO$5<AC$5)*AP46+(AU$5<AC$5)*AV46))) | AF46: =IF(AD46-AE46<0.005,0,AD46-AE46) | AG46: =AL45 | AH46: =AG46*Plan!D11/100/12 | AI46: =MIN(Plan!E11,AG46+AH46) | AJ46: =AG46+AH46-AI46 | AK46: =MIN(AJ46,MAX(0,$B46-((E$5<AI$5)*F46+(K$5<AI$5)*L46+(Q$5<AI$5)*R46+(W$5<AI$5)*X46+(AC$5<AI$5)*AD46+(AO$5<AI$5)*AP46+(AU$5<AI$5)*AV46))) | AL46: =IF(AJ46-AK46<0.005,0,AJ46-AK46) | AM46: =AR45 | AN46: =AM46*Plan!D12/100/12 | AO46: =MIN(Plan!E12,AM46+AN46) | AP46: =AM46+AN46-AO46 | AQ46: =MIN(AP46,MAX(0,$B46-((E$5<AO$5)*F46+(K$5<AO$5)*L46+(Q$5<AO$5)*R46+(W$5<AO$5)*X46+(AC$5<AO$5)*AD46+(AI$5<AO$5)*AJ46+(AU$5<AO$5)*AV46))) | AR46: =IF(AP46-AQ46<0.005,0,AP46-AQ46) | AS46: =AX45 | AT46: =AS46*Plan!D13/100/12 | AU46: =MIN(Plan!E13,AS46+AT46) | AV46: =AS46+AT46-AU46 | AW46: =MIN(AV46,MAX(0,$B46-((E$5<AU$5)*F46+(K$5<AU$5)*L46+(Q$5<AU$5)*R46+(W$5<AU$5)*X46+(AC$5<AU$5)*AD46+(AI$5<AU$5)*AJ46+(AO$5<AU$5)*AP46))) | AX46: =IF(AV46-AW46<0.005,0,AV46-AW46) | BC46: =H46+N46+T46+Z46+AF46+AL46+AR46+AX46
A47: 41 | B47: =MAX(0,$B$3-(E47+K47+Q47+W47+AC47+AI47+AO47+AU47)) | C47: =H46 | D47: =C47*Plan!D6/100/12 | E47: =MIN(Plan!E6,C47+D47) | F47: =C47+D47-E47 | G47: =MIN(F47,MAX(0,$B47-((K$5<E$5)*L47+(Q$5<E$5)*R47+(W$5<E$5)*X47+(AC$5<E$5)*AD47+(AI$5<E$5)*AJ47+(AO$5<E$5)*AP47+(AU$5<E$5)*AV47))) | H47: =IF(F47-G47<0.005,0,F47-G47) | I47: =N46 | J47: =I47*Plan!D7/100/12 | K47: =MIN(Plan!E7,I47+J47) | L47: =I47+J47-K47 | M47: =MIN(L47,MAX(0,$B47-((E$5<K$5)*F47+(Q$5<K$5)*R47+(W$5<K$5)*X47+(AC$5<K$5)*AD47+(AI$5<K$5)*AJ47+(AO$5<K$5)*AP47+(AU$5<K$5)*AV47))) | N47: =IF(L47-M47<0.005,0,L47-M47) | O47: =T46 | P47: =O47*Plan!D8/100/12 | Q47: =MIN(Plan!E8,O47+P47) | R47: =O47+P47-Q47 | S47: =MIN(R47,MAX(0,$B47-((E$5<Q$5)*F47+(K$5<Q$5)*L47+(W$5<Q$5)*X47+(AC$5<Q$5)*AD47+(AI$5<Q$5)*AJ47+(AO$5<Q$5)*AP47+(AU$5<Q$5)*AV47))) | T47: =IF(R47-S47<0.005,0,R47-S47) | U47: =Z46 | V47: =U47*Plan!D9/100/12 | W47: =MIN(Plan!E9,U47+V47) | X47: =U47+V47-W47 | Y47: =MIN(X47,MAX(0,$B47-((E$5<W$5)*F47+(K$5<W$5)*L47+(Q$5<W$5)*R47+(AC$5<W$5)*AD47+(AI$5<W$5)*AJ47+(AO$5<W$5)*AP47+(AU$5<W$5)*AV47))) | Z47: =IF(X47-Y47<0.005,0,X47-Y47) | AA47: =AF46 | AB47: =AA47*Plan!D10/100/12 | AC47: =MIN(Plan!E10,AA47+AB47) | AD47: =AA47+AB47-AC47 | AE47: =MIN(AD47,MAX(0,$B47-((E$5<AC$5)*F47+(K$5<AC$5)*L47+(Q$5<AC$5)*R47+(W$5<AC$5)*X47+(AI$5<AC$5)*AJ47+(AO$5<AC$5)*AP47+(AU$5<AC$5)*AV47))) | AF47: =IF(AD47-AE47<0.005,0,AD47-AE47) | AG47: =AL46 | AH47: =AG47*Plan!D11/100/12 | AI47: =MIN(Plan!E11,AG47+AH47) | AJ47: =AG47+AH47-AI47 | AK47: =MIN(AJ47,MAX(0,$B47-((E$5<AI$5)*F47+(K$5<AI$5)*L47+(Q$5<AI$5)*R47+(W$5<AI$5)*X47+(AC$5<AI$5)*AD47+(AO$5<AI$5)*AP47+(AU$5<AI$5)*AV47))) | AL47: =IF(AJ47-AK47<0.005,0,AJ47-AK47) | AM47: =AR46 | AN47: =AM47*Plan!D12/100/12 | AO47: =MIN(Plan!E12,AM47+AN47) | AP47: =AM47+AN47-AO47 | AQ47: =MIN(AP47,MAX(0,$B47-((E$5<AO$5)*F47+(K$5<AO$5)*L47+(Q$5<AO$5)*R47+(W$5<AO$5)*X47+(AC$5<AO$5)*AD47+(AI$5<AO$5)*AJ47+(AU$5<AO$5)*AV47))) | AR47: =IF(AP47-AQ47<0.005,0,AP47-AQ47) | AS47: =AX46 | AT47: =AS47*Plan!D13/100/12 | AU47: =MIN(Plan!E13,AS47+AT47) | AV47: =AS47+AT47-AU47 | AW47: =MIN(AV47,MAX(0,$B47-((E$5<AU$5)*F47+(K$5<AU$5)*L47+(Q$5<AU$5)*R47+(W$5<AU$5)*X47+(AC$5<AU$5)*AD47+(AI$5<AU$5)*AJ47+(AO$5<AU$5)*AP47))) | AX47: =IF(AV47-AW47<0.005,0,AV47-AW47) | BC47: =H47+N47+T47+Z47+AF47+AL47+AR47+AX47
A48: 42 | B48: =MAX(0,$B$3-(E48+K48+Q48+W48+AC48+AI48+AO48+AU48)) | C48: =H47 | D48: =C48*Plan!D6/100/12 | E48: =MIN(Plan!E6,C48+D48) | F48: =C48+D48-E48 | G48: =MIN(F48,MAX(0,$B48-((K$5<E$5)*L48+(Q$5<E$5)*R48+(W$5<E$5)*X48+(AC$5<E$5)*AD48+(AI$5<E$5)*AJ48+(AO$5<E$5)*AP48+(AU$5<E$5)*AV48))) | H48: =IF(F48-G48<0.005,0,F48-G48) | I48: =N47 | J48: =I48*Plan!D7/100/12 | K48: =MIN(Plan!E7,I48+J48) | L48: =I48+J48-K48 | M48: =MIN(L48,MAX(0,$B48-((E$5<K$5)*F48+(Q$5<K$5)*R48+(W$5<K$5)*X48+(AC$5<K$5)*AD48+(AI$5<K$5)*AJ48+(AO$5<K$5)*AP48+(AU$5<K$5)*AV48))) | N48: =IF(L48-M48<0.005,0,L48-M48) | O48: =T47 | P48: =O48*Plan!D8/100/12 | Q48: =MIN(Plan!E8,O48+P48) | R48: =O48+P48-Q48 | S48: =MIN(R48,MAX(0,$B48-((E$5<Q$5)*F48+(K$5<Q$5)*L48+(W$5<Q$5)*X48+(AC$5<Q$5)*AD48+(AI$5<Q$5)*AJ48+(AO$5<Q$5)*AP48+(AU$5<Q$5)*AV48))) | T48: =IF(R48-S48<0.005,0,R48-S48) | U48: =Z47 | V48: =U48*Plan!D9/100/12 | W48: =MIN(Plan!E9,U48+V48) | X48: =U48+V48-W48 | Y48: =MIN(X48,MAX(0,$B48-((E$5<W$5)*F48+(K$5<W$5)*L48+(Q$5<W$5)*R48+(AC$5<W$5)*AD48+(AI$5<W$5)*AJ48+(AO$5<W$5)*AP48+(AU$5<W$5)*AV48))) | Z48: =IF(X48-Y48<0.005,0,X48-Y48) | AA48: =AF47 | AB48: =AA48*Plan!D10/100/12 | AC48: =MIN(Plan!E10,AA48+AB48) | AD48: =AA48+AB48-AC48 | AE48: =MIN(AD48,MAX(0,$B48-((E$5<AC$5)*F48+(K$5<AC$5)*L48+(Q$5<AC$5)*R48+(W$5<AC$5)*X48+(AI$5<AC$5)*AJ48+(AO$5<AC$5)*AP48+(AU$5<AC$5)*AV48))) | AF48: =IF(AD48-AE48<0.005,0,AD48-AE48) | AG48: =AL47 | AH48: =AG48*Plan!D11/100/12 | AI48: =MIN(Plan!E11,AG48+AH48) | AJ48: =AG48+AH48-AI48 | AK48: =MIN(AJ48,MAX(0,$B48-((E$5<AI$5)*F48+(K$5<AI$5)*L48+(Q$5<AI$5)*R48+(W$5<AI$5)*X48+(AC$5<AI$5)*AD48+(AO$5<AI$5)*AP48+(AU$5<AI$5)*AV48))) | AL48: =IF(AJ48-AK48<0.005,0,AJ48-AK48) | AM48: =AR47 | AN48: =AM48*Plan!D12/100/12 | AO48: =MIN(Plan!E12,AM48+AN48) | AP48: =AM48+AN48-AO48 | AQ48: =MIN(AP48,MAX(0,$B48-((E$5<AO$5)*F48+(K$5<AO$5)*L48+(Q$5<AO$5)*R48+(W$5<AO$5)*X48+(AC$5<AO$5)*AD48+(AI$5<AO$5)*AJ48+(AU$5<AO$5)*AV48))) | AR48: =IF(AP48-AQ48<0.005,0,AP48-AQ48) | AS48: =AX47 | AT48: =AS48*Plan!D13/100/12 | AU48: =MIN(Plan!E13,AS48+AT48) | AV48: =AS48+AT48-AU48 | AW48: =MIN(AV48,MAX(0,$B48-((E$5<AU$5)*F48+(K$5<AU$5)*L48+(Q$5<AU$5)*R48+(W$5<AU$5)*X48+(AC$5<AU$5)*AD48+(AI$5<AU$5)*AJ48+(AO$5<AU$5)*AP48))) | AX48: =IF(AV48-AW48<0.005,0,AV48-AW48) | BC48: =H48+N48+T48+Z48+AF48+AL48+AR48+AX48
A49: 43 | B49: =MAX(0,$B$3-(E49+K49+Q49+W49+AC49+AI49+AO49+AU49)) | C49: =H48 | D49: =C49*Plan!D6/100/12 | E49: =MIN(Plan!E6,C49+D49) | F49: =C49+D49-E49 | G49: =MIN(F49,MAX(0,$B49-((K$5<E$5)*L49+(Q$5<E$5)*R49+(W$5<E$5)*X49+(AC$5<E$5)*AD49+(AI$5<E$5)*AJ49+(AO$5<E$5)*AP49+(AU$5<E$5)*AV49))) | H49: =IF(F49-G49<0.005,0,F49-G49) | I49: =N48 | J49: =I49*Plan!D7/100/12 | K49: =MIN(Plan!E7,I49+J49) | L49: =I49+J49-K49 | M49: =MIN(L49,MAX(0,$B49-((E$5<K$5)*F49+(Q$5<K$5)*R49+(W$5<K$5)*X49+(AC$5<K$5)*AD49+(AI$5<K$5)*AJ49+(AO$5<K$5)*AP49+(AU$5<K$5)*AV49))) | N49: =IF(L49-M49<0.005,0,L49-M49) | O49: =T48 | P49: =O49*Plan!D8/100/12 | Q49: =MIN(Plan!E8,O49+P49) | R49: =O49+P49-Q49 | S49: =MIN(R49,MAX(0,$B49-((E$5<Q$5)*F49+(K$5<Q$5)*L49+(W$5<Q$5)*X49+(AC$5<Q$5)*AD49+(AI$5<Q$5)*AJ49+(AO$5<Q$5)*AP49+(AU$5<Q$5)*AV49))) | T49: =IF(R49-S49<0.005,0,R49-S49) | U49: =Z48 | V49: =U49*Plan!D9/100/12 | W49: =MIN(Plan!E9,U49+V49) | X49: =U49+V49-W49 | Y49: =MIN(X49,MAX(0,$B49-((E$5<W$5)*F49+(K$5<W$5)*L49+(Q$5<W$5)*R49+(AC$5<W$5)*AD49+(AI$5<W$5)*AJ49+(AO$5<W$5)*AP49+(AU$5<W$5)*AV49))) | Z49: =IF(X49-Y49<0.005,0,X49-Y49) | AA49: =AF48 | AB49: =AA49*Plan!D10/100/12 | AC49: =MIN(Plan!E10,AA49+AB49) | AD49: =AA49+AB49-AC49 | AE49: =MIN(AD49,MAX(0,$B49-((E$5<AC$5)*F49+(K$5<AC$5)*L49+(Q$5<AC$5)*R49+(W$5<AC$5)*X49+(AI$5<AC$5)*AJ49+(AO$5<AC$5)*AP49+(AU$5<AC$5)*AV49))) | AF49: =IF(AD49-AE49<0.005,0,AD49-AE49) | AG49: =AL48 | AH49: =AG49*Plan!D11/100/12 | AI49: =MIN(Plan!E11,AG49+AH49) | AJ49: =AG49+AH49-AI49 | AK49: =MIN(AJ49,MAX(0,$B49-((E$5<AI$5)*F49+(K$5<AI$5)*L49+(Q$5<AI$5)*R49+(W$5<AI$5)*X49+(AC$5<AI$5)*AD49+(AO$5<AI$5)*AP49+(AU$5<AI$5)*AV49))) | AL49: =IF(AJ49-AK49<0.005,0,AJ49-AK49) | AM49: =AR48 | AN49: =AM49*Plan!D12/100/12 | AO49: =MIN(Plan!E12,AM49+AN49) | AP49: =AM49+AN49-AO49 | AQ49: =MIN(AP49,MAX(0,$B49-((E$5<AO$5)*F49+(K$5<AO$5)*L49+(Q$5<AO$5)*R49+(W$5<AO$5)*X49+(AC$5<AO$5)*AD49+(AI$5<AO$5)*AJ49+(AU$5<AO$5)*AV49))) | AR49: =IF(AP49-AQ49<0.005,0,AP49-AQ49) | AS49: =AX48 | AT49: =AS49*Plan!D13/100/12 | AU49: =MIN(Plan!E13,AS49+AT49) | AV49: =AS49+AT49-AU49 | AW49: =MIN(AV49,MAX(0,$B49-((E$5<AU$5)*F49+(K$5<AU$5)*L49+(Q$5<AU$5)*R49+(W$5<AU$5)*X49+(AC$5<AU$5)*AD49+(AI$5<AU$5)*AJ49+(AO$5<AU$5)*AP49))) | AX49: =IF(AV49-AW49<0.005,0,AV49-AW49) | BC49: =H49+N49+T49+Z49+AF49+AL49+AR49+AX49
A50: 44 | B50: =MAX(0,$B$3-(E50+K50+Q50+W50+AC50+AI50+AO50+AU50)) | C50: =H49 | D50: =C50*Plan!D6/100/12 | E50: =MIN(Plan!E6,C50+D50) | F50: =C50+D50-E50 | G50: =MIN(F50,MAX(0,$B50-((K$5<E$5)*L50+(Q$5<E$5)*R50+(W$5<E$5)*X50+(AC$5<E$5)*AD50+(AI$5<E$5)*AJ50+(AO$5<E$5)*AP50+(AU$5<E$5)*AV50))) | H50: =IF(F50-G50<0.005,0,F50-G50) | I50: =N49 | J50: =I50*Plan!D7/100/12 | K50: =MIN(Plan!E7,I50+J50) | L50: =I50+J50-K50 | M50: =MIN(L50,MAX(0,$B50-((E$5<K$5)*F50+(Q$5<K$5)*R50+(W$5<K$5)*X50+(AC$5<K$5)*AD50+(AI$5<K$5)*AJ50+(AO$5<K$5)*AP50+(AU$5<K$5)*AV50))) | N50: =IF(L50-M50<0.005,0,L50-M50) | O50: =T49 | P50: =O50*Plan!D8/100/12 | Q50: =MIN(Plan!E8,O50+P50) | R50: =O50+P50-Q50 | S50: =MIN(R50,MAX(0,$B50-((E$5<Q$5)*F50+(K$5<Q$5)*L50+(W$5<Q$5)*X50+(AC$5<Q$5)*AD50+(AI$5<Q$5)*AJ50+(AO$5<Q$5)*AP50+(AU$5<Q$5)*AV50))) | T50: =IF(R50-S50<0.005,0,R50-S50) | U50: =Z49 | V50: =U50*Plan!D9/100/12 | W50: =MIN(Plan!E9,U50+V50) | X50: =U50+V50-W50 | Y50: =MIN(X50,MAX(0,$B50-((E$5<W$5)*F50+(K$5<W$5)*L50+(Q$5<W$5)*R50+(AC$5<W$5)*AD50+(AI$5<W$5)*AJ50+(AO$5<W$5)*AP50+(AU$5<W$5)*AV50))) | Z50: =IF(X50-Y50<0.005,0,X50-Y50) | AA50: =AF49 | AB50: =AA50*Plan!D10/100/12 | AC50: =MIN(Plan!E10,AA50+AB50) | AD50: =AA50+AB50-AC50 | AE50: =MIN(AD50,MAX(0,$B50-((E$5<AC$5)*F50+(K$5<AC$5)*L50+(Q$5<AC$5)*R50+(W$5<AC$5)*X50+(AI$5<AC$5)*AJ50+(AO$5<AC$5)*AP50+(AU$5<AC$5)*AV50))) | AF50: =IF(AD50-AE50<0.005,0,AD50-AE50) | AG50: =AL49 | AH50: =AG50*Plan!D11/100/12 | AI50: =MIN(Plan!E11,AG50+AH50) | AJ50: =AG50+AH50-AI50 | AK50: =MIN(AJ50,MAX(0,$B50-((E$5<AI$5)*F50+(K$5<AI$5)*L50+(Q$5<AI$5)*R50+(W$5<AI$5)*X50+(AC$5<AI$5)*AD50+(AO$5<AI$5)*AP50+(AU$5<AI$5)*AV50))) | AL50: =IF(AJ50-AK50<0.005,0,AJ50-AK50) | AM50: =AR49 | AN50: =AM50*Plan!D12/100/12 | AO50: =MIN(Plan!E12,AM50+AN50) | AP50: =AM50+AN50-AO50 | AQ50: =MIN(AP50,MAX(0,$B50-((E$5<AO$5)*F50+(K$5<AO$5)*L50+(Q$5<AO$5)*R50+(W$5<AO$5)*X50+(AC$5<AO$5)*AD50+(AI$5<AO$5)*AJ50+(AU$5<AO$5)*AV50))) | AR50: =IF(AP50-AQ50<0.005,0,AP50-AQ50) | AS50: =AX49 | AT50: =AS50*Plan!D13/100/12 | AU50: =MIN(Plan!E13,AS50+AT50) | AV50: =AS50+AT50-AU50 | AW50: =MIN(AV50,MAX(0,$B50-((E$5<AU$5)*F50+(K$5<AU$5)*L50+(Q$5<AU$5)*R50+(W$5<AU$5)*X50+(AC$5<AU$5)*AD50+(AI$5<AU$5)*AJ50+(AO$5<AU$5)*AP50))) | AX50: =IF(AV50-AW50<0.005,0,AV50-AW50) | BC50: =H50+N50+T50+Z50+AF50+AL50+AR50+AX50
A51: 45 | B51: =MAX(0,$B$3-(E51+K51+Q51+W51+AC51+AI51+AO51+AU51)) | C51: =H50 | D51: =C51*Plan!D6/100/12 | E51: =MIN(Plan!E6,C51+D51) | F51: =C51+D51-E51 | G51: =MIN(F51,MAX(0,$B51-((K$5<E$5)*L51+(Q$5<E$5)*R51+(W$5<E$5)*X51+(AC$5<E$5)*AD51+(AI$5<E$5)*AJ51+(AO$5<E$5)*AP51+(AU$5<E$5)*AV51))) | H51: =IF(F51-G51<0.005,0,F51-G51) | I51: =N50 | J51: =I51*Plan!D7/100/12 | K51: =MIN(Plan!E7,I51+J51) | L51: =I51+J51-K51 | M51: =MIN(L51,MAX(0,$B51-((E$5<K$5)*F51+(Q$5<K$5)*R51+(W$5<K$5)*X51+(AC$5<K$5)*AD51+(AI$5<K$5)*AJ51+(AO$5<K$5)*AP51+(AU$5<K$5)*AV51))) | N51: =IF(L51-M51<0.005,0,L51-M51) | O51: =T50 | P51: =O51*Plan!D8/100/12 | Q51: =MIN(Plan!E8,O51+P51) | R51: =O51+P51-Q51 | S51: =MIN(R51,MAX(0,$B51-((E$5<Q$5)*F51+(K$5<Q$5)*L51+(W$5<Q$5)*X51+(AC$5<Q$5)*AD51+(AI$5<Q$5)*AJ51+(AO$5<Q$5)*AP51+(AU$5<Q$5)*AV51))) | T51: =IF(R51-S51<0.005,0,R51-S51) | U51: =Z50 | V51: =U51*Plan!D9/100/12 | W51: =MIN(Plan!E9,U51+V51) | X51: =U51+V51-W51 | Y51: =MIN(X51,MAX(0,$B51-((E$5<W$5)*F51+(K$5<W$5)*L51+(Q$5<W$5)*R51+(AC$5<W$5)*AD51+(AI$5<W$5)*AJ51+(AO$5<W$5)*AP51+(AU$5<W$5)*AV51))) | Z51: =IF(X51-Y51<0.005,0,X51-Y51) | AA51: =AF50 | AB51: =AA51*Plan!D10/100/12 | AC51: =MIN(Plan!E10,AA51+AB51) | AD51: =AA51+AB51-AC51 | AE51: =MIN(AD51,MAX(0,$B51-((E$5<AC$5)*F51+(K$5<AC$5)*L51+(Q$5<AC$5)*R51+(W$5<AC$5)*X51+(AI$5<AC$5)*AJ51+(AO$5<AC$5)*AP51+(AU$5<AC$5)*AV51))) | AF51: =IF(AD51-AE51<0.005,0,AD51-AE51) | AG51: =AL50 | AH51: =AG51*Plan!D11/100/12 | AI51: =MIN(Plan!E11,AG51+AH51) | AJ51: =AG51+AH51-AI51 | AK51: =MIN(AJ51,MAX(0,$B51-((E$5<AI$5)*F51+(K$5<AI$5)*L51+(Q$5<AI$5)*R51+(W$5<AI$5)*X51+(AC$5<AI$5)*AD51+(AO$5<AI$5)*AP51+(AU$5<AI$5)*AV51))) | AL51: =IF(AJ51-AK51<0.005,0,AJ51-AK51) | AM51: =AR50 | AN51: =AM51*Plan!D12/100/12 | AO51: =MIN(Plan!E12,AM51+AN51) | AP51: =AM51+AN51-AO51 | AQ51: =MIN(AP51,MAX(0,$B51-((E$5<AO$5)*F51+(K$5<AO$5)*L51+(Q$5<AO$5)*R51+(W$5<AO$5)*X51+(AC$5<AO$5)*AD51+(AI$5<AO$5)*AJ51+(AU$5<AO$5)*AV51))) | AR51: =IF(AP51-AQ51<0.005,0,AP51-AQ51) | AS51: =AX50 | AT51: =AS51*Plan!D13/100/12 | AU51: =MIN(Plan!E13,AS51+AT51) | AV51: =AS51+AT51-AU51 | AW51: =MIN(AV51,MAX(0,$B51-((E$5<AU$5)*F51+(K$5<AU$5)*L51+(Q$5<AU$5)*R51+(W$5<AU$5)*X51+(AC$5<AU$5)*AD51+(AI$5<AU$5)*AJ51+(AO$5<AU$5)*AP51))) | AX51: =IF(AV51-AW51<0.005,0,AV51-AW51) | BC51: =H51+N51+T51+Z51+AF51+AL51+AR51+AX51
A52: 46 | B52: =MAX(0,$B$3-(E52+K52+Q52+W52+AC52+AI52+AO52+AU52)) | C52: =H51 | D52: =C52*Plan!D6/100/12 | E52: =MIN(Plan!E6,C52+D52) | F52: =C52+D52-E52 | G52: =MIN(F52,MAX(0,$B52-((K$5<E$5)*L52+(Q$5<E$5)*R52+(W$5<E$5)*X52+(AC$5<E$5)*AD52+(AI$5<E$5)*AJ52+(AO$5<E$5)*AP52+(AU$5<E$5)*AV52))) | H52: =IF(F52-G52<0.005,0,F52-G52) | I52: =N51 | J52: =I52*Plan!D7/100/12 | K52: =MIN(Plan!E7,I52+J52) | L52: =I52+J52-K52 | M52: =MIN(L52,MAX(0,$B52-((E$5<K$5)*F52+(Q$5<K$5)*R52+(W$5<K$5)*X52+(AC$5<K$5)*AD52+(AI$5<K$5)*AJ52+(AO$5<K$5)*AP52+(AU$5<K$5)*AV52))) | N52: =IF(L52-M52<0.005,0,L52-M52) | O52: =T51 | P52: =O52*Plan!D8/100/12 | Q52: =MIN(Plan!E8,O52+P52) | R52: =O52+P52-Q52 | S52: =MIN(R52,MAX(0,$B52-((E$5<Q$5)*F52+(K$5<Q$5)*L52+(W$5<Q$5)*X52+(AC$5<Q$5)*AD52+(AI$5<Q$5)*AJ52+(AO$5<Q$5)*AP52+(AU$5<Q$5)*AV52))) | T52: =IF(R52-S52<0.005,0,R52-S52) | U52: =Z51 | V52: =U52*Plan!D9/100/12 | W52: =MIN(Plan!E9,U52+V52) | X52: =U52+V52-W52 | Y52: =MIN(X52,MAX(0,$B52-((E$5<W$5)*F52+(K$5<W$5)*L52+(Q$5<W$5)*R52+(AC$5<W$5)*AD52+(AI$5<W$5)*AJ52+(AO$5<W$5)*AP52+(AU$5<W$5)*AV52))) | Z52: =IF(X52-Y52<0.005,0,X52-Y52) | AA52: =AF51 | AB52: =AA52*Plan!D10/100/12 | AC52: =MIN(Plan!E10,AA52+AB52) | AD52: =AA52+AB52-AC52 | AE52: =MIN(AD52,MAX(0,$B52-((E$5<AC$5)*F52+(K$5<AC$5)*L52+(Q$5<AC$5)*R52+(W$5<AC$5)*X52+(AI$5<AC$5)*AJ52+(AO$5<AC$5)*AP52+(AU$5<AC$5)*AV52))) | AF52: =IF(AD52-AE52<0.005,0,AD52-AE52) | AG52: =AL51 | AH52: =AG52*Plan!D11/100/12 | AI52: =MIN(Plan!E11,AG52+AH52) | AJ52: =AG52+AH52-AI52 | AK52: =MIN(AJ52,MAX(0,$B52-((E$5<AI$5)*F52+(K$5<AI$5)*L52+(Q$5<AI$5)*R52+(W$5<AI$5)*X52+(AC$5<AI$5)*AD52+(AO$5<AI$5)*AP52+(AU$5<AI$5)*AV52))) | AL52: =IF(AJ52-AK52<0.005,0,AJ52-AK52) | AM52: =AR51 | AN52: =AM52*Plan!D12/100/12 | AO52: =MIN(Plan!E12,AM52+AN52) | AP52: =AM52+AN52-AO52 | AQ52: =MIN(AP52,MAX(0,$B52-((E$5<AO$5)*F52+(K$5<AO$5)*L52+(Q$5<AO$5)*R52+(W$5<AO$5)*X52+(AC$5<AO$5)*AD52+(AI$5<AO$5)*AJ52+(AU$5<AO$5)*AV52))) | AR52: =IF(AP52-AQ52<0.005,0,AP52-AQ52) | AS52: =AX51 | AT52: =AS52*Plan!D13/100/12 | AU52: =MIN(Plan!E13,AS52+AT52) | AV52: =AS52+AT52-AU52 | AW52: =MIN(AV52,MAX(0,$B52-((E$5<AU$5)*F52+(K$5<AU$5)*L52+(Q$5<AU$5)*R52+(W$5<AU$5)*X52+(AC$5<AU$5)*AD52+(AI$5<AU$5)*AJ52+(AO$5<AU$5)*AP52))) | AX52: =IF(AV52-AW52<0.005,0,AV52-AW52) | BC52: =H52+N52+T52+Z52+AF52+AL52+AR52+AX52
A53: 47 | B53: =MAX(0,$B$3-(E53+K53+Q53+W53+AC53+AI53+AO53+AU53)) | C53: =H52 | D53: =C53*Plan!D6/100/12 | E53: =MIN(Plan!E6,C53+D53) | F53: =C53+D53-E53 | G53: =MIN(F53,MAX(0,$B53-((K$5<E$5)*L53+(Q$5<E$5)*R53+(W$5<E$5)*X53+(AC$5<E$5)*AD53+(AI$5<E$5)*AJ53+(AO$5<E$5)*AP53+(AU$5<E$5)*AV53))) | H53: =IF(F53-G53<0.005,0,F53-G53) | I53: =N52 | J53: =I53*Plan!D7/100/12 | K53: =MIN(Plan!E7,I53+J53) | L53: =I53+J53-K53 | M53: =MIN(L53,MAX(0,$B53-((E$5<K$5)*F53+(Q$5<K$5)*R53+(W$5<K$5)*X53+(AC$5<K$5)*AD53+(AI$5<K$5)*AJ53+(AO$5<K$5)*AP53+(AU$5<K$5)*AV53))) | N53: =IF(L53-M53<0.005,0,L53-M53) | O53: =T52 | P53: =O53*Plan!D8/100/12 | Q53: =MIN(Plan!E8,O53+P53) | R53: =O53+P53-Q53 | S53: =MIN(R53,MAX(0,$B53-((E$5<Q$5)*F53+(K$5<Q$5)*L53+(W$5<Q$5)*X53+(AC$5<Q$5)*AD53+(AI$5<Q$5)*AJ53+(AO$5<Q$5)*AP53+(AU$5<Q$5)*AV53))) | T53: =IF(R53-S53<0.005,0,R53-S53) | U53: =Z52 | V53: =U53*Plan!D9/100/12 | W53: =MIN(Plan!E9,U53+V53) | X53: =U53+V53-W53 | Y53: =MIN(X53,MAX(0,$B53-((E$5<W$5)*F53+(K$5<W$5)*L53+(Q$5<W$5)*R53+(AC$5<W$5)*AD53+(AI$5<W$5)*AJ53+(AO$5<W$5)*AP53+(AU$5<W$5)*AV53))) | Z53: =IF(X53-Y53<0.005,0,X53-Y53) | AA53: =AF52 | AB53: =AA53*Plan!D10/100/12 | AC53: =MIN(Plan!E10,AA53+AB53) | AD53: =AA53+AB53-AC53 | AE53: =MIN(AD53,MAX(0,$B53-((E$5<AC$5)*F53+(K$5<AC$5)*L53+(Q$5<AC$5)*R53+(W$5<AC$5)*X53+(AI$5<AC$5)*AJ53+(AO$5<AC$5)*AP53+(AU$5<AC$5)*AV53))) | AF53: =IF(AD53-AE53<0.005,0,AD53-AE53) | AG53: =AL52 | AH53: =AG53*Plan!D11/100/12 | AI53: =MIN(Plan!E11,AG53+AH53) | AJ53: =AG53+AH53-AI53 | AK53: =MIN(AJ53,MAX(0,$B53-((E$5<AI$5)*F53+(K$5<AI$5)*L53+(Q$5<AI$5)*R53+(W$5<AI$5)*X53+(AC$5<AI$5)*AD53+(AO$5<AI$5)*AP53+(AU$5<AI$5)*AV53))) | AL53: =IF(AJ53-AK53<0.005,0,AJ53-AK53) | AM53: =AR52 | AN53: =AM53*Plan!D12/100/12 | AO53: =MIN(Plan!E12,AM53+AN53) | AP53: =AM53+AN53-AO53 | AQ53: =MIN(AP53,MAX(0,$B53-((E$5<AO$5)*F53+(K$5<AO$5)*L53+(Q$5<AO$5)*R53+(W$5<AO$5)*X53+(AC$5<AO$5)*AD53+(AI$5<AO$5)*AJ53+(AU$5<AO$5)*AV53))) | AR53: =IF(AP53-AQ53<0.005,0,AP53-AQ53) | AS53: =AX52 | AT53: =AS53*Plan!D13/100/12 | AU53: =MIN(Plan!E13,AS53+AT53) | AV53: =AS53+AT53-AU53 | AW53: =MIN(AV53,MAX(0,$B53-((E$5<AU$5)*F53+(K$5<AU$5)*L53+(Q$5<AU$5)*R53+(W$5<AU$5)*X53+(AC$5<AU$5)*AD53+(AI$5<AU$5)*AJ53+(AO$5<AU$5)*AP53))) | AX53: =IF(AV53-AW53<0.005,0,AV53-AW53) | BC53: =H53+N53+T53+Z53+AF53+AL53+AR53+AX53
A54: 48 | B54: =MAX(0,$B$3-(E54+K54+Q54+W54+AC54+AI54+AO54+AU54)) | C54: =H53 | D54: =C54*Plan!D6/100/12 | E54: =MIN(Plan!E6,C54+D54) | F54: =C54+D54-E54 | G54: =MIN(F54,MAX(0,$B54-((K$5<E$5)*L54+(Q$5<E$5)*R54+(W$5<E$5)*X54+(AC$5<E$5)*AD54+(AI$5<E$5)*AJ54+(AO$5<E$5)*AP54+(AU$5<E$5)*AV54))) | H54: =IF(F54-G54<0.005,0,F54-G54) | I54: =N53 | J54: =I54*Plan!D7/100/12 | K54: =MIN(Plan!E7,I54+J54) | L54: =I54+J54-K54 | M54: =MIN(L54,MAX(0,$B54-((E$5<K$5)*F54+(Q$5<K$5)*R54+(W$5<K$5)*X54+(AC$5<K$5)*AD54+(AI$5<K$5)*AJ54+(AO$5<K$5)*AP54+(AU$5<K$5)*AV54))) | N54: =IF(L54-M54<0.005,0,L54-M54) | O54: =T53 | P54: =O54*Plan!D8/100/12 | Q54: =MIN(Plan!E8,O54+P54) | R54: =O54+P54-Q54 | S54: =MIN(R54,MAX(0,$B54-((E$5<Q$5)*F54+(K$5<Q$5)*L54+(W$5<Q$5)*X54+(AC$5<Q$5)*AD54+(AI$5<Q$5)*AJ54+(AO$5<Q$5)*AP54+(AU$5<Q$5)*AV54))) | T54: =IF(R54-S54<0.005,0,R54-S54) | U54: =Z53 | V54: =U54*Plan!D9/100/12 | W54: =MIN(Plan!E9,U54+V54) | X54: =U54+V54-W54 | Y54: =MIN(X54,MAX(0,$B54-((E$5<W$5)*F54+(K$5<W$5)*L54+(Q$5<W$5)*R54+(AC$5<W$5)*AD54+(AI$5<W$5)*AJ54+(AO$5<W$5)*AP54+(AU$5<W$5)*AV54))) | Z54: =IF(X54-Y54<0.005,0,X54-Y54) | AA54: =AF53 | AB54: =AA54*Plan!D10/100/12 | AC54: =MIN(Plan!E10,AA54+AB54) | AD54: =AA54+AB54-AC54 | AE54: =MIN(AD54,MAX(0,$B54-((E$5<AC$5)*F54+(K$5<AC$5)*L54+(Q$5<AC$5)*R54+(W$5<AC$5)*X54+(AI$5<AC$5)*AJ54+(AO$5<AC$5)*AP54+(AU$5<AC$5)*AV54))) | AF54: =IF(AD54-AE54<0.005,0,AD54-AE54) | AG54: =AL53 | AH54: =AG54*Plan!D11/100/12 | AI54: =MIN(Plan!E11,AG54+AH54) | AJ54: =AG54+AH54-AI54 | AK54: =MIN(AJ54,MAX(0,$B54-((E$5<AI$5)*F54+(K$5<AI$5)*L54+(Q$5<AI$5)*R54+(W$5<AI$5)*X54+(AC$5<AI$5)*AD54+(AO$5<AI$5)*AP54+(AU$5<AI$5)*AV54))) | AL54: =IF(AJ54-AK54<0.005,0,AJ54-AK54) | AM54: =AR53 | AN54: =AM54*Plan!D12/100/12 | AO54: =MIN(Plan!E12,AM54+AN54) | AP54: =AM54+AN54-AO54 | AQ54: =MIN(AP54,MAX(0,$B54-((E$5<AO$5)*F54+(K$5<AO$5)*L54+(Q$5<AO$5)*R54+(W$5<AO$5)*X54+(AC$5<AO$5)*AD54+(AI$5<AO$5)*AJ54+(AU$5<AO$5)*AV54))) | AR54: =IF(AP54-AQ54<0.005,0,AP54-AQ54) | AS54: =AX53 | AT54: =AS54*Plan!D13/100/12 | AU54: =MIN(Plan!E13,AS54+AT54) | AV54: =AS54+AT54-AU54 | AW54: =MIN(AV54,MAX(0,$B54-((E$5<AU$5)*F54+(K$5<AU$5)*L54+(Q$5<AU$5)*R54+(W$5<AU$5)*X54+(AC$5<AU$5)*AD54+(AI$5<AU$5)*AJ54+(AO$5<AU$5)*AP54))) | AX54: =IF(AV54-AW54<0.005,0,AV54-AW54) | BC54: =H54+N54+T54+Z54+AF54+AL54+AR54+AX54
A55: 49 | B55: =MAX(0,$B$3-(E55+K55+Q55+W55+AC55+AI55+AO55+AU55)) | C55: =H54 | D55: =C55*Plan!D6/100/12 | E55: =MIN(Plan!E6,C55+D55) | F55: =C55+D55-E55 | G55: =MIN(F55,MAX(0,$B55-((K$5<E$5)*L55+(Q$5<E$5)*R55+(W$5<E$5)*X55+(AC$5<E$5)*AD55+(AI$5<E$5)*AJ55+(AO$5<E$5)*AP55+(AU$5<E$5)*AV55))) | H55: =IF(F55-G55<0.005,0,F55-G55) | I55: =N54 | J55: =I55*Plan!D7/100/12 | K55: =MIN(Plan!E7,I55+J55) | L55: =I55+J55-K55 | M55: =MIN(L55,MAX(0,$B55-((E$5<K$5)*F55+(Q$5<K$5)*R55+(W$5<K$5)*X55+(AC$5<K$5)*AD55+(AI$5<K$5)*AJ55+(AO$5<K$5)*AP55+(AU$5<K$5)*AV55))) | N55: =IF(L55-M55<0.005,0,L55-M55) | O55: =T54 | P55: =O55*Plan!D8/100/12 | Q55: =MIN(Plan!E8,O55+P55) | R55: =O55+P55-Q55 | S55: =MIN(R55,MAX(0,$B55-((E$5<Q$5)*F55+(K$5<Q$5)*L55+(W$5<Q$5)*X55+(AC$5<Q$5)*AD55+(AI$5<Q$5)*AJ55+(AO$5<Q$5)*AP55+(AU$5<Q$5)*AV55))) | T55: =IF(R55-S55<0.005,0,R55-S55) | U55: =Z54 | V55: =U55*Plan!D9/100/12 | W55: =MIN(Plan!E9,U55+V55) | X55: =U55+V55-W55 | Y55: =MIN(X55,MAX(0,$B55-((E$5<W$5)*F55+(K$5<W$5)*L55+(Q$5<W$5)*R55+(AC$5<W$5)*AD55+(AI$5<W$5)*AJ55+(AO$5<W$5)*AP55+(AU$5<W$5)*AV55))) | Z55: =IF(X55-Y55<0.005,0,X55-Y55) | AA55: =AF54 | AB55: =AA55*Plan!D10/100/12 | AC55: =MIN(Plan!E10,AA55+AB55) | AD55: =AA55+AB55-AC55 | AE55: =MIN(AD55,MAX(0,$B55-((E$5<AC$5)*F55+(K$5<AC$5)*L55+(Q$5<AC$5)*R55+(W$5<AC$5)*X55+(AI$5<AC$5)*AJ55+(AO$5<AC$5)*AP55+(AU$5<AC$5)*AV55))) | AF55: =IF(AD55-AE55<0.005,0,AD55-AE55) | AG55: =AL54 | AH55: =AG55*Plan!D11/100/12 | AI55: =MIN(Plan!E11,AG55+AH55) | AJ55: =AG55+AH55-AI55 | AK55: =MIN(AJ55,MAX(0,$B55-((E$5<AI$5)*F55+(K$5<AI$5)*L55+(Q$5<AI$5)*R55+(W$5<AI$5)*X55+(AC$5<AI$5)*AD55+(AO$5<AI$5)*AP55+(AU$5<AI$5)*AV55))) | AL55: =IF(AJ55-AK55<0.005,0,AJ55-AK55) | AM55: =AR54 | AN55: =AM55*Plan!D12/100/12 | AO55: =MIN(Plan!E12,AM55+AN55) | AP55: =AM55+AN55-AO55 | AQ55: =MIN(AP55,MAX(0,$B55-((E$5<AO$5)*F55+(K$5<AO$5)*L55+(Q$5<AO$5)*R55+(W$5<AO$5)*X55+(AC$5<AO$5)*AD55+(AI$5<AO$5)*AJ55+(AU$5<AO$5)*AV55))) | AR55: =IF(AP55-AQ55<0.005,0,AP55-AQ55) | AS55: =AX54 | AT55: =AS55*Plan!D13/100/12 | AU55: =MIN(Plan!E13,AS55+AT55) | AV55: =AS55+AT55-AU55 | AW55: =MIN(AV55,MAX(0,$B55-((E$5<AU$5)*F55+(K$5<AU$5)*L55+(Q$5<AU$5)*R55+(W$5<AU$5)*X55+(AC$5<AU$5)*AD55+(AI$5<AU$5)*AJ55+(AO$5<AU$5)*AP55))) | AX55: =IF(AV55-AW55<0.005,0,AV55-AW55) | BC55: =H55+N55+T55+Z55+AF55+AL55+AR55+AX55
A56: 50 | B56: =MAX(0,$B$3-(E56+K56+Q56+W56+AC56+AI56+AO56+AU56)) | C56: =H55 | D56: =C56*Plan!D6/100/12 | E56: =MIN(Plan!E6,C56+D56) | F56: =C56+D56-E56 | G56: =MIN(F56,MAX(0,$B56-((K$5<E$5)*L56+(Q$5<E$5)*R56+(W$5<E$5)*X56+(AC$5<E$5)*AD56+(AI$5<E$5)*AJ56+(AO$5<E$5)*AP56+(AU$5<E$5)*AV56))) | H56: =IF(F56-G56<0.005,0,F56-G56) | I56: =N55 | J56: =I56*Plan!D7/100/12 | K56: =MIN(Plan!E7,I56+J56) | L56: =I56+J56-K56 | M56: =MIN(L56,MAX(0,$B56-((E$5<K$5)*F56+(Q$5<K$5)*R56+(W$5<K$5)*X56+(AC$5<K$5)*AD56+(AI$5<K$5)*AJ56+(AO$5<K$5)*AP56+(AU$5<K$5)*AV56))) | N56: =IF(L56-M56<0.005,0,L56-M56) | O56: =T55 | P56: =O56*Plan!D8/100/12 | Q56: =MIN(Plan!E8,O56+P56) | R56: =O56+P56-Q56 | S56: =MIN(R56,MAX(0,$B56-((E$5<Q$5)*F56+(K$5<Q$5)*L56+(W$5<Q$5)*X56+(AC$5<Q$5)*AD56+(AI$5<Q$5)*AJ56+(AO$5<Q$5)*AP56+(AU$5<Q$5)*AV56))) | T56: =IF(R56-S56<0.005,0,R56-S56) | U56: =Z55 | V56: =U56*Plan!D9/100/12 | W56: =MIN(Plan!E9,U56+V56) | X56: =U56+V56-W56 | Y56: =MIN(X56,MAX(0,$B56-((E$5<W$5)*F56+(K$5<W$5)*L56+(Q$5<W$5)*R56+(AC$5<W$5)*AD56+(AI$5<W$5)*AJ56+(AO$5<W$5)*AP56+(AU$5<W$5)*AV56))) | Z56: =IF(X56-Y56<0.005,0,X56-Y56) | AA56: =AF55 | AB56: =AA56*Plan!D10/100/12 | AC56: =MIN(Plan!E10,AA56+AB56) | AD56: =AA56+AB56-AC56 | AE56: =MIN(AD56,MAX(0,$B56-((E$5<AC$5)*F56+(K$5<AC$5)*L56+(Q$5<AC$5)*R56+(W$5<AC$5)*X56+(AI$5<AC$5)*AJ56+(AO$5<AC$5)*AP56+(AU$5<AC$5)*AV56))) | AF56: =IF(AD56-AE56<0.005,0,AD56-AE56) | AG56: =AL55 | AH56: =AG56*Plan!D11/100/12 | AI56: =MIN(Plan!E11,AG56+AH56) | AJ56: =AG56+AH56-AI56 | AK56: =MIN(AJ56,MAX(0,$B56-((E$5<AI$5)*F56+(K$5<AI$5)*L56+(Q$5<AI$5)*R56+(W$5<AI$5)*X56+(AC$5<AI$5)*AD56+(AO$5<AI$5)*AP56+(AU$5<AI$5)*AV56))) | AL56: =IF(AJ56-AK56<0.005,0,AJ56-AK56) | AM56: =AR55 | AN56: =AM56*Plan!D12/100/12 | AO56: =MIN(Plan!E12,AM56+AN56) | AP56: =AM56+AN56-AO56 | AQ56: =MIN(AP56,MAX(0,$B56-((E$5<AO$5)*F56+(K$5<AO$5)*L56+(Q$5<AO$5)*R56+(W$5<AO$5)*X56+(AC$5<AO$5)*AD56+(AI$5<AO$5)*AJ56+(AU$5<AO$5)*AV56))) | AR56: =IF(AP56-AQ56<0.005,0,AP56-AQ56) | AS56: =AX55 | AT56: =AS56*Plan!D13/100/12 | AU56: =MIN(Plan!E13,AS56+AT56) | AV56: =AS56+AT56-AU56 | AW56: =MIN(AV56,MAX(0,$B56-((E$5<AU$5)*F56+(K$5<AU$5)*L56+(Q$5<AU$5)*R56+(W$5<AU$5)*X56+(AC$5<AU$5)*AD56+(AI$5<AU$5)*AJ56+(AO$5<AU$5)*AP56))) | AX56: =IF(AV56-AW56<0.005,0,AV56-AW56) | BC56: =H56+N56+T56+Z56+AF56+AL56+AR56+AX56
A57: 51 | B57: =MAX(0,$B$3-(E57+K57+Q57+W57+AC57+AI57+AO57+AU57)) | C57: =H56 | D57: =C57*Plan!D6/100/12 | E57: =MIN(Plan!E6,C57+D57) | F57: =C57+D57-E57 | G57: =MIN(F57,MAX(0,$B57-((K$5<E$5)*L57+(Q$5<E$5)*R57+(W$5<E$5)*X57+(AC$5<E$5)*AD57+(AI$5<E$5)*AJ57+(AO$5<E$5)*AP57+(AU$5<E$5)*AV57))) | H57: =IF(F57-G57<0.005,0,F57-G57) | I57: =N56 | J57: =I57*Plan!D7/100/12 | K57: =MIN(Plan!E7,I57+J57) | L57: =I57+J57-K57 | M57: =MIN(L57,MAX(0,$B57-((E$5<K$5)*F57+(Q$5<K$5)*R57+(W$5<K$5)*X57+(AC$5<K$5)*AD57+(AI$5<K$5)*AJ57+(AO$5<K$5)*AP57+(AU$5<K$5)*AV57))) | N57: =IF(L57-M57<0.005,0,L57-M57) | O57: =T56 | P57: =O57*Plan!D8/100/12 | Q57: =MIN(Plan!E8,O57+P57) | R57: =O57+P57-Q57 | S57: =MIN(R57,MAX(0,$B57-((E$5<Q$5)*F57+(K$5<Q$5)*L57+(W$5<Q$5)*X57+(AC$5<Q$5)*AD57+(AI$5<Q$5)*AJ57+(AO$5<Q$5)*AP57+(AU$5<Q$5)*AV57))) | T57: =IF(R57-S57<0.005,0,R57-S57) | U57: =Z56 | V57: =U57*Plan!D9/100/12 | W57: =MIN(Plan!E9,U57+V57) | X57: =U57+V57-W57 | Y57: =MIN(X57,MAX(0,$B57-((E$5<W$5)*F57+(K$5<W$5)*L57+(Q$5<W$5)*R57+(AC$5<W$5)*AD57+(AI$5<W$5)*AJ57+(AO$5<W$5)*AP57+(AU$5<W$5)*AV57))) | Z57: =IF(X57-Y57<0.005,0,X57-Y57) | AA57: =AF56 | AB57: =AA57*Plan!D10/100/12 | AC57: =MIN(Plan!E10,AA57+AB57) | AD57: =AA57+AB57-AC57 | AE57: =MIN(AD57,MAX(0,$B57-((E$5<AC$5)*F57+(K$5<AC$5)*L57+(Q$5<AC$5)*R57+(W$5<AC$5)*X57+(AI$5<AC$5)*AJ57+(AO$5<AC$5)*AP57+(AU$5<AC$5)*AV57))) | AF57: =IF(AD57-AE57<0.005,0,AD57-AE57) | AG57: =AL56 | AH57: =AG57*Plan!D11/100/12 | AI57: =MIN(Plan!E11,AG57+AH57) | AJ57: =AG57+AH57-AI57 | AK57: =MIN(AJ57,MAX(0,$B57-((E$5<AI$5)*F57+(K$5<AI$5)*L57+(Q$5<AI$5)*R57+(W$5<AI$5)*X57+(AC$5<AI$5)*AD57+(AO$5<AI$5)*AP57+(AU$5<AI$5)*AV57))) | AL57: =IF(AJ57-AK57<0.005,0,AJ57-AK57) | AM57: =AR56 | AN57: =AM57*Plan!D12/100/12 | AO57: =MIN(Plan!E12,AM57+AN57) | AP57: =AM57+AN57-AO57 | AQ57: =MIN(AP57,MAX(0,$B57-((E$5<AO$5)*F57+(K$5<AO$5)*L57+(Q$5<AO$5)*R57+(W$5<AO$5)*X57+(AC$5<AO$5)*AD57+(AI$5<AO$5)*AJ57+(AU$5<AO$5)*AV57))) | AR57: =IF(AP57-AQ57<0.005,0,AP57-AQ57) | AS57: =AX56 | AT57: =AS57*Plan!D13/100/12 | AU57: =MIN(Plan!E13,AS57+AT57) | AV57: =AS57+AT57-AU57 | AW57: =MIN(AV57,MAX(0,$B57-((E$5<AU$5)*F57+(K$5<AU$5)*L57+(Q$5<AU$5)*R57+(W$5<AU$5)*X57+(AC$5<AU$5)*AD57+(AI$5<AU$5)*AJ57+(AO$5<AU$5)*AP57))) | AX57: =IF(AV57-AW57<0.005,0,AV57-AW57) | BC57: =H57+N57+T57+Z57+AF57+AL57+AR57+AX57
A58: 52 | B58: =MAX(0,$B$3-(E58+K58+Q58+W58+AC58+AI58+AO58+AU58)) | C58: =H57 | D58: =C58*Plan!D6/100/12 | E58: =MIN(Plan!E6,C58+D58) | F58: =C58+D58-E58 | G58: =MIN(F58,MAX(0,$B58-((K$5<E$5)*L58+(Q$5<E$5)*R58+(W$5<E$5)*X58+(AC$5<E$5)*AD58+(AI$5<E$5)*AJ58+(AO$5<E$5)*AP58+(AU$5<E$5)*AV58))) | H58: =IF(F58-G58<0.005,0,F58-G58) | I58: =N57 | J58: =I58*Plan!D7/100/12 | K58: =MIN(Plan!E7,I58+J58) | L58: =I58+J58-K58 | M58: =MIN(L58,MAX(0,$B58-((E$5<K$5)*F58+(Q$5<K$5)*R58+(W$5<K$5)*X58+(AC$5<K$5)*AD58+(AI$5<K$5)*AJ58+(AO$5<K$5)*AP58+(AU$5<K$5)*AV58))) | N58: =IF(L58-M58<0.005,0,L58-M58) | O58: =T57 | P58: =O58*Plan!D8/100/12 | Q58: =MIN(Plan!E8,O58+P58) | R58: =O58+P58-Q58 | S58: =MIN(R58,MAX(0,$B58-((E$5<Q$5)*F58+(K$5<Q$5)*L58+(W$5<Q$5)*X58+(AC$5<Q$5)*AD58+(AI$5<Q$5)*AJ58+(AO$5<Q$5)*AP58+(AU$5<Q$5)*AV58))) | T58: =IF(R58-S58<0.005,0,R58-S58) | U58: =Z57 | V58: =U58*Plan!D9/100/12 | W58: =MIN(Plan!E9,U58+V58) | X58: =U58+V58-W58 | Y58: =MIN(X58,MAX(0,$B58-((E$5<W$5)*F58+(K$5<W$5)*L58+(Q$5<W$5)*R58+(AC$5<W$5)*AD58+(AI$5<W$5)*AJ58+(AO$5<W$5)*AP58+(AU$5<W$5)*AV58))) | Z58: =IF(X58-Y58<0.005,0,X58-Y58) | AA58: =AF57 | AB58: =AA58*Plan!D10/100/12 | AC58: =MIN(Plan!E10,AA58+AB58) | AD58: =AA58+AB58-AC58 | AE58: =MIN(AD58,MAX(0,$B58-((E$5<AC$5)*F58+(K$5<AC$5)*L58+(Q$5<AC$5)*R58+(W$5<AC$5)*X58+(AI$5<AC$5)*AJ58+(AO$5<AC$5)*AP58+(AU$5<AC$5)*AV58))) | AF58: =IF(AD58-AE58<0.005,0,AD58-AE58) | AG58: =AL57 | AH58: =AG58*Plan!D11/100/12 | AI58: =MIN(Plan!E11,AG58+AH58) | AJ58: =AG58+AH58-AI58 | AK58: =MIN(AJ58,MAX(0,$B58-((E$5<AI$5)*F58+(K$5<AI$5)*L58+(Q$5<AI$5)*R58+(W$5<AI$5)*X58+(AC$5<AI$5)*AD58+(AO$5<AI$5)*AP58+(AU$5<AI$5)*AV58))) | AL58: =IF(AJ58-AK58<0.005,0,AJ58-AK58) | AM58: =AR57 | AN58: =AM58*Plan!D12/100/12 | AO58: =MIN(Plan!E12,AM58+AN58) | AP58: =AM58+AN58-AO58 | AQ58: =MIN(AP58,MAX(0,$B58-((E$5<AO$5)*F58+(K$5<AO$5)*L58+(Q$5<AO$5)*R58+(W$5<AO$5)*X58+(AC$5<AO$5)*AD58+(AI$5<AO$5)*AJ58+(AU$5<AO$5)*AV58))) | AR58: =IF(AP58-AQ58<0.005,0,AP58-AQ58) | AS58: =AX57 | AT58: =AS58*Plan!D13/100/12 | AU58: =MIN(Plan!E13,AS58+AT58) | AV58: =AS58+AT58-AU58 | AW58: =MIN(AV58,MAX(0,$B58-((E$5<AU$5)*F58+(K$5<AU$5)*L58+(Q$5<AU$5)*R58+(W$5<AU$5)*X58+(AC$5<AU$5)*AD58+(AI$5<AU$5)*AJ58+(AO$5<AU$5)*AP58))) | AX58: =IF(AV58-AW58<0.005,0,AV58-AW58) | BC58: =H58+N58+T58+Z58+AF58+AL58+AR58+AX58
A59: 53 | B59: =MAX(0,$B$3-(E59+K59+Q59+W59+AC59+AI59+AO59+AU59)) | C59: =H58 | D59: =C59*Plan!D6/100/12 | E59: =MIN(Plan!E6,C59+D59) | F59: =C59+D59-E59 | G59: =MIN(F59,MAX(0,$B59-((K$5<E$5)*L59+(Q$5<E$5)*R59+(W$5<E$5)*X59+(AC$5<E$5)*AD59+(AI$5<E$5)*AJ59+(AO$5<E$5)*AP59+(AU$5<E$5)*AV59))) | H59: =IF(F59-G59<0.005,0,F59-G59) | I59: =N58 | J59: =I59*Plan!D7/100/12 | K59: =MIN(Plan!E7,I59+J59) | L59: =I59+J59-K59 | M59: =MIN(L59,MAX(0,$B59-((E$5<K$5)*F59+(Q$5<K$5)*R59+(W$5<K$5)*X59+(AC$5<K$5)*AD59+(AI$5<K$5)*AJ59+(AO$5<K$5)*AP59+(AU$5<K$5)*AV59))) | N59: =IF(L59-M59<0.005,0,L59-M59) | O59: =T58 | P59: =O59*Plan!D8/100/12 | Q59: =MIN(Plan!E8,O59+P59) | R59: =O59+P59-Q59 | S59: =MIN(R59,MAX(0,$B59-((E$5<Q$5)*F59+(K$5<Q$5)*L59+(W$5<Q$5)*X59+(AC$5<Q$5)*AD59+(AI$5<Q$5)*AJ59+(AO$5<Q$5)*AP59+(AU$5<Q$5)*AV59))) | T59: =IF(R59-S59<0.005,0,R59-S59) | U59: =Z58 | V59: =U59*Plan!D9/100/12 | W59: =MIN(Plan!E9,U59+V59) | X59: =U59+V59-W59 | Y59: =MIN(X59,MAX(0,$B59-((E$5<W$5)*F59+(K$5<W$5)*L59+(Q$5<W$5)*R59+(AC$5<W$5)*AD59+(AI$5<W$5)*AJ59+(AO$5<W$5)*AP59+(AU$5<W$5)*AV59))) | Z59: =IF(X59-Y59<0.005,0,X59-Y59) | AA59: =AF58 | AB59: =AA59*Plan!D10/100/12 | AC59: =MIN(Plan!E10,AA59+AB59) | AD59: =AA59+AB59-AC59 | AE59: =MIN(AD59,MAX(0,$B59-((E$5<AC$5)*F59+(K$5<AC$5)*L59+(Q$5<AC$5)*R59+(W$5<AC$5)*X59+(AI$5<AC$5)*AJ59+(AO$5<AC$5)*AP59+(AU$5<AC$5)*AV59))) | AF59: =IF(AD59-AE59<0.005,0,AD59-AE59) | AG59: =AL58 | AH59: =AG59*Plan!D11/100/12 | AI59: =MIN(Plan!E11,AG59+AH59) | AJ59: =AG59+AH59-AI59 | AK59: =MIN(AJ59,MAX(0,$B59-((E$5<AI$5)*F59+(K$5<AI$5)*L59+(Q$5<AI$5)*R59+(W$5<AI$5)*X59+(AC$5<AI$5)*AD59+(AO$5<AI$5)*AP59+(AU$5<AI$5)*AV59))) | AL59: =IF(AJ59-AK59<0.005,0,AJ59-AK59) | AM59: =AR58 | AN59: =AM59*Plan!D12/100/12 | AO59: =MIN(Plan!E12,AM59+AN59) | AP59: =AM59+AN59-AO59 | AQ59: =MIN(AP59,MAX(0,$B59-((E$5<AO$5)*F59+(K$5<AO$5)*L59+(Q$5<AO$5)*R59+(W$5<AO$5)*X59+(AC$5<AO$5)*AD59+(AI$5<AO$5)*AJ59+(AU$5<AO$5)*AV59))) | AR59: =IF(AP59-AQ59<0.005,0,AP59-AQ59) | AS59: =AX58 | AT59: =AS59*Plan!D13/100/12 | AU59: =MIN(Plan!E13,AS59+AT59) | AV59: =AS59+AT59-AU59 | AW59: =MIN(AV59,MAX(0,$B59-((E$5<AU$5)*F59+(K$5<AU$5)*L59+(Q$5<AU$5)*R59+(W$5<AU$5)*X59+(AC$5<AU$5)*AD59+(AI$5<AU$5)*AJ59+(AO$5<AU$5)*AP59))) | AX59: =IF(AV59-AW59<0.005,0,AV59-AW59) | BC59: =H59+N59+T59+Z59+AF59+AL59+AR59+AX59
A60: 54 | B60: =MAX(0,$B$3-(E60+K60+Q60+W60+AC60+AI60+AO60+AU60)) | C60: =H59 | D60: =C60*Plan!D6/100/12 | E60: =MIN(Plan!E6,C60+D60) | F60: =C60+D60-E60 | G60: =MIN(F60,MAX(0,$B60-((K$5<E$5)*L60+(Q$5<E$5)*R60+(W$5<E$5)*X60+(AC$5<E$5)*AD60+(AI$5<E$5)*AJ60+(AO$5<E$5)*AP60+(AU$5<E$5)*AV60))) | H60: =IF(F60-G60<0.005,0,F60-G60) | I60: =N59 | J60: =I60*Plan!D7/100/12 | K60: =MIN(Plan!E7,I60+J60) | L60: =I60+J60-K60 | M60: =MIN(L60,MAX(0,$B60-((E$5<K$5)*F60+(Q$5<K$5)*R60+(W$5<K$5)*X60+(AC$5<K$5)*AD60+(AI$5<K$5)*AJ60+(AO$5<K$5)*AP60+(AU$5<K$5)*AV60))) | N60: =IF(L60-M60<0.005,0,L60-M60) | O60: =T59 | P60: =O60*Plan!D8/100/12 | Q60: =MIN(Plan!E8,O60+P60) | R60: =O60+P60-Q60 | S60: =MIN(R60,MAX(0,$B60-((E$5<Q$5)*F60+(K$5<Q$5)*L60+(W$5<Q$5)*X60+(AC$5<Q$5)*AD60+(AI$5<Q$5)*AJ60+(AO$5<Q$5)*AP60+(AU$5<Q$5)*AV60))) | T60: =IF(R60-S60<0.005,0,R60-S60) | U60: =Z59 | V60: =U60*Plan!D9/100/12 | W60: =MIN(Plan!E9,U60+V60) | X60: =U60+V60-W60 | Y60: =MIN(X60,MAX(0,$B60-((E$5<W$5)*F60+(K$5<W$5)*L60+(Q$5<W$5)*R60+(AC$5<W$5)*AD60+(AI$5<W$5)*AJ60+(AO$5<W$5)*AP60+(AU$5<W$5)*AV60))) | Z60: =IF(X60-Y60<0.005,0,X60-Y60) | AA60: =AF59 | AB60: =AA60*Plan!D10/100/12 | AC60: =MIN(Plan!E10,AA60+AB60) | AD60: =AA60+AB60-AC60 | AE60: =MIN(AD60,MAX(0,$B60-((E$5<AC$5)*F60+(K$5<AC$5)*L60+(Q$5<AC$5)*R60+(W$5<AC$5)*X60+(AI$5<AC$5)*AJ60+(AO$5<AC$5)*AP60+(AU$5<AC$5)*AV60))) | AF60: =IF(AD60-AE60<0.005,0,AD60-AE60) | AG60: =AL59 | AH60: =AG60*Plan!D11/100/12 | AI60: =MIN(Plan!E11,AG60+AH60) | AJ60: =AG60+AH60-AI60 | AK60: =MIN(AJ60,MAX(0,$B60-((E$5<AI$5)*F60+(K$5<AI$5)*L60+(Q$5<AI$5)*R60+(W$5<AI$5)*X60+(AC$5<AI$5)*AD60+(AO$5<AI$5)*AP60+(AU$5<AI$5)*AV60))) | AL60: =IF(AJ60-AK60<0.005,0,AJ60-AK60) | AM60: =AR59 | AN60: =AM60*Plan!D12/100/12 | AO60: =MIN(Plan!E12,AM60+AN60) | AP60: =AM60+AN60-AO60 | AQ60: =MIN(AP60,MAX(0,$B60-((E$5<AO$5)*F60+(K$5<AO$5)*L60+(Q$5<AO$5)*R60+(W$5<AO$5)*X60+(AC$5<AO$5)*AD60+(AI$5<AO$5)*AJ60+(AU$5<AO$5)*AV60))) | AR60: =IF(AP60-AQ60<0.005,0,AP60-AQ60) | AS60: =AX59 | AT60: =AS60*Plan!D13/100/12 | AU60: =MIN(Plan!E13,AS60+AT60) | AV60: =AS60+AT60-AU60 | AW60: =MIN(AV60,MAX(0,$B60-((E$5<AU$5)*F60+(K$5<AU$5)*L60+(Q$5<AU$5)*R60+(W$5<AU$5)*X60+(AC$5<AU$5)*AD60+(AI$5<AU$5)*AJ60+(AO$5<AU$5)*AP60))) | AX60: =IF(AV60-AW60<0.005,0,AV60-AW60) | BC60: =H60+N60+T60+Z60+AF60+AL60+AR60+AX60
A61: 55 | B61: =MAX(0,$B$3-(E61+K61+Q61+W61+AC61+AI61+AO61+AU61)) | C61: =H60 | D61: =C61*Plan!D6/100/12 | E61: =MIN(Plan!E6,C61+D61) | F61: =C61+D61-E61 | G61: =MIN(F61,MAX(0,$B61-((K$5<E$5)*L61+(Q$5<E$5)*R61+(W$5<E$5)*X61+(AC$5<E$5)*AD61+(AI$5<E$5)*AJ61+(AO$5<E$5)*AP61+(AU$5<E$5)*AV61))) | H61: =IF(F61-G61<0.005,0,F61-G61) | I61: =N60 | J61: =I61*Plan!D7/100/12 | K61: =MIN(Plan!E7,I61+J61) | L61: =I61+J61-K61 | M61: =MIN(L61,MAX(0,$B61-((E$5<K$5)*F61+(Q$5<K$5)*R61+(W$5<K$5)*X61+(AC$5<K$5)*AD61+(AI$5<K$5)*AJ61+(AO$5<K$5)*AP61+(AU$5<K$5)*AV61))) | N61: =IF(L61-M61<0.005,0,L61-M61) | O61: =T60 | P61: =O61*Plan!D8/100/12 | Q61: =MIN(Plan!E8,O61+P61) | R61: =O61+P61-Q61 | S61: =MIN(R61,MAX(0,$B61-((E$5<Q$5)*F61+(K$5<Q$5)*L61+(W$5<Q$5)*X61+(AC$5<Q$5)*AD61+(AI$5<Q$5)*AJ61+(AO$5<Q$5)*AP61+(AU$5<Q$5)*AV61))) | T61: =IF(R61-S61<0.005,0,R61-S61) | U61: =Z60 | V61: =U61*Plan!D9/100/12 | W61: =MIN(Plan!E9,U61+V61) | X61: =U61+V61-W61 | Y61: =MIN(X61,MAX(0,$B61-((E$5<W$5)*F61+(K$5<W$5)*L61+(Q$5<W$5)*R61+(AC$5<W$5)*AD61+(AI$5<W$5)*AJ61+(AO$5<W$5)*AP61+(AU$5<W$5)*AV61))) | Z61: =IF(X61-Y61<0.005,0,X61-Y61) | AA61: =AF60 | AB61: =AA61*Plan!D10/100/12 | AC61: =MIN(Plan!E10,AA61+AB61) | AD61: =AA61+AB61-AC61 | AE61: =MIN(AD61,MAX(0,$B61-((E$5<AC$5)*F61+(K$5<AC$5)*L61+(Q$5<AC$5)*R61+(W$5<AC$5)*X61+(AI$5<AC$5)*AJ61+(AO$5<AC$5)*AP61+(AU$5<AC$5)*AV61))) | AF61: =IF(AD61-AE61<0.005,0,AD61-AE61) | AG61: =AL60 | AH61: =AG61*Plan!D11/100/12 | AI61: =MIN(Plan!E11,AG61+AH61) | AJ61: =AG61+AH61-AI61 | AK61: =MIN(AJ61,MAX(0,$B61-((E$5<AI$5)*F61+(K$5<AI$5)*L61+(Q$5<AI$5)*R61+(W$5<AI$5)*X61+(AC$5<AI$5)*AD61+(AO$5<AI$5)*AP61+(AU$5<AI$5)*AV61))) | AL61: =IF(AJ61-AK61<0.005,0,AJ61-AK61) | AM61: =AR60 | AN61: =AM61*Plan!D12/100/12 | AO61: =MIN(Plan!E12,AM61+AN61) | AP61: =AM61+AN61-AO61 | AQ61: =MIN(AP61,MAX(0,$B61-((E$5<AO$5)*F61+(K$5<AO$5)*L61+(Q$5<AO$5)*R61+(W$5<AO$5)*X61+(AC$5<AO$5)*AD61+(AI$5<AO$5)*AJ61+(AU$5<AO$5)*AV61))) | AR61: =IF(AP61-AQ61<0.005,0,AP61-AQ61) | AS61: =AX60 | AT61: =AS61*Plan!D13/100/12 | AU61: =MIN(Plan!E13,AS61+AT61) | AV61: =AS61+AT61-AU61 | AW61: =MIN(AV61,MAX(0,$B61-((E$5<AU$5)*F61+(K$5<AU$5)*L61+(Q$5<AU$5)*R61+(W$5<AU$5)*X61+(AC$5<AU$5)*AD61+(AI$5<AU$5)*AJ61+(AO$5<AU$5)*AP61))) | AX61: =IF(AV61-AW61<0.005,0,AV61-AW61) | BC61: =H61+N61+T61+Z61+AF61+AL61+AR61+AX61
A62: 56 | B62: =MAX(0,$B$3-(E62+K62+Q62+W62+AC62+AI62+AO62+AU62)) | C62: =H61 | D62: =C62*Plan!D6/100/12 | E62: =MIN(Plan!E6,C62+D62) | F62: =C62+D62-E62 | G62: =MIN(F62,MAX(0,$B62-((K$5<E$5)*L62+(Q$5<E$5)*R62+(W$5<E$5)*X62+(AC$5<E$5)*AD62+(AI$5<E$5)*AJ62+(AO$5<E$5)*AP62+(AU$5<E$5)*AV62))) | H62: =IF(F62-G62<0.005,0,F62-G62) | I62: =N61 | J62: =I62*Plan!D7/100/12 | K62: =MIN(Plan!E7,I62+J62) | L62: =I62+J62-K62 | M62: =MIN(L62,MAX(0,$B62-((E$5<K$5)*F62+(Q$5<K$5)*R62+(W$5<K$5)*X62+(AC$5<K$5)*AD62+(AI$5<K$5)*AJ62+(AO$5<K$5)*AP62+(AU$5<K$5)*AV62))) | N62: =IF(L62-M62<0.005,0,L62-M62) | O62: =T61 | P62: =O62*Plan!D8/100/12 | Q62: =MIN(Plan!E8,O62+P62) | R62: =O62+P62-Q62 | S62: =MIN(R62,MAX(0,$B62-((E$5<Q$5)*F62+(K$5<Q$5)*L62+(W$5<Q$5)*X62+(AC$5<Q$5)*AD62+(AI$5<Q$5)*AJ62+(AO$5<Q$5)*AP62+(AU$5<Q$5)*AV62))) | T62: =IF(R62-S62<0.005,0,R62-S62) | U62: =Z61 | V62: =U62*Plan!D9/100/12 | W62: =MIN(Plan!E9,U62+V62) | X62: =U62+V62-W62 | Y62: =MIN(X62,MAX(0,$B62-((E$5<W$5)*F62+(K$5<W$5)*L62+(Q$5<W$5)*R62+(AC$5<W$5)*AD62+(AI$5<W$5)*AJ62+(AO$5<W$5)*AP62+(AU$5<W$5)*AV62))) | Z62: =IF(X62-Y62<0.005,0,X62-Y62) | AA62: =AF61 | AB62: =AA62*Plan!D10/100/12 | AC62: =MIN(Plan!E10,AA62+AB62) | AD62: =AA62+AB62-AC62 | AE62: =MIN(AD62,MAX(0,$B62-((E$5<AC$5)*F62+(K$5<AC$5)*L62+(Q$5<AC$5)*R62+(W$5<AC$5)*X62+(AI$5<AC$5)*AJ62+(AO$5<AC$5)*AP62+(AU$5<AC$5)*AV62))) | AF62: =IF(AD62-AE62<0.005,0,AD62-AE62) | AG62: =AL61 | AH62: =AG62*Plan!D11/100/12 | AI62: =MIN(Plan!E11,AG62+AH62) | AJ62: =AG62+AH62-AI62 | AK62: =MIN(AJ62,MAX(0,$B62-((E$5<AI$5)*F62+(K$5<AI$5)*L62+(Q$5<AI$5)*R62+(W$5<AI$5)*X62+(AC$5<AI$5)*AD62+(AO$5<AI$5)*AP62+(AU$5<AI$5)*AV62))) | AL62: =IF(AJ62-AK62<0.005,0,AJ62-AK62) | AM62: =AR61 | AN62: =AM62*Plan!D12/100/12 | AO62: =MIN(Plan!E12,AM62+AN62) | AP62: =AM62+AN62-AO62 | AQ62: =MIN(AP62,MAX(0,$B62-((E$5<AO$5)*F62+(K$5<AO$5)*L62+(Q$5<AO$5)*R62+(W$5<AO$5)*X62+(AC$5<AO$5)*AD62+(AI$5<AO$5)*AJ62+(AU$5<AO$5)*AV62))) | AR62: =IF(AP62-AQ62<0.005,0,AP62-AQ62) | AS62: =AX61 | AT62: =AS62*Plan!D13/100/12 | AU62: =MIN(Plan!E13,AS62+AT62) | AV62: =AS62+AT62-AU62 | AW62: =MIN(AV62,MAX(0,$B62-((E$5<AU$5)*F62+(K$5<AU$5)*L62+(Q$5<AU$5)*R62+(W$5<AU$5)*X62+(AC$5<AU$5)*AD62+(AI$5<AU$5)*AJ62+(AO$5<AU$5)*AP62))) | AX62: =IF(AV62-AW62<0.005,0,AV62-AW62) | BC62: =H62+N62+T62+Z62+AF62+AL62+AR62+AX62
A63: 57 | B63: =MAX(0,$B$3-(E63+K63+Q63+W63+AC63+AI63+AO63+AU63)) | C63: =H62 | D63: =C63*Plan!D6/100/12 | E63: =MIN(Plan!E6,C63+D63) | F63: =C63+D63-E63 | G63: =MIN(F63,MAX(0,$B63-((K$5<E$5)*L63+(Q$5<E$5)*R63+(W$5<E$5)*X63+(AC$5<E$5)*AD63+(AI$5<E$5)*AJ63+(AO$5<E$5)*AP63+(AU$5<E$5)*AV63))) | H63: =IF(F63-G63<0.005,0,F63-G63) | I63: =N62 | J63: =I63*Plan!D7/100/12 | K63: =MIN(Plan!E7,I63+J63) | L63: =I63+J63-K63 | M63: =MIN(L63,MAX(0,$B63-((E$5<K$5)*F63+(Q$5<K$5)*R63+(W$5<K$5)*X63+(AC$5<K$5)*AD63+(AI$5<K$5)*AJ63+(AO$5<K$5)*AP63+(AU$5<K$5)*AV63))) | N63: =IF(L63-M63<0.005,0,L63-M63) | O63: =T62 | P63: =O63*Plan!D8/100/12 | Q63: =MIN(Plan!E8,O63+P63) | R63: =O63+P63-Q63 | S63: =MIN(R63,MAX(0,$B63-((E$5<Q$5)*F63+(K$5<Q$5)*L63+(W$5<Q$5)*X63+(AC$5<Q$5)*AD63+(AI$5<Q$5)*AJ63+(AO$5<Q$5)*AP63+(AU$5<Q$5)*AV63))) | T63: =IF(R63-S63<0.005,0,R63-S63) | U63: =Z62 | V63: =U63*Plan!D9/100/12 | W63: =MIN(Plan!E9,U63+V63) | X63: =U63+V63-W63 | Y63: =MIN(X63,MAX(0,$B63-((E$5<W$5)*F63+(K$5<W$5)*L63+(Q$5<W$5)*R63+(AC$5<W$5)*AD63+(AI$5<W$5)*AJ63+(AO$5<W$5)*AP63+(AU$5<W$5)*AV63))) | Z63: =IF(X63-Y63<0.005,0,X63-Y63) | AA63: =AF62 | AB63: =AA63*Plan!D10/100/12 | AC63: =MIN(Plan!E10,AA63+AB63) | AD63: =AA63+AB63-AC63 | AE63: =MIN(AD63,MAX(0,$B63-((E$5<AC$5)*F63+(K$5<AC$5)*L63+(Q$5<AC$5)*R63+(W$5<AC$5)*X63+(AI$5<AC$5)*AJ63+(AO$5<AC$5)*AP63+(AU$5<AC$5)*AV63))) | AF63: =IF(AD63-AE63<0.005,0,AD63-AE63) | AG63: =AL62 | AH63: =AG63*Plan!D11/100/12 | AI63: =MIN(Plan!E11,AG63+AH63) | AJ63: =AG63+AH63-AI63 | AK63: =MIN(AJ63,MAX(0,$B63-((E$5<AI$5)*F63+(K$5<AI$5)*L63+(Q$5<AI$5)*R63+(W$5<AI$5)*X63+(AC$5<AI$5)*AD63+(AO$5<AI$5)*AP63+(AU$5<AI$5)*AV63))) | AL63: =IF(AJ63-AK63<0.005,0,AJ63-AK63) | AM63: =AR62 | AN63: =AM63*Plan!D12/100/12 | AO63: =MIN(Plan!E12,AM63+AN63) | AP63: =AM63+AN63-AO63 | AQ63: =MIN(AP63,MAX(0,$B63-((E$5<AO$5)*F63+(K$5<AO$5)*L63+(Q$5<AO$5)*R63+(W$5<AO$5)*X63+(AC$5<AO$5)*AD63+(AI$5<AO$5)*AJ63+(AU$5<AO$5)*AV63))) | AR63: =IF(AP63-AQ63<0.005,0,AP63-AQ63) | AS63: =AX62 | AT63: =AS63*Plan!D13/100/12 | AU63: =MIN(Plan!E13,AS63+AT63) | AV63: =AS63+AT63-AU63 | AW63: =MIN(AV63,MAX(0,$B63-((E$5<AU$5)*F63+(K$5<AU$5)*L63+(Q$5<AU$5)*R63+(W$5<AU$5)*X63+(AC$5<AU$5)*AD63+(AI$5<AU$5)*AJ63+(AO$5<AU$5)*AP63))) | AX63: =IF(AV63-AW63<0.005,0,AV63-AW63) | BC63: =H63+N63+T63+Z63+AF63+AL63+AR63+AX63
A64: 58 | B64: =MAX(0,$B$3-(E64+K64+Q64+W64+AC64+AI64+AO64+AU64)) | C64: =H63 | D64: =C64*Plan!D6/100/12 | E64: =MIN(Plan!E6,C64+D64) | F64: =C64+D64-E64 | G64: =MIN(F64,MAX(0,$B64-((K$5<E$5)*L64+(Q$5<E$5)*R64+(W$5<E$5)*X64+(AC$5<E$5)*AD64+(AI$5<E$5)*AJ64+(AO$5<E$5)*AP64+(AU$5<E$5)*AV64))) | H64: =IF(F64-G64<0.005,0,F64-G64) | I64: =N63 | J64: =I64*Plan!D7/100/12 | K64: =MIN(Plan!E7,I64+J64) | L64: =I64+J64-K64 | M64: =MIN(L64,MAX(0,$B64-((E$5<K$5)*F64+(Q$5<K$5)*R64+(W$5<K$5)*X64+(AC$5<K$5)*AD64+(AI$5<K$5)*AJ64+(AO$5<K$5)*AP64+(AU$5<K$5)*AV64))) | N64: =IF(L64-M64<0.005,0,L64-M64) | O64: =T63 | P64: =O64*Plan!D8/100/12 | Q64: =MIN(Plan!E8,O64+P64) | R64: =O64+P64-Q64 | S64: =MIN(R64,MAX(0,$B64-((E$5<Q$5)*F64+(K$5<Q$5)*L64+(W$5<Q$5)*X64+(AC$5<Q$5)*AD64+(AI$5<Q$5)*AJ64+(AO$5<Q$5)*AP64+(AU$5<Q$5)*AV64))) | T64: =IF(R64-S64<0.005,0,R64-S64) | U64: =Z63 | V64: =U64*Plan!D9/100/12 | W64: =MIN(Plan!E9,U64+V64) | X64: =U64+V64-W64 | Y64: =MIN(X64,MAX(0,$B64-((E$5<W$5)*F64+(K$5<W$5)*L64+(Q$5<W$5)*R64+(AC$5<W$5)*AD64+(AI$5<W$5)*AJ64+(AO$5<W$5)*AP64+(AU$5<W$5)*AV64))) | Z64: =IF(X64-Y64<0.005,0,X64-Y64) | AA64: =AF63 | AB64: =AA64*Plan!D10/100/12 | AC64: =MIN(Plan!E10,AA64+AB64) | AD64: =AA64+AB64-AC64 | AE64: =MIN(AD64,MAX(0,$B64-((E$5<AC$5)*F64+(K$5<AC$5)*L64+(Q$5<AC$5)*R64+(W$5<AC$5)*X64+(AI$5<AC$5)*AJ64+(AO$5<AC$5)*AP64+(AU$5<AC$5)*AV64))) | AF64: =IF(AD64-AE64<0.005,0,AD64-AE64) | AG64: =AL63 | AH64: =AG64*Plan!D11/100/12 | AI64: =MIN(Plan!E11,AG64+AH64) | AJ64: =AG64+AH64-AI64 | AK64: =MIN(AJ64,MAX(0,$B64-((E$5<AI$5)*F64+(K$5<AI$5)*L64+(Q$5<AI$5)*R64+(W$5<AI$5)*X64+(AC$5<AI$5)*AD64+(AO$5<AI$5)*AP64+(AU$5<AI$5)*AV64))) | AL64: =IF(AJ64-AK64<0.005,0,AJ64-AK64) | AM64: =AR63 | AN64: =AM64*Plan!D12/100/12 | AO64: =MIN(Plan!E12,AM64+AN64) | AP64: =AM64+AN64-AO64 | AQ64: =MIN(AP64,MAX(0,$B64-((E$5<AO$5)*F64+(K$5<AO$5)*L64+(Q$5<AO$5)*R64+(W$5<AO$5)*X64+(AC$5<AO$5)*AD64+(AI$5<AO$5)*AJ64+(AU$5<AO$5)*AV64))) | AR64: =IF(AP64-AQ64<0.005,0,AP64-AQ64) | AS64: =AX63 | AT64: =AS64*Plan!D13/100/12 | AU64: =MIN(Plan!E13,AS64+AT64) | AV64: =AS64+AT64-AU64 | AW64: =MIN(AV64,MAX(0,$B64-((E$5<AU$5)*F64+(K$5<AU$5)*L64+(Q$5<AU$5)*R64+(W$5<AU$5)*X64+(AC$5<AU$5)*AD64+(AI$5<AU$5)*AJ64+(AO$5<AU$5)*AP64))) | AX64: =IF(AV64-AW64<0.005,0,AV64-AW64) | BC64: =H64+N64+T64+Z64+AF64+AL64+AR64+AX64
A65: 59 | B65: =MAX(0,$B$3-(E65+K65+Q65+W65+AC65+AI65+AO65+AU65)) | C65: =H64 | D65: =C65*Plan!D6/100/12 | E65: =MIN(Plan!E6,C65+D65) | F65: =C65+D65-E65 | G65: =MIN(F65,MAX(0,$B65-((K$5<E$5)*L65+(Q$5<E$5)*R65+(W$5<E$5)*X65+(AC$5<E$5)*AD65+(AI$5<E$5)*AJ65+(AO$5<E$5)*AP65+(AU$5<E$5)*AV65))) | H65: =IF(F65-G65<0.005,0,F65-G65) | I65: =N64 | J65: =I65*Plan!D7/100/12 | K65: =MIN(Plan!E7,I65+J65) | L65: =I65+J65-K65 | M65: =MIN(L65,MAX(0,$B65-((E$5<K$5)*F65+(Q$5<K$5)*R65+(W$5<K$5)*X65+(AC$5<K$5)*AD65+(AI$5<K$5)*AJ65+(AO$5<K$5)*AP65+(AU$5<K$5)*AV65))) | N65: =IF(L65-M65<0.005,0,L65-M65) | O65: =T64 | P65: =O65*Plan!D8/100/12 | Q65: =MIN(Plan!E8,O65+P65) | R65: =O65+P65-Q65 | S65: =MIN(R65,MAX(0,$B65-((E$5<Q$5)*F65+(K$5<Q$5)*L65+(W$5<Q$5)*X65+(AC$5<Q$5)*AD65+(AI$5<Q$5)*AJ65+(AO$5<Q$5)*AP65+(AU$5<Q$5)*AV65))) | T65: =IF(R65-S65<0.005,0,R65-S65) | U65: =Z64 | V65: =U65*Plan!D9/100/12 | W65: =MIN(Plan!E9,U65+V65) | X65: =U65+V65-W65 | Y65: =MIN(X65,MAX(0,$B65-((E$5<W$5)*F65+(K$5<W$5)*L65+(Q$5<W$5)*R65+(AC$5<W$5)*AD65+(AI$5<W$5)*AJ65+(AO$5<W$5)*AP65+(AU$5<W$5)*AV65))) | Z65: =IF(X65-Y65<0.005,0,X65-Y65) | AA65: =AF64 | AB65: =AA65*Plan!D10/100/12 | AC65: =MIN(Plan!E10,AA65+AB65) | AD65: =AA65+AB65-AC65 | AE65: =MIN(AD65,MAX(0,$B65-((E$5<AC$5)*F65+(K$5<AC$5)*L65+(Q$5<AC$5)*R65+(W$5<AC$5)*X65+(AI$5<AC$5)*AJ65+(AO$5<AC$5)*AP65+(AU$5<AC$5)*AV65))) | AF65: =IF(AD65-AE65<0.005,0,AD65-AE65) | AG65: =AL64 | AH65: =AG65*Plan!D11/100/12 | AI65: =MIN(Plan!E11,AG65+AH65) | AJ65: =AG65+AH65-AI65 | AK65: =MIN(AJ65,MAX(0,$B65-((E$5<AI$5)*F65+(K$5<AI$5)*L65+(Q$5<AI$5)*R65+(W$5<AI$5)*X65+(AC$5<AI$5)*AD65+(AO$5<AI$5)*AP65+(AU$5<AI$5)*AV65))) | AL65: =IF(AJ65-AK65<0.005,0,AJ65-AK65) | AM65: =AR64 | AN65: =AM65*Plan!D12/100/12 | AO65: =MIN(Plan!E12,AM65+AN65) | AP65: =AM65+AN65-AO65 | AQ65: =MIN(AP65,MAX(0,$B65-((E$5<AO$5)*F65+(K$5<AO$5)*L65+(Q$5<AO$5)*R65+(W$5<AO$5)*X65+(AC$5<AO$5)*AD65+(AI$5<AO$5)*AJ65+(AU$5<AO$5)*AV65))) | AR65: =IF(AP65-AQ65<0.005,0,AP65-AQ65) | AS65: =AX64 | AT65: =AS65*Plan!D13/100/12 | AU65: =MIN(Plan!E13,AS65+AT65) | AV65: =AS65+AT65-AU65 | AW65: =MIN(AV65,MAX(0,$B65-((E$5<AU$5)*F65+(K$5<AU$5)*L65+(Q$5<AU$5)*R65+(W$5<AU$5)*X65+(AC$5<AU$5)*AD65+(AI$5<AU$5)*AJ65+(AO$5<AU$5)*AP65))) | AX65: =IF(AV65-AW65<0.005,0,AV65-AW65) | BC65: =H65+N65+T65+Z65+AF65+AL65+AR65+AX65
A66: 60 | B66: =MAX(0,$B$3-(E66+K66+Q66+W66+AC66+AI66+AO66+AU66)) | C66: =H65 | D66: =C66*Plan!D6/100/12 | E66: =MIN(Plan!E6,C66+D66) | F66: =C66+D66-E66 | G66: =MIN(F66,MAX(0,$B66-((K$5<E$5)*L66+(Q$5<E$5)*R66+(W$5<E$5)*X66+(AC$5<E$5)*AD66+(AI$5<E$5)*AJ66+(AO$5<E$5)*AP66+(AU$5<E$5)*AV66))) | H66: =IF(F66-G66<0.005,0,F66-G66) | I66: =N65 | J66: =I66*Plan!D7/100/12 | K66: =MIN(Plan!E7,I66+J66) | L66: =I66+J66-K66 | M66: =MIN(L66,MAX(0,$B66-((E$5<K$5)*F66+(Q$5<K$5)*R66+(W$5<K$5)*X66+(AC$5<K$5)*AD66+(AI$5<K$5)*AJ66+(AO$5<K$5)*AP66+(AU$5<K$5)*AV66))) | N66: =IF(L66-M66<0.005,0,L66-M66) | O66: =T65 | P66: =O66*Plan!D8/100/12 | Q66: =MIN(Plan!E8,O66+P66) | R66: =O66+P66-Q66 | S66: =MIN(R66,MAX(0,$B66-((E$5<Q$5)*F66+(K$5<Q$5)*L66+(W$5<Q$5)*X66+(AC$5<Q$5)*AD66+(AI$5<Q$5)*AJ66+(AO$5<Q$5)*AP66+(AU$5<Q$5)*AV66))) | T66: =IF(R66-S66<0.005,0,R66-S66) | U66: =Z65 | V66: =U66*Plan!D9/100/12 | W66: =MIN(Plan!E9,U66+V66) | X66: =U66+V66-W66 | Y66: =MIN(X66,MAX(0,$B66-((E$5<W$5)*F66+(K$5<W$5)*L66+(Q$5<W$5)*R66+(AC$5<W$5)*AD66+(AI$5<W$5)*AJ66+(AO$5<W$5)*AP66+(AU$5<W$5)*AV66))) | Z66: =IF(X66-Y66<0.005,0,X66-Y66) | AA66: =AF65 | AB66: =AA66*Plan!D10/100/12 | AC66: =MIN(Plan!E10,AA66+AB66) | AD66: =AA66+AB66-AC66 | AE66: =MIN(AD66,MAX(0,$B66-((E$5<AC$5)*F66+(K$5<AC$5)*L66+(Q$5<AC$5)*R66+(W$5<AC$5)*X66+(AI$5<AC$5)*AJ66+(AO$5<AC$5)*AP66+(AU$5<AC$5)*AV66))) | AF66: =IF(AD66-AE66<0.005,0,AD66-AE66) | AG66: =AL65 | AH66: =AG66*Plan!D11/100/12 | AI66: =MIN(Plan!E11,AG66+AH66) | AJ66: =AG66+AH66-AI66 | AK66: =MIN(AJ66,MAX(0,$B66-((E$5<AI$5)*F66+(K$5<AI$5)*L66+(Q$5<AI$5)*R66+(W$5<AI$5)*X66+(AC$5<AI$5)*AD66+(AO$5<AI$5)*AP66+(AU$5<AI$5)*AV66))) | AL66: =IF(AJ66-AK66<0.005,0,AJ66-AK66) | AM66: =AR65 | AN66: =AM66*Plan!D12/100/12 | AO66: =MIN(Plan!E12,AM66+AN66) | AP66: =AM66+AN66-AO66 | AQ66: =MIN(AP66,MAX(0,$B66-((E$5<AO$5)*F66+(K$5<AO$5)*L66+(Q$5<AO$5)*R66+(W$5<AO$5)*X66+(AC$5<AO$5)*AD66+(AI$5<AO$5)*AJ66+(AU$5<AO$5)*AV66))) | AR66: =IF(AP66-AQ66<0.005,0,AP66-AQ66) | AS66: =AX65 | AT66: =AS66*Plan!D13/100/12 | AU66: =MIN(Plan!E13,AS66+AT66) | AV66: =AS66+AT66-AU66 | AW66: =MIN(AV66,MAX(0,$B66-((E$5<AU$5)*F66+(K$5<AU$5)*L66+(Q$5<AU$5)*R66+(W$5<AU$5)*X66+(AC$5<AU$5)*AD66+(AI$5<AU$5)*AJ66+(AO$5<AU$5)*AP66))) | AX66: =IF(AV66-AW66<0.005,0,AV66-AW66) | BC66: =H66+N66+T66+Z66+AF66+AL66+AR66+AX66
A67: 61 | B67: =MAX(0,$B$3-(E67+K67+Q67+W67+AC67+AI67+AO67+AU67)) | C67: =H66 | D67: =C67*Plan!D6/100/12 | E67: =MIN(Plan!E6,C67+D67) | F67: =C67+D67-E67 | G67: =MIN(F67,MAX(0,$B67-((K$5<E$5)*L67+(Q$5<E$5)*R67+(W$5<E$5)*X67+(AC$5<E$5)*AD67+(AI$5<E$5)*AJ67+(AO$5<E$5)*AP67+(AU$5<E$5)*AV67))) | H67: =IF(F67-G67<0.005,0,F67-G67) | I67: =N66 | J67: =I67*Plan!D7/100/12 | K67: =MIN(Plan!E7,I67+J67) | L67: =I67+J67-K67 | M67: =MIN(L67,MAX(0,$B67-((E$5<K$5)*F67+(Q$5<K$5)*R67+(W$5<K$5)*X67+(AC$5<K$5)*AD67+(AI$5<K$5)*AJ67+(AO$5<K$5)*AP67+(AU$5<K$5)*AV67))) | N67: =IF(L67-M67<0.005,0,L67-M67) | O67: =T66 | P67: =O67*Plan!D8/100/12 | Q67: =MIN(Plan!E8,O67+P67) | R67: =O67+P67-Q67 | S67: =MIN(R67,MAX(0,$B67-((E$5<Q$5)*F67+(K$5<Q$5)*L67+(W$5<Q$5)*X67+(AC$5<Q$5)*AD67+(AI$5<Q$5)*AJ67+(AO$5<Q$5)*AP67+(AU$5<Q$5)*AV67))) | T67: =IF(R67-S67<0.005,0,R67-S67) | U67: =Z66 | V67: =U67*Plan!D9/100/12 | W67: =MIN(Plan!E9,U67+V67) | X67: =U67+V67-W67 | Y67: =MIN(X67,MAX(0,$B67-((E$5<W$5)*F67+(K$5<W$5)*L67+(Q$5<W$5)*R67+(AC$5<W$5)*AD67+(AI$5<W$5)*AJ67+(AO$5<W$5)*AP67+(AU$5<W$5)*AV67))) | Z67: =IF(X67-Y67<0.005,0,X67-Y67) | AA67: =AF66 | AB67: =AA67*Plan!D10/100/12 | AC67: =MIN(Plan!E10,AA67+AB67) | AD67: =AA67+AB67-AC67 | AE67: =MIN(AD67,MAX(0,$B67-((E$5<AC$5)*F67+(K$5<AC$5)*L67+(Q$5<AC$5)*R67+(W$5<AC$5)*X67+(AI$5<AC$5)*AJ67+(AO$5<AC$5)*AP67+(AU$5<AC$5)*AV67))) | AF67: =IF(AD67-AE67<0.005,0,AD67-AE67) | AG67: =AL66 | AH67: =AG67*Plan!D11/100/12 | AI67: =MIN(Plan!E11,AG67+AH67) | AJ67: =AG67+AH67-AI67 | AK67: =MIN(AJ67,MAX(0,$B67-((E$5<AI$5)*F67+(K$5<AI$5)*L67+(Q$5<AI$5)*R67+(W$5<AI$5)*X67+(AC$5<AI$5)*AD67+(AO$5<AI$5)*AP67+(AU$5<AI$5)*AV67))) | AL67: =IF(AJ67-AK67<0.005,0,AJ67-AK67) | AM67: =AR66 | AN67: =AM67*Plan!D12/100/12 | AO67: =MIN(Plan!E12,AM67+AN67) | AP67: =AM67+AN67-AO67 | AQ67: =MIN(AP67,MAX(0,$B67-((E$5<AO$5)*F67+(K$5<AO$5)*L67+(Q$5<AO$5)*R67+(W$5<AO$5)*X67+(AC$5<AO$5)*AD67+(AI$5<AO$5)*AJ67+(AU$5<AO$5)*AV67))) | AR67: =IF(AP67-AQ67<0.005,0,AP67-AQ67) | AS67: =AX66 | AT67: =AS67*Plan!D13/100/12 | AU67: =MIN(Plan!E13,AS67+AT67) | AV67: =AS67+AT67-AU67 | AW67: =MIN(AV67,MAX(0,$B67-((E$5<AU$5)*F67+(K$5<AU$5)*L67+(Q$5<AU$5)*R67+(W$5<AU$5)*X67+(AC$5<AU$5)*AD67+(AI$5<AU$5)*AJ67+(AO$5<AU$5)*AP67))) | AX67: =IF(AV67-AW67<0.005,0,AV67-AW67) | BC67: =H67+N67+T67+Z67+AF67+AL67+AR67+AX67
A68: 62 | B68: =MAX(0,$B$3-(E68+K68+Q68+W68+AC68+AI68+AO68+AU68)) | C68: =H67 | D68: =C68*Plan!D6/100/12 | E68: =MIN(Plan!E6,C68+D68) | F68: =C68+D68-E68 | G68: =MIN(F68,MAX(0,$B68-((K$5<E$5)*L68+(Q$5<E$5)*R68+(W$5<E$5)*X68+(AC$5<E$5)*AD68+(AI$5<E$5)*AJ68+(AO$5<E$5)*AP68+(AU$5<E$5)*AV68))) | H68: =IF(F68-G68<0.005,0,F68-G68) | I68: =N67 | J68: =I68*Plan!D7/100/12 | K68: =MIN(Plan!E7,I68+J68) | L68: =I68+J68-K68 | M68: =MIN(L68,MAX(0,$B68-((E$5<K$5)*F68+(Q$5<K$5)*R68+(W$5<K$5)*X68+(AC$5<K$5)*AD68+(AI$5<K$5)*AJ68+(AO$5<K$5)*AP68+(AU$5<K$5)*AV68))) | N68: =IF(L68-M68<0.005,0,L68-M68) | O68: =T67 | P68: =O68*Plan!D8/100/12 | Q68: =MIN(Plan!E8,O68+P68) | R68: =O68+P68-Q68 | S68: =MIN(R68,MAX(0,$B68-((E$5<Q$5)*F68+(K$5<Q$5)*L68+(W$5<Q$5)*X68+(AC$5<Q$5)*AD68+(AI$5<Q$5)*AJ68+(AO$5<Q$5)*AP68+(AU$5<Q$5)*AV68))) | T68: =IF(R68-S68<0.005,0,R68-S68) | U68: =Z67 | V68: =U68*Plan!D9/100/12 | W68: =MIN(Plan!E9,U68+V68) | X68: =U68+V68-W68 | Y68: =MIN(X68,MAX(0,$B68-((E$5<W$5)*F68+(K$5<W$5)*L68+(Q$5<W$5)*R68+(AC$5<W$5)*AD68+(AI$5<W$5)*AJ68+(AO$5<W$5)*AP68+(AU$5<W$5)*AV68))) | Z68: =IF(X68-Y68<0.005,0,X68-Y68) | AA68: =AF67 | AB68: =AA68*Plan!D10/100/12 | AC68: =MIN(Plan!E10,AA68+AB68) | AD68: =AA68+AB68-AC68 | AE68: =MIN(AD68,MAX(0,$B68-((E$5<AC$5)*F68+(K$5<AC$5)*L68+(Q$5<AC$5)*R68+(W$5<AC$5)*X68+(AI$5<AC$5)*AJ68+(AO$5<AC$5)*AP68+(AU$5<AC$5)*AV68))) | AF68: =IF(AD68-AE68<0.005,0,AD68-AE68) | AG68: =AL67 | AH68: =AG68*Plan!D11/100/12 | AI68: =MIN(Plan!E11,AG68+AH68) | AJ68: =AG68+AH68-AI68 | AK68: =MIN(AJ68,MAX(0,$B68-((E$5<AI$5)*F68+(K$5<AI$5)*L68+(Q$5<AI$5)*R68+(W$5<AI$5)*X68+(AC$5<AI$5)*AD68+(AO$5<AI$5)*AP68+(AU$5<AI$5)*AV68))) | AL68: =IF(AJ68-AK68<0.005,0,AJ68-AK68) | AM68: =AR67 | AN68: =AM68*Plan!D12/100/12 | AO68: =MIN(Plan!E12,AM68+AN68) | AP68: =AM68+AN68-AO68 | AQ68: =MIN(AP68,MAX(0,$B68-((E$5<AO$5)*F68+(K$5<AO$5)*L68+(Q$5<AO$5)*R68+(W$5<AO$5)*X68+(AC$5<AO$5)*AD68+(AI$5<AO$5)*AJ68+(AU$5<AO$5)*AV68))) | AR68: =IF(AP68-AQ68<0.005,0,AP68-AQ68) | AS68: =AX67 | AT68: =AS68*Plan!D13/100/12 | AU68: =MIN(Plan!E13,AS68+AT68) | AV68: =AS68+AT68-AU68 | AW68: =MIN(AV68,MAX(0,$B68-((E$5<AU$5)*F68+(K$5<AU$5)*L68+(Q$5<AU$5)*R68+(W$5<AU$5)*X68+(AC$5<AU$5)*AD68+(AI$5<AU$5)*AJ68+(AO$5<AU$5)*AP68))) | AX68: =IF(AV68-AW68<0.005,0,AV68-AW68) | BC68: =H68+N68+T68+Z68+AF68+AL68+AR68+AX68
A69: 63 | B69: =MAX(0,$B$3-(E69+K69+Q69+W69+AC69+AI69+AO69+AU69)) | C69: =H68 | D69: =C69*Plan!D6/100/12 | E69: =MIN(Plan!E6,C69+D69) | F69: =C69+D69-E69 | G69: =MIN(F69,MAX(0,$B69-((K$5<E$5)*L69+(Q$5<E$5)*R69+(W$5<E$5)*X69+(AC$5<E$5)*AD69+(AI$5<E$5)*AJ69+(AO$5<E$5)*AP69+(AU$5<E$5)*AV69))) | H69: =IF(F69-G69<0.005,0,F69-G69) | I69: =N68 | J69: =I69*Plan!D7/100/12 | K69: =MIN(Plan!E7,I69+J69) | L69: =I69+J69-K69 | M69: =MIN(L69,MAX(0,$B69-((E$5<K$5)*F69+(Q$5<K$5)*R69+(W$5<K$5)*X69+(AC$5<K$5)*AD69+(AI$5<K$5)*AJ69+(AO$5<K$5)*AP69+(AU$5<K$5)*AV69))) | N69: =IF(L69-M69<0.005,0,L69-M69) | O69: =T68 | P69: =O69*Plan!D8/100/12 | Q69: =MIN(Plan!E8,O69+P69) | R69: =O69+P69-Q69 | S69: =MIN(R69,MAX(0,$B69-((E$5<Q$5)*F69+(K$5<Q$5)*L69+(W$5<Q$5)*X69+(AC$5<Q$5)*AD69+(AI$5<Q$5)*AJ69+(AO$5<Q$5)*AP69+(AU$5<Q$5)*AV69))) | T69: =IF(R69-S69<0.005,0,R69-S69) | U69: =Z68 | V69: =U69*Plan!D9/100/12 | W69: =MIN(Plan!E9,U69+V69) | X69: =U69+V69-W69 | Y69: =MIN(X69,MAX(0,$B69-((E$5<W$5)*F69+(K$5<W$5)*L69+(Q$5<W$5)*R69+(AC$5<W$5)*AD69+(AI$5<W$5)*AJ69+(AO$5<W$5)*AP69+(AU$5<W$5)*AV69))) | Z69: =IF(X69-Y69<0.005,0,X69-Y69) | AA69: =AF68 | AB69: =AA69*Plan!D10/100/12 | AC69: =MIN(Plan!E10,AA69+AB69) | AD69: =AA69+AB69-AC69 | AE69: =MIN(AD69,MAX(0,$B69-((E$5<AC$5)*F69+(K$5<AC$5)*L69+(Q$5<AC$5)*R69+(W$5<AC$5)*X69+(AI$5<AC$5)*AJ69+(AO$5<AC$5)*AP69+(AU$5<AC$5)*AV69))) | AF69: =IF(AD69-AE69<0.005,0,AD69-AE69) | AG69: =AL68 | AH69: =AG69*Plan!D11/100/12 | AI69: =MIN(Plan!E11,AG69+AH69) | AJ69: =AG69+AH69-AI69 | AK69: =MIN(AJ69,MAX(0,$B69-((E$5<AI$5)*F69+(K$5<AI$5)*L69+(Q$5<AI$5)*R69+(W$5<AI$5)*X69+(AC$5<AI$5)*AD69+(AO$5<AI$5)*AP69+(AU$5<AI$5)*AV69))) | AL69: =IF(AJ69-AK69<0.005,0,AJ69-AK69) | AM69: =AR68 | AN69: =AM69*Plan!D12/100/12 | AO69: =MIN(Plan!E12,AM69+AN69) | AP69: =AM69+AN69-AO69 | AQ69: =MIN(AP69,MAX(0,$B69-((E$5<AO$5)*F69+(K$5<AO$5)*L69+(Q$5<AO$5)*R69+(W$5<AO$5)*X69+(AC$5<AO$5)*AD69+(AI$5<AO$5)*AJ69+(AU$5<AO$5)*AV69))) | AR69: =IF(AP69-AQ69<0.005,0,AP69-AQ69) | AS69: =AX68 | AT69: =AS69*Plan!D13/100/12 | AU69: =MIN(Plan!E13,AS69+AT69) | AV69: =AS69+AT69-AU69 | AW69: =MIN(AV69,MAX(0,$B69-((E$5<AU$5)*F69+(K$5<AU$5)*L69+(Q$5<AU$5)*R69+(W$5<AU$5)*X69+(AC$5<AU$5)*AD69+(AI$5<AU$5)*AJ69+(AO$5<AU$5)*AP69))) | AX69: =IF(AV69-AW69<0.005,0,AV69-AW69) | BC69: =H69+N69+T69+Z69+AF69+AL69+AR69+AX69
A70: 64 | B70: =MAX(0,$B$3-(E70+K70+Q70+W70+AC70+AI70+AO70+AU70)) | C70: =H69 | D70: =C70*Plan!D6/100/12 | E70: =MIN(Plan!E6,C70+D70) | F70: =C70+D70-E70 | G70: =MIN(F70,MAX(0,$B70-((K$5<E$5)*L70+(Q$5<E$5)*R70+(W$5<E$5)*X70+(AC$5<E$5)*AD70+(AI$5<E$5)*AJ70+(AO$5<E$5)*AP70+(AU$5<E$5)*AV70))) | H70: =IF(F70-G70<0.005,0,F70-G70) | I70: =N69 | J70: =I70*Plan!D7/100/12 | K70: =MIN(Plan!E7,I70+J70) | L70: =I70+J70-K70 | M70: =MIN(L70,MAX(0,$B70-((E$5<K$5)*F70+(Q$5<K$5)*R70+(W$5<K$5)*X70+(AC$5<K$5)*AD70+(AI$5<K$5)*AJ70+(AO$5<K$5)*AP70+(AU$5<K$5)*AV70))) | N70: =IF(L70-M70<0.005,0,L70-M70) | O70: =T69 | P70: =O70*Plan!D8/100/12 | Q70: =MIN(Plan!E8,O70+P70) | R70: =O70+P70-Q70 | S70: =MIN(R70,MAX(0,$B70-((E$5<Q$5)*F70+(K$5<Q$5)*L70+(W$5<Q$5)*X70+(AC$5<Q$5)*AD70+(AI$5<Q$5)*AJ70+(AO$5<Q$5)*AP70+(AU$5<Q$5)*AV70))) | T70: =IF(R70-S70<0.005,0,R70-S70) | U70: =Z69 | V70: =U70*Plan!D9/100/12 | W70: =MIN(Plan!E9,U70+V70) | X70: =U70+V70-W70 | Y70: =MIN(X70,MAX(0,$B70-((E$5<W$5)*F70+(K$5<W$5)*L70+(Q$5<W$5)*R70+(AC$5<W$5)*AD70+(AI$5<W$5)*AJ70+(AO$5<W$5)*AP70+(AU$5<W$5)*AV70))) | Z70: =IF(X70-Y70<0.005,0,X70-Y70) | AA70: =AF69 | AB70: =AA70*Plan!D10/100/12 | AC70: =MIN(Plan!E10,AA70+AB70) | AD70: =AA70+AB70-AC70 | AE70: =MIN(AD70,MAX(0,$B70-((E$5<AC$5)*F70+(K$5<AC$5)*L70+(Q$5<AC$5)*R70+(W$5<AC$5)*X70+(AI$5<AC$5)*AJ70+(AO$5<AC$5)*AP70+(AU$5<AC$5)*AV70))) | AF70: =IF(AD70-AE70<0.005,0,AD70-AE70) | AG70: =AL69 | AH70: =AG70*Plan!D11/100/12 | AI70: =MIN(Plan!E11,AG70+AH70) | AJ70: =AG70+AH70-AI70 | AK70: =MIN(AJ70,MAX(0,$B70-((E$5<AI$5)*F70+(K$5<AI$5)*L70+(Q$5<AI$5)*R70+(W$5<AI$5)*X70+(AC$5<AI$5)*AD70+(AO$5<AI$5)*AP70+(AU$5<AI$5)*AV70))) | AL70: =IF(AJ70-AK70<0.005,0,AJ70-AK70) | AM70: =AR69 | AN70: =AM70*Plan!D12/100/12 | AO70: =MIN(Plan!E12,AM70+AN70) | AP70: =AM70+AN70-AO70 | AQ70: =MIN(AP70,MAX(0,$B70-((E$5<AO$5)*F70+(K$5<AO$5)*L70+(Q$5<AO$5)*R70+(W$5<AO$5)*X70+(AC$5<AO$5)*AD70+(AI$5<AO$5)*AJ70+(AU$5<AO$5)*AV70))) | AR70: =IF(AP70-AQ70<0.005,0,AP70-AQ70) | AS70: =AX69 | AT70: =AS70*Plan!D13/100/12 | AU70: =MIN(Plan!E13,AS70+AT70) | AV70: =AS70+AT70-AU70 | AW70: =MIN(AV70,MAX(0,$B70-((E$5<AU$5)*F70+(K$5<AU$5)*L70+(Q$5<AU$5)*R70+(W$5<AU$5)*X70+(AC$5<AU$5)*AD70+(AI$5<AU$5)*AJ70+(AO$5<AU$5)*AP70))) | AX70: =IF(AV70-AW70<0.005,0,AV70-AW70) | BC70: =H70+N70+T70+Z70+AF70+AL70+AR70+AX70
A71: 65 | B71: =MAX(0,$B$3-(E71+K71+Q71+W71+AC71+AI71+AO71+AU71)) | C71: =H70 | D71: =C71*Plan!D6/100/12 | E71: =MIN(Plan!E6,C71+D71) | F71: =C71+D71-E71 | G71: =MIN(F71,MAX(0,$B71-((K$5<E$5)*L71+(Q$5<E$5)*R71+(W$5<E$5)*X71+(AC$5<E$5)*AD71+(AI$5<E$5)*AJ71+(AO$5<E$5)*AP71+(AU$5<E$5)*AV71))) | H71: =IF(F71-G71<0.005,0,F71-G71) | I71: =N70 | J71: =I71*Plan!D7/100/12 | K71: =MIN(Plan!E7,I71+J71) | L71: =I71+J71-K71 | M71: =MIN(L71,MAX(0,$B71-((E$5<K$5)*F71+(Q$5<K$5)*R71+(W$5<K$5)*X71+(AC$5<K$5)*AD71+(AI$5<K$5)*AJ71+(AO$5<K$5)*AP71+(AU$5<K$5)*AV71))) | N71: =IF(L71-M71<0.005,0,L71-M71) | O71: =T70 | P71: =O71*Plan!D8/100/12 | Q71: =MIN(Plan!E8,O71+P71) | R71: =O71+P71-Q71 | S71: =MIN(R71,MAX(0,$B71-((E$5<Q$5)*F71+(K$5<Q$5)*L71+(W$5<Q$5)*X71+(AC$5<Q$5)*AD71+(AI$5<Q$5)*AJ71+(AO$5<Q$5)*AP71+(AU$5<Q$5)*AV71))) | T71: =IF(R71-S71<0.005,0,R71-S71) | U71: =Z70 | V71: =U71*Plan!D9/100/12 | W71: =MIN(Plan!E9,U71+V71) | X71: =U71+V71-W71 | Y71: =MIN(X71,MAX(0,$B71-((E$5<W$5)*F71+(K$5<W$5)*L71+(Q$5<W$5)*R71+(AC$5<W$5)*AD71+(AI$5<W$5)*AJ71+(AO$5<W$5)*AP71+(AU$5<W$5)*AV71))) | Z71: =IF(X71-Y71<0.005,0,X71-Y71) | AA71: =AF70 | AB71: =AA71*Plan!D10/100/12 | AC71: =MIN(Plan!E10,AA71+AB71) | AD71: =AA71+AB71-AC71 | AE71: =MIN(AD71,MAX(0,$B71-((E$5<AC$5)*F71+(K$5<AC$5)*L71+(Q$5<AC$5)*R71+(W$5<AC$5)*X71+(AI$5<AC$5)*AJ71+(AO$5<AC$5)*AP71+(AU$5<AC$5)*AV71))) | AF71: =IF(AD71-AE71<0.005,0,AD71-AE71) | AG71: =AL70 | AH71: =AG71*Plan!D11/100/12 | AI71: =MIN(Plan!E11,AG71+AH71) | AJ71: =AG71+AH71-AI71 | AK71: =MIN(AJ71,MAX(0,$B71-((E$5<AI$5)*F71+(K$5<AI$5)*L71+(Q$5<AI$5)*R71+(W$5<AI$5)*X71+(AC$5<AI$5)*AD71+(AO$5<AI$5)*AP71+(AU$5<AI$5)*AV71))) | AL71: =IF(AJ71-AK71<0.005,0,AJ71-AK71) | AM71: =AR70 | AN71: =AM71*Plan!D12/100/12 | AO71: =MIN(Plan!E12,AM71+AN71) | AP71: =AM71+AN71-AO71 | AQ71: =MIN(AP71,MAX(0,$B71-((E$5<AO$5)*F71+(K$5<AO$5)*L71+(Q$5<AO$5)*R71+(W$5<AO$5)*X71+(AC$5<AO$5)*AD71+(AI$5<AO$5)*AJ71+(AU$5<AO$5)*AV71))) | AR71: =IF(AP71-AQ71<0.005,0,AP71-AQ71) | AS71: =AX70 | AT71: =AS71*Plan!D13/100/12 | AU71: =MIN(Plan!E13,AS71+AT71) | AV71: =AS71+AT71-AU71 | AW71: =MIN(AV71,MAX(0,$B71-((E$5<AU$5)*F71+(K$5<AU$5)*L71+(Q$5<AU$5)*R71+(W$5<AU$5)*X71+(AC$5<AU$5)*AD71+(AI$5<AU$5)*AJ71+(AO$5<AU$5)*AP71))) | AX71: =IF(AV71-AW71<0.005,0,AV71-AW71) | BC71: =H71+N71+T71+Z71+AF71+AL71+AR71+AX71
A72: 66 | B72: =MAX(0,$B$3-(E72+K72+Q72+W72+AC72+AI72+AO72+AU72)) | C72: =H71 | D72: =C72*Plan!D6/100/12 | E72: =MIN(Plan!E6,C72+D72) | F72: =C72+D72-E72 | G72: =MIN(F72,MAX(0,$B72-((K$5<E$5)*L72+(Q$5<E$5)*R72+(W$5<E$5)*X72+(AC$5<E$5)*AD72+(AI$5<E$5)*AJ72+(AO$5<E$5)*AP72+(AU$5<E$5)*AV72))) | H72: =IF(F72-G72<0.005,0,F72-G72) | I72: =N71 | J72: =I72*Plan!D7/100/12 | K72: =MIN(Plan!E7,I72+J72) | L72: =I72+J72-K72 | M72: =MIN(L72,MAX(0,$B72-((E$5<K$5)*F72+(Q$5<K$5)*R72+(W$5<K$5)*X72+(AC$5<K$5)*AD72+(AI$5<K$5)*AJ72+(AO$5<K$5)*AP72+(AU$5<K$5)*AV72))) | N72: =IF(L72-M72<0.005,0,L72-M72) | O72: =T71 | P72: =O72*Plan!D8/100/12 | Q72: =MIN(Plan!E8,O72+P72) | R72: =O72+P72-Q72 | S72: =MIN(R72,MAX(0,$B72-((E$5<Q$5)*F72+(K$5<Q$5)*L72+(W$5<Q$5)*X72+(AC$5<Q$5)*AD72+(AI$5<Q$5)*AJ72+(AO$5<Q$5)*AP72+(AU$5<Q$5)*AV72))) | T72: =IF(R72-S72<0.005,0,R72-S72) | U72: =Z71 | V72: =U72*Plan!D9/100/12 | W72: =MIN(Plan!E9,U72+V72) | X72: =U72+V72-W72 | Y72: =MIN(X72,MAX(0,$B72-((E$5<W$5)*F72+(K$5<W$5)*L72+(Q$5<W$5)*R72+(AC$5<W$5)*AD72+(AI$5<W$5)*AJ72+(AO$5<W$5)*AP72+(AU$5<W$5)*AV72))) | Z72: =IF(X72-Y72<0.005,0,X72-Y72) | AA72: =AF71 | AB72: =AA72*Plan!D10/100/12 | AC72: =MIN(Plan!E10,AA72+AB72) | AD72: =AA72+AB72-AC72 | AE72: =MIN(AD72,MAX(0,$B72-((E$5<AC$5)*F72+(K$5<AC$5)*L72+(Q$5<AC$5)*R72+(W$5<AC$5)*X72+(AI$5<AC$5)*AJ72+(AO$5<AC$5)*AP72+(AU$5<AC$5)*AV72))) | AF72: =IF(AD72-AE72<0.005,0,AD72-AE72) | AG72: =AL71 | AH72: =AG72*Plan!D11/100/12 | AI72: =MIN(Plan!E11,AG72+AH72) | AJ72: =AG72+AH72-AI72 | AK72: =MIN(AJ72,MAX(0,$B72-((E$5<AI$5)*F72+(K$5<AI$5)*L72+(Q$5<AI$5)*R72+(W$5<AI$5)*X72+(AC$5<AI$5)*AD72+(AO$5<AI$5)*AP72+(AU$5<AI$5)*AV72))) | AL72: =IF(AJ72-AK72<0.005,0,AJ72-AK72) | AM72: =AR71 | AN72: =AM72*Plan!D12/100/12 | AO72: =MIN(Plan!E12,AM72+AN72) | AP72: =AM72+AN72-AO72 | AQ72: =MIN(AP72,MAX(0,$B72-((E$5<AO$5)*F72+(K$5<AO$5)*L72+(Q$5<AO$5)*R72+(W$5<AO$5)*X72+(AC$5<AO$5)*AD72+(AI$5<AO$5)*AJ72+(AU$5<AO$5)*AV72))) | AR72: =IF(AP72-AQ72<0.005,0,AP72-AQ72) | AS72: =AX71 | AT72: =AS72*Plan!D13/100/12 | AU72: =MIN(Plan!E13,AS72+AT72) | AV72: =AS72+AT72-AU72 | AW72: =MIN(AV72,MAX(0,$B72-((E$5<AU$5)*F72+(K$5<AU$5)*L72+(Q$5<AU$5)*R72+(W$5<AU$5)*X72+(AC$5<AU$5)*AD72+(AI$5<AU$5)*AJ72+(AO$5<AU$5)*AP72))) | AX72: =IF(AV72-AW72<0.005,0,AV72-AW72) | BC72: =H72+N72+T72+Z72+AF72+AL72+AR72+AX72
A73: 67 | B73: =MAX(0,$B$3-(E73+K73+Q73+W73+AC73+AI73+AO73+AU73)) | C73: =H72 | D73: =C73*Plan!D6/100/12 | E73: =MIN(Plan!E6,C73+D73) | F73: =C73+D73-E73 | G73: =MIN(F73,MAX(0,$B73-((K$5<E$5)*L73+(Q$5<E$5)*R73+(W$5<E$5)*X73+(AC$5<E$5)*AD73+(AI$5<E$5)*AJ73+(AO$5<E$5)*AP73+(AU$5<E$5)*AV73))) | H73: =IF(F73-G73<0.005,0,F73-G73) | I73: =N72 | J73: =I73*Plan!D7/100/12 | K73: =MIN(Plan!E7,I73+J73) | L73: =I73+J73-K73 | M73: =MIN(L73,MAX(0,$B73-((E$5<K$5)*F73+(Q$5<K$5)*R73+(W$5<K$5)*X73+(AC$5<K$5)*AD73+(AI$5<K$5)*AJ73+(AO$5<K$5)*AP73+(AU$5<K$5)*AV73))) | N73: =IF(L73-M73<0.005,0,L73-M73) | O73: =T72 | P73: =O73*Plan!D8/100/12 | Q73: =MIN(Plan!E8,O73+P73) | R73: =O73+P73-Q73 | S73: =MIN(R73,MAX(0,$B73-((E$5<Q$5)*F73+(K$5<Q$5)*L73+(W$5<Q$5)*X73+(AC$5<Q$5)*AD73+(AI$5<Q$5)*AJ73+(AO$5<Q$5)*AP73+(AU$5<Q$5)*AV73))) | T73: =IF(R73-S73<0.005,0,R73-S73) | U73: =Z72 | V73: =U73*Plan!D9/100/12 | W73: =MIN(Plan!E9,U73+V73) | X73: =U73+V73-W73 | Y73: =MIN(X73,MAX(0,$B73-((E$5<W$5)*F73+(K$5<W$5)*L73+(Q$5<W$5)*R73+(AC$5<W$5)*AD73+(AI$5<W$5)*AJ73+(AO$5<W$5)*AP73+(AU$5<W$5)*AV73))) | Z73: =IF(X73-Y73<0.005,0,X73-Y73) | AA73: =AF72 | AB73: =AA73*Plan!D10/100/12 | AC73: =MIN(Plan!E10,AA73+AB73) | AD73: =AA73+AB73-AC73 | AE73: =MIN(AD73,MAX(0,$B73-((E$5<AC$5)*F73+(K$5<AC$5)*L73+(Q$5<AC$5)*R73+(W$5<AC$5)*X73+(AI$5<AC$5)*AJ73+(AO$5<AC$5)*AP73+(AU$5<AC$5)*AV73))) | AF73: =IF(AD73-AE73<0.005,0,AD73-AE73) | AG73: =AL72 | AH73: =AG73*Plan!D11/100/12 | AI73: =MIN(Plan!E11,AG73+AH73) | AJ73: =AG73+AH73-AI73 | AK73: =MIN(AJ73,MAX(0,$B73-((E$5<AI$5)*F73+(K$5<AI$5)*L73+(Q$5<AI$5)*R73+(W$5<AI$5)*X73+(AC$5<AI$5)*AD73+(AO$5<AI$5)*AP73+(AU$5<AI$5)*AV73))) | AL73: =IF(AJ73-AK73<0.005,0,AJ73-AK73) | AM73: =AR72 | AN73: =AM73*Plan!D12/100/12 | AO73: =MIN(Plan!E12,AM73+AN73) | AP73: =AM73+AN73-AO73 | AQ73: =MIN(AP73,MAX(0,$B73-((E$5<AO$5)*F73+(K$5<AO$5)*L73+(Q$5<AO$5)*R73+(W$5<AO$5)*X73+(AC$5<AO$5)*AD73+(AI$5<AO$5)*AJ73+(AU$5<AO$5)*AV73))) | AR73: =IF(AP73-AQ73<0.005,0,AP73-AQ73) | AS73: =AX72 | AT73: =AS73*Plan!D13/100/12 | AU73: =MIN(Plan!E13,AS73+AT73) | AV73: =AS73+AT73-AU73 | AW73: =MIN(AV73,MAX(0,$B73-((E$5<AU$5)*F73+(K$5<AU$5)*L73+(Q$5<AU$5)*R73+(W$5<AU$5)*X73+(AC$5<AU$5)*AD73+(AI$5<AU$5)*AJ73+(AO$5<AU$5)*AP73))) | AX73: =IF(AV73-AW73<0.005,0,AV73-AW73) | BC73: =H73+N73+T73+Z73+AF73+AL73+AR73+AX73
A74: 68 | B74: =MAX(0,$B$3-(E74+K74+Q74+W74+AC74+AI74+AO74+AU74)) | C74: =H73 | D74: =C74*Plan!D6/100/12 | E74: =MIN(Plan!E6,C74+D74) | F74: =C74+D74-E74 | G74: =MIN(F74,MAX(0,$B74-((K$5<E$5)*L74+(Q$5<E$5)*R74+(W$5<E$5)*X74+(AC$5<E$5)*AD74+(AI$5<E$5)*AJ74+(AO$5<E$5)*AP74+(AU$5<E$5)*AV74))) | H74: =IF(F74-G74<0.005,0,F74-G74) | I74: =N73 | J74: =I74*Plan!D7/100/12 | K74: =MIN(Plan!E7,I74+J74) | L74: =I74+J74-K74 | M74: =MIN(L74,MAX(0,$B74-((E$5<K$5)*F74+(Q$5<K$5)*R74+(W$5<K$5)*X74+(AC$5<K$5)*AD74+(AI$5<K$5)*AJ74+(AO$5<K$5)*AP74+(AU$5<K$5)*AV74))) | N74: =IF(L74-M74<0.005,0,L74-M74) | O74: =T73 | P74: =O74*Plan!D8/100/12 | Q74: =MIN(Plan!E8,O74+P74) | R74: =O74+P74-Q74 | S74: =MIN(R74,MAX(0,$B74-((E$5<Q$5)*F74+(K$5<Q$5)*L74+(W$5<Q$5)*X74+(AC$5<Q$5)*AD74+(AI$5<Q$5)*AJ74+(AO$5<Q$5)*AP74+(AU$5<Q$5)*AV74))) | T74: =IF(R74-S74<0.005,0,R74-S74) | U74: =Z73 | V74: =U74*Plan!D9/100/12 | W74: =MIN(Plan!E9,U74+V74) | X74: =U74+V74-W74 | Y74: =MIN(X74,MAX(0,$B74-((E$5<W$5)*F74+(K$5<W$5)*L74+(Q$5<W$5)*R74+(AC$5<W$5)*AD74+(AI$5<W$5)*AJ74+(AO$5<W$5)*AP74+(AU$5<W$5)*AV74))) | Z74: =IF(X74-Y74<0.005,0,X74-Y74) | AA74: =AF73 | AB74: =AA74*Plan!D10/100/12 | AC74: =MIN(Plan!E10,AA74+AB74) | AD74: =AA74+AB74-AC74 | AE74: =MIN(AD74,MAX(0,$B74-((E$5<AC$5)*F74+(K$5<AC$5)*L74+(Q$5<AC$5)*R74+(W$5<AC$5)*X74+(AI$5<AC$5)*AJ74+(AO$5<AC$5)*AP74+(AU$5<AC$5)*AV74))) | AF74: =IF(AD74-AE74<0.005,0,AD74-AE74) | AG74: =AL73 | AH74: =AG74*Plan!D11/100/12 | AI74: =MIN(Plan!E11,AG74+AH74) | AJ74: =AG74+AH74-AI74 | AK74: =MIN(AJ74,MAX(0,$B74-((E$5<AI$5)*F74+(K$5<AI$5)*L74+(Q$5<AI$5)*R74+(W$5<AI$5)*X74+(AC$5<AI$5)*AD74+(AO$5<AI$5)*AP74+(AU$5<AI$5)*AV74))) | AL74: =IF(AJ74-AK74<0.005,0,AJ74-AK74) | AM74: =AR73 | AN74: =AM74*Plan!D12/100/12 | AO74: =MIN(Plan!E12,AM74+AN74) | AP74: =AM74+AN74-AO74 | AQ74: =MIN(AP74,MAX(0,$B74-((E$5<AO$5)*F74+(K$5<AO$5)*L74+(Q$5<AO$5)*R74+(W$5<AO$5)*X74+(AC$5<AO$5)*AD74+(AI$5<AO$5)*AJ74+(AU$5<AO$5)*AV74))) | AR74: =IF(AP74-AQ74<0.005,0,AP74-AQ74) | AS74: =AX73 | AT74: =AS74*Plan!D13/100/12 | AU74: =MIN(Plan!E13,AS74+AT74) | AV74: =AS74+AT74-AU74 | AW74: =MIN(AV74,MAX(0,$B74-((E$5<AU$5)*F74+(K$5<AU$5)*L74+(Q$5<AU$5)*R74+(W$5<AU$5)*X74+(AC$5<AU$5)*AD74+(AI$5<AU$5)*AJ74+(AO$5<AU$5)*AP74))) | AX74: =IF(AV74-AW74<0.005,0,AV74-AW74) | BC74: =H74+N74+T74+Z74+AF74+AL74+AR74+AX74
A75: 69 | B75: =MAX(0,$B$3-(E75+K75+Q75+W75+AC75+AI75+AO75+AU75)) | C75: =H74 | D75: =C75*Plan!D6/100/12 | E75: =MIN(Plan!E6,C75+D75) | F75: =C75+D75-E75 | G75: =MIN(F75,MAX(0,$B75-((K$5<E$5)*L75+(Q$5<E$5)*R75+(W$5<E$5)*X75+(AC$5<E$5)*AD75+(AI$5<E$5)*AJ75+(AO$5<E$5)*AP75+(AU$5<E$5)*AV75))) | H75: =IF(F75-G75<0.005,0,F75-G75) | I75: =N74 | J75: =I75*Plan!D7/100/12 | K75: =MIN(Plan!E7,I75+J75) | L75: =I75+J75-K75 | M75: =MIN(L75,MAX(0,$B75-((E$5<K$5)*F75+(Q$5<K$5)*R75+(W$5<K$5)*X75+(AC$5<K$5)*AD75+(AI$5<K$5)*AJ75+(AO$5<K$5)*AP75+(AU$5<K$5)*AV75))) | N75: =IF(L75-M75<0.005,0,L75-M75) | O75: =T74 | P75: =O75*Plan!D8/100/12 | Q75: =MIN(Plan!E8,O75+P75) | R75: =O75+P75-Q75 | S75: =MIN(R75,MAX(0,$B75-((E$5<Q$5)*F75+(K$5<Q$5)*L75+(W$5<Q$5)*X75+(AC$5<Q$5)*AD75+(AI$5<Q$5)*AJ75+(AO$5<Q$5)*AP75+(AU$5<Q$5)*AV75))) | T75: =IF(R75-S75<0.005,0,R75-S75) | U75: =Z74 | V75: =U75*Plan!D9/100/12 | W75: =MIN(Plan!E9,U75+V75) | X75: =U75+V75-W75 | Y75: =MIN(X75,MAX(0,$B75-((E$5<W$5)*F75+(K$5<W$5)*L75+(Q$5<W$5)*R75+(AC$5<W$5)*AD75+(AI$5<W$5)*AJ75+(AO$5<W$5)*AP75+(AU$5<W$5)*AV75))) | Z75: =IF(X75-Y75<0.005,0,X75-Y75) | AA75: =AF74 | AB75: =AA75*Plan!D10/100/12 | AC75: =MIN(Plan!E10,AA75+AB75) | AD75: =AA75+AB75-AC75 | AE75: =MIN(AD75,MAX(0,$B75-((E$5<AC$5)*F75+(K$5<AC$5)*L75+(Q$5<AC$5)*R75+(W$5<AC$5)*X75+(AI$5<AC$5)*AJ75+(AO$5<AC$5)*AP75+(AU$5<AC$5)*AV75))) | AF75: =IF(AD75-AE75<0.005,0,AD75-AE75) | AG75: =AL74 | AH75: =AG75*Plan!D11/100/12 | AI75: =MIN(Plan!E11,AG75+AH75) | AJ75: =AG75+AH75-AI75 | AK75: =MIN(AJ75,MAX(0,$B75-((E$5<AI$5)*F75+(K$5<AI$5)*L75+(Q$5<AI$5)*R75+(W$5<AI$5)*X75+(AC$5<AI$5)*AD75+(AO$5<AI$5)*AP75+(AU$5<AI$5)*AV75))) | AL75: =IF(AJ75-AK75<0.005,0,AJ75-AK75) | AM75: =AR74 | AN75: =AM75*Plan!D12/100/12 | AO75: =MIN(Plan!E12,AM75+AN75) | AP75: =AM75+AN75-AO75 | AQ75: =MIN(AP75,MAX(0,$B75-((E$5<AO$5)*F75+(K$5<AO$5)*L75+(Q$5<AO$5)*R75+(W$5<AO$5)*X75+(AC$5<AO$5)*AD75+(AI$5<AO$5)*AJ75+(AU$5<AO$5)*AV75))) | AR75: =IF(AP75-AQ75<0.005,0,AP75-AQ75) | AS75: =AX74 | AT75: =AS75*Plan!D13/100/12 | AU75: =MIN(Plan!E13,AS75+AT75) | AV75: =AS75+AT75-AU75 | AW75: =MIN(AV75,MAX(0,$B75-((E$5<AU$5)*F75+(K$5<AU$5)*L75+(Q$5<AU$5)*R75+(W$5<AU$5)*X75+(AC$5<AU$5)*AD75+(AI$5<AU$5)*AJ75+(AO$5<AU$5)*AP75))) | AX75: =IF(AV75-AW75<0.005,0,AV75-AW75) | BC75: =H75+N75+T75+Z75+AF75+AL75+AR75+AX75
A76: 70 | B76: =MAX(0,$B$3-(E76+K76+Q76+W76+AC76+AI76+AO76+AU76)) | C76: =H75 | D76: =C76*Plan!D6/100/12 | E76: =MIN(Plan!E6,C76+D76) | F76: =C76+D76-E76 | G76: =MIN(F76,MAX(0,$B76-((K$5<E$5)*L76+(Q$5<E$5)*R76+(W$5<E$5)*X76+(AC$5<E$5)*AD76+(AI$5<E$5)*AJ76+(AO$5<E$5)*AP76+(AU$5<E$5)*AV76))) | H76: =IF(F76-G76<0.005,0,F76-G76) | I76: =N75 | J76: =I76*Plan!D7/100/12 | K76: =MIN(Plan!E7,I76+J76) | L76: =I76+J76-K76 | M76: =MIN(L76,MAX(0,$B76-((E$5<K$5)*F76+(Q$5<K$5)*R76+(W$5<K$5)*X76+(AC$5<K$5)*AD76+(AI$5<K$5)*AJ76+(AO$5<K$5)*AP76+(AU$5<K$5)*AV76))) | N76: =IF(L76-M76<0.005,0,L76-M76) | O76: =T75 | P76: =O76*Plan!D8/100/12 | Q76: =MIN(Plan!E8,O76+P76) | R76: =O76+P76-Q76 | S76: =MIN(R76,MAX(0,$B76-((E$5<Q$5)*F76+(K$5<Q$5)*L76+(W$5<Q$5)*X76+(AC$5<Q$5)*AD76+(AI$5<Q$5)*AJ76+(AO$5<Q$5)*AP76+(AU$5<Q$5)*AV76))) | T76: =IF(R76-S76<0.005,0,R76-S76) | U76: =Z75 | V76: =U76*Plan!D9/100/12 | W76: =MIN(Plan!E9,U76+V76) | X76: =U76+V76-W76 | Y76: =MIN(X76,MAX(0,$B76-((E$5<W$5)*F76+(K$5<W$5)*L76+(Q$5<W$5)*R76+(AC$5<W$5)*AD76+(AI$5<W$5)*AJ76+(AO$5<W$5)*AP76+(AU$5<W$5)*AV76))) | Z76: =IF(X76-Y76<0.005,0,X76-Y76) | AA76: =AF75 | AB76: =AA76*Plan!D10/100/12 | AC76: =MIN(Plan!E10,AA76+AB76) | AD76: =AA76+AB76-AC76 | AE76: =MIN(AD76,MAX(0,$B76-((E$5<AC$5)*F76+(K$5<AC$5)*L76+(Q$5<AC$5)*R76+(W$5<AC$5)*X76+(AI$5<AC$5)*AJ76+(AO$5<AC$5)*AP76+(AU$5<AC$5)*AV76))) | AF76: =IF(AD76-AE76<0.005,0,AD76-AE76) | AG76: =AL75 | AH76: =AG76*Plan!D11/100/12 | AI76: =MIN(Plan!E11,AG76+AH76) | AJ76: =AG76+AH76-AI76 | AK76: =MIN(AJ76,MAX(0,$B76-((E$5<AI$5)*F76+(K$5<AI$5)*L76+(Q$5<AI$5)*R76+(W$5<AI$5)*X76+(AC$5<AI$5)*AD76+(AO$5<AI$5)*AP76+(AU$5<AI$5)*AV76))) | AL76: =IF(AJ76-AK76<0.005,0,AJ76-AK76) | AM76: =AR75 | AN76: =AM76*Plan!D12/100/12 | AO76: =MIN(Plan!E12,AM76+AN76) | AP76: =AM76+AN76-AO76 | AQ76: =MIN(AP76,MAX(0,$B76-((E$5<AO$5)*F76+(K$5<AO$5)*L76+(Q$5<AO$5)*R76+(W$5<AO$5)*X76+(AC$5<AO$5)*AD76+(AI$5<AO$5)*AJ76+(AU$5<AO$5)*AV76))) | AR76: =IF(AP76-AQ76<0.005,0,AP76-AQ76) | AS76: =AX75 | AT76: =AS76*Plan!D13/100/12 | AU76: =MIN(Plan!E13,AS76+AT76) | AV76: =AS76+AT76-AU76 | AW76: =MIN(AV76,MAX(0,$B76-((E$5<AU$5)*F76+(K$5<AU$5)*L76+(Q$5<AU$5)*R76+(W$5<AU$5)*X76+(AC$5<AU$5)*AD76+(AI$5<AU$5)*AJ76+(AO$5<AU$5)*AP76))) | AX76: =IF(AV76-AW76<0.005,0,AV76-AW76) | BC76: =H76+N76+T76+Z76+AF76+AL76+AR76+AX76
A77: 71 | B77: =MAX(0,$B$3-(E77+K77+Q77+W77+AC77+AI77+AO77+AU77)) | C77: =H76 | D77: =C77*Plan!D6/100/12 | E77: =MIN(Plan!E6,C77+D77) | F77: =C77+D77-E77 | G77: =MIN(F77,MAX(0,$B77-((K$5<E$5)*L77+(Q$5<E$5)*R77+(W$5<E$5)*X77+(AC$5<E$5)*AD77+(AI$5<E$5)*AJ77+(AO$5<E$5)*AP77+(AU$5<E$5)*AV77))) | H77: =IF(F77-G77<0.005,0,F77-G77) | I77: =N76 | J77: =I77*Plan!D7/100/12 | K77: =MIN(Plan!E7,I77+J77) | L77: =I77+J77-K77 | M77: =MIN(L77,MAX(0,$B77-((E$5<K$5)*F77+(Q$5<K$5)*R77+(W$5<K$5)*X77+(AC$5<K$5)*AD77+(AI$5<K$5)*AJ77+(AO$5<K$5)*AP77+(AU$5<K$5)*AV77))) | N77: =IF(L77-M77<0.005,0,L77-M77) | O77: =T76 | P77: =O77*Plan!D8/100/12 | Q77: =MIN(Plan!E8,O77+P77) | R77: =O77+P77-Q77 | S77: =MIN(R77,MAX(0,$B77-((E$5<Q$5)*F77+(K$5<Q$5)*L77+(W$5<Q$5)*X77+(AC$5<Q$5)*AD77+(AI$5<Q$5)*AJ77+(AO$5<Q$5)*AP77+(AU$5<Q$5)*AV77))) | T77: =IF(R77-S77<0.005,0,R77-S77) | U77: =Z76 | V77: =U77*Plan!D9/100/12 | W77: =MIN(Plan!E9,U77+V77) | X77: =U77+V77-W77 | Y77: =MIN(X77,MAX(0,$B77-((E$5<W$5)*F77+(K$5<W$5)*L77+(Q$5<W$5)*R77+(AC$5<W$5)*AD77+(AI$5<W$5)*AJ77+(AO$5<W$5)*AP77+(AU$5<W$5)*AV77))) | Z77: =IF(X77-Y77<0.005,0,X77-Y77) | AA77: =AF76 | AB77: =AA77*Plan!D10/100/12 | AC77: =MIN(Plan!E10,AA77+AB77) | AD77: =AA77+AB77-AC77 | AE77: =MIN(AD77,MAX(0,$B77-((E$5<AC$5)*F77+(K$5<AC$5)*L77+(Q$5<AC$5)*R77+(W$5<AC$5)*X77+(AI$5<AC$5)*AJ77+(AO$5<AC$5)*AP77+(AU$5<AC$5)*AV77))) | AF77: =IF(AD77-AE77<0.005,0,AD77-AE77) | AG77: =AL76 | AH77: =AG77*Plan!D11/100/12 | AI77: =MIN(Plan!E11,AG77+AH77) | AJ77: =AG77+AH77-AI77 | AK77: =MIN(AJ77,MAX(0,$B77-((E$5<AI$5)*F77+(K$5<AI$5)*L77+(Q$5<AI$5)*R77+(W$5<AI$5)*X77+(AC$5<AI$5)*AD77+(AO$5<AI$5)*AP77+(AU$5<AI$5)*AV77))) | AL77: =IF(AJ77-AK77<0.005,0,AJ77-AK77) | AM77: =AR76 | AN77: =AM77*Plan!D12/100/12 | AO77: =MIN(Plan!E12,AM77+AN77) | AP77: =AM77+AN77-AO77 | AQ77: =MIN(AP77,MAX(0,$B77-((E$5<AO$5)*F77+(K$5<AO$5)*L77+(Q$5<AO$5)*R77+(W$5<AO$5)*X77+(AC$5<AO$5)*AD77+(AI$5<AO$5)*AJ77+(AU$5<AO$5)*AV77))) | AR77: =IF(AP77-AQ77<0.005,0,AP77-AQ77) | AS77: =AX76 | AT77: =AS77*Plan!D13/100/12 | AU77: =MIN(Plan!E13,AS77+AT77) | AV77: =AS77+AT77-AU77 | AW77: =MIN(AV77,MAX(0,$B77-((E$5<AU$5)*F77+(K$5<AU$5)*L77+(Q$5<AU$5)*R77+(W$5<AU$5)*X77+(AC$5<AU$5)*AD77+(AI$5<AU$5)*AJ77+(AO$5<AU$5)*AP77))) | AX77: =IF(AV77-AW77<0.005,0,AV77-AW77) | BC77: =H77+N77+T77+Z77+AF77+AL77+AR77+AX77
A78: 72 | B78: =MAX(0,$B$3-(E78+K78+Q78+W78+AC78+AI78+AO78+AU78)) | C78: =H77 | D78: =C78*Plan!D6/100/12 | E78: =MIN(Plan!E6,C78+D78) | F78: =C78+D78-E78 | G78: =MIN(F78,MAX(0,$B78-((K$5<E$5)*L78+(Q$5<E$5)*R78+(W$5<E$5)*X78+(AC$5<E$5)*AD78+(AI$5<E$5)*AJ78+(AO$5<E$5)*AP78+(AU$5<E$5)*AV78))) | H78: =IF(F78-G78<0.005,0,F78-G78) | I78: =N77 | J78: =I78*Plan!D7/100/12 | K78: =MIN(Plan!E7,I78+J78) | L78: =I78+J78-K78 | M78: =MIN(L78,MAX(0,$B78-((E$5<K$5)*F78+(Q$5<K$5)*R78+(W$5<K$5)*X78+(AC$5<K$5)*AD78+(AI$5<K$5)*AJ78+(AO$5<K$5)*AP78+(AU$5<K$5)*AV78))) | N78: =IF(L78-M78<0.005,0,L78-M78) | O78: =T77 | P78: =O78*Plan!D8/100/12 | Q78: =MIN(Plan!E8,O78+P78) | R78: =O78+P78-Q78 | S78: =MIN(R78,MAX(0,$B78-((E$5<Q$5)*F78+(K$5<Q$5)*L78+(W$5<Q$5)*X78+(AC$5<Q$5)*AD78+(AI$5<Q$5)*AJ78+(AO$5<Q$5)*AP78+(AU$5<Q$5)*AV78))) | T78: =IF(R78-S78<0.005,0,R78-S78) | U78: =Z77 | V78: =U78*Plan!D9/100/12 | W78: =MIN(Plan!E9,U78+V78) | X78: =U78+V78-W78 | Y78: =MIN(X78,MAX(0,$B78-((E$5<W$5)*F78+(K$5<W$5)*L78+(Q$5<W$5)*R78+(AC$5<W$5)*AD78+(AI$5<W$5)*AJ78+(AO$5<W$5)*AP78+(AU$5<W$5)*AV78))) | Z78: =IF(X78-Y78<0.005,0,X78-Y78) | AA78: =AF77 | AB78: =AA78*Plan!D10/100/12 | AC78: =MIN(Plan!E10,AA78+AB78) | AD78: =AA78+AB78-AC78 | AE78: =MIN(AD78,MAX(0,$B78-((E$5<AC$5)*F78+(K$5<AC$5)*L78+(Q$5<AC$5)*R78+(W$5<AC$5)*X78+(AI$5<AC$5)*AJ78+(AO$5<AC$5)*AP78+(AU$5<AC$5)*AV78))) | AF78: =IF(AD78-AE78<0.005,0,AD78-AE78) | AG78: =AL77 | AH78: =AG78*Plan!D11/100/12 | AI78: =MIN(Plan!E11,AG78+AH78) | AJ78: =AG78+AH78-AI78 | AK78: =MIN(AJ78,MAX(0,$B78-((E$5<AI$5)*F78+(K$5<AI$5)*L78+(Q$5<AI$5)*R78+(W$5<AI$5)*X78+(AC$5<AI$5)*AD78+(AO$5<AI$5)*AP78+(AU$5<AI$5)*AV78))) | AL78: =IF(AJ78-AK78<0.005,0,AJ78-AK78) | AM78: =AR77 | AN78: =AM78*Plan!D12/100/12 | AO78: =MIN(Plan!E12,AM78+AN78) | AP78: =AM78+AN78-AO78 | AQ78: =MIN(AP78,MAX(0,$B78-((E$5<AO$5)*F78+(K$5<AO$5)*L78+(Q$5<AO$5)*R78+(W$5<AO$5)*X78+(AC$5<AO$5)*AD78+(AI$5<AO$5)*AJ78+(AU$5<AO$5)*AV78))) | AR78: =IF(AP78-AQ78<0.005,0,AP78-AQ78) | AS78: =AX77 | AT78: =AS78*Plan!D13/100/12 | AU78: =MIN(Plan!E13,AS78+AT78) | AV78: =AS78+AT78-AU78 | AW78: =MIN(AV78,MAX(0,$B78-((E$5<AU$5)*F78+(K$5<AU$5)*L78+(Q$5<AU$5)*R78+(W$5<AU$5)*X78+(AC$5<AU$5)*AD78+(AI$5<AU$5)*AJ78+(AO$5<AU$5)*AP78))) | AX78: =IF(AV78-AW78<0.005,0,AV78-AW78) | BC78: =H78+N78+T78+Z78+AF78+AL78+AR78+AX78
A79: 73 | B79: =MAX(0,$B$3-(E79+K79+Q79+W79+AC79+AI79+AO79+AU79)) | C79: =H78 | D79: =C79*Plan!D6/100/12 | E79: =MIN(Plan!E6,C79+D79) | F79: =C79+D79-E79 | G79: =MIN(F79,MAX(0,$B79-((K$5<E$5)*L79+(Q$5<E$5)*R79+(W$5<E$5)*X79+(AC$5<E$5)*AD79+(AI$5<E$5)*AJ79+(AO$5<E$5)*AP79+(AU$5<E$5)*AV79))) | H79: =IF(F79-G79<0.005,0,F79-G79) | I79: =N78 | J79: =I79*Plan!D7/100/12 | K79: =MIN(Plan!E7,I79+J79) | L79: =I79+J79-K79 | M79: =MIN(L79,MAX(0,$B79-((E$5<K$5)*F79+(Q$5<K$5)*R79+(W$5<K$5)*X79+(AC$5<K$5)*AD79+(AI$5<K$5)*AJ79+(AO$5<K$5)*AP79+(AU$5<K$5)*AV79))) | N79: =IF(L79-M79<0.005,0,L79-M79) | O79: =T78 | P79: =O79*Plan!D8/100/12 | Q79: =MIN(Plan!E8,O79+P79) | R79: =O79+P79-Q79 | S79: =MIN(R79,MAX(0,$B79-((E$5<Q$5)*F79+(K$5<Q$5)*L79+(W$5<Q$5)*X79+(AC$5<Q$5)*AD79+(AI$5<Q$5)*AJ79+(AO$5<Q$5)*AP79+(AU$5<Q$5)*AV79))) | T79: =IF(R79-S79<0.005,0,R79-S79) | U79: =Z78 | V79: =U79*Plan!D9/100/12 | W79: =MIN(Plan!E9,U79+V79) | X79: =U79+V79-W79 | Y79: =MIN(X79,MAX(0,$B79-((E$5<W$5)*F79+(K$5<W$5)*L79+(Q$5<W$5)*R79+(AC$5<W$5)*AD79+(AI$5<W$5)*AJ79+(AO$5<W$5)*AP79+(AU$5<W$5)*AV79))) | Z79: =IF(X79-Y79<0.005,0,X79-Y79) | AA79: =AF78 | AB79: =AA79*Plan!D10/100/12 | AC79: =MIN(Plan!E10,AA79+AB79) | AD79: =AA79+AB79-AC79 | AE79: =MIN(AD79,MAX(0,$B79-((E$5<AC$5)*F79+(K$5<AC$5)*L79+(Q$5<AC$5)*R79+(W$5<AC$5)*X79+(AI$5<AC$5)*AJ79+(AO$5<AC$5)*AP79+(AU$5<AC$5)*AV79))) | AF79: =IF(AD79-AE79<0.005,0,AD79-AE79) | AG79: =AL78 | AH79: =AG79*Plan!D11/100/12 | AI79: =MIN(Plan!E11,AG79+AH79) | AJ79: =AG79+AH79-AI79 | AK79: =MIN(AJ79,MAX(0,$B79-((E$5<AI$5)*F79+(K$5<AI$5)*L79+(Q$5<AI$5)*R79+(W$5<AI$5)*X79+(AC$5<AI$5)*AD79+(AO$5<AI$5)*AP79+(AU$5<AI$5)*AV79))) | AL79: =IF(AJ79-AK79<0.005,0,AJ79-AK79) | AM79: =AR78 | AN79: =AM79*Plan!D12/100/12 | AO79: =MIN(Plan!E12,AM79+AN79) | AP79: =AM79+AN79-AO79 | AQ79: =MIN(AP79,MAX(0,$B79-((E$5<AO$5)*F79+(K$5<AO$5)*L79+(Q$5<AO$5)*R79+(W$5<AO$5)*X79+(AC$5<AO$5)*AD79+(AI$5<AO$5)*AJ79+(AU$5<AO$5)*AV79))) | AR79: =IF(AP79-AQ79<0.005,0,AP79-AQ79) | AS79: =AX78 | AT79: =AS79*Plan!D13/100/12 | AU79: =MIN(Plan!E13,AS79+AT79) | AV79: =AS79+AT79-AU79 | AW79: =MIN(AV79,MAX(0,$B79-((E$5<AU$5)*F79+(K$5<AU$5)*L79+(Q$5<AU$5)*R79+(W$5<AU$5)*X79+(AC$5<AU$5)*AD79+(AI$5<AU$5)*AJ79+(AO$5<AU$5)*AP79))) | AX79: =IF(AV79-AW79<0.005,0,AV79-AW79) | BC79: =H79+N79+T79+Z79+AF79+AL79+AR79+AX79
A80: 74 | B80: =MAX(0,$B$3-(E80+K80+Q80+W80+AC80+AI80+AO80+AU80)) | C80: =H79 | D80: =C80*Plan!D6/100/12 | E80: =MIN(Plan!E6,C80+D80) | F80: =C80+D80-E80 | G80: =MIN(F80,MAX(0,$B80-((K$5<E$5)*L80+(Q$5<E$5)*R80+(W$5<E$5)*X80+(AC$5<E$5)*AD80+(AI$5<E$5)*AJ80+(AO$5<E$5)*AP80+(AU$5<E$5)*AV80))) | H80: =IF(F80-G80<0.005,0,F80-G80) | I80: =N79 | J80: =I80*Plan!D7/100/12 | K80: =MIN(Plan!E7,I80+J80) | L80: =I80+J80-K80 | M80: =MIN(L80,MAX(0,$B80-((E$5<K$5)*F80+(Q$5<K$5)*R80+(W$5<K$5)*X80+(AC$5<K$5)*AD80+(AI$5<K$5)*AJ80+(AO$5<K$5)*AP80+(AU$5<K$5)*AV80))) | N80: =IF(L80-M80<0.005,0,L80-M80) | O80: =T79 | P80: =O80*Plan!D8/100/12 | Q80: =MIN(Plan!E8,O80+P80) | R80: =O80+P80-Q80 | S80: =MIN(R80,MAX(0,$B80-((E$5<Q$5)*F80+(K$5<Q$5)*L80+(W$5<Q$5)*X80+(AC$5<Q$5)*AD80+(AI$5<Q$5)*AJ80+(AO$5<Q$5)*AP80+(AU$5<Q$5)*AV80))) | T80: =IF(R80-S80<0.005,0,R80-S80) | U80: =Z79 | V80: =U80*Plan!D9/100/12 | W80: =MIN(Plan!E9,U80+V80) | X80: =U80+V80-W80 | Y80: =MIN(X80,MAX(0,$B80-((E$5<W$5)*F80+(K$5<W$5)*L80+(Q$5<W$5)*R80+(AC$5<W$5)*AD80+(AI$5<W$5)*AJ80+(AO$5<W$5)*AP80+(AU$5<W$5)*AV80))) | Z80: =IF(X80-Y80<0.005,0,X80-Y80) | AA80: =AF79 | AB80: =AA80*Plan!D10/100/12 | AC80: =MIN(Plan!E10,AA80+AB80) | AD80: =AA80+AB80-AC80 | AE80: =MIN(AD80,MAX(0,$B80-((E$5<AC$5)*F80+(K$5<AC$5)*L80+(Q$5<AC$5)*R80+(W$5<AC$5)*X80+(AI$5<AC$5)*AJ80+(AO$5<AC$5)*AP80+(AU$5<AC$5)*AV80))) | AF80: =IF(AD80-AE80<0.005,0,AD80-AE80) | AG80: =AL79 | AH80: =AG80*Plan!D11/100/12 | AI80: =MIN(Plan!E11,AG80+AH80) | AJ80: =AG80+AH80-AI80 | AK80: =MIN(AJ80,MAX(0,$B80-((E$5<AI$5)*F80+(K$5<AI$5)*L80+(Q$5<AI$5)*R80+(W$5<AI$5)*X80+(AC$5<AI$5)*AD80+(AO$5<AI$5)*AP80+(AU$5<AI$5)*AV80))) | AL80: =IF(AJ80-AK80<0.005,0,AJ80-AK80) | AM80: =AR79 | AN80: =AM80*Plan!D12/100/12 | AO80: =MIN(Plan!E12,AM80+AN80) | AP80: =AM80+AN80-AO80 | AQ80: =MIN(AP80,MAX(0,$B80-((E$5<AO$5)*F80+(K$5<AO$5)*L80+(Q$5<AO$5)*R80+(W$5<AO$5)*X80+(AC$5<AO$5)*AD80+(AI$5<AO$5)*AJ80+(AU$5<AO$5)*AV80))) | AR80: =IF(AP80-AQ80<0.005,0,AP80-AQ80) | AS80: =AX79 | AT80: =AS80*Plan!D13/100/12 | AU80: =MIN(Plan!E13,AS80+AT80) | AV80: =AS80+AT80-AU80 | AW80: =MIN(AV80,MAX(0,$B80-((E$5<AU$5)*F80+(K$5<AU$5)*L80+(Q$5<AU$5)*R80+(W$5<AU$5)*X80+(AC$5<AU$5)*AD80+(AI$5<AU$5)*AJ80+(AO$5<AU$5)*AP80))) | AX80: =IF(AV80-AW80<0.005,0,AV80-AW80) | BC80: =H80+N80+T80+Z80+AF80+AL80+AR80+AX80
A81: 75 | B81: =MAX(0,$B$3-(E81+K81+Q81+W81+AC81+AI81+AO81+AU81)) | C81: =H80 | D81: =C81*Plan!D6/100/12 | E81: =MIN(Plan!E6,C81+D81) | F81: =C81+D81-E81 | G81: =MIN(F81,MAX(0,$B81-((K$5<E$5)*L81+(Q$5<E$5)*R81+(W$5<E$5)*X81+(AC$5<E$5)*AD81+(AI$5<E$5)*AJ81+(AO$5<E$5)*AP81+(AU$5<E$5)*AV81))) | H81: =IF(F81-G81<0.005,0,F81-G81) | I81: =N80 | J81: =I81*Plan!D7/100/12 | K81: =MIN(Plan!E7,I81+J81) | L81: =I81+J81-K81 | M81: =MIN(L81,MAX(0,$B81-((E$5<K$5)*F81+(Q$5<K$5)*R81+(W$5<K$5)*X81+(AC$5<K$5)*AD81+(AI$5<K$5)*AJ81+(AO$5<K$5)*AP81+(AU$5<K$5)*AV81))) | N81: =IF(L81-M81<0.005,0,L81-M81) | O81: =T80 | P81: =O81*Plan!D8/100/12 | Q81: =MIN(Plan!E8,O81+P81) | R81: =O81+P81-Q81 | S81: =MIN(R81,MAX(0,$B81-((E$5<Q$5)*F81+(K$5<Q$5)*L81+(W$5<Q$5)*X81+(AC$5<Q$5)*AD81+(AI$5<Q$5)*AJ81+(AO$5<Q$5)*AP81+(AU$5<Q$5)*AV81))) | T81: =IF(R81-S81<0.005,0,R81-S81) | U81: =Z80 | V81: =U81*Plan!D9/100/12 | W81: =MIN(Plan!E9,U81+V81) | X81: =U81+V81-W81 | Y81: =MIN(X81,MAX(0,$B81-((E$5<W$5)*F81+(K$5<W$5)*L81+(Q$5<W$5)*R81+(AC$5<W$5)*AD81+(AI$5<W$5)*AJ81+(AO$5<W$5)*AP81+(AU$5<W$5)*AV81))) | Z81: =IF(X81-Y81<0.005,0,X81-Y81) | AA81: =AF80 | AB81: =AA81*Plan!D10/100/12 | AC81: =MIN(Plan!E10,AA81+AB81) | AD81: =AA81+AB81-AC81 | AE81: =MIN(AD81,MAX(0,$B81-((E$5<AC$5)*F81+(K$5<AC$5)*L81+(Q$5<AC$5)*R81+(W$5<AC$5)*X81+(AI$5<AC$5)*AJ81+(AO$5<AC$5)*AP81+(AU$5<AC$5)*AV81))) | AF81: =IF(AD81-AE81<0.005,0,AD81-AE81) | AG81: =AL80 | AH81: =AG81*Plan!D11/100/12 | AI81: =MIN(Plan!E11,AG81+AH81) | AJ81: =AG81+AH81-AI81 | AK81: =MIN(AJ81,MAX(0,$B81-((E$5<AI$5)*F81+(K$5<AI$5)*L81+(Q$5<AI$5)*R81+(W$5<AI$5)*X81+(AC$5<AI$5)*AD81+(AO$5<AI$5)*AP81+(AU$5<AI$5)*AV81))) | AL81: =IF(AJ81-AK81<0.005,0,AJ81-AK81) | AM81: =AR80 | AN81: =AM81*Plan!D12/100/12 | AO81: =MIN(Plan!E12,AM81+AN81) | AP81: =AM81+AN81-AO81 | AQ81: =MIN(AP81,MAX(0,$B81-((E$5<AO$5)*F81+(K$5<AO$5)*L81+(Q$5<AO$5)*R81+(W$5<AO$5)*X81+(AC$5<AO$5)*AD81+(AI$5<AO$5)*AJ81+(AU$5<AO$5)*AV81))) | AR81: =IF(AP81-AQ81<0.005,0,AP81-AQ81) | AS81: =AX80 | AT81: =AS81*Plan!D13/100/12 | AU81: =MIN(Plan!E13,AS81+AT81) | AV81: =AS81+AT81-AU81 | AW81: =MIN(AV81,MAX(0,$B81-((E$5<AU$5)*F81+(K$5<AU$5)*L81+(Q$5<AU$5)*R81+(W$5<AU$5)*X81+(AC$5<AU$5)*AD81+(AI$5<AU$5)*AJ81+(AO$5<AU$5)*AP81))) | AX81: =IF(AV81-AW81<0.005,0,AV81-AW81) | BC81: =H81+N81+T81+Z81+AF81+AL81+AR81+AX81
A82: 76 | B82: =MAX(0,$B$3-(E82+K82+Q82+W82+AC82+AI82+AO82+AU82)) | C82: =H81 | D82: =C82*Plan!D6/100/12 | E82: =MIN(Plan!E6,C82+D82) | F82: =C82+D82-E82 | G82: =MIN(F82,MAX(0,$B82-((K$5<E$5)*L82+(Q$5<E$5)*R82+(W$5<E$5)*X82+(AC$5<E$5)*AD82+(AI$5<E$5)*AJ82+(AO$5<E$5)*AP82+(AU$5<E$5)*AV82))) | H82: =IF(F82-G82<0.005,0,F82-G82) | I82: =N81 | J82: =I82*Plan!D7/100/12 | K82: =MIN(Plan!E7,I82+J82) | L82: =I82+J82-K82 | M82: =MIN(L82,MAX(0,$B82-((E$5<K$5)*F82+(Q$5<K$5)*R82+(W$5<K$5)*X82+(AC$5<K$5)*AD82+(AI$5<K$5)*AJ82+(AO$5<K$5)*AP82+(AU$5<K$5)*AV82))) | N82: =IF(L82-M82<0.005,0,L82-M82) | O82: =T81 | P82: =O82*Plan!D8/100/12 | Q82: =MIN(Plan!E8,O82+P82) | R82: =O82+P82-Q82 | S82: =MIN(R82,MAX(0,$B82-((E$5<Q$5)*F82+(K$5<Q$5)*L82+(W$5<Q$5)*X82+(AC$5<Q$5)*AD82+(AI$5<Q$5)*AJ82+(AO$5<Q$5)*AP82+(AU$5<Q$5)*AV82))) | T82: =IF(R82-S82<0.005,0,R82-S82) | U82: =Z81 | V82: =U82*Plan!D9/100/12 | W82: =MIN(Plan!E9,U82+V82) | X82: =U82+V82-W82 | Y82: =MIN(X82,MAX(0,$B82-((E$5<W$5)*F82+(K$5<W$5)*L82+(Q$5<W$5)*R82+(AC$5<W$5)*AD82+(AI$5<W$5)*AJ82+(AO$5<W$5)*AP82+(AU$5<W$5)*AV82))) | Z82: =IF(X82-Y82<0.005,0,X82-Y82) | AA82: =AF81 | AB82: =AA82*Plan!D10/100/12 | AC82: =MIN(Plan!E10,AA82+AB82) | AD82: =AA82+AB82-AC82 | AE82: =MIN(AD82,MAX(0,$B82-((E$5<AC$5)*F82+(K$5<AC$5)*L82+(Q$5<AC$5)*R82+(W$5<AC$5)*X82+(AI$5<AC$5)*AJ82+(AO$5<AC$5)*AP82+(AU$5<AC$5)*AV82))) | AF82: =IF(AD82-AE82<0.005,0,AD82-AE82) | AG82: =AL81 | AH82: =AG82*Plan!D11/100/12 | AI82: =MIN(Plan!E11,AG82+AH82) | AJ82: =AG82+AH82-AI82 | AK82: =MIN(AJ82,MAX(0,$B82-((E$5<AI$5)*F82+(K$5<AI$5)*L82+(Q$5<AI$5)*R82+(W$5<AI$5)*X82+(AC$5<AI$5)*AD82+(AO$5<AI$5)*AP82+(AU$5<AI$5)*AV82))) | AL82: =IF(AJ82-AK82<0.005,0,AJ82-AK82) | AM82: =AR81 | AN82: =AM82*Plan!D12/100/12 | AO82: =MIN(Plan!E12,AM82+AN82) | AP82: =AM82+AN82-AO82 | AQ82: =MIN(AP82,MAX(0,$B82-((E$5<AO$5)*F82+(K$5<AO$5)*L82+(Q$5<AO$5)*R82+(W$5<AO$5)*X82+(AC$5<AO$5)*AD82+(AI$5<AO$5)*AJ82+(AU$5<AO$5)*AV82))) | AR82: =IF(AP82-AQ82<0.005,0,AP82-AQ82) | AS82: =AX81 | AT82: =AS82*Plan!D13/100/12 | AU82: =MIN(Plan!E13,AS82+AT82) | AV82: =AS82+AT82-AU82 | AW82: =MIN(AV82,MAX(0,$B82-((E$5<AU$5)*F82+(K$5<AU$5)*L82+(Q$5<AU$5)*R82+(W$5<AU$5)*X82+(AC$5<AU$5)*AD82+(AI$5<AU$5)*AJ82+(AO$5<AU$5)*AP82))) | AX82: =IF(AV82-AW82<0.005,0,AV82-AW82) | BC82: =H82+N82+T82+Z82+AF82+AL82+AR82+AX82
A83: 77 | B83: =MAX(0,$B$3-(E83+K83+Q83+W83+AC83+AI83+AO83+AU83)) | C83: =H82 | D83: =C83*Plan!D6/100/12 | E83: =MIN(Plan!E6,C83+D83) | F83: =C83+D83-E83 | G83: =MIN(F83,MAX(0,$B83-((K$5<E$5)*L83+(Q$5<E$5)*R83+(W$5<E$5)*X83+(AC$5<E$5)*AD83+(AI$5<E$5)*AJ83+(AO$5<E$5)*AP83+(AU$5<E$5)*AV83))) | H83: =IF(F83-G83<0.005,0,F83-G83) | I83: =N82 | J83: =I83*Plan!D7/100/12 | K83: =MIN(Plan!E7,I83+J83) | L83: =I83+J83-K83 | M83: =MIN(L83,MAX(0,$B83-((E$5<K$5)*F83+(Q$5<K$5)*R83+(W$5<K$5)*X83+(AC$5<K$5)*AD83+(AI$5<K$5)*AJ83+(AO$5<K$5)*AP83+(AU$5<K$5)*AV83))) | N83: =IF(L83-M83<0.005,0,L83-M83) | O83: =T82 | P83: =O83*Plan!D8/100/12 | Q83: =MIN(Plan!E8,O83+P83) | R83: =O83+P83-Q83 | S83: =MIN(R83,MAX(0,$B83-((E$5<Q$5)*F83+(K$5<Q$5)*L83+(W$5<Q$5)*X83+(AC$5<Q$5)*AD83+(AI$5<Q$5)*AJ83+(AO$5<Q$5)*AP83+(AU$5<Q$5)*AV83))) | T83: =IF(R83-S83<0.005,0,R83-S83) | U83: =Z82 | V83: =U83*Plan!D9/100/12 | W83: =MIN(Plan!E9,U83+V83) | X83: =U83+V83-W83 | Y83: =MIN(X83,MAX(0,$B83-((E$5<W$5)*F83+(K$5<W$5)*L83+(Q$5<W$5)*R83+(AC$5<W$5)*AD83+(AI$5<W$5)*AJ83+(AO$5<W$5)*AP83+(AU$5<W$5)*AV83))) | Z83: =IF(X83-Y83<0.005,0,X83-Y83) | AA83: =AF82 | AB83: =AA83*Plan!D10/100/12 | AC83: =MIN(Plan!E10,AA83+AB83) | AD83: =AA83+AB83-AC83 | AE83: =MIN(AD83,MAX(0,$B83-((E$5<AC$5)*F83+(K$5<AC$5)*L83+(Q$5<AC$5)*R83+(W$5<AC$5)*X83+(AI$5<AC$5)*AJ83+(AO$5<AC$5)*AP83+(AU$5<AC$5)*AV83))) | AF83: =IF(AD83-AE83<0.005,0,AD83-AE83) | AG83: =AL82 | AH83: =AG83*Plan!D11/100/12 | AI83: =MIN(Plan!E11,AG83+AH83) | AJ83: =AG83+AH83-AI83 | AK83: =MIN(AJ83,MAX(0,$B83-((E$5<AI$5)*F83+(K$5<AI$5)*L83+(Q$5<AI$5)*R83+(W$5<AI$5)*X83+(AC$5<AI$5)*AD83+(AO$5<AI$5)*AP83+(AU$5<AI$5)*AV83))) | AL83: =IF(AJ83-AK83<0.005,0,AJ83-AK83) | AM83: =AR82 | AN83: =AM83*Plan!D12/100/12 | AO83: =MIN(Plan!E12,AM83+AN83) | AP83: =AM83+AN83-AO83 | AQ83: =MIN(AP83,MAX(0,$B83-((E$5<AO$5)*F83+(K$5<AO$5)*L83+(Q$5<AO$5)*R83+(W$5<AO$5)*X83+(AC$5<AO$5)*AD83+(AI$5<AO$5)*AJ83+(AU$5<AO$5)*AV83))) | AR83: =IF(AP83-AQ83<0.005,0,AP83-AQ83) | AS83: =AX82 | AT83: =AS83*Plan!D13/100/12 | AU83: =MIN(Plan!E13,AS83+AT83) | AV83: =AS83+AT83-AU83 | AW83: =MIN(AV83,MAX(0,$B83-((E$5<AU$5)*F83+(K$5<AU$5)*L83+(Q$5<AU$5)*R83+(W$5<AU$5)*X83+(AC$5<AU$5)*AD83+(AI$5<AU$5)*AJ83+(AO$5<AU$5)*AP83))) | AX83: =IF(AV83-AW83<0.005,0,AV83-AW83) | BC83: =H83+N83+T83+Z83+AF83+AL83+AR83+AX83
A84: 78 | B84: =MAX(0,$B$3-(E84+K84+Q84+W84+AC84+AI84+AO84+AU84)) | C84: =H83 | D84: =C84*Plan!D6/100/12 | E84: =MIN(Plan!E6,C84+D84) | F84: =C84+D84-E84 | G84: =MIN(F84,MAX(0,$B84-((K$5<E$5)*L84+(Q$5<E$5)*R84+(W$5<E$5)*X84+(AC$5<E$5)*AD84+(AI$5<E$5)*AJ84+(AO$5<E$5)*AP84+(AU$5<E$5)*AV84))) | H84: =IF(F84-G84<0.005,0,F84-G84) | I84: =N83 | J84: =I84*Plan!D7/100/12 | K84: =MIN(Plan!E7,I84+J84) | L84: =I84+J84-K84 | M84: =MIN(L84,MAX(0,$B84-((E$5<K$5)*F84+(Q$5<K$5)*R84+(W$5<K$5)*X84+(AC$5<K$5)*AD84+(AI$5<K$5)*AJ84+(AO$5<K$5)*AP84+(AU$5<K$5)*AV84))) | N84: =IF(L84-M84<0.005,0,L84-M84) | O84: =T83 | P84: =O84*Plan!D8/100/12 | Q84: =MIN(Plan!E8,O84+P84) | R84: =O84+P84-Q84 | S84: =MIN(R84,MAX(0,$B84-((E$5<Q$5)*F84+(K$5<Q$5)*L84+(W$5<Q$5)*X84+(AC$5<Q$5)*AD84+(AI$5<Q$5)*AJ84+(AO$5<Q$5)*AP84+(AU$5<Q$5)*AV84))) | T84: =IF(R84-S84<0.005,0,R84-S84) | U84: =Z83 | V84: =U84*Plan!D9/100/12 | W84: =MIN(Plan!E9,U84+V84) | X84: =U84+V84-W84 | Y84: =MIN(X84,MAX(0,$B84-((E$5<W$5)*F84+(K$5<W$5)*L84+(Q$5<W$5)*R84+(AC$5<W$5)*AD84+(AI$5<W$5)*AJ84+(AO$5<W$5)*AP84+(AU$5<W$5)*AV84))) | Z84: =IF(X84-Y84<0.005,0,X84-Y84) | AA84: =AF83 | AB84: =AA84*Plan!D10/100/12 | AC84: =MIN(Plan!E10,AA84+AB84) | AD84: =AA84+AB84-AC84 | AE84: =MIN(AD84,MAX(0,$B84-((E$5<AC$5)*F84+(K$5<AC$5)*L84+(Q$5<AC$5)*R84+(W$5<AC$5)*X84+(AI$5<AC$5)*AJ84+(AO$5<AC$5)*AP84+(AU$5<AC$5)*AV84))) | AF84: =IF(AD84-AE84<0.005,0,AD84-AE84) | AG84: =AL83 | AH84: =AG84*Plan!D11/100/12 | AI84: =MIN(Plan!E11,AG84+AH84) | AJ84: =AG84+AH84-AI84 | AK84: =MIN(AJ84,MAX(0,$B84-((E$5<AI$5)*F84+(K$5<AI$5)*L84+(Q$5<AI$5)*R84+(W$5<AI$5)*X84+(AC$5<AI$5)*AD84+(AO$5<AI$5)*AP84+(AU$5<AI$5)*AV84))) | AL84: =IF(AJ84-AK84<0.005,0,AJ84-AK84) | AM84: =AR83 | AN84: =AM84*Plan!D12/100/12 | AO84: =MIN(Plan!E12,AM84+AN84) | AP84: =AM84+AN84-AO84 | AQ84: =MIN(AP84,MAX(0,$B84-((E$5<AO$5)*F84+(K$5<AO$5)*L84+(Q$5<AO$5)*R84+(W$5<AO$5)*X84+(AC$5<AO$5)*AD84+(AI$5<AO$5)*AJ84+(AU$5<AO$5)*AV84))) | AR84: =IF(AP84-AQ84<0.005,0,AP84-AQ84) | AS84: =AX83 | AT84: =AS84*Plan!D13/100/12 | AU84: =MIN(Plan!E13,AS84+AT84) | AV84: =AS84+AT84-AU84 | AW84: =MIN(AV84,MAX(0,$B84-((E$5<AU$5)*F84+(K$5<AU$5)*L84+(Q$5<AU$5)*R84+(W$5<AU$5)*X84+(AC$5<AU$5)*AD84+(AI$5<AU$5)*AJ84+(AO$5<AU$5)*AP84))) | AX84: =IF(AV84-AW84<0.005,0,AV84-AW84) | BC84: =H84+N84+T84+Z84+AF84+AL84+AR84+AX84
A85: 79 | B85: =MAX(0,$B$3-(E85+K85+Q85+W85+AC85+AI85+AO85+AU85)) | C85: =H84 | D85: =C85*Plan!D6/100/12 | E85: =MIN(Plan!E6,C85+D85) | F85: =C85+D85-E85 | G85: =MIN(F85,MAX(0,$B85-((K$5<E$5)*L85+(Q$5<E$5)*R85+(W$5<E$5)*X85+(AC$5<E$5)*AD85+(AI$5<E$5)*AJ85+(AO$5<E$5)*AP85+(AU$5<E$5)*AV85))) | H85: =IF(F85-G85<0.005,0,F85-G85) | I85: =N84 | J85: =I85*Plan!D7/100/12 | K85: =MIN(Plan!E7,I85+J85) | L85: =I85+J85-K85 | M85: =MIN(L85,MAX(0,$B85-((E$5<K$5)*F85+(Q$5<K$5)*R85+(W$5<K$5)*X85+(AC$5<K$5)*AD85+(AI$5<K$5)*AJ85+(AO$5<K$5)*AP85+(AU$5<K$5)*AV85))) | N85: =IF(L85-M85<0.005,0,L85-M85) | O85: =T84 | P85: =O85*Plan!D8/100/12 | Q85: =MIN(Plan!E8,O85+P85) | R85: =O85+P85-Q85 | S85: =MIN(R85,MAX(0,$B85-((E$5<Q$5)*F85+(K$5<Q$5)*L85+(W$5<Q$5)*X85+(AC$5<Q$5)*AD85+(AI$5<Q$5)*AJ85+(AO$5<Q$5)*AP85+(AU$5<Q$5)*AV85))) | T85: =IF(R85-S85<0.005,0,R85-S85) | U85: =Z84 | V85: =U85*Plan!D9/100/12 | W85: =MIN(Plan!E9,U85+V85) | X85: =U85+V85-W85 | Y85: =MIN(X85,MAX(0,$B85-((E$5<W$5)*F85+(K$5<W$5)*L85+(Q$5<W$5)*R85+(AC$5<W$5)*AD85+(AI$5<W$5)*AJ85+(AO$5<W$5)*AP85+(AU$5<W$5)*AV85))) | Z85: =IF(X85-Y85<0.005,0,X85-Y85) | AA85: =AF84 | AB85: =AA85*Plan!D10/100/12 | AC85: =MIN(Plan!E10,AA85+AB85) | AD85: =AA85+AB85-AC85 | AE85: =MIN(AD85,MAX(0,$B85-((E$5<AC$5)*F85+(K$5<AC$5)*L85+(Q$5<AC$5)*R85+(W$5<AC$5)*X85+(AI$5<AC$5)*AJ85+(AO$5<AC$5)*AP85+(AU$5<AC$5)*AV85))) | AF85: =IF(AD85-AE85<0.005,0,AD85-AE85) | AG85: =AL84 | AH85: =AG85*Plan!D11/100/12 | AI85: =MIN(Plan!E11,AG85+AH85) | AJ85: =AG85+AH85-AI85 | AK85: =MIN(AJ85,MAX(0,$B85-((E$5<AI$5)*F85+(K$5<AI$5)*L85+(Q$5<AI$5)*R85+(W$5<AI$5)*X85+(AC$5<AI$5)*AD85+(AO$5<AI$5)*AP85+(AU$5<AI$5)*AV85))) | AL85: =IF(AJ85-AK85<0.005,0,AJ85-AK85) | AM85: =AR84 | AN85: =AM85*Plan!D12/100/12 | AO85: =MIN(Plan!E12,AM85+AN85) | AP85: =AM85+AN85-AO85 | AQ85: =MIN(AP85,MAX(0,$B85-((E$5<AO$5)*F85+(K$5<AO$5)*L85+(Q$5<AO$5)*R85+(W$5<AO$5)*X85+(AC$5<AO$5)*AD85+(AI$5<AO$5)*AJ85+(AU$5<AO$5)*AV85))) | AR85: =IF(AP85-AQ85<0.005,0,AP85-AQ85) | AS85: =AX84 | AT85: =AS85*Plan!D13/100/12 | AU85: =MIN(Plan!E13,AS85+AT85) | AV85: =AS85+AT85-AU85 | AW85: =MIN(AV85,MAX(0,$B85-((E$5<AU$5)*F85+(K$5<AU$5)*L85+(Q$5<AU$5)*R85+(W$5<AU$5)*X85+(AC$5<AU$5)*AD85+(AI$5<AU$5)*AJ85+(AO$5<AU$5)*AP85))) | AX85: =IF(AV85-AW85<0.005,0,AV85-AW85) | BC85: =H85+N85+T85+Z85+AF85+AL85+AR85+AX85
A86: 80 | B86: =MAX(0,$B$3-(E86+K86+Q86+W86+AC86+AI86+AO86+AU86)) | C86: =H85 | D86: =C86*Plan!D6/100/12 | E86: =MIN(Plan!E6,C86+D86) | F86: =C86+D86-E86 | G86: =MIN(F86,MAX(0,$B86-((K$5<E$5)*L86+(Q$5<E$5)*R86+(W$5<E$5)*X86+(AC$5<E$5)*AD86+(AI$5<E$5)*AJ86+(AO$5<E$5)*AP86+(AU$5<E$5)*AV86))) | H86: =IF(F86-G86<0.005,0,F86-G86) | I86: =N85 | J86: =I86*Plan!D7/100/12 | K86: =MIN(Plan!E7,I86+J86) | L86: =I86+J86-K86 | M86: =MIN(L86,MAX(0,$B86-((E$5<K$5)*F86+(Q$5<K$5)*R86+(W$5<K$5)*X86+(AC$5<K$5)*AD86+(AI$5<K$5)*AJ86+(AO$5<K$5)*AP86+(AU$5<K$5)*AV86))) | N86: =IF(L86-M86<0.005,0,L86-M86) | O86: =T85 | P86: =O86*Plan!D8/100/12 | Q86: =MIN(Plan!E8,O86+P86) | R86: =O86+P86-Q86 | S86: =MIN(R86,MAX(0,$B86-((E$5<Q$5)*F86+(K$5<Q$5)*L86+(W$5<Q$5)*X86+(AC$5<Q$5)*AD86+(AI$5<Q$5)*AJ86+(AO$5<Q$5)*AP86+(AU$5<Q$5)*AV86))) | T86: =IF(R86-S86<0.005,0,R86-S86) | U86: =Z85 | V86: =U86*Plan!D9/100/12 | W86: =MIN(Plan!E9,U86+V86) | X86: =U86+V86-W86 | Y86: =MIN(X86,MAX(0,$B86-((E$5<W$5)*F86+(K$5<W$5)*L86+(Q$5<W$5)*R86+(AC$5<W$5)*AD86+(AI$5<W$5)*AJ86+(AO$5<W$5)*AP86+(AU$5<W$5)*AV86))) | Z86: =IF(X86-Y86<0.005,0,X86-Y86) | AA86: =AF85 | AB86: =AA86*Plan!D10/100/12 | AC86: =MIN(Plan!E10,AA86+AB86) | AD86: =AA86+AB86-AC86 | AE86: =MIN(AD86,MAX(0,$B86-((E$5<AC$5)*F86+(K$5<AC$5)*L86+(Q$5<AC$5)*R86+(W$5<AC$5)*X86+(AI$5<AC$5)*AJ86+(AO$5<AC$5)*AP86+(AU$5<AC$5)*AV86))) | AF86: =IF(AD86-AE86<0.005,0,AD86-AE86) | AG86: =AL85 | AH86: =AG86*Plan!D11/100/12 | AI86: =MIN(Plan!E11,AG86+AH86) | AJ86: =AG86+AH86-AI86 | AK86: =MIN(AJ86,MAX(0,$B86-((E$5<AI$5)*F86+(K$5<AI$5)*L86+(Q$5<AI$5)*R86+(W$5<AI$5)*X86+(AC$5<AI$5)*AD86+(AO$5<AI$5)*AP86+(AU$5<AI$5)*AV86))) | AL86: =IF(AJ86-AK86<0.005,0,AJ86-AK86) | AM86: =AR85 | AN86: =AM86*Plan!D12/100/12 | AO86: =MIN(Plan!E12,AM86+AN86) | AP86: =AM86+AN86-AO86 | AQ86: =MIN(AP86,MAX(0,$B86-((E$5<AO$5)*F86+(K$5<AO$5)*L86+(Q$5<AO$5)*R86+(W$5<AO$5)*X86+(AC$5<AO$5)*AD86+(AI$5<AO$5)*AJ86+(AU$5<AO$5)*AV86))) | AR86: =IF(AP86-AQ86<0.005,0,AP86-AQ86) | AS86: =AX85 | AT86: =AS86*Plan!D13/100/12 | AU86: =MIN(Plan!E13,AS86+AT86) | AV86: =AS86+AT86-AU86 | AW86: =MIN(AV86,MAX(0,$B86-((E$5<AU$5)*F86+(K$5<AU$5)*L86+(Q$5<AU$5)*R86+(W$5<AU$5)*X86+(AC$5<AU$5)*AD86+(AI$5<AU$5)*AJ86+(AO$5<AU$5)*AP86))) | AX86: =IF(AV86-AW86<0.005,0,AV86-AW86) | BC86: =H86+N86+T86+Z86+AF86+AL86+AR86+AX86
A87: 81 | B87: =MAX(0,$B$3-(E87+K87+Q87+W87+AC87+AI87+AO87+AU87)) | C87: =H86 | D87: =C87*Plan!D6/100/12 | E87: =MIN(Plan!E6,C87+D87) | F87: =C87+D87-E87 | G87: =MIN(F87,MAX(0,$B87-((K$5<E$5)*L87+(Q$5<E$5)*R87+(W$5<E$5)*X87+(AC$5<E$5)*AD87+(AI$5<E$5)*AJ87+(AO$5<E$5)*AP87+(AU$5<E$5)*AV87))) | H87: =IF(F87-G87<0.005,0,F87-G87) | I87: =N86 | J87: =I87*Plan!D7/100/12 | K87: =MIN(Plan!E7,I87+J87) | L87: =I87+J87-K87 | M87: =MIN(L87,MAX(0,$B87-((E$5<K$5)*F87+(Q$5<K$5)*R87+(W$5<K$5)*X87+(AC$5<K$5)*AD87+(AI$5<K$5)*AJ87+(AO$5<K$5)*AP87+(AU$5<K$5)*AV87))) | N87: =IF(L87-M87<0.005,0,L87-M87) | O87: =T86 | P87: =O87*Plan!D8/100/12 | Q87: =MIN(Plan!E8,O87+P87) | R87: =O87+P87-Q87 | S87: =MIN(R87,MAX(0,$B87-((E$5<Q$5)*F87+(K$5<Q$5)*L87+(W$5<Q$5)*X87+(AC$5<Q$5)*AD87+(AI$5<Q$5)*AJ87+(AO$5<Q$5)*AP87+(AU$5<Q$5)*AV87))) | T87: =IF(R87-S87<0.005,0,R87-S87) | U87: =Z86 | V87: =U87*Plan!D9/100/12 | W87: =MIN(Plan!E9,U87+V87) | X87: =U87+V87-W87 | Y87: =MIN(X87,MAX(0,$B87-((E$5<W$5)*F87+(K$5<W$5)*L87+(Q$5<W$5)*R87+(AC$5<W$5)*AD87+(AI$5<W$5)*AJ87+(AO$5<W$5)*AP87+(AU$5<W$5)*AV87))) | Z87: =IF(X87-Y87<0.005,0,X87-Y87) | AA87: =AF86 | AB87: =AA87*Plan!D10/100/12 | AC87: =MIN(Plan!E10,AA87+AB87) | AD87: =AA87+AB87-AC87 | AE87: =MIN(AD87,MAX(0,$B87-((E$5<AC$5)*F87+(K$5<AC$5)*L87+(Q$5<AC$5)*R87+(W$5<AC$5)*X87+(AI$5<AC$5)*AJ87+(AO$5<AC$5)*AP87+(AU$5<AC$5)*AV87))) | AF87: =IF(AD87-AE87<0.005,0,AD87-AE87) | AG87: =AL86 | AH87: =AG87*Plan!D11/100/12 | AI87: =MIN(Plan!E11,AG87+AH87) | AJ87: =AG87+AH87-AI87 | AK87: =MIN(AJ87,MAX(0,$B87-((E$5<AI$5)*F87+(K$5<AI$5)*L87+(Q$5<AI$5)*R87+(W$5<AI$5)*X87+(AC$5<AI$5)*AD87+(AO$5<AI$5)*AP87+(AU$5<AI$5)*AV87))) | AL87: =IF(AJ87-AK87<0.005,0,AJ87-AK87) | AM87: =AR86 | AN87: =AM87*Plan!D12/100/12 | AO87: =MIN(Plan!E12,AM87+AN87) | AP87: =AM87+AN87-AO87 | AQ87: =MIN(AP87,MAX(0,$B87-((E$5<AO$5)*F87+(K$5<AO$5)*L87+(Q$5<AO$5)*R87+(W$5<AO$5)*X87+(AC$5<AO$5)*AD87+(AI$5<AO$5)*AJ87+(AU$5<AO$5)*AV87))) | AR87: =IF(AP87-AQ87<0.005,0,AP87-AQ87) | AS87: =AX86 | AT87: =AS87*Plan!D13/100/12 | AU87: =MIN(Plan!E13,AS87+AT87) | AV87: =AS87+AT87-AU87 | AW87: =MIN(AV87,MAX(0,$B87-((E$5<AU$5)*F87+(K$5<AU$5)*L87+(Q$5<AU$5)*R87+(W$5<AU$5)*X87+(AC$5<AU$5)*AD87+(AI$5<AU$5)*AJ87+(AO$5<AU$5)*AP87))) | AX87: =IF(AV87-AW87<0.005,0,AV87-AW87) | BC87: =H87+N87+T87+Z87+AF87+AL87+AR87+AX87
A88: 82 | B88: =MAX(0,$B$3-(E88+K88+Q88+W88+AC88+AI88+AO88+AU88)) | C88: =H87 | D88: =C88*Plan!D6/100/12 | E88: =MIN(Plan!E6,C88+D88) | F88: =C88+D88-E88 | G88: =MIN(F88,MAX(0,$B88-((K$5<E$5)*L88+(Q$5<E$5)*R88+(W$5<E$5)*X88+(AC$5<E$5)*AD88+(AI$5<E$5)*AJ88+(AO$5<E$5)*AP88+(AU$5<E$5)*AV88))) | H88: =IF(F88-G88<0.005,0,F88-G88) | I88: =N87 | J88: =I88*Plan!D7/100/12 | K88: =MIN(Plan!E7,I88+J88) | L88: =I88+J88-K88 | M88: =MIN(L88,MAX(0,$B88-((E$5<K$5)*F88+(Q$5<K$5)*R88+(W$5<K$5)*X88+(AC$5<K$5)*AD88+(AI$5<K$5)*AJ88+(AO$5<K$5)*AP88+(AU$5<K$5)*AV88))) | N88: =IF(L88-M88<0.005,0,L88-M88) | O88: =T87 | P88: =O88*Plan!D8/100/12 | Q88: =MIN(Plan!E8,O88+P88) | R88: =O88+P88-Q88 | S88: =MIN(R88,MAX(0,$B88-((E$5<Q$5)*F88+(K$5<Q$5)*L88+(W$5<Q$5)*X88+(AC$5<Q$5)*AD88+(AI$5<Q$5)*AJ88+(AO$5<Q$5)*AP88+(AU$5<Q$5)*AV88))) | T88: =IF(R88-S88<0.005,0,R88-S88) | U88: =Z87 | V88: =U88*Plan!D9/100/12 | W88: =MIN(Plan!E9,U88+V88) | X88: =U88+V88-W88 | Y88: =MIN(X88,MAX(0,$B88-((E$5<W$5)*F88+(K$5<W$5)*L88+(Q$5<W$5)*R88+(AC$5<W$5)*AD88+(AI$5<W$5)*AJ88+(AO$5<W$5)*AP88+(AU$5<W$5)*AV88))) | Z88: =IF(X88-Y88<0.005,0,X88-Y88) | AA88: =AF87 | AB88: =AA88*Plan!D10/100/12 | AC88: =MIN(Plan!E10,AA88+AB88) | AD88: =AA88+AB88-AC88 | AE88: =MIN(AD88,MAX(0,$B88-((E$5<AC$5)*F88+(K$5<AC$5)*L88+(Q$5<AC$5)*R88+(W$5<AC$5)*X88+(AI$5<AC$5)*AJ88+(AO$5<AC$5)*AP88+(AU$5<AC$5)*AV88))) | AF88: =IF(AD88-AE88<0.005,0,AD88-AE88) | AG88: =AL87 | AH88: =AG88*Plan!D11/100/12 | AI88: =MIN(Plan!E11,AG88+AH88) | AJ88: =AG88+AH88-AI88 | AK88: =MIN(AJ88,MAX(0,$B88-((E$5<AI$5)*F88+(K$5<AI$5)*L88+(Q$5<AI$5)*R88+(W$5<AI$5)*X88+(AC$5<AI$5)*AD88+(AO$5<AI$5)*AP88+(AU$5<AI$5)*AV88))) | AL88: =IF(AJ88-AK88<0.005,0,AJ88-AK88) | AM88: =AR87 | AN88: =AM88*Plan!D12/100/12 | AO88: =MIN(Plan!E12,AM88+AN88) | AP88: =AM88+AN88-AO88 | AQ88: =MIN(AP88,MAX(0,$B88-((E$5<AO$5)*F88+(K$5<AO$5)*L88+(Q$5<AO$5)*R88+(W$5<AO$5)*X88+(AC$5<AO$5)*AD88+(AI$5<AO$5)*AJ88+(AU$5<AO$5)*AV88))) | AR88: =IF(AP88-AQ88<0.005,0,AP88-AQ88) | AS88: =AX87 | AT88: =AS88*Plan!D13/100/12 | AU88: =MIN(Plan!E13,AS88+AT88) | AV88: =AS88+AT88-AU88 | AW88: =MIN(AV88,MAX(0,$B88-((E$5<AU$5)*F88+(K$5<AU$5)*L88+(Q$5<AU$5)*R88+(W$5<AU$5)*X88+(AC$5<AU$5)*AD88+(AI$5<AU$5)*AJ88+(AO$5<AU$5)*AP88))) | AX88: =IF(AV88-AW88<0.005,0,AV88-AW88) | BC88: =H88+N88+T88+Z88+AF88+AL88+AR88+AX88
A89: 83 | B89: =MAX(0,$B$3-(E89+K89+Q89+W89+AC89+AI89+AO89+AU89)) | C89: =H88 | D89: =C89*Plan!D6/100/12 | E89: =MIN(Plan!E6,C89+D89) | F89: =C89+D89-E89 | G89: =MIN(F89,MAX(0,$B89-((K$5<E$5)*L89+(Q$5<E$5)*R89+(W$5<E$5)*X89+(AC$5<E$5)*AD89+(AI$5<E$5)*AJ89+(AO$5<E$5)*AP89+(AU$5<E$5)*AV89))) | H89: =IF(F89-G89<0.005,0,F89-G89) | I89: =N88 | J89: =I89*Plan!D7/100/12 | K89: =MIN(Plan!E7,I89+J89) | L89: =I89+J89-K89 | M89: =MIN(L89,MAX(0,$B89-((E$5<K$5)*F89+(Q$5<K$5)*R89+(W$5<K$5)*X89+(AC$5<K$5)*AD89+(AI$5<K$5)*AJ89+(AO$5<K$5)*AP89+(AU$5<K$5)*AV89))) | N89: =IF(L89-M89<0.005,0,L89-M89) | O89: =T88 | P89: =O89*Plan!D8/100/12 | Q89: =MIN(Plan!E8,O89+P89) | R89: =O89+P89-Q89 | S89: =MIN(R89,MAX(0,$B89-((E$5<Q$5)*F89+(K$5<Q$5)*L89+(W$5<Q$5)*X89+(AC$5<Q$5)*AD89+(AI$5<Q$5)*AJ89+(AO$5<Q$5)*AP89+(AU$5<Q$5)*AV89))) | T89: =IF(R89-S89<0.005,0,R89-S89) | U89: =Z88 | V89: =U89*Plan!D9/100/12 | W89: =MIN(Plan!E9,U89+V89) | X89: =U89+V89-W89 | Y89: =MIN(X89,MAX(0,$B89-((E$5<W$5)*F89+(K$5<W$5)*L89+(Q$5<W$5)*R89+(AC$5<W$5)*AD89+(AI$5<W$5)*AJ89+(AO$5<W$5)*AP89+(AU$5<W$5)*AV89))) | Z89: =IF(X89-Y89<0.005,0,X89-Y89) | AA89: =AF88 | AB89: =AA89*Plan!D10/100/12 | AC89: =MIN(Plan!E10,AA89+AB89) | AD89: =AA89+AB89-AC89 | AE89: =MIN(AD89,MAX(0,$B89-((E$5<AC$5)*F89+(K$5<AC$5)*L89+(Q$5<AC$5)*R89+(W$5<AC$5)*X89+(AI$5<AC$5)*AJ89+(AO$5<AC$5)*AP89+(AU$5<AC$5)*AV89))) | AF89: =IF(AD89-AE89<0.005,0,AD89-AE89) | AG89: =AL88 | AH89: =AG89*Plan!D11/100/12 | AI89: =MIN(Plan!E11,AG89+AH89) | AJ89: =AG89+AH89-AI89 | AK89: =MIN(AJ89,MAX(0,$B89-((E$5<AI$5)*F89+(K$5<AI$5)*L89+(Q$5<AI$5)*R89+(W$5<AI$5)*X89+(AC$5<AI$5)*AD89+(AO$5<AI$5)*AP89+(AU$5<AI$5)*AV89))) | AL89: =IF(AJ89-AK89<0.005,0,AJ89-AK89) | AM89: =AR88 | AN89: =AM89*Plan!D12/100/12 | AO89: =MIN(Plan!E12,AM89+AN89) | AP89: =AM89+AN89-AO89 | AQ89: =MIN(AP89,MAX(0,$B89-((E$5<AO$5)*F89+(K$5<AO$5)*L89+(Q$5<AO$5)*R89+(W$5<AO$5)*X89+(AC$5<AO$5)*AD89+(AI$5<AO$5)*AJ89+(AU$5<AO$5)*AV89))) | AR89: =IF(AP89-AQ89<0.005,0,AP89-AQ89) | AS89: =AX88 | AT89: =AS89*Plan!D13/100/12 | AU89: =MIN(Plan!E13,AS89+AT89) | AV89: =AS89+AT89-AU89 | AW89: =MIN(AV89,MAX(0,$B89-((E$5<AU$5)*F89+(K$5<AU$5)*L89+(Q$5<AU$5)*R89+(W$5<AU$5)*X89+(AC$5<AU$5)*AD89+(AI$5<AU$5)*AJ89+(AO$5<AU$5)*AP89))) | AX89: =IF(AV89-AW89<0.005,0,AV89-AW89) | BC89: =H89+N89+T89+Z89+AF89+AL89+AR89+AX89
A90: 84 | B90: =MAX(0,$B$3-(E90+K90+Q90+W90+AC90+AI90+AO90+AU90)) | C90: =H89 | D90: =C90*Plan!D6/100/12 | E90: =MIN(Plan!E6,C90+D90) | F90: =C90+D90-E90 | G90: =MIN(F90,MAX(0,$B90-((K$5<E$5)*L90+(Q$5<E$5)*R90+(W$5<E$5)*X90+(AC$5<E$5)*AD90+(AI$5<E$5)*AJ90+(AO$5<E$5)*AP90+(AU$5<E$5)*AV90))) | H90: =IF(F90-G90<0.005,0,F90-G90) | I90: =N89 | J90: =I90*Plan!D7/100/12 | K90: =MIN(Plan!E7,I90+J90) | L90: =I90+J90-K90 | M90: =MIN(L90,MAX(0,$B90-((E$5<K$5)*F90+(Q$5<K$5)*R90+(W$5<K$5)*X90+(AC$5<K$5)*AD90+(AI$5<K$5)*AJ90+(AO$5<K$5)*AP90+(AU$5<K$5)*AV90))) | N90: =IF(L90-M90<0.005,0,L90-M90) | O90: =T89 | P90: =O90*Plan!D8/100/12 | Q90: =MIN(Plan!E8,O90+P90) | R90: =O90+P90-Q90 | S90: =MIN(R90,MAX(0,$B90-((E$5<Q$5)*F90+(K$5<Q$5)*L90+(W$5<Q$5)*X90+(AC$5<Q$5)*AD90+(AI$5<Q$5)*AJ90+(AO$5<Q$5)*AP90+(AU$5<Q$5)*AV90))) | T90: =IF(R90-S90<0.005,0,R90-S90) | U90: =Z89 | V90: =U90*Plan!D9/100/12 | W90: =MIN(Plan!E9,U90+V90) | X90: =U90+V90-W90 | Y90: =MIN(X90,MAX(0,$B90-((E$5<W$5)*F90+(K$5<W$5)*L90+(Q$5<W$5)*R90+(AC$5<W$5)*AD90+(AI$5<W$5)*AJ90+(AO$5<W$5)*AP90+(AU$5<W$5)*AV90))) | Z90: =IF(X90-Y90<0.005,0,X90-Y90) | AA90: =AF89 | AB90: =AA90*Plan!D10/100/12 | AC90: =MIN(Plan!E10,AA90+AB90) | AD90: =AA90+AB90-AC90 | AE90: =MIN(AD90,MAX(0,$B90-((E$5<AC$5)*F90+(K$5<AC$5)*L90+(Q$5<AC$5)*R90+(W$5<AC$5)*X90+(AI$5<AC$5)*AJ90+(AO$5<AC$5)*AP90+(AU$5<AC$5)*AV90))) | AF90: =IF(AD90-AE90<0.005,0,AD90-AE90) | AG90: =AL89 | AH90: =AG90*Plan!D11/100/12 | AI90: =MIN(Plan!E11,AG90+AH90) | AJ90: =AG90+AH90-AI90 | AK90: =MIN(AJ90,MAX(0,$B90-((E$5<AI$5)*F90+(K$5<AI$5)*L90+(Q$5<AI$5)*R90+(W$5<AI$5)*X90+(AC$5<AI$5)*AD90+(AO$5<AI$5)*AP90+(AU$5<AI$5)*AV90))) | AL90: =IF(AJ90-AK90<0.005,0,AJ90-AK90) | AM90: =AR89 | AN90: =AM90*Plan!D12/100/12 | AO90: =MIN(Plan!E12,AM90+AN90) | AP90: =AM90+AN90-AO90 | AQ90: =MIN(AP90,MAX(0,$B90-((E$5<AO$5)*F90+(K$5<AO$5)*L90+(Q$5<AO$5)*R90+(W$5<AO$5)*X90+(AC$5<AO$5)*AD90+(AI$5<AO$5)*AJ90+(AU$5<AO$5)*AV90))) | AR90: =IF(AP90-AQ90<0.005,0,AP90-AQ90) | AS90: =AX89 | AT90: =AS90*Plan!D13/100/12 | AU90: =MIN(Plan!E13,AS90+AT90) | AV90: =AS90+AT90-AU90 | AW90: =MIN(AV90,MAX(0,$B90-((E$5<AU$5)*F90+(K$5<AU$5)*L90+(Q$5<AU$5)*R90+(W$5<AU$5)*X90+(AC$5<AU$5)*AD90+(AI$5<AU$5)*AJ90+(AO$5<AU$5)*AP90))) | AX90: =IF(AV90-AW90<0.005,0,AV90-AW90) | BC90: =H90+N90+T90+Z90+AF90+AL90+AR90+AX90
