Workbook

Sheet Budget
A1: Hochzeits-Budget-Plan
A2: Gelbe Felder ausfüllen, alles andere rechnet sich selbst.
A4: Gäste | B4: 80 | N4: Kosten total | O4: =SUM(D12:D51)
A5: Budget total | B5: 35000 | N5: pro Gast | O5: =IF($B$4>0,O4/$B$4,0)
A6: Hochzeitsdatum | B6: =DATE(YEAR(TODAY())+1,MONTH(TODAY()),15) | N6: Übrig (+) / über Budget (−) | O6: =$B$5-O4
A7: Heute schon gespart | B7: 6000 | N7: Jeder zusätzliche Gast kostet | O7: =SUMIF(C12:C51,"ja",B12:B51)
A8: Ihr spart pro Monat | B8: 1500 | N8: Höchstens so viele Gäste im Budget | O8: =IF(SUMIF(C12:C51,"ja",B12:B51)>0,MAX(0,INT(($B$5-(O4-SUMIF(C12:C51,"ja",B12:B51)*$B$4))/SUMIF(C12:C51,"ja",B12:B51))),"–")
N9: Noch zu bezahlen | O9: =SUM(J12:J51)
N10: Monate bis zur Hochzeit | O10: =MAX(0,(YEAR($B$6)-YEAR(TODAY()))*12+MONTH($B$6)-MONTH(TODAY()))
A11: Posten | B11: Betrag | C11: pro Gast | D11: Kosten | E11: Anzahlung % | F11: Monate vorher | G11: Anzahlung fällig | H11: Anzahlung | I11: schon bezahlt | J11: offen | K11: Rest am Hochzeitstag | L11: Anzahlung offen | N11: Nötige Sparrate pro Monat | O11: =MAX('Zahlungsplan'!G5:G40)
A12: Location / Saalmiete | B12: 3000 | C12: nein | D12: =IF(C12="ja",N(B12)*$B$4,N(B12)) | E12: 0.5 | F12: 12 | G12: =IF(H12-MIN(D12,N(I12))>0.004,MAX(TODAY(),DATE(YEAR($B$6),MONTH($B$6)-N(F12),1)),"") | H12: =D12*MIN(1,MAX(0,N(E12))) | I12: 0 | J12: =D12-MIN(D12,N(I12)) | K12: =J12-L12 | L12: =MAX(0,H12-MIN(D12,N(I12))) | M12: =IF(G12="","",YEAR(G12)*12+MONTH(G12)) | N12: Mit eurer Sparrate: Lücke (−) / Reserve (+) | O12: =MIN('Zahlungsplan'!F5:F40)
A13: Essen | B13: 120 | C13: ja | D13: =IF(C13="ja",N(B13)*$B$4,N(B13)) | E13: 0.3 | F13: 3 | G13: =IF(H13-MIN(D13,N(I13))>0.004,MAX(TODAY(),DATE(YEAR($B$6),MONTH($B$6)-N(F13),1)),"") | H13: =D13*MIN(1,MAX(0,N(E13))) | I13: 0 | J13: =D13-MIN(D13,N(I13)) | K13: =J13-L13 | L13: =MAX(0,H13-MIN(D13,N(I13))) | M13: =IF(G13="","",YEAR(G13)*12+MONTH(G13))
A14: Getränke | B14: 45 | C14: ja | D14: =IF(C14="ja",N(B14)*$B$4,N(B14)) | E14: 0 | F14: 0 | G14: =IF(H14-MIN(D14,N(I14))>0.004,MAX(TODAY(),DATE(YEAR($B$6),MONTH($B$6)-N(F14),1)),"") | H14: =D14*MIN(1,MAX(0,N(E14))) | I14: 0 | J14: =D14-MIN(D14,N(I14)) | K14: =J14-L14 | L14: =MAX(0,H14-MIN(D14,N(I14))) | M14: =IF(G14="","",YEAR(G14)*12+MONTH(G14)) | N14: =IF('Zahlungsplan'!B5>$B$7,"Sofort fällig ist mehr, als ihr gespart habt!","")
A15: Apéro | B15: 25 | C15: ja | D15: =IF(C15="ja",N(B15)*$B$4,N(B15)) | E15: 0 | F15: 0 | G15: =IF(H15-MIN(D15,N(I15))>0.004,MAX(TODAY(),DATE(YEAR($B$6),MONTH($B$6)-N(F15),1)),"") | H15: =D15*MIN(1,MAX(0,N(E15))) | I15: 0 | J15: =D15-MIN(D15,N(I15)) | K15: =J15-L15 | L15: =MAX(0,H15-MIN(D15,N(I15))) | M15: =IF(G15="","",YEAR(G15)*12+MONTH(G15))
A16: Hochzeitstorte | B16: 10 | C16: ja | D16: =IF(C16="ja",N(B16)*$B$4,N(B16)) | E16: 0.3 | F16: 2 | G16: =IF(H16-MIN(D16,N(I16))>0.004,MAX(TODAY(),DATE(YEAR($B$6),MONTH($B$6)-N(F16),1)),"") | H16: =D16*MIN(1,MAX(0,N(E16))) | I16: 0 | J16: =D16-MIN(D16,N(I16)) | K16: =J16-L16 | L16: =MAX(0,H16-MIN(D16,N(I16))) | M16: =IF(G16="","",YEAR(G16)*12+MONTH(G16))
A17: Fotografie | B17: 3500 | C17: nein | D17: =IF(C17="ja",N(B17)*$B$4,N(B17)) | E17: 0.3 | F17: 9 | G17: =IF(H17-MIN(D17,N(I17))>0.004,MAX(TODAY(),DATE(YEAR($B$6),MONTH($B$6)-N(F17),1)),"") | H17: =D17*MIN(1,MAX(0,N(E17))) | I17: 0 | J17: =D17-MIN(D17,N(I17)) | K17: =J17-L17 | L17: =MAX(0,H17-MIN(D17,N(I17))) | M17: =IF(G17="","",YEAR(G17)*12+MONTH(G17))
A18: Musik / DJ | B18: 2000 | C18: nein | D18: =IF(C18="ja",N(B18)*$B$4,N(B18)) | E18: 0.3 | F18: 6 | G18: =IF(H18-MIN(D18,N(I18))>0.004,MAX(TODAY(),DATE(YEAR($B$6),MONTH($B$6)-N(F18),1)),"") | H18: =D18*MIN(1,MAX(0,N(E18))) | I18: 0 | J18: =D18-MIN(D18,N(I18)) | K18: =J18-L18 | L18: =MAX(0,H18-MIN(D18,N(I18))) | M18: =IF(G18="","",YEAR(G18)*12+MONTH(G18))
A19: Kleid und Anzug | B19: 3200 | C19: nein | D19: =IF(C19="ja",N(B19)*$B$4,N(B19)) | E19: 0.5 | F19: 8 | G19: =IF(H19-MIN(D19,N(I19))>0.004,MAX(TODAY(),DATE(YEAR($B$6),MONTH($B$6)-N(F19),1)),"") | H19: =D19*MIN(1,MAX(0,N(E19))) | I19: 0 | J19: =D19-MIN(D19,N(I19)) | K19: =J19-L19 | L19: =MAX(0,H19-MIN(D19,N(I19))) | M19: =IF(G19="","",YEAR(G19)*12+MONTH(G19))
A20: Ringe | B20: 2500 | C20: nein | D20: =IF(C20="ja",N(B20)*$B$4,N(B20)) | E20: 1 | F20: 3 | G20: =IF(H20-MIN(D20,N(I20))>0.004,MAX(TODAY(),DATE(YEAR($B$6),MONTH($B$6)-N(F20),1)),"") | H20: =D20*MIN(1,MAX(0,N(E20))) | I20: 0 | J20: =D20-MIN(D20,N(I20)) | K20: =J20-L20 | L20: =MAX(0,H20-MIN(D20,N(I20))) | M20: =IF(G20="","",YEAR(G20)*12+MONTH(G20))
A21: Blumen und Deko | B21: 1800 | C21: nein | D21: =IF(C21="ja",N(B21)*$B$4,N(B21)) | E21: 0.3 | F21: 4 | G21: =IF(H21-MIN(D21,N(I21))>0.004,MAX(TODAY(),DATE(YEAR($B$6),MONTH($B$6)-N(F21),1)),"") | H21: =D21*MIN(1,MAX(0,N(E21))) | I21: 0 | J21: =D21-MIN(D21,N(I21)) | K21: =J21-L21 | L21: =MAX(0,H21-MIN(D21,N(I21))) | M21: =IF(G21="","",YEAR(G21)*12+MONTH(G21))
A22: Einladungen und Papeterie | B22: 8 | C22: ja | D22: =IF(C22="ja",N(B22)*$B$4,N(B22)) | E22: 1 | F22: 5 | G22: =IF(H22-MIN(D22,N(I22))>0.004,MAX(TODAY(),DATE(YEAR($B$6),MONTH($B$6)-N(F22),1)),"") | H22: =D22*MIN(1,MAX(0,N(E22))) | I22: 0 | J22: =D22-MIN(D22,N(I22)) | K22: =J22-L22 | L22: =MAX(0,H22-MIN(D22,N(I22))) | M22: =IF(G22="","",YEAR(G22)*12+MONTH(G22))
A23: Zivilstandsamt | B23: 350 | C23: nein | D23: =IF(C23="ja",N(B23)*$B$4,N(B23)) | E23: 1 | F23: 2 | G23: =IF(H23-MIN(D23,N(I23))>0.004,MAX(TODAY(),DATE(YEAR($B$6),MONTH($B$6)-N(F23),1)),"") | H23: =D23*MIN(1,MAX(0,N(E23))) | I23: 0 | J23: =D23-MIN(D23,N(I23)) | K23: =J23-L23 | L23: =MAX(0,H23-MIN(D23,N(I23))) | M23: =IF(G23="","",YEAR(G23)*12+MONTH(G23))
A24: Reserve für Unvorhergesehenes | B24: 2000 | C24: nein | D24: =IF(C24="ja",N(B24)*$B$4,N(B24)) | E24: 0 | F24: 0 | G24: =IF(H24-MIN(D24,N(I24))>0.004,MAX(TODAY(),DATE(YEAR($B$6),MONTH($B$6)-N(F24),1)),"") | H24: =D24*MIN(1,MAX(0,N(E24))) | I24: 0 | J24: =D24-MIN(D24,N(I24)) | K24: =J24-L24 | L24: =MAX(0,H24-MIN(D24,N(I24))) | M24: =IF(G24="","",YEAR(G24)*12+MONTH(G24))
D25: =IF(C25="ja",N(B25)*$B$4,N(B25)) | G25: =IF(H25-MIN(D25,N(I25))>0.004,MAX(TODAY(),DATE(YEAR($B$6),MONTH($B$6)-N(F25),1)),"") | H25: =D25*MIN(1,MAX(0,N(E25))) | J25: =D25-MIN(D25,N(I25)) | K25: =J25-L25 | L25: =MAX(0,H25-MIN(D25,N(I25))) | M25: =IF(G25="","",YEAR(G25)*12+MONTH(G25))
D26: =IF(C26="ja",N(B26)*$B$4,N(B26)) | G26: =IF(H26-MIN(D26,N(I26))>0.004,MAX(TODAY(),DATE(YEAR($B$6),MONTH($B$6)-N(F26),1)),"") | H26: =D26*MIN(1,MAX(0,N(E26))) | J26: =D26-MIN(D26,N(I26)) | K26: =J26-L26 | L26: =MAX(0,H26-MIN(D26,N(I26))) | M26: =IF(G26="","",YEAR(G26)*12+MONTH(G26))
D27: =IF(C27="ja",N(B27)*$B$4,N(B27)) | G27: =IF(H27-MIN(D27,N(I27))>0.004,MAX(TODAY(),DATE(YEAR($B$6),MONTH($B$6)-N(F27),1)),"") | H27: =D27*MIN(1,MAX(0,N(E27))) | J27: =D27-MIN(D27,N(I27)) | K27: =J27-L27 | L27: =MAX(0,H27-MIN(D27,N(I27))) | M27: =IF(G27="","",YEAR(G27)*12+MONTH(G27))
D28: =IF(C28="ja",N(B28)*$B$4,N(B28)) | G28: =IF(H28-MIN(D28,N(I28))>0.004,MAX(TODAY(),DATE(YEAR($B$6),MONTH($B$6)-N(F28),1)),"") | H28: =D28*MIN(1,MAX(0,N(E28))) | J28: =D28-MIN(D28,N(I28)) | K28: =J28-L28 | L28: =MAX(0,H28-MIN(D28,N(I28))) | M28: =IF(G28="","",YEAR(G28)*12+MONTH(G28))
D29: =IF(C29="ja",N(B29)*$B$4,N(B29)) | G29: =IF(H29-MIN(D29,N(I29))>0.004,MAX(TODAY(),DATE(YEAR($B$6),MONTH($B$6)-N(F29),1)),"") | H29: =D29*MIN(1,MAX(0,N(E29))) | J29: =D29-MIN(D29,N(I29)) | K29: =J29-L29 | L29: =MAX(0,H29-MIN(D29,N(I29))) | M29: =IF(G29="","",YEAR(G29)*12+MONTH(G29))
D30: =IF(C30="ja",N(B30)*$B$4,N(B30)) | G30: =IF(H30-MIN(D30,N(I30))>0.004,MAX(TODAY(),DATE(YEAR($B$6),MONTH($B$6)-N(F30),1)),"") | H30: =D30*MIN(1,MAX(0,N(E30))) | J30: =D30-MIN(D30,N(I30)) | K30: =J30-L30 | L30: =MAX(0,H30-MIN(D30,N(I30))) | M30: =IF(G30="","",YEAR(G30)*12+MONTH(G30))
D31: =IF(C31="ja",N(B31)*$B$4,N(B31)) | G31: =IF(H31-MIN(D31,N(I31))>0.004,MAX(TODAY(),DATE(YEAR($B$6),MONTH($B$6)-N(F31),1)),"") | H31: =D31*MIN(1,MAX(0,N(E31))) | J31: =D31-MIN(D31,N(I31)) | K31: =J31-L31 | L31: =MAX(0,H31-MIN(D31,N(I31))) | M31: =IF(G31="","",YEAR(G31)*12+MONTH(G31))
D32: =IF(C32="ja",N(B32)*$B$4,N(B32)) | G32: =IF(H32-MIN(D32,N(I32))>0.004,MAX(TODAY(),DATE(YEAR($B$6),MONTH($B$6)-N(F32),1)),"") | H32: =D32*MIN(1,MAX(0,N(E32))) | J32: =D32-MIN(D32,N(I32)) | K32: =J32-L32 | L32: =MAX(0,H32-MIN(D32,N(I32))) | M32: =IF(G32="","",YEAR(G32)*12+MONTH(G32))
D33: =IF(C33="ja",N(B33)*$B$4,N(B33)) | G33: =IF(H33-MIN(D33,N(I33))>0.004,MAX(TODAY(),DATE(YEAR($B$6),MONTH($B$6)-N(F33),1)),"") | H33: =D33*MIN(1,MAX(0,N(E33))) | J33: =D33-MIN(D33,N(I33)) | K33: =J33-L33 | L33: =MAX(0,H33-MIN(D33,N(I33))) | M33: =IF(G33="","",YEAR(G33)*12+MONTH(G33))
D34: =IF(C34="ja",N(B34)*$B$4,N(B34)) | G34: =IF(H34-MIN(D34,N(I34))>0.004,MAX(TODAY(),DATE(YEAR($B$6),MONTH($B$6)-N(F34),1)),"") | H34: =D34*MIN(1,MAX(0,N(E34))) | J34: =D34-MIN(D34,N(I34)) | K34: =J34-L34 | L34: =MAX(0,H34-MIN(D34,N(I34))) | M34: =IF(G34="","",YEAR(G34)*12+MONTH(G34))
D35: =IF(C35="ja",N(B35)*$B$4,N(B35)) | G35: =IF(H35-MIN(D35,N(I35))>0.004,MAX(TODAY(),DATE(YEAR($B$6),MONTH($B$6)-N(F35),1)),"") | H35: =D35*MIN(1,MAX(0,N(E35))) | J35: =D35-MIN(D35,N(I35)) | K35: =J35-L35 | L35: =MAX(0,H35-MIN(D35,N(I35))) | M35: =IF(G35="","",YEAR(G35)*12+MONTH(G35))
D36: =IF(C36="ja",N(B36)*$B$4,N(B36)) | G36: =IF(H36-MIN(D36,N(I36))>0.004,MAX(TODAY(),DATE(YEAR($B$6),MONTH($B$6)-N(F36),1)),"") | H36: =D36*MIN(1,MAX(0,N(E36))) | J36: =D36-MIN(D36,N(I36)) | K36: =J36-L36 | L36: =MAX(0,H36-MIN(D36,N(I36))) | M36: =IF(G36="","",YEAR(G36)*12+MONTH(G36))
... D51: =IF(C51="ja",N(B51)*$B$4,N(B51)) | G51: =IF(H51-MIN(D51,N(I51))>0.004,MAX(TODAY(),DATE(YEAR($B$6),MONTH($B$6)-N(F51),1)),"") | H51: =D51*MIN(1,MAX(0,N(E51))) | J51: =D51-MIN(D51,N(I51)) | K51: =J51-L51 | L51: =MAX(0,H51-MIN(D51,N(I51))) | M51: =IF(G51="","",YEAR(G51)*12+MONTH(G51))

Sheet Zahlungsplan
A1: Zahlungsplan
A2: Rot = mit eurer Sparrate fehlt bis zu diesem Monat Geld. Anzahlungen am 1. des Monats, Rest im Hochzeitsmonat.
A4: Monat | B4: fällig in diesem Monat | C4: fällig bis dann | D4: Monate ab heute | E4: angespart bis dann | F4: Lücke (−) / Reserve (+) | G4: nötige Rate bis hier
A5: =DATE(YEAR(TODAY()),MONTH(TODAY())+0,1) | B5: =IF(A5<=DATE(YEAR('Budget'!$B$6),MONTH('Budget'!$B$6),1),SUMIF('Budget'!$M$12:$M$51,YEAR(A5)*12+MONTH(A5),'Budget'!$L$12:$L$51)+IF(AND(YEAR(A5)=YEAR('Budget'!$B$6),MONTH(A5)=MONTH('Budget'!$B$6)),SUM('Budget'!$K$12:$K$51),0),"") | C5: =IF(A5<=DATE(YEAR('Budget'!$B$6),MONTH('Budget'!$B$6),1),SUM($B$5:B5),"") | D5: =IF(A5<=DATE(YEAR('Budget'!$B$6),MONTH('Budget'!$B$6),1),0,"") | E5: =IF(A5<=DATE(YEAR('Budget'!$B$6),MONTH('Budget'!$B$6),1),'Budget'!$B$7+'Budget'!$B$8*0,"") | F5: =IF(A5<=DATE(YEAR('Budget'!$B$6),MONTH('Budget'!$B$6),1),E5-C5,"") | G5: =IF(A5<=DATE(YEAR('Budget'!$B$6),MONTH('Budget'!$B$6),1),IF(0>0,MAX(0,(C5-'Budget'!$B$7)/0),0),"")
A6: =DATE(YEAR(TODAY()),MONTH(TODAY())+1,1) | B6: =IF(A6<=DATE(YEAR('Budget'!$B$6),MONTH('Budget'!$B$6),1),SUMIF('Budget'!$M$12:$M$51,YEAR(A6)*12+MONTH(A6),'Budget'!$L$12:$L$51)+IF(AND(YEAR(A6)=YEAR('Budget'!$B$6),MONTH(A6)=MONTH('Budget'!$B$6)),SUM('Budget'!$K$12:$K$51),0),"") | C6: =IF(A6<=DATE(YEAR('Budget'!$B$6),MONTH('Budget'!$B$6),1),SUM($B$5:B6),"") | D6: =IF(A6<=DATE(YEAR('Budget'!$B$6),MONTH('Budget'!$B$6),1),1,"") | E6: =IF(A6<=DATE(YEAR('Budget'!$B$6),MONTH('Budget'!$B$6),1),'Budget'!$B$7+'Budget'!$B$8*1,"") | F6: =IF(A6<=DATE(YEAR('Budget'!$B$6),MONTH('Budget'!$B$6),1),E6-C6,"") | G6: =IF(A6<=DATE(YEAR('Budget'!$B$6),MONTH('Budget'!$B$6),1),IF(1>0,MAX(0,(C6-'Budget'!$B$7)/1),0),"")
A7: =DATE(YEAR(TODAY()),MONTH(TODAY())+2,1) | B7: =IF(A7<=DATE(YEAR('Budget'!$B$6),MONTH('Budget'!$B$6),1),SUMIF('Budget'!$M$12:$M$51,YEAR(A7)*12+MONTH(A7),'Budget'!$L$12:$L$51)+IF(AND(YEAR(A7)=YEAR('Budget'!$B$6),MONTH(A7)=MONTH('Budget'!$B$6)),SUM('Budget'!$K$12:$K$51),0),"") | C7: =IF(A7<=DATE(YEAR('Budget'!$B$6),MONTH('Budget'!$B$6),1),SUM($B$5:B7),"") | D7: =IF(A7<=DATE(YEAR('Budget'!$B$6),MONTH('Budget'!$B$6),1),2,"") | E7: =IF(A7<=DATE(YEAR('Budget'!$B$6),MONTH('Budget'!$B$6),1),'Budget'!$B$7+'Budget'!$B$8*2,"") | F7: =IF(A7<=DATE(YEAR('Budget'!$B$6),MONTH('Budget'!$B$6),1),E7-C7,"") | G7: =IF(A7<=DATE(YEAR('Budget'!$B$6),MONTH('Budget'!$B$6),1),IF(2>0,MAX(0,(C7-'Budget'!$B$7)/2),0),"")
A8: =DATE(YEAR(TODAY()),MONTH(TODAY())+3,1) | B8: =IF(A8<=DATE(YEAR('Budget'!$B$6),MONTH('Budget'!$B$6),1),SUMIF('Budget'!$M$12:$M$51,YEAR(A8)*12+MONTH(A8),'Budget'!$L$12:$L$51)+IF(AND(YEAR(A8)=YEAR('Budget'!$B$6),MONTH(A8)=MONTH('Budget'!$B$6)),SUM('Budget'!$K$12:$K$51),0),"") | C8: =IF(A8<=DATE(YEAR('Budget'!$B$6),MONTH('Budget'!$B$6),1),SUM($B$5:B8),"") | D8: =IF(A8<=DATE(YEAR('Budget'!$B$6),MONTH('Budget'!$B$6),1),3,"") | E8: =IF(A8<=DATE(YEAR('Budget'!$B$6),MONTH('Budget'!$B$6),1),'Budget'!$B$7+'Budget'!$B$8*3,"") | F8: =IF(A8<=DATE(YEAR('Budget'!$B$6),MONTH('Budget'!$B$6),1),E8-C8,"") | G8: =IF(A8<=DATE(YEAR('Budget'!$B$6),MONTH('Budget'!$B$6),1),IF(3>0,MAX(0,(C8-'Budget'!$B$7)/3),0),"")
A9: =DATE(YEAR(TODAY()),MONTH(TODAY())+4,1) | B9: =IF(A9<=DATE(YEAR('Budget'!$B$6),MONTH('Budget'!$B$6),1),SUMIF('Budget'!$M$12:$M$51,YEAR(A9)*12+MONTH(A9),'Budget'!$L$12:$L$51)+IF(AND(YEAR(A9)=YEAR('Budget'!$B$6),MONTH(A9)=MONTH('Budget'!$B$6)),SUM('Budget'!$K$12:$K$51),0),"") | C9: =IF(A9<=DATE(YEAR('Budget'!$B$6),MONTH('Budget'!$B$6),1),SUM($B$5:B9),"") | D9: =IF(A9<=DATE(YEAR('Budget'!$B$6),MONTH('Budget'!$B$6),1),4,"") | E9: =IF(A9<=DATE(YEAR('Budget'!$B$6),MONTH('Budget'!$B$6),1),'Budget'!$B$7+'Budget'!$B$8*4,"") | F9: =IF(A9<=DATE(YEAR('Budget'!$B$6),MONTH('Budget'!$B$6),1),E9-C9,"") | G9: =IF(A9<=DATE(YEAR('Budget'!$B$6),MONTH('Budget'!$B$6),1),IF(4>0,MAX(0,(C9-'Budget'!$B$7)/4),0),"")
A10: =DATE(YEAR(TODAY()),MONTH(TODAY())+5,1) | B10: =IF(A10<=DATE(YEAR('Budget'!$B$6),MONTH('Budget'!$B$6),1),SUMIF('Budget'!$M$12:$M$51,YEAR(A10)*12+MONTH(A10),'Budget'!$L$12:$L$51)+IF(AND(YEAR(A10)=YEAR('Budget'!$B$6),MONTH(A10)=MONTH('Budget'!$B$6)),SUM('Budget'!$K$12:$K$51),0),"") | C10: =IF(A10<=DATE(YEAR('Budget'!$B$6),MONTH('Budget'!$B$6),1),SUM($B$5:B10),"") | D10: =IF(A10<=DATE(YEAR('Budget'!$B$6),MONTH('Budget'!$B$6),1),5,"") | E10: =IF(A10<=DATE(YEAR('Budget'!$B$6),MONTH('Budget'!$B$6),1),'Budget'!$B$7+'Budget'!$B$8*5,"") | F10: =IF(A10<=DATE(YEAR('Budget'!$B$6),MONTH('Budget'!$B$6),1),E10-C10,"") | G10: =IF(A10<=DATE(YEAR('Budget'!$B$6),MONTH('Budget'!$B$6),1),IF(5>0,MAX(0,(C10-'Budget'!$B$7)/5),0),"")
A11: =DATE(YEAR(TODAY()),MONTH(TODAY())+6,1) | B11: =IF(A11<=DATE(YEAR('Budget'!$B$6),MONTH('Budget'!$B$6),1),SUMIF('Budget'!$M$12:$M$51,YEAR(A11)*12+MONTH(A11),'Budget'!$L$12:$L$51)+IF(AND(YEAR(A11)=YEAR('Budget'!$B$6),MONTH(A11)=MONTH('Budget'!$B$6)),SUM('Budget'!$K$12:$K$51),0),"") | C11: =IF(A11<=DATE(YEAR('Budget'!$B$6),MONTH('Budget'!$B$6),1),SUM($B$5:B11),"") | D11: =IF(A11<=DATE(YEAR('Budget'!$B$6),MONTH('Budget'!$B$6),1),6,"") | E11: =IF(A11<=DATE(YEAR('Budget'!$B$6),MONTH('Budget'!$B$6),1),'Budget'!$B$7+'Budget'!$B$8*6,"") | F11: =IF(A11<=DATE(YEAR('Budget'!$B$6),MONTH('Budget'!$B$6),1),E11-C11,"") | G11: =IF(A11<=DATE(YEAR('Budget'!$B$6),MONTH('Budget'!$B$6),1),IF(6>0,MAX(0,(C11-'Budget'!$B$7)/6),0),"")
A12: =DATE(YEAR(TODAY()),MONTH(TODAY())+7,1) | B12: =IF(A12<=DATE(YEAR('Budget'!$B$6),MONTH('Budget'!$B$6),1),SUMIF('Budget'!$M$12:$M$51,YEAR(A12)*12+MONTH(A12),'Budget'!$L$12:$L$51)+IF(AND(YEAR(A12)=YEAR('Budget'!$B$6),MONTH(A12)=MONTH('Budget'!$B$6)),SUM('Budget'!$K$12:$K$51),0),"") | C12: =IF(A12<=DATE(YEAR('Budget'!$B$6),MONTH('Budget'!$B$6),1),SUM($B$5:B12),"") | D12: =IF(A12<=DATE(YEAR('Budget'!$B$6),MONTH('Budget'!$B$6),1),7,"") | E12: =IF(A12<=DATE(YEAR('Budget'!$B$6),MONTH('Budget'!$B$6),1),'Budget'!$B$7+'Budget'!$B$8*7,"") | F12: =IF(A12<=DATE(YEAR('Budget'!$B$6),MONTH('Budget'!$B$6),1),E12-C12,"") | G12: =IF(A12<=DATE(YEAR('Budget'!$B$6),MONTH('Budget'!$B$6),1),IF(7>0,MAX(0,(C12-'Budget'!$B$7)/7),0),"")
A13: =DATE(YEAR(TODAY()),MONTH(TODAY())+8,1) | B13: =IF(A13<=DATE(YEAR('Budget'!$B$6),MONTH('Budget'!$B$6),1),SUMIF('Budget'!$M$12:$M$51,YEAR(A13)*12+MONTH(A13),'Budget'!$L$12:$L$51)+IF(AND(YEAR(A13)=YEAR('Budget'!$B$6),MONTH(A13)=MONTH('Budget'!$B$6)),SUM('Budget'!$K$12:$K$51),0),"") | C13: =IF(A13<=DATE(YEAR('Budget'!$B$6),MONTH('Budget'!$B$6),1),SUM($B$5:B13),"") | D13: =IF(A13<=DATE(YEAR('Budget'!$B$6),MONTH('Budget'!$B$6),1),8,"") | E13: =IF(A13<=DATE(YEAR('Budget'!$B$6),MONTH('Budget'!$B$6),1),'Budget'!$B$7+'Budget'!$B$8*8,"") | F13: =IF(A13<=DATE(YEAR('Budget'!$B$6),MONTH('Budget'!$B$6),1),E13-C13,"") | G13: =IF(A13<=DATE(YEAR('Budget'!$B$6),MONTH('Budget'!$B$6),1),IF(8>0,MAX(0,(C13-'Budget'!$B$7)/8),0),"")
A14: =DATE(YEAR(TODAY()),MONTH(TODAY())+9,1) | B14: =IF(A14<=DATE(YEAR('Budget'!$B$6),MONTH('Budget'!$B$6),1),SUMIF('Budget'!$M$12:$M$51,YEAR(A14)*12+MONTH(A14),'Budget'!$L$12:$L$51)+IF(AND(YEAR(A14)=YEAR('Budget'!$B$6),MONTH(A14)=MONTH('Budget'!$B$6)),SUM('Budget'!$K$12:$K$51),0),"") | C14: =IF(A14<=DATE(YEAR('Budget'!$B$6),MONTH('Budget'!$B$6),1),SUM($B$5:B14),"") | D14: =IF(A14<=DATE(YEAR('Budget'!$B$6),MONTH('Budget'!$B$6),1),9,"") | E14: =IF(A14<=DATE(YEAR('Budget'!$B$6),MONTH('Budget'!$B$6),1),'Budget'!$B$7+'Budget'!$B$8*9,"") | F14: =IF(A14<=DATE(YEAR('Budget'!$B$6),MONTH('Budget'!$B$6),1),E14-C14,"") | G14: =IF(A14<=DATE(YEAR('Budget'!$B$6),MONTH('Budget'!$B$6),1),IF(9>0,MAX(0,(C14-'Budget'!$B$7)/9),0),"")
A15: =DATE(YEAR(TODAY()),MONTH(TODAY())+10,1) | B15: =IF(A15<=DATE(YEAR('Budget'!$B$6),MONTH('Budget'!$B$6),1),SUMIF('Budget'!$M$12:$M$51,YEAR(A15)*12+MONTH(A15),'Budget'!$L$12:$L$51)+IF(AND(YEAR(A15)=YEAR('Budget'!$B$6),MONTH(A15)=MONTH('Budget'!$B$6)),SUM('Budget'!$K$12:$K$51),0),"") | C15: =IF(A15<=DATE(YEAR('Budget'!$B$6),MONTH('Budget'!$B$6),1),SUM($B$5:B15),"") | D15: =IF(A15<=DATE(YEAR('Budget'!$B$6),MONTH('Budget'!$B$6),1),10,"") | E15: =IF(A15<=DATE(YEAR('Budget'!$B$6),MONTH('Budget'!$B$6),1),'Budget'!$B$7+'Budget'!$B$8*10,"") | F15: =IF(A15<=DATE(YEAR('Budget'!$B$6),MONTH('Budget'!$B$6),1),E15-C15,"") | G15: =IF(A15<=DATE(YEAR('Budget'!$B$6),MONTH('Budget'!$B$6),1),IF(10>0,MAX(0,(C15-'Budget'!$B$7)/10),0),"")
A16: =DATE(YEAR(TODAY()),MONTH(TODAY())+11,1) | B16: =IF(A16<=DATE(YEAR('Budget'!$B$6),MONTH('Budget'!$B$6),1),SUMIF('Budget'!$M$12:$M$51,YEAR(A16)*12+MONTH(A16),'Budget'!$L$12:$L$51)+IF(AND(YEAR(A16)=YEAR('Budget'!$B$6),MONTH(A16)=MONTH('Budget'!$B$6)),SUM('Budget'!$K$12:$K$51),0),"") | C16: =IF(A16<=DATE(YEAR('Budget'!$B$6),MONTH('Budget'!$B$6),1),SUM($B$5:B16),"") | D16: =IF(A16<=DATE(YEAR('Budget'!$B$6),MONTH('Budget'!$B$6),1),11,"") | E16: =IF(A16<=DATE(YEAR('Budget'!$B$6),MONTH('Budget'!$B$6),1),'Budget'!$B$7+'Budget'!$B$8*11,"") | F16: =IF(A16<=DATE(YEAR('Budget'!$B$6),MONTH('Budget'!$B$6),1),E16-C16,"") | G16: =IF(A16<=DATE(YEAR('Budget'!$B$6),MONTH('Budget'!$B$6),1),IF(11>0,MAX(0,(C16-'Budget'!$B$7)/11),0),"")
A17: =DATE(YEAR(TODAY()),MONTH(TODAY())+12,1) | B17: =IF(A17<=DATE(YEAR('Budget'!$B$6),MONTH('Budget'!$B$6),1),SUMIF('Budget'!$M$12:$M$51,YEAR(A17)*12+MONTH(A17),'Budget'!$L$12:$L$51)+IF(AND(YEAR(A17)=YEAR('Budget'!$B$6),MONTH(A17)=MONTH('Budget'!$B$6)),SUM('Budget'!$K$12:$K$51),0),"") | C17: =IF(A17<=DATE(YEAR('Budget'!$B$6),MONTH('Budget'!$B$6),1),SUM($B$5:B17),"") | D17: =IF(A17<=DATE(YEAR('Budget'!$B$6),MONTH('Budget'!$B$6),1),12,"") | E17: =IF(A17<=DATE(YEAR('Budget'!$B$6),MONTH('Budget'!$B$6),1),'Budget'!$B$7+'Budget'!$B$8*12,"") | F17: =IF(A17<=DATE(YEAR('Budget'!$B$6),MONTH('Budget'!$B$6),1),E17-C17,"") | G17: =IF(A17<=DATE(YEAR('Budget'!$B$6),MONTH('Budget'!$B$6),1),IF(12>0,MAX(0,(C17-'Budget'!$B$7)/12),0),"")
A18: =DATE(YEAR(TODAY()),MONTH(TODAY())+13,1) | B18: =IF(A18<=DATE(YEAR('Budget'!$B$6),MONTH('Budget'!$B$6),1),SUMIF('Budget'!$M$12:$M$51,YEAR(A18)*12+MONTH(A18),'Budget'!$L$12:$L$51)+IF(AND(YEAR(A18)=YEAR('Budget'!$B$6),MONTH(A18)=MONTH('Budget'!$B$6)),SUM('Budget'!$K$12:$K$51),0),"") | C18: =IF(A18<=DATE(YEAR('Budget'!$B$6),MONTH('Budget'!$B$6),1),SUM($B$5:B18),"") | D18: =IF(A18<=DATE(YEAR('Budget'!$B$6),MONTH('Budget'!$B$6),1),13,"") | E18: =IF(A18<=DATE(YEAR('Budget'!$B$6),MONTH('Budget'!$B$6),1),'Budget'!$B$7+'Budget'!$B$8*13,"") | F18: =IF(A18<=DATE(YEAR('Budget'!$B$6),MONTH('Budget'!$B$6),1),E18-C18,"") | G18: =IF(A18<=DATE(YEAR('Budget'!$B$6),MONTH('Budget'!$B$6),1),IF(13>0,MAX(0,(C18-'Budget'!$B$7)/13),0),"")
A19: =DATE(YEAR(TODAY()),MONTH(TODAY())+14,1) | B19: =IF(A19<=DATE(YEAR('Budget'!$B$6),MONTH('Budget'!$B$6),1),SUMIF('Budget'!$M$12:$M$51,YEAR(A19)*12+MONTH(A19),'Budget'!$L$12:$L$51)+IF(AND(YEAR(A19)=YEAR('Budget'!$B$6),MONTH(A19)=MONTH('Budget'!$B$6)),SUM('Budget'!$K$12:$K$51),0),"") | C19: =IF(A19<=DATE(YEAR('Budget'!$B$6),MONTH('Budget'!$B$6),1),SUM($B$5:B19),"") | D19: =IF(A19<=DATE(YEAR('Budget'!$B$6),MONTH('Budget'!$B$6),1),14,"") | E19: =IF(A19<=DATE(YEAR('Budget'!$B$6),MONTH('Budget'!$B$6),1),'Budget'!$B$7+'Budget'!$B$8*14,"") | F19: =IF(A19<=DATE(YEAR('Budget'!$B$6),MONTH('Budget'!$B$6),1),E19-C19,"") | G19: =IF(A19<=DATE(YEAR('Budget'!$B$6),MONTH('Budget'!$B$6),1),IF(14>0,MAX(0,(C19-'Budget'!$B$7)/14),0),"")
A20: =DATE(YEAR(TODAY()),MONTH(TODAY())+15,1) | B20: =IF(A20<=DATE(YEAR('Budget'!$B$6),MONTH('Budget'!$B$6),1),SUMIF('Budget'!$M$12:$M$51,YEAR(A20)*12+MONTH(A20),'Budget'!$L$12:$L$51)+IF(AND(YEAR(A20)=YEAR('Budget'!$B$6),MONTH(A20)=MONTH('Budget'!$B$6)),SUM('Budget'!$K$12:$K$51),0),"") | C20: =IF(A20<=DATE(YEAR('Budget'!$B$6),MONTH('Budget'!$B$6),1),SUM($B$5:B20),"") | D20: =IF(A20<=DATE(YEAR('Budget'!$B$6),MONTH('Budget'!$B$6),1),15,"") | E20: =IF(A20<=DATE(YEAR('Budget'!$B$6),MONTH('Budget'!$B$6),1),'Budget'!$B$7+'Budget'!$B$8*15,"") | F20: =IF(A20<=DATE(YEAR('Budget'!$B$6),MONTH('Budget'!$B$6),1),E20-C20,"") | G20: =IF(A20<=DATE(YEAR('Budget'!$B$6),MONTH('Budget'!$B$6),1),IF(15>0,MAX(0,(C20-'Budget'!$B$7)/15),0),"")
A21: =DATE(YEAR(TODAY()),MONTH(TODAY())+16,1) | B21: =IF(A21<=DATE(YEAR('Budget'!$B$6),MONTH('Budget'!$B$6),1),SUMIF('Budget'!$M$12:$M$51,YEAR(A21)*12+MONTH(A21),'Budget'!$L$12:$L$51)+IF(AND(YEAR(A21)=YEAR('Budget'!$B$6),MONTH(A21)=MONTH('Budget'!$B$6)),SUM('Budget'!$K$12:$K$51),0),"") | C21: =IF(A21<=DATE(YEAR('Budget'!$B$6),MONTH('Budget'!$B$6),1),SUM($B$5:B21),"") | D21: =IF(A21<=DATE(YEAR('Budget'!$B$6),MONTH('Budget'!$B$6),1),16,"") | E21: =IF(A21<=DATE(YEAR('Budget'!$B$6),MONTH('Budget'!$B$6),1),'Budget'!$B$7+'Budget'!$B$8*16,"") | F21: =IF(A21<=DATE(YEAR('Budget'!$B$6),MONTH('Budget'!$B$6),1),E21-C21,"") | G21: =IF(A21<=DATE(YEAR('Budget'!$B$6),MONTH('Budget'!$B$6),1),IF(16>0,MAX(0,(C21-'Budget'!$B$7)/16),0),"")
A22: =DATE(YEAR(TODAY()),MONTH(TODAY())+17,1) | B22: =IF(A22<=DATE(YEAR('Budget'!$B$6),MONTH('Budget'!$B$6),1),SUMIF('Budget'!$M$12:$M$51,YEAR(A22)*12+MONTH(A22),'Budget'!$L$12:$L$51)+IF(AND(YEAR(A22)=YEAR('Budget'!$B$6),MONTH(A22)=MONTH('Budget'!$B$6)),SUM('Budget'!$K$12:$K$51),0),"") | C22: =IF(A22<=DATE(YEAR('Budget'!$B$6),MONTH('Budget'!$B$6),1),SUM($B$5:B22),"") | D22: =IF(A22<=DATE(YEAR('Budget'!$B$6),MONTH('Budget'!$B$6),1),17,"") | E22: =IF(A22<=DATE(YEAR('Budget'!$B$6),MONTH('Budget'!$B$6),1),'Budget'!$B$7+'Budget'!$B$8*17,"") | F22: =IF(A22<=DATE(YEAR('Budget'!$B$6),MONTH('Budget'!$B$6),1),E22-C22,"") | G22: =IF(A22<=DATE(YEAR('Budget'!$B$6),MONTH('Budget'!$B$6),1),IF(17>0,MAX(0,(C22-'Budget'!$B$7)/17),0),"")
A23: =DATE(YEAR(TODAY()),MONTH(TODAY())+18,1) | B23: =IF(A23<=DATE(YEAR('Budget'!$B$6),MONTH('Budget'!$B$6),1),SUMIF('Budget'!$M$12:$M$51,YEAR(A23)*12+MONTH(A23),'Budget'!$L$12:$L$51)+IF(AND(YEAR(A23)=YEAR('Budget'!$B$6),MONTH(A23)=MONTH('Budget'!$B$6)),SUM('Budget'!$K$12:$K$51),0),"") | C23: =IF(A23<=DATE(YEAR('Budget'!$B$6),MONTH('Budget'!$B$6),1),SUM($B$5:B23),"") | D23: =IF(A23<=DATE(YEAR('Budget'!$B$6),MONTH('Budget'!$B$6),1),18,"") | E23: =IF(A23<=DATE(YEAR('Budget'!$B$6),MONTH('Budget'!$B$6),1),'Budget'!$B$7+'Budget'!$B$8*18,"") | F23: =IF(A23<=DATE(YEAR('Budget'!$B$6),MONTH('Budget'!$B$6),1),E23-C23,"") | G23: =IF(A23<=DATE(YEAR('Budget'!$B$6),MONTH('Budget'!$B$6),1),IF(18>0,MAX(0,(C23-'Budget'!$B$7)/18),0),"")
A24: =DATE(YEAR(TODAY()),MONTH(TODAY())+19,1) | B24: =IF(A24<=DATE(YEAR('Budget'!$B$6),MONTH('Budget'!$B$6),1),SUMIF('Budget'!$M$12:$M$51,YEAR(A24)*12+MONTH(A24),'Budget'!$L$12:$L$51)+IF(AND(YEAR(A24)=YEAR('Budget'!$B$6),MONTH(A24)=MONTH('Budget'!$B$6)),SUM('Budget'!$K$12:$K$51),0),"") | C24: =IF(A24<=DATE(YEAR('Budget'!$B$6),MONTH('Budget'!$B$6),1),SUM($B$5:B24),"") | D24: =IF(A24<=DATE(YEAR('Budget'!$B$6),MONTH('Budget'!$B$6),1),19,"") | E24: =IF(A24<=DATE(YEAR('Budget'!$B$6),MONTH('Budget'!$B$6),1),'Budget'!$B$7+'Budget'!$B$8*19,"") | F24: =IF(A24<=DATE(YEAR('Budget'!$B$6),MONTH('Budget'!$B$6),1),E24-C24,"") | G24: =IF(A24<=DATE(YEAR('Budget'!$B$6),MONTH('Budget'!$B$6),1),IF(19>0,MAX(0,(C24-'Budget'!$B$7)/19),0),"")
A25: =DATE(YEAR(TODAY()),MONTH(TODAY())+20,1) | B25: =IF(A25<=DATE(YEAR('Budget'!$B$6),MONTH('Budget'!$B$6),1),SUMIF('Budget'!$M$12:$M$51,YEAR(A25)*12+MONTH(A25),'Budget'!$L$12:$L$51)+IF(AND(YEAR(A25)=YEAR('Budget'!$B$6),MONTH(A25)=MONTH('Budget'!$B$6)),SUM('Budget'!$K$12:$K$51),0),"") | C25: =IF(A25<=DATE(YEAR('Budget'!$B$6),MONTH('Budget'!$B$6),1),SUM($B$5:B25),"") | D25: =IF(A25<=DATE(YEAR('Budget'!$B$6),MONTH('Budget'!$B$6),1),20,"") | E25: =IF(A25<=DATE(YEAR('Budget'!$B$6),MONTH('Budget'!$B$6),1),'Budget'!$B$7+'Budget'!$B$8*20,"") | F25: =IF(A25<=DATE(YEAR('Budget'!$B$6),MONTH('Budget'!$B$6),1),E25-C25,"") | G25: =IF(A25<=DATE(YEAR('Budget'!$B$6),MONTH('Budget'!$B$6),1),IF(20>0,MAX(0,(C25-'Budget'!$B$7)/20),0),"")
A26: =DATE(YEAR(TODAY()),MONTH(TODAY())+21,1) | B26: =IF(A26<=DATE(YEAR('Budget'!$B$6),MONTH('Budget'!$B$6),1),SUMIF('Budget'!$M$12:$M$51,YEAR(A26)*12+MONTH(A26),'Budget'!$L$12:$L$51)+IF(AND(YEAR(A26)=YEAR('Budget'!$B$6),MONTH(A26)=MONTH('Budget'!$B$6)),SUM('Budget'!$K$12:$K$51),0),"") | C26: =IF(A26<=DATE(YEAR('Budget'!$B$6),MONTH('Budget'!$B$6),1),SUM($B$5:B26),"") | D26: =IF(A26<=DATE(YEAR('Budget'!$B$6),MONTH('Budget'!$B$6),1),21,"") | E26: =IF(A26<=DATE(YEAR('Budget'!$B$6),MONTH('Budget'!$B$6),1),'Budget'!$B$7+'Budget'!$B$8*21,"") | F26: =IF(A26<=DATE(YEAR('Budget'!$B$6),MONTH('Budget'!$B$6),1),E26-C26,"") | G26: =IF(A26<=DATE(YEAR('Budget'!$B$6),MONTH('Budget'!$B$6),1),IF(21>0,MAX(0,(C26-'Budget'!$B$7)/21),0),"")
A27: =DATE(YEAR(TODAY()),MONTH(TODAY())+22,1) | B27: =IF(A27<=DATE(YEAR('Budget'!$B$6),MONTH('Budget'!$B$6),1),SUMIF('Budget'!$M$12:$M$51,YEAR(A27)*12+MONTH(A27),'Budget'!$L$12:$L$51)+IF(AND(YEAR(A27)=YEAR('Budget'!$B$6),MONTH(A27)=MONTH('Budget'!$B$6)),SUM('Budget'!$K$12:$K$51),0),"") | C27: =IF(A27<=DATE(YEAR('Budget'!$B$6),MONTH('Budget'!$B$6),1),SUM($B$5:B27),"") | D27: =IF(A27<=DATE(YEAR('Budget'!$B$6),MONTH('Budget'!$B$6),1),22,"") | E27: =IF(A27<=DATE(YEAR('Budget'!$B$6),MONTH('Budget'!$B$6),1),'Budget'!$B$7+'Budget'!$B$8*22,"") | F27: =IF(A27<=DATE(YEAR('Budget'!$B$6),MONTH('Budget'!$B$6),1),E27-C27,"") | G27: =IF(A27<=DATE(YEAR('Budget'!$B$6),MONTH('Budget'!$B$6),1),IF(22>0,MAX(0,(C27-'Budget'!$B$7)/22),0),"")
A28: =DATE(YEAR(TODAY()),MONTH(TODAY())+23,1) | B28: =IF(A28<=DATE(YEAR('Budget'!$B$6),MONTH('Budget'!$B$6),1),SUMIF('Budget'!$M$12:$M$51,YEAR(A28)*12+MONTH(A28),'Budget'!$L$12:$L$51)+IF(AND(YEAR(A28)=YEAR('Budget'!$B$6),MONTH(A28)=MONTH('Budget'!$B$6)),SUM('Budget'!$K$12:$K$51),0),"") | C28: =IF(A28<=DATE(YEAR('Budget'!$B$6),MONTH('Budget'!$B$6),1),SUM($B$5:B28),"") | D28: =IF(A28<=DATE(YEAR('Budget'!$B$6),MONTH('Budget'!$B$6),1),23,"") | E28: =IF(A28<=DATE(YEAR('Budget'!$B$6),MONTH('Budget'!$B$6),1),'Budget'!$B$7+'Budget'!$B$8*23,"") | F28: =IF(A28<=DATE(YEAR('Budget'!$B$6),MONTH('Budget'!$B$6),1),E28-C28,"") | G28: =IF(A28<=DATE(YEAR('Budget'!$B$6),MONTH('Budget'!$B$6),1),IF(23>0,MAX(0,(C28-'Budget'!$B$7)/23),0),"")
A29: =DATE(YEAR(TODAY()),MONTH(TODAY())+24,1) | B29: =IF(A29<=DATE(YEAR('Budget'!$B$6),MONTH('Budget'!$B$6),1),SUMIF('Budget'!$M$12:$M$51,YEAR(A29)*12+MONTH(A29),'Budget'!$L$12:$L$51)+IF(AND(YEAR(A29)=YEAR('Budget'!$B$6),MONTH(A29)=MONTH('Budget'!$B$6)),SUM('Budget'!$K$12:$K$51),0),"") | C29: =IF(A29<=DATE(YEAR('Budget'!$B$6),MONTH('Budget'!$B$6),1),SUM($B$5:B29),"") | D29: =IF(A29<=DATE(YEAR('Budget'!$B$6),MONTH('Budget'!$B$6),1),24,"") | E29: =IF(A29<=DATE(YEAR('Budget'!$B$6),MONTH('Budget'!$B$6),1),'Budget'!$B$7+'Budget'!$B$8*24,"") | F29: =IF(A29<=DATE(YEAR('Budget'!$B$6),MONTH('Budget'!$B$6),1),E29-C29,"") | G29: =IF(A29<=DATE(YEAR('Budget'!$B$6),MONTH('Budget'!$B$6),1),IF(24>0,MAX(0,(C29-'Budget'!$B$7)/24),0),"")
A30: =DATE(YEAR(TODAY()),MONTH(TODAY())+25,1) | B30: =IF(A30<=DATE(YEAR('Budget'!$B$6),MONTH('Budget'!$B$6),1),SUMIF('Budget'!$M$12:$M$51,YEAR(A30)*12+MONTH(A30),'Budget'!$L$12:$L$51)+IF(AND(YEAR(A30)=YEAR('Budget'!$B$6),MONTH(A30)=MONTH('Budget'!$B$6)),SUM('Budget'!$K$12:$K$51),0),"") | C30: =IF(A30<=DATE(YEAR('Budget'!$B$6),MONTH('Budget'!$B$6),1),SUM($B$5:B30),"") | D30: =IF(A30<=DATE(YEAR('Budget'!$B$6),MONTH('Budget'!$B$6),1),25,"") | E30: =IF(A30<=DATE(YEAR('Budget'!$B$6),MONTH('Budget'!$B$6),1),'Budget'!$B$7+'Budget'!$B$8*25,"") | F30: =IF(A30<=DATE(YEAR('Budget'!$B$6),MONTH('Budget'!$B$6),1),E30-C30,"") | G30: =IF(A30<=DATE(YEAR('Budget'!$B$6),MONTH('Budget'!$B$6),1),IF(25>0,MAX(0,(C30-'Budget'!$B$7)/25),0),"")
A31: =DATE(YEAR(TODAY()),MONTH(TODAY())+26,1) | B31: =IF(A31<=DATE(YEAR('Budget'!$B$6),MONTH('Budget'!$B$6),1),SUMIF('Budget'!$M$12:$M$51,YEAR(A31)*12+MONTH(A31),'Budget'!$L$12:$L$51)+IF(AND(YEAR(A31)=YEAR('Budget'!$B$6),MONTH(A31)=MONTH('Budget'!$B$6)),SUM('Budget'!$K$12:$K$51),0),"") | C31: =IF(A31<=DATE(YEAR('Budget'!$B$6),MONTH('Budget'!$B$6),1),SUM($B$5:B31),"") | D31: =IF(A31<=DATE(YEAR('Budget'!$B$6),MONTH('Budget'!$B$6),1),26,"") | E31: =IF(A31<=DATE(YEAR('Budget'!$B$6),MONTH('Budget'!$B$6),1),'Budget'!$B$7+'Budget'!$B$8*26,"") | F31: =IF(A31<=DATE(YEAR('Budget'!$B$6),MONTH('Budget'!$B$6),1),E31-C31,"") | G31: =IF(A31<=DATE(YEAR('Budget'!$B$6),MONTH('Budget'!$B$6),1),IF(26>0,MAX(0,(C31-'Budget'!$B$7)/26),0),"")
A32: =DATE(YEAR(TODAY()),MONTH(TODAY())+27,1) | B32: =IF(A32<=DATE(YEAR('Budget'!$B$6),MONTH('Budget'!$B$6),1),SUMIF('Budget'!$M$12:$M$51,YEAR(A32)*12+MONTH(A32),'Budget'!$L$12:$L$51)+IF(AND(YEAR(A32)=YEAR('Budget'!$B$6),MONTH(A32)=MONTH('Budget'!$B$6)),SUM('Budget'!$K$12:$K$51),0),"") | C32: =IF(A32<=DATE(YEAR('Budget'!$B$6),MONTH('Budget'!$B$6),1),SUM($B$5:B32),"") | D32: =IF(A32<=DATE(YEAR('Budget'!$B$6),MONTH('Budget'!$B$6),1),27,"") | E32: =IF(A32<=DATE(YEAR('Budget'!$B$6),MONTH('Budget'!$B$6),1),'Budget'!$B$7+'Budget'!$B$8*27,"") | F32: =IF(A32<=DATE(YEAR('Budget'!$B$6),MONTH('Budget'!$B$6),1),E32-C32,"") | G32: =IF(A32<=DATE(YEAR('Budget'!$B$6),MONTH('Budget'!$B$6),1),IF(27>0,MAX(0,(C32-'Budget'!$B$7)/27),0),"")
A33: =DATE(YEAR(TODAY()),MONTH(TODAY())+28,1) | B33: =IF(A33<=DATE(YEAR('Budget'!$B$6),MONTH('Budget'!$B$6),1),SUMIF('Budget'!$M$12:$M$51,YEAR(A33)*12+MONTH(A33),'Budget'!$L$12:$L$51)+IF(AND(YEAR(A33)=YEAR('Budget'!$B$6),MONTH(A33)=MONTH('Budget'!$B$6)),SUM('Budget'!$K$12:$K$51),0),"") | C33: =IF(A33<=DATE(YEAR('Budget'!$B$6),MONTH('Budget'!$B$6),1),SUM($B$5:B33),"") | D33: =IF(A33<=DATE(YEAR('Budget'!$B$6),MONTH('Budget'!$B$6),1),28,"") | E33: =IF(A33<=DATE(YEAR('Budget'!$B$6),MONTH('Budget'!$B$6),1),'Budget'!$B$7+'Budget'!$B$8*28,"") | F33: =IF(A33<=DATE(YEAR('Budget'!$B$6),MONTH('Budget'!$B$6),1),E33-C33,"") | G33: =IF(A33<=DATE(YEAR('Budget'!$B$6),MONTH('Budget'!$B$6),1),IF(28>0,MAX(0,(C33-'Budget'!$B$7)/28),0),"")
A34: =DATE(YEAR(TODAY()),MONTH(TODAY())+29,1) | B34: =IF(A34<=DATE(YEAR('Budget'!$B$6),MONTH('Budget'!$B$6),1),SUMIF('Budget'!$M$12:$M$51,YEAR(A34)*12+MONTH(A34),'Budget'!$L$12:$L$51)+IF(AND(YEAR(A34)=YEAR('Budget'!$B$6),MONTH(A34)=MONTH('Budget'!$B$6)),SUM('Budget'!$K$12:$K$51),0),"") | C34: =IF(A34<=DATE(YEAR('Budget'!$B$6),MONTH('Budget'!$B$6),1),SUM($B$5:B34),"") | D34: =IF(A34<=DATE(YEAR('Budget'!$B$6),MONTH('Budget'!$B$6),1),29,"") | E34: =IF(A34<=DATE(YEAR('Budget'!$B$6),MONTH('Budget'!$B$6),1),'Budget'!$B$7+'Budget'!$B$8*29,"") | F34: =IF(A34<=DATE(YEAR('Budget'!$B$6),MONTH('Budget'!$B$6),1),E34-C34,"") | G34: =IF(A34<=DATE(YEAR('Budget'!$B$6),MONTH('Budget'!$B$6),1),IF(29>0,MAX(0,(C34-'Budget'!$B$7)/29),0),"")
A35: =DATE(YEAR(TODAY()),MONTH(TODAY())+30,1) | B35: =IF(A35<=DATE(YEAR('Budget'!$B$6),MONTH('Budget'!$B$6),1),SUMIF('Budget'!$M$12:$M$51,YEAR(A35)*12+MONTH(A35),'Budget'!$L$12:$L$51)+IF(AND(YEAR(A35)=YEAR('Budget'!$B$6),MONTH(A35)=MONTH('Budget'!$B$6)),SUM('Budget'!$K$12:$K$51),0),"") | C35: =IF(A35<=DATE(YEAR('Budget'!$B$6),MONTH('Budget'!$B$6),1),SUM($B$5:B35),"") | D35: =IF(A35<=DATE(YEAR('Budget'!$B$6),MONTH('Budget'!$B$6),1),30,"") | E35: =IF(A35<=DATE(YEAR('Budget'!$B$6),MONTH('Budget'!$B$6),1),'Budget'!$B$7+'Budget'!$B$8*30,"") | F35: =IF(A35<=DATE(YEAR('Budget'!$B$6),MONTH('Budget'!$B$6),1),E35-C35,"") | G35: =IF(A35<=DATE(YEAR('Budget'!$B$6),MONTH('Budget'!$B$6),1),IF(30>0,MAX(0,(C35-'Budget'!$B$7)/30),0),"")
A36: =DATE(YEAR(TODAY()),MONTH(TODAY())+31,1) | B36: =IF(A36<=DATE(YEAR('Budget'!$B$6),MONTH('Budget'!$B$6),1),SUMIF('Budget'!$M$12:$M$51,YEAR(A36)*12+MONTH(A36),'Budget'!$L$12:$L$51)+IF(AND(YEAR(A36)=YEAR('Budget'!$B$6),MONTH(A36)=MONTH('Budget'!$B$6)),SUM('Budget'!$K$12:$K$51),0),"") | C36: =IF(A36<=DATE(YEAR('Budget'!$B$6),MONTH('Budget'!$B$6),1),SUM($B$5:B36),"") | D36: =IF(A36<=DATE(YEAR('Budget'!$B$6),MONTH('Budget'!$B$6),1),31,"") | E36: =IF(A36<=DATE(YEAR('Budget'!$B$6),MONTH('Budget'!$B$6),1),'Budget'!$B$7+'Budget'!$B$8*31,"") | F36: =IF(A36<=DATE(YEAR('Budget'!$B$6),MONTH('Budget'!$B$6),1),E36-C36,"") | G36: =IF(A36<=DATE(YEAR('Budget'!$B$6),MONTH('Budget'!$B$6),1),IF(31>0,MAX(0,(C36-'Budget'!$B$7)/31),0),"")
A37: =DATE(YEAR(TODAY()),MONTH(TODAY())+32,1) | B37: =IF(A37<=DATE(YEAR('Budget'!$B$6),MONTH('Budget'!$B$6),1),SUMIF('Budget'!$M$12:$M$51,YEAR(A37)*12+MONTH(A37),'Budget'!$L$12:$L$51)+IF(AND(YEAR(A37)=YEAR('Budget'!$B$6),MONTH(A37)=MONTH('Budget'!$B$6)),SUM('Budget'!$K$12:$K$51),0),"") | C37: =IF(A37<=DATE(YEAR('Budget'!$B$6),MONTH('Budget'!$B$6),1),SUM($B$5:B37),"") | D37: =IF(A37<=DATE(YEAR('Budget'!$B$6),MONTH('Budget'!$B$6),1),32,"") | E37: =IF(A37<=DATE(YEAR('Budget'!$B$6),MONTH('Budget'!$B$6),1),'Budget'!$B$7+'Budget'!$B$8*32,"") | F37: =IF(A37<=DATE(YEAR('Budget'!$B$6),MONTH('Budget'!$B$6),1),E37-C37,"") | G37: =IF(A37<=DATE(YEAR('Budget'!$B$6),MONTH('Budget'!$B$6),1),IF(32>0,MAX(0,(C37-'Budget'!$B$7)/32),0),"")
A38: =DATE(YEAR(TODAY()),MONTH(TODAY())+33,1) | B38: =IF(A38<=DATE(YEAR('Budget'!$B$6),MONTH('Budget'!$B$6),1),SUMIF('Budget'!$M$12:$M$51,YEAR(A38)*12+MONTH(A38),'Budget'!$L$12:$L$51)+IF(AND(YEAR(A38)=YEAR('Budget'!$B$6),MONTH(A38)=MONTH('Budget'!$B$6)),SUM('Budget'!$K$12:$K$51),0),"") | C38: =IF(A38<=DATE(YEAR('Budget'!$B$6),MONTH('Budget'!$B$6),1),SUM($B$5:B38),"") | D38: =IF(A38<=DATE(YEAR('Budget'!$B$6),MONTH('Budget'!$B$6),1),33,"") | E38: =IF(A38<=DATE(YEAR('Budget'!$B$6),MONTH('Budget'!$B$6),1),'Budget'!$B$7+'Budget'!$B$8*33,"") | F38: =IF(A38<=DATE(YEAR('Budget'!$B$6),MONTH('Budget'!$B$6),1),E38-C38,"") | G38: =IF(A38<=DATE(YEAR('Budget'!$B$6),MONTH('Budget'!$B$6),1),IF(33>0,MAX(0,(C38-'Budget'!$B$7)/33),0),"")
A39: =DATE(YEAR(TODAY()),MONTH(TODAY())+34,1) | B39: =IF(A39<=DATE(YEAR('Budget'!$B$6),MONTH('Budget'!$B$6),1),SUMIF('Budget'!$M$12:$M$51,YEAR(A39)*12+MONTH(A39),'Budget'!$L$12:$L$51)+IF(AND(YEAR(A39)=YEAR('Budget'!$B$6),MONTH(A39)=MONTH('Budget'!$B$6)),SUM('Budget'!$K$12:$K$51),0),"") | C39: =IF(A39<=DATE(YEAR('Budget'!$B$6),MONTH('Budget'!$B$6),1),SUM($B$5:B39),"") | D39: =IF(A39<=DATE(YEAR('Budget'!$B$6),MONTH('Budget'!$B$6),1),34,"") | E39: =IF(A39<=DATE(YEAR('Budget'!$B$6),MONTH('Budget'!$B$6),1),'Budget'!$B$7+'Budget'!$B$8*34,"") | F39: =IF(A39<=DATE(YEAR('Budget'!$B$6),MONTH('Budget'!$B$6),1),E39-C39,"") | G39: =IF(A39<=DATE(YEAR('Budget'!$B$6),MONTH('Budget'!$B$6),1),IF(34>0,MAX(0,(C39-'Budget'!$B$7)/34),0),"")
A40: =DATE(YEAR(TODAY()),MONTH(TODAY())+35,1) | B40: =IF(A40<=DATE(YEAR('Budget'!$B$6),MONTH('Budget'!$B$6),1),SUMIF('Budget'!$M$12:$M$51,YEAR(A40)*12+MONTH(A40),'Budget'!$L$12:$L$51)+IF(AND(YEAR(A40)=YEAR('Budget'!$B$6),MONTH(A40)=MONTH('Budget'!$B$6)),SUM('Budget'!$K$12:$K$51),0),"") | C40: =IF(A40<=DATE(YEAR('Budget'!$B$6),MONTH('Budget'!$B$6),1),SUM($B$5:B40),"") | D40: =IF(A40<=DATE(YEAR('Budget'!$B$6),MONTH('Budget'!$B$6),1),35,"") | E40: =IF(A40<=DATE(YEAR('Budget'!$B$6),MONTH('Budget'!$B$6),1),'Budget'!$B$7+'Budget'!$B$8*35,"") | F40: =IF(A40<=DATE(YEAR('Budget'!$B$6),MONTH('Budget'!$B$6),1),E40-C40,"") | G40: =IF(A40<=DATE(YEAR('Budget'!$B$6),MONTH('Budget'!$B$6),1),IF(35>0,MAX(0,(C40-'Budget'!$B$7)/35),0),"")

Sheet Anleitung
A1: Hochzeits-Budget-Plan — so geht's
A3: 1. Blatt „Budget“: Gäste, Budget, Datum, schon Gespartes und eure monatliche Sparrate eintragen.
A4: 2. Posten mit den Preisen aus euren Offerten. „pro Gast“ = ja, wenn der Preis pro Person gilt (Essen, Getränke, Torte).
A5: 3. Anzahlung: wie viel Prozent der Anbieter vorher will und wie viele Monate vor der Hochzeit. Steht in der Offerte.
A6: 4. Schon bezahlt: bereits überwiesene Beträge. Sie decken zuerst die Anzahlung, dann den Rest.
A7: 5. Oben rechts: Kosten pro Gast, wie viele Gäste ins Budget passen und die Sparrate, die jede Zahlung deckt.
A8: 6. Blatt „Zahlungsplan“: Monat für Monat, was fällig wird. Rot = mit eurer Sparrate fehlt dann Geld.
A10: Der grösste Hebel ist die Gästeliste: Pauschalen bleiben gleich, Essen und Getränke wachsen mit jedem Gast.
A11: Die Beispielbeträge sind Platzhalter, keine Durchschnittspreise. Funktioniert mit jeder Währung.
A12: Google Tabellen: Datei in Google Drive hochladen → Öffnen mit → Google Tabellen.
A14: Private Nutzung. Weitergabe und Weiterverkauf nicht gestattet.
A15: © aban news · abannews.com
